Workbook

Sheet BALANCE N
A1: Compte | B1: Intitulé | C1: Préfixe 2 | D1: Préfixe 3 | E1: Préfixe 4 | F1: Solde final débit | G1: Solde final crédit
A2: 2441 | B2: Matériel et mobilier de bureau | C2: 24 | D2: 244 | E2: 2441 | F2: 1500000 | G2: 0
A3: 2844 | B3: Amortissements du matériel et mobilier | C3: 28 | D3: 284 | E3: 2844 | F3: 0 | G3: 500000
A4: 331 | B4: Matières consommables | C4: 33 | D4: 331 | E4: 331 | F4: 200000 | G4: 0
A5: 521 | B5: Banques locales | C5: 52 | D5: 521 | E5: 521 | F5: 1200000 | G5: 0
A6: 571 | B6: Caisse | C6: 57 | D6: 571 | E6: 571 | F6: 400000 | G6: 0
A7: 1011 | B7: Dotation non consomptible | C7: 10 | D7: 101 | E7: 1011 | F7: 0 | G7: 1500000
A8: 112 | B8: Réserves statutaires | C8: 11 | D8: 112 | E8: 112 | F8: 0 | G8: 200000
A9: 4011 | B9: Fournisseurs | C9: 40 | D9: 401 | E9: 4011 | F9: 0 | G9: 150000
A10: 601 | B10: Achats de biens et services liés à l'activité | C10: 60 | D10: 601 | E10: 601 | F10: 1800000 | G10: 0
A11: 622 | B11: Locations et charges locatives | C11: 62 | D11: 622 | E11: 622 | F11: 600000 | G11: 0
A12: 661 | B12: Salaires | C12: 66 | D12: 661 | E12: 661 | F12: 1300000 | G12: 0
A13: 641 | B13: Impôts et taxes directs | C13: 64 | D13: 641 | E13: 641 | F13: 100000 | G13: 0
... A18: 711 | B18: Subventions d'exploitation | C18: 71 | D18: 711 | E18: 711 | F18: 0 | G18: 1050000

Sheet CONTROLE BALANCE
A1: EQUILIBRE DE LA BALANCE
A2: BALANCE N | B2: Mouvements Débit | C2: Mouvements Crédit | D2: Solde Final Débit | E2: Solde Final Crédit
B3: =SUM('BALANCE N'!H2:H18) | C3: =SUM('BALANCE N'!I2:I18) | D3: =SUM('BALANCE N'!F2:F18) | E3: =SUM('BALANCE N'!G2:G18)
B4: =IF(ROUND(B3-C3,0)=0,"Equilibre","Déséquilibre : écart de "&TEXT(B3-C3,"#,##0")) | D4: =IF(ROUND(D3-E3,0)=0,"Equilibre","Déséquilibre : écart de "&TEXT(D3-E3,"#,##0"))

Sheet Couverture
E26: CLUB SOLIDARITE QUARTIER
E31: LIASSE SMT
E34: Exercice clos le 31-12-2025

Sheet Garde
B12: ETATS FINANCIERS NORMALISES DU SYSTEME COMPTABLE DES ENTITES A BUT NON LUCRATIF (SYCEBNL)
B13: Associations, Ordres Professionnels, Fondations et Assimilées
C16: Exercice clos le 31-12-2025 - Durée (en mois) : 12
B20: DESIGNATION DE L'ENTITE
B22: DENOMINATION SOCIALE : | E22: CLUB SOLIDARITE QUARTIER
B24: SIGLE USUEL :
B26: ADRESSE COMPLETE :
B28: N° de compte contribuable (NCC) : | E28: ASBL-0093
B30: N° de télédéclarant (NTD) :
B32: SYSTEME MINIMAL DE TRESORERIE
B34: Documents déposés | H34: Réservé à l'administration
B35: Fiche d'identification et renseignements divers | F35: X | H35: Date de dépôt
B36: Bilan (actif et passif) | F36: X
B37: Compte de résultat | F37: X
B38: Notes annexes 1 à 5 | F38: X
H39: Nom de l'agent ayant réceptionné le dépôt
H43: Signature de l'agent et cachet du service
B48: Nombre de pages déposées par exemplaire :
B49: Nombre d'exemplaires déposés :

Sheet Fiche 1
A1: - 1 -
I2: FICHE 1
A3: Dénomination sociale : CLUB SOLIDARITE QUARTIER
A4: Adresse : | I4: Sigle usuel :
A5: N° de compte contribuable (NCC) : ASBL-0093 | G5: Exercice clos le 31-12-2025 | I5: Durée (en mois) : 12
A6: N° de télédéclarant (NTD) :
A7: FICHE D'IDENTIFICATION ET RENSEIGNEMENTS DIVERS
A8: SYCEBNL - Système minimal de trésorerie
A10: ZA | B10: EXERCICE COMPTABLE | G10: DU : 01-01-2025 AU : 31-12-2025
A11: ZB | B11: DATE D'ARRETE EFFECTIF DES COMPTES
A12: ZC | B12: EXERCICE PRECEDENT CLOS LE
A13: ZD | B13: DUREE DE L'EXERCICE PRECEDENT (EN MOIS)
A14: ZE | B14: N° REGISTRE (RCCM, F92, CONVENTION...) ET GREFFE
A15: ZF | B15: N° REPERTOIRE DES ENTITES
A16: ZG | B16: N° DE CAISSE SOCIALE
A17: ZH | B17: N° CODE IMPORTATEUR
A18: ZI | B18: CODE ACTIVITE PRINCIPALE
A19: ZJ | B19: DESIGNATION DE L'ENTITE ET SIGLE | G19: CLUB SOLIDARITE QUARTIER
A20: ZK | B20: N° DE TELEPHONE, ADRESSE E-MAIL, BOITE POSTALE, VILLE
A21: ZL | B21: ADRESSE GEOGRAPHIQUE COMPLETE (IMMEUBLE, RUE, QUARTIER, VILLE, PAYS)
A22: ZM | B22: DESIGNATION PRECISE DE L'ACTIVITE PRINCIPALE EXERCEE
A23: ZN | B23: % DE CAPACITE DE PRODUCTION UTILE
A24: ZO | B24: NOM, ADRESSE, TELEPHONE, E-MAIL ET QUALITE DE LA PERSONNE A CONTACTER EN CAS DE DEMANDE
A25: ZP | B25: NOM, ADRESSE, TELEPHONE ET E-MAIL DU SALARIE OU DU PROFESSIONNEL COMPTABLE AYANT ETABLI LES ETATS FINANCIERS
A26: ZQ | B26: NOM, ADRESSE, TELEPHONE, E-MAIL ET N° D'INSCRIPTION A L'ORDRE DE L'EXPERT-COMPTABLE AYANT DELIVRE L'ATTESTATION DE VISA
A27: ZR | B27: NOM, ADRESSE, TELEPHONE, E-MAIL ET N° D'INSCRIPTION DU COMMISSAIRE AUX COMPTES, LE CAS ECHEANT
A28: ZS | B28: ETATS FINANCIERS APPROUVES PAR L'ORGANE COMPETENT (OUI / NON)
A29: ZT | B29: NOM DU SIGNATAIRE DES ETATS FINANCIERS
A30: ZU | B30: QUALITE DU SIGNATAIRE DES ETATS FINANCIERS
A31: ZV | B31: DATE DE SIGNATURE
A32: ZW | B32: DOMICILIATIONS BANCAIRES (BANQUE ET NUMERO DE COMPTE)
B34: Signature

Sheet Fiche 2
A1: - 2 -
I2: FICHE 2
A3: Dénomination sociale : CLUB SOLIDARITE QUARTIER
A4: Adresse : | I4: Sigle usuel :
A5: N° de compte contribuable (NCC) : ASBL-0093 | G5: Exercice clos le 31-12-2025 | I5: Durée (en mois) : 12
A6: N° de télédéclarant (NTD) :
A7: FICHE D'IDENTIFICATION ET RENSEIGNEMENTS DIVERS
A8: EQUIPE DE L'ENTITE A BUT NON LUCRATIF
A10: Nom et Prénoms | C10: Nationalité | D10: Autres nationalités (à préciser) (2) | E10: Qualité | F10: N° d'identification fiscale | H10: Adresse (BP, ville, pays, adresse géographique et adresse e-mail)
A32: (2) Mentionner les autres nationalités le cas échéant.

Sheet Bilan paysage
A1: - 3 -
I2: BILAN SYCEBNL - SMT PAGE 1/1
A3: Dénomination sociale : CLUB SOLIDARITE QUARTIER
A4: Adresse : | I4: Sigle usuel :
A5: N° de compte contribuable (NCC) : ASBL-0093 | G5: Exercice clos le 31-12-2025 | I5: Durée (en mois) : 12
A6: N° de télédéclarant (NTD) :
C7: BILAN
A8: REF | B8: ACTIF | C8: NOTE | D8: EXERCICE N | E8: EXERCICE N-1 | F8: REF | G8: PASSIF | H8: NOTE | I8: EXERCICE N | J8: EXERCICE N-1
A10: GA | B10: Immobilisations (1) | C10: 1 | D10: ='Bilan-Actif'!D9 | E10: ='Bilan-Actif'!E9 | F10: HA | G10: Dotations | H10: 5 | I10: ='Bilan-Passif'!D9 | J10: ='Bilan-Passif'!E9
A11: GB | B11: Stocks | C11: 2 | D11: ='Bilan-Actif'!D10 | E11: ='Bilan-Actif'!E10 | F11: HB | G11: Résultat net de l'exercice (en + ou en -) | I11: ='Bilan-Passif'!D10 | J11: ='Bilan-Passif'!E10
A12: GC | B12: Adhérents, clients-usagers et autres débiteurs | C12: 3 | D12: ='Bilan-Actif'!D11 | E12: ='Bilan-Actif'!E11 | F12: HC | G12: Autres fonds propres | I12: ='Bilan-Passif'!D11 | J12: ='Bilan-Passif'!E11
A13: GD | B13: Caisse | C13: 4 | D13: ='Bilan-Actif'!D12 | E13: ='Bilan-Actif'!E12 | F13: HD | G13: Fournisseurs et autres créditeurs | H13: 3 | I13: ='Bilan-Passif'!D12 | J13: ='Bilan-Passif'!E12
A14: GE | B14: Banque (en + ou en -) | C14: 4 | D14: ='Bilan-Actif'!D13 | E14: ='Bilan-Actif'!E13 | F14: HZ | G14: TOTAL PASSIF | I14: ='Bilan-Passif'!D13 | J14: ='Bilan-Passif'!E13
A15: GZ | B15: TOTAL ACTIF | D15: ='Bilan-Actif'!D14 | E15: ='Bilan-Actif'!E14

Sheet Bilan-Actif
A1: - 4 -
D2: BILAN SYCEBNL - SMT PAGE 1/2
A3: Dénomination sociale : CLUB SOLIDARITE QUARTIER
A4: Adresse : | D4: Sigle usuel :
A5: N° de compte contribuable (NCC) : ASBL-0093 | C5: Exercice clos le 31-12-2025 | D5: Durée (en mois) : 12
A6: N° de télédéclarant (NTD) :
A7: BILAN
A8: REF | B8: ACTIF | C8: NOTE | D8: EXERCICE N | E8: EXERCICE N-1
A9: GA | B9: Immobilisations (1) | C9: 1 | D9: =SUMIF('BALANCE N'!$A$2:$A$50,"2*",'BALANCE N'!$F$2:$F$50)-SUMIF('BALANCE N'!$A$2:$A$50,"2*",'BALANCE N'!$G$2:$G$50)
A10: GB | B10: Stocks | C10: 2 | D10: =SUMIF('BALANCE N'!$A$2:$A$50,"3*",'BALANCE N'!$F$2:$F$50)-SUMIF('BALANCE N'!$A$2:$A$50,"3*",'BALANCE N'!$G$2:$G$50)
A11: GC | B11: Adhérents, clients-usagers et autres débiteurs | C11: 3 | D11: =SUMIF('BALANCE N'!$A$2:$A$50,"4*",'BALANCE N'!$F$2:$F$50)-(SUMIF('BALANCE N'!$A$2:$A$50,"49*",'BALANCE N'!$G$2:$G$50)+SUMIF('BALANCE N'!$A$2:$A$50,"590*",'BALANCE N'!$G$2:$G$50)+SUMIF('BALANCE N'!$A$2:$A$50,"591*",'BALANCE N'!$G$2:$G$50))+(SUMIF('BALANCE N'!$A$2:$A$50,"50*",'BALANCE N'!$F$2:$F$50)-SUMIF('BALANCE N'!$A$2:$A$50,"50*",'BALANCE N'!$G$2:$G$50)+SUMIF('BALANCE N'!$A$2:$A$50,"51*",'BALANCE N'!$F$2:$F$50)-SUMIF('BALANCE N'!$A$2:$A$50,"51*",'BALANCE N'!$G$2:$G$50))
A12: GD | B12: Caisse | C12: 4 | D12: =SUMIF('BALANCE N'!$A$2:$A$50,"57*",'BALANCE N'!$F$2:$F$50)-SUMIF('BALANCE N'!$A$2:$A$50,"57*",'BALANCE N'!$G$2:$G$50)
A13: GE | B13: Banque (en + ou en -) | C13: 4 | D13: =SUMIF('BALANCE N'!$A$2:$A$50,"53*",'BALANCE N'!$F$2:$F$50)-SUMIF('BALANCE N'!$A$2:$A$50,"53*",'BALANCE N'!$G$2:$G$50)+SUMIF('BALANCE N'!$A$2:$A$50,"56*",'BALANCE N'!$F$2:$F$50)-SUMIF('BALANCE N'!$A$2:$A$50,"56*",'BALANCE N'!$G$2:$G$50)+SUMIF('BALANCE N'!$A$2:$A$50,"58*",'BALANCE N'!$F$2:$F$50)-SUMIF('BALANCE N'!$A$2:$A$50,"58*",'BALANCE N'!$G$2:$G$50)+SUMIF('BALANCE N'!$A$2:$A$50,"52*",'BALANCE N'!$F$2:$F$50)-SUMIF('BALANCE N'!$A$2:$A$50,"52*",'BALANCE N'!$G$2:$G$50)+SUMIF('BALANCE N'!$A$2:$A$50,"55*",'BALANCE N'!$F$2:$F$50)-SUMIF('BALANCE N'!$A$2:$A$50,"55*",'BALANCE N'!$G$2:$G$50)-(SUMIF('BALANCE N'!$A$2:$A$50,"593*",'BALANCE N'!$G$2:$G$50)+SUMIF('BALANCE N'!$A$2:$A$50,"595*",'BALANCE N'!$G$2:$G$50)+SUMIF('BALANCE N'!$A$2:$A$50,"592*",'BALANCE N'!$G$2:$G$50))
A14: GZ | B14: TOTAL ACTIF | D14: =SUM(D9:D13)
A16: (1) à faire figurer sur l'état de situation si montants significatifs (Partie 4, ch. 4).

Sheet Bilan-Passif
A1: - 5 -
D2: BILAN SYCEBNL - SMT PAGE 2/2
A3: Dénomination sociale : CLUB SOLIDARITE QUARTIER
A4: Adresse : | D4: Sigle usuel :
A5: N° de compte contribuable (NCC) : ASBL-0093 | C5: Exercice clos le 31-12-2025 | D5: Durée (en mois) : 12
A6: N° de télédéclarant (NTD) :
A7: BILAN
A8: REF | B8: PASSIF | C8: NOTE | D8: EXERCICE N | E8: EXERCICE N-1
A9: HA | B9: Dotations | C9: 5 | D9: =SUMIF('BALANCE N'!$A$2:$A$50,"10*",'BALANCE N'!$G$2:$G$50)-SUMIF('BALANCE N'!$A$2:$A$50,"10*",'BALANCE N'!$F$2:$F$50)
A10: HB | B10: Résultat net de l'exercice (en + ou en -) | D10: ='Résultat'!D24+(SUMIF('BALANCE N'!$A$2:$A$50,"13*",'BALANCE N'!$G$2:$G$50)-SUMIF('BALANCE N'!$A$2:$A$50,"13*",'BALANCE N'!$F$2:$F$50))
A11: HC | B11: Autres fonds propres | D11: =SUMIF('BALANCE N'!$A$2:$A$50,"17*",'BALANCE N'!$G$2:$G$50)-SUMIF('BALANCE N'!$A$2:$A$50,"17*",'BALANCE N'!$F$2:$F$50)+SUMIF('BALANCE N'!$A$2:$A$50,"19*",'BALANCE N'!$G$2:$G$50)-SUMIF('BALANCE N'!$A$2:$A$50,"19*",'BALANCE N'!$F$2:$F$50)+SUMIF('BALANCE N'!$A$2:$A$50,"12*",'BALANCE N'!$G$2:$G$50)-SUMIF('BALANCE N'!$A$2:$A$50,"12*",'BALANCE N'!$F$2:$F$50)+SUMIF('BALANCE N'!$A$2:$A$50,"16*",'BALANCE N'!$G$2:$G$50)-SUMIF('BALANCE N'!$A$2:$A$50,"16*",'BALANCE N'!$F$2:$F$50)+SUMIF('BALANCE N'!$A$2:$A$50,"11*",'BALANCE N'!$G$2:$G$50)-SUMIF('BALANCE N'!$A$2:$A$50,"11*",'BALANCE N'!$F$2:$F$50)+SUMIF('BALANCE N'!$A$2:$A$50,"14*",'BALANCE N'!$G$2:$G$50)-SUMIF('BALANCE N'!$A$2:$A$50,"14*",'BALANCE N'!$F$2:$F$50)+SUMIF('BALANCE N'!$A$2:$A$50,"15*",'BALANCE N'!$G$2:$G$50)-SUMIF('BALANCE N'!$A$2:$A$50,"15*",'BALANCE N'!$F$2:$F$50)+SUMIF('BALANCE N'!$A$2:$A$50,"18*",'BALANCE N'!$G$2:$G$50)-SUMIF('BALANCE N'!$A$2:$A$50,"18*",'BALANCE N'!$F$2:$F$50)
A12: HD | B12: Fournisseurs et autres créditeurs | C12: 3 | D12: =SUMIF('BALANCE N'!$A$2:$A$50,"4*",'BALANCE N'!$G$2:$G$50)-SUMIF('BALANCE N'!$A$2:$A$50,"49*",'BALANCE N'!$G$2:$G$50)+(SUMIF('BALANCE N'!$A$2:$A$50,"599*",'BALANCE N'!$G$2:$G$50)-SUMIF('BALANCE N'!$A$2:$A$50,"599*",'BALANCE N'!$F$2:$F$50))
A13: HZ | B13: TOTAL PASSIF | D13: =SUM(D9:D12)
A15: Autres fonds propres : réserves, report à nouveau, subventions, fonds affectés/reportés, emprunts et provisions (le modèle SMT ne les distingue pas).

Sheet Résultat
A1: - 6 -
D2: COMPTE DE RESULTAT SYCEBNL - SMT
A3: Dénomination sociale : CLUB SOLIDARITE QUARTIER
A4: Adresse : | D4: Sigle usuel :
A5: N° de compte contribuable (NCC) : ASBL-0093 | C5: Exercice clos le 31-12-2025 | D5: Durée (en mois) : 12
A6: N° de télédéclarant (NTD) :
A7: COMPTE DE RESULTAT
A8: REF | B8: LIBELLES | C8: NOTE | D8: EXERCICE N | E8: EXERCICE N-1
A9: KA | B9: Revenus encaissés | C9: 4 | D9: =SUMIF('BALANCE N'!$A$2:$A$50,"70*",'BALANCE N'!$G$2:$G$50)-SUMIF('BALANCE N'!$A$2:$A$50,"70*",'BALANCE N'!$F$2:$F$50)
A10: KB | B10: Autres recettes sur activités | C10: 4 | D10: =SUMIF('BALANCE N'!$A$2:$A$50,"84*",'BALANCE N'!$G$2:$G$50)-SUMIF('BALANCE N'!$A$2:$A$50,"84*",'BALANCE N'!$F$2:$F$50)+SUMIF('BALANCE N'!$A$2:$A$50,"72*",'BALANCE N'!$G$2:$G$50)-SUMIF('BALANCE N'!$A$2:$A$50,"72*",'BALANCE N'!$F$2:$F$50)+SUMIF('BALANCE N'!$A$2:$A$50,"71*",'BALANCE N'!$G$2:$G$50)-SUMIF('BALANCE N'!$A$2:$A$50,"71*",'BALANCE N'!$F$2:$F$50)+SUMIF('BALANCE N'!$A$2:$A$50,"77*",'BALANCE N'!$G$2:$G$50)-SUMIF('BALANCE N'!$A$2:$A$50,"77*",'BALANCE N'!$F$2:$F$50)+SUMIF('BALANCE N'!$A$2:$A$50,"79*",'BALANCE N'!$G$2:$G$50)-SUMIF('BALANCE N'!$A$2:$A$50,"79*",'BALANCE N'!$F$2:$F$50)+SUMIF('BALANCE N'!$A$2:$A$50,"78*",'BALANCE N'!$G$2:$G$50)-SUMIF('BALANCE N'!$A$2:$A$50,"78*",'BALANCE N'!$F$2:$F$50)+SUMIF('BALANCE N'!$A$2:$A$50,"82*",'BALANCE N'!$G$2:$G$50)-SUMIF('BALANCE N'!$A$2:$A$50,"82*",'BALANCE N'!$F$2:$F$50)+SUMIF('BALANCE N'!$A$2:$A$50,"88*",'BALANCE N'!$G$2:$G$50)-SUMIF('BALANCE N'!$A$2:$A$50,"88*",'BALANCE N'!$F$2:$F$50)+SUMIF('BALANCE N'!$A$2:$A$50,"86*",'BALANCE N'!$G$2:$G$50)-SUMIF('BALANCE N'!$A$2:$A$50,"86*",'BALANCE N'!$F$2:$F$50)+SUMIF('BALANCE N'!$A$2:$A$50,"75*",'BALANCE N'!$G$2:$G$50)-SUMIF('BALANCE N'!$A$2:$A$50,"75*",'BALANCE N'!$F$2:$F$50)
A11: KX | B11: TOTAL DES REVENUS ENCAISSÉS (A) | D11: =D9+D10
A12: JA | B12: Dépenses sur achats | C12: 4 | D12: =SUMIF('BALANCE N'!$A$2:$A$50,"60*",'BALANCE N'!$F$2:$F$50)-SUMIF('BALANCE N'!$A$2:$A$50,"60*",'BALANCE N'!$G$2:$G$50)-SUMIF('BALANCE N'!$A$2:$A$50,"603*",'BALANCE N'!$F$2:$F$50)+SUMIF('BALANCE N'!$A$2:$A$50,"603*",'BALANCE N'!$G$2:$G$50)
A13: JB | B13: Dépenses sur loyers | C13: 4 | D13: =SUMIF('BALANCE N'!$A$2:$A$50,"622*",'BALANCE N'!$F$2:$F$50)-SUMIF('BALANCE N'!$A$2:$A$50,"622*",'BALANCE N'!$G$2:$G$50)
A14: JC | B14: Dépenses sur salaires | C14: 4 | D14: =SUMIF('BALANCE N'!$A$2:$A$50,"66*",'BALANCE N'!$F$2:$F$50)-SUMIF('BALANCE N'!$A$2:$A$50,"66*",'BALANCE N'!$G$2:$G$50)
A15: JD | B15: Dépenses sur impôts et taxes | C15: 4 | D15: =SUMIF('BALANCE N'!$A$2:$A$50,"64*",'BALANCE N'!$F$2:$F$50)-SUMIF('BALANCE N'!$A$2:$A$50,"64*",'BALANCE N'!$G$2:$G$50)
A16: JE | B16: Charges d'intérêts | C16: 4 | D16: =SUMIF('BALANCE N'!$A$2:$A$50,"67*",'BALANCE N'!$F$2:$F$50)-SUMIF('BALANCE N'!$A$2:$A$50,"67*",'BALANCE N'!$G$2:$G$50)
A17: JF | B17: Autres dépenses sur activités | C17: 4 | D17: =SUMIF('BALANCE N'!$A$2:$A$50,"61*",'BALANCE N'!$F$2:$F$50)-SUMIF('BALANCE N'!$A$2:$A$50,"61*",'BALANCE N'!$G$2:$G$50)+SUMIF('BALANCE N'!$A$2:$A$50,"62*",'BALANCE N'!$F$2:$F$50)-SUMIF('BALANCE N'!$A$2:$A$50,"62*",'BALANCE N'!$G$2:$G$50)-SUMIF('BALANCE N'!$A$2:$A$50,"81*",'BALANCE N'!$F$2:$F$50)+SUMIF('BALANCE N'!$A$2:$A$50,"81*",'BALANCE N'!$G$2:$G$50)-SUMIF('BALANCE N'!$A$2:$A$50,"65*",'BALANCE N'!$F$2:$F$50)+SUMIF('BALANCE N'!$A$2:$A$50,"65*",'BALANCE N'!$G$2:$G$50)-SUMIF('BALANCE N'!$A$2:$A$50,"63*",'BALANCE N'!$F$2:$F$50)+SUMIF('BALANCE N'!$A$2:$A$50,"63*",'BALANCE N'!$G$2:$G$50)-SUMIF('BALANCE N'!$A$2:$A$50,"83*",'BALANCE N'!$F$2:$F$50)+SUMIF('BALANCE N'!$A$2:$A$50,"83*",'BALANCE N'!$G$2:$G$50)-SUMIF('BALANCE N'!$A$2:$A$50,"87*",'BALANCE N'!$F$2:$F$50)+SUMIF('BALANCE N'!$A$2:$A$50,"87*",'BALANCE N'!$G$2:$G$50)-SUMIF('BALANCE N'!$A$2:$A$50,"622*",'BALANCE N'!$F$2:$F$50)+SUMIF('BALANCE N'!$A$2:$A$50,"622*",'BALANCE N'!$G$2:$G$50)
A18: JX | B18: TOTAL DÉPENSES SUR CHARGES (B) | D18: =D12+D13+D14+D15+D16+D17
A19: KZ | B19: SOLDE : excédent (+) ou insuffisance (-) de recettes (C = A - B) | D19: =D11-D18
A20: VA | B20: + Variations des stocks sur les achats [N - (N-1)] | C20: 2 | D20: =(SUMIF('BALANCE N'!$A$2:$A$50,"603*",'BALANCE N'!$G$2:$G$50)-SUMIF('BALANCE N'!$A$2:$A$50,"603*",'BALANCE N'!$F$2:$F$50))+(SUMIF('BALANCE N'!$A$2:$A$50,"73*",'BALANCE N'!$G$2:$G$50)-SUMIF('BALANCE N'!$A$2:$A$50,"73*",'BALANCE N'!$F$2:$F$50))
A21: VB | B21: + Variation des créances [N - (N-1)] - à saisir depuis la Note 3 | C21: 3 | D21: 0
A22: VC | B22: - Variation des dettes d'exploitation [N - (N-1)] - à saisir depuis la Note 3 | C22: 3 | D22: 0
A23: JG | B23: DOTATIONS AUX AMORTISSEMENTS | D23: =SUMIF('BALANCE N'!$A$2:$A$50,"69*",'BALANCE N'!$F$2:$F$50)-SUMIF('BALANCE N'!$A$2:$A$50,"69*",'BALANCE N'!$G$2:$G$50)+SUMIF('BALANCE N'!$A$2:$A$50,"85*",'BALANCE N'!$F$2:$F$50)-SUMIF('BALANCE N'!$A$2:$A$50,"85*",'BALANCE N'!$G$2:$G$50)+SUMIF('BALANCE N'!$A$2:$A$50,"68*",'BALANCE N'!$F$2:$F$50)-SUMIF('BALANCE N'!$A$2:$A$50,"68*",'BALANCE N'!$G$2:$G$50)
A24: KZC | B24: RÉSULTAT NET DE L'EXERCICE | D24: =D19+D20+D21-D22-D23
A26: Les variations de créances (VB) et de dettes (VC) se saisissent depuis l'état extra-comptable de la Note 3 ; si la balance porte une classe 4 mouvementée (base engagement), les laisser à zéro.

Sheet NOTES ANNEXES
A1: - 7 -
I2: NOTES ANNEXES
A3: Dénomination sociale : CLUB SOLIDARITE QUARTIER
A4: Adresse : | I4: Sigle usuel :
A5: N° de compte contribuable (NCC) : ASBL-0093 | G5: Exercice clos le 31-12-2025 | I5: Durée (en mois) : 12
A6: N° de télédéclarant (NTD) :
A7: FICHE RECAPITULATIVE NOTES ANNEXES PRESENTEES (1)
A8: NOTES | B8: INTITULES | I8: A (2) | J8: N/A (2)
A9: Partie 1 : Notes sur le bilan
A10: Note 1 | B10: Tableau d'acquisition et de suivi du matériel, du mobilier et des cautions
A11: Note 2 | B11: État des stocks
A12: Note 3 | B12: État des créances et des dettes non échues
A13: Note 5 | B13: Dotations
A14: Partie 2 : Notes sur le compte de résultat
A15: Note 4 | B15: Journal unique de trésorerie
A17: (1) Les notes non documentées ne doivent pas être jointes aux états financiers ; dans une note, les lignes non chiffrées doivent être supprimées.
A18: (2) A : applicable ; N/A : non applicable. Cocher la colonne correspondante pour chaque note.

Sheet NOTE 1 IMMOBILISATIONS
A1: - 8 -
F2: NOTE 1 SYCEBNL - SMT
A3: Dénomination sociale : CLUB SOLIDARITE QUARTIER
A4: Adresse : | F4: Sigle usuel :
A5: N° de compte contribuable (NCC) : ASBL-0093 | D5: Exercice clos le 31-12-2025 | F5: Durée (en mois) : 12
A6: N° de télédéclarant (NTD) :
A7: NOTE 1 : TABLEAU D'ACQUISITION ET DE SUIVI DU MATERIEL, DU MOBILIER ET AUTRES IMMOBILISATIONS
A8: Date | B8: Désignation | C8: Montant | D8: Date d'acquisition | E8: Durée d'utilité | F8: Date de sortie | G8: Prix de cession
B9: 2441 - Matériel et mobilier de bureau | C9: =SUMIF('BALANCE N'!$A$2:$A$50,"2441*",'BALANCE N'!$F$2:$F$50)-SUMIF('BALANCE N'!$A$2:$A$50,"2441*",'BALANCE N'!$G$2:$G$50)
B10: TOTAL IMMOBILISATIONS BRUTES | C10: =SUM(C9:C9)
B11: Amortissements et dépréciations cumulés (28/29) | C11: =SUMIF('BALANCE N'!$A$2:$A$50,"29*",'BALANCE N'!$G$2:$G$50)-SUMIF('BALANCE N'!$A$2:$A$50,"29*",'BALANCE N'!$F$2:$F$50)+SUMIF('BALANCE N'!$A$2:$A$50,"28*",'BALANCE N'!$G$2:$G$50)-SUMIF('BALANCE N'!$A$2:$A$50,"28*",'BALANCE N'!$F$2:$F$50)
B12: VALEUR NETTE (= poste GA du bilan) | C12: =C10-C11

Sheet NOTE 2 STOCKS
A1: - 9 -
D2: NOTE 2 SYCEBNL - SMT
A3: Dénomination sociale : CLUB SOLIDARITE QUARTIER
A4: Adresse : | D4: Sigle usuel :
A5: N° de compte contribuable (NCC) : ASBL-0093 | C5: Exercice clos le 31-12-2025 | D5: Durée (en mois) : 12
A6: N° de télédéclarant (NTD) :
A7: NOTE 2 : ETAT DES STOCKS
A8: Référence | B8: Désignation | C8: Quantité | D8: Prix unitaire | E8: Montant
A9: 331 | B9: Matières consommables | E9: =SUMIF('BALANCE N'!$A$2:$A$50,"331*",'BALANCE N'!$F$2:$F$50)-SUMIF('BALANCE N'!$A$2:$A$50,"331*",'BALANCE N'!$G$2:$G$50)
B12: VALEUR DU STOCK FINAL | E12: =SUMIF('BALANCE N'!$A$2:$A$50,"3*",'BALANCE N'!$F$2:$F$50)-SUMIF('BALANCE N'!$A$2:$A$50,"3*",'BALANCE N'!$G$2:$G$50)
B13: VALEUR DU STOCK INITIAL | E13: 0

Sheet NOTE 3 CREANCES-DETTES
A1: - 10 -
E2: NOTE 3 SYCEBNL - SMT
A3: Dénomination sociale : CLUB SOLIDARITE QUARTIER
A4: Adresse : | E4: Sigle usuel :
A5: N° de compte contribuable (NCC) : ASBL-0093 | C5: Exercice clos le 31-12-2025 | E5: Durée (en mois) : 12
A6: N° de télédéclarant (NTD) :
A7: NOTE 3 : ETAT DES CREANCES ET DES DETTES NON ECHUES
A8: CRÉANCES - nom des clients-usagers et autres débiteurs
A9: Date | B9: Nom | C9: Montant au 31/12/N | D9: Montant au 01/01/N | E9: Variation en valeur | F9: Variation en %
E10: =C10-D10 | F10: =IF(D10=0,"",(C10-D10)/D10)
E11: =C11-D11 | F11: =IF(D11=0,"",(C11-D11)/D11)
E12: =C12-D12 | F12: =IF(D12=0,"",(C12-D12)/D12)
E13: =C13-D13 | F13: =IF(D13=0,"",(C13-D13)/D13)
E14: =C14-D14 | F14: =IF(D14=0,"",(C14-D14)/D14)
E15: =C15-D15 | F15: =IF(D15=0,"",(C15-D15)/D15)
B16: TOTAL DES CRÉANCES | C16: =SUM(C10:C15) | D16: =SUM(D10:D15) | E16: =SUM(E10:E15)
B17: Rappel balance (classe 4, soldes débiteurs) - contrôle | C17: =SUMIF('BALANCE N'!$A$2:$A$50,"4*",'BALANCE N'!$F$2:$F$50) | D17: =0
A20: DETTES - nom des fournisseurs et autres créditeurs
A21: Date | B21: Nom | C21: Montant au 31/12/N | D21: Montant au 01/01/N | E21: Variation en valeur | F21: Variation en %
E22: =C22-D22 | F22: =IF(D22=0,"",(C22-D22)/D22)
E23: =C23-D23 | F23: =IF(D23=0,"",(C23-D23)/D23)
E24: =C24-D24 | F24: =IF(D24=0,"",(C24-D24)/D24)
E25: =C25-D25 | F25: =IF(D25=0,"",(C25-D25)/D25)
E26: =C26-D26 | F26: =IF(D26=0,"",(C26-D26)/D26)
E27: =C27-D27 | F27: =IF(D27=0,"",(C27-D27)/D27)
B28: TOTAL DES DETTES | C28: =SUM(C22:C27) | D28: =SUM(D22:D27) | E28: =SUM(E22:E27)
B29: Rappel balance (classe 4, soldes créditeurs) - contrôle | C29: =SUMIF('BALANCE N'!$A$2:$A$50,"4*",'BALANCE N'!$G$2:$G$50) | D29: =0
A32: Reporter la variation des créances en VB et celle des dettes en VC du compte de résultat.

Sheet NOTE 4 JOURNAL TRESORERIE
A1: - 11 -
J2: NOTE 4 SYCEBNL - SMT
A3: Dénomination sociale : CLUB SOLIDARITE QUARTIER
A4: Adresse : | J4: Sigle usuel :
A5: N° de compte contribuable (NCC) : ASBL-0093 | H5: Exercice clos le 31-12-2025 | J5: Durée (en mois) : 12
A6: N° de télédéclarant (NTD) :
A7: NOTE 4 : JOURNAL UNIQUE DE TRESORERIE
A8: Dates | B8: Libellés | C8: Recettes | D8: Dépenses | E8: Solde | F8: Vent. recettes : Cotisations | G8: Subventions | H8: Autres | I8: Vent. dépenses : Achats de biens liés à l'activité | J8: Autres achats / Transport / Services extérieurs | K8: Salaires / Autres
B9: Report à nouveau
E10: =E9+C10-D10
E11: =E10+C11-D11
E12: =E11+C12-D12
E13: =E12+C13-D13
E14: =E13+C14-D14
E15: =E14+C15-D15
E16: =E15+C16-D16
E17: =E16+C17-D17
E18: =E17+C18-D18
E19: =E18+C19-D19
E20: =E19+C20-D20
E21: =E20+C21-D21
... E23: =E22+C23-D23
B24: Solde à reporter | E24: =E23

Sheet NOTE 5 DOTATIONS
A1: - 12 -
D2: NOTE 5 SYCEBNL - SMT
A3: Dénomination sociale : CLUB SOLIDARITE QUARTIER
A4: Adresse : | D4: Sigle usuel :
A5: N° de compte contribuable (NCC) : ASBL-0093 | C5: Exercice clos le 31-12-2025 | D5: Durée (en mois) : 12
A6: N° de télédéclarant (NTD) :
A7: NOTE 5 : DOTATION
A8: Nom et prénoms des membres | B8: Nationalité | C8: Montant | D8: Avec / sans droit d'entrée
A9: Dotation non consomptible - rappel balance | C9: =SUMIF('BALANCE N'!$A$2:$A$50,"101*",'BALANCE N'!$G$2:$G$50)-SUMIF('BALANCE N'!$A$2:$A$50,"101*",'BALANCE N'!$F$2:$F$50)+SUMIF('BALANCE N'!$A$2:$A$50,"102*",'BALANCE N'!$G$2:$G$50)-SUMIF('BALANCE N'!$A$2:$A$50,"102*",'BALANCE N'!$F$2:$F$50)
A13: Droit d'entrée - rappel balance | C13: =SUMIF('BALANCE N'!$A$2:$A$50,"103*",'BALANCE N'!$G$2:$G$50)-SUMIF('BALANCE N'!$A$2:$A$50,"103*",'BALANCE N'!$F$2:$F$50)
A17: Dotation consomptible - rappel balance | C17: =SUMIF('BALANCE N'!$A$2:$A$50,"104*",'BALANCE N'!$G$2:$G$50)-SUMIF('BALANCE N'!$A$2:$A$50,"104*",'BALANCE N'!$F$2:$F$50)
A21: TOTAL | C21: =C9+C13+C17

Sheet TABLE COMMENTAIRE
A1: TABLE DES COMMENTAIRES | G1: COMMENTAIRES PAGE 1/2
A2: Dénomination sociale : CLUB SOLIDARITE QUARTIER
A3: Adresse : | F3: Sigle usuel :
A4: N° de compte contribuable (NCC) : ASBL-0093 | E4: Exercice clos le 31-12-2025 | G4: Durée (en mois) : 12
A5: N° de télédéclarant (NTD) :
A6: Partie 1 : Notes sur le bilan
A7: Note 1 | B7: Tableau d'acquisition et de suivi du matériel, du mobilier et des cautions
A9: Note 2 | B9: État des stocks
A11: Note 3 | B11: État des créances et des dettes non échues
A13: Note 5 | B13: Dotations
A15: TABLE DES COMMENTAIRES | G15: COMMENTAIRES PAGE 2/2
A16: Dénomination sociale : CLUB SOLIDARITE QUARTIER
A17: Adresse : | F17: Sigle usuel :
A18: N° de compte contribuable (NCC) : ASBL-0093 | E18: Exercice clos le 31-12-2025 | G18: Durée (en mois) : 12
A19: N° de télédéclarant (NTD) :
A20: Partie 2 : Notes sur le compte de résultat
A21: Note 4 | B21: Journal unique de trésorerie

Sheet CONTROLES
A1: Contrôle | B1: Valeur | C1: Attendu
A2: Total solde débit balance | B2: =SUM('BALANCE N'!F2:F18)
A3: Total solde crédit balance | B3: =SUM('BALANCE N'!G2:G18)
A4: Écart balance (doit être 0) | B4: =B2-B3 | C4: 0
A5: Total actif (GZ) | B5: ='Bilan-Actif'!D14
A6: Total passif (HZ) | B6: ='Bilan-Passif'!D13
A7: Écart actif - passif (doit être 0) | B7: =B5-B6 | C7: 0
A8: Résultat net (compte de résultat, KZC) | B8: ='Résultat'!D24

Sheet ANOMALIES
A1: Gravité | B1: Compte | C1: Intitulé | D1: Problème | E1: Solution proposée
A2: INFO | C2: Classe 4 | D2: La balance porte des comptes de tiers : recettes/dépenses incluent des montants non encaissés/décaissés (base engagement). | E2: Laisser VB/VC à zéro dans ce cas ; ne les servir que pour une balance de trésorerie pure (Note 3).
A3: INFO | C3: SMT - seuil | D3: Vérifier l'assujettissement : ressources annuelles ≤ 30 M FCFA (Acte uniforme SYCEBNL, art. 5-6). | E3: Au-delà, monter le jeu du Système normal (monter_etats_sycebnl.py) ou des projets (monter_projets.py).
