Workbook

Sheet BALANCE N
A1: Compte | B1: Intitulé | C1: Préfixe 2 | D1: Préfixe 3 | E1: Préfixe 4 | F1: Solde final débit | G1: Solde final crédit | J1: Poste(s) d'affectation
A2: 2441 | B2: Matériel et mobilier de bureau | C2: 24 | D2: 244 | E2: 2441 | F2: 4000000 | G2: 0 | J2: AD
A3: 2451 | B3: Matériel de transport automobile | C3: 24 | D3: 245 | E3: 2451 | F3: 8000000 | G3: 0 | J3: AE
A4: 2751 | B4: Dépôts et cautionnements - loyers d'avance | C4: 27 | D4: 275 | E4: 2751 | F4: 500000 | G4: 0 | J4: AG
A5: 521 | B5: Banques locales | C5: 52 | D5: 521 | E5: 521 | F5: 2450000 | G5: 0 | J5: BW, DW
A6: 571 | B6: Caisse | C6: 57 | D6: 571 | E6: 571 | F6: 200000 | G6: 0 | J6: BW
A7: 162 | B7: Fonds affectés aux investissements - bailleurs | C7: 16 | D7: 162 | E7: 162 | F7: 0 | G7: 12500000 | J7: CA
A8: 462 | B8: Bailleurs - fonds d'administration | C8: 46 | D8: 462 | E8: 462 | F8: 0 | G8: 1200000 | J8: DF
A9: 4011 | B9: Fournisseurs | C9: 40 | D9: 401 | E9: 4011 | F9: 0 | G9: 800000 | J9: DG
A10: 422 | B10: Personnel, rémunérations dues | C10: 42 | D10: 422 | E10: 422 | F10: 0 | G10: 300000 | J10: BE, DH
A11: 431 | B11: Sécurité sociale | C11: 43 | D11: 431 | E11: 431 | F11: 0 | G11: 150000 | J11: BE, DH
A12: 447 | B12: État, impôts retenus à la source | C12: 44 | D12: 447 | E12: 447 | F12: 0 | G12: 100000 | J12: BE, DH
A13: 601 | B13: Achats de biens et services liés à l'activité | C13: 60 | D13: 601 | E13: 601 | F13: 2500000 | G13: 0 | J13: TA
... A23: 771 | B23: Intérêts de prêts et créances diverses | C23: 77 | D23: 771 | E23: 771 | F23: 0 | G23: 50000 | J23: RD

Sheet BALANCE N-1
A1: Compte | B1: Intitulé | C1: Préfixe 2 | D1: Préfixe 3 | E1: Préfixe 4 | F1: Solde final débit | G1: Solde final crédit | J1: Poste(s) d'affectation
A2: 2441 | B2: Matériel et mobilier de bureau | C2: 24 | D2: 244 | E2: 2441 | F2: 4000000 | G2: 0 | J2: AD
A3: 2451 | B3: Matériel de transport automobile | C3: 24 | D3: 245 | E3: 2451 | F3: 5000000 | G3: 0 | J3: AE
A4: 2751 | B4: Dépôts et cautionnements - loyers d'avance | C4: 27 | D4: 275 | E4: 2751 | F4: 500000 | G4: 0 | J4: AG
A5: 521 | B5: Banques locales | C5: 52 | D5: 521 | E5: 521 | F5: 1800000 | G5: 0 | J5: BW, DW
A6: 571 | B6: Caisse | C6: 57 | D6: 571 | E6: 571 | F6: 100000 | G6: 0 | J6: BW
A7: 162 | B7: Fonds affectés aux investissements - bailleurs | C7: 16 | D7: 162 | E7: 162 | F7: 0 | G7: 10000000 | J7: CA
A8: 462 | B8: Bailleurs - fonds d'administration | C8: 46 | D8: 462 | E8: 462 | F8: 0 | G8: 700000 | J8: DF
A9: 4011 | B9: Fournisseurs | C9: 40 | D9: 401 | E9: 4011 | F9: 0 | G9: 500000 | J9: DG
A10: 422 | B10: Personnel, rémunérations dues | C10: 42 | D10: 422 | E10: 422 | F10: 0 | G10: 150000 | J10: BE, DH
A11: 431 | B11: Sécurité sociale | C11: 43 | D11: 431 | E11: 431 | F11: 0 | G11: 50000 | J11: BE, DH

Sheet CONTROLE BALANCE
A1: EQUILIBRE DE LA BALANCE
A2: BALANCE N | B2: Mouvements Débit | C2: Mouvements Crédit | D2: Solde Final Débit | E2: Solde Final Crédit
B3: =SUM('BALANCE N'!H2:H23) | C3: =SUM('BALANCE N'!I2:I23) | D3: =SUM('BALANCE N'!F2:F23) | E3: =SUM('BALANCE N'!G2:G23)
B4: =IF(ROUND(B3-C3,0)=0,"Equilibre","Déséquilibre : écart de "&TEXT(B3-C3,"#,##0")) | D4: =IF(ROUND(D3-E3,0)=0,"Equilibre","Déséquilibre : écart de "&TEXT(D3-E3,"#,##0"))
A5: BALANCE N-1 | B5: Mouvements Débit | C5: Mouvements Crédit | D5: Solde Final Débit | E5: Solde Final Crédit
B6: =SUM('BALANCE N-1'!H2:H11) | C6: =SUM('BALANCE N-1'!I2:I11) | D6: =SUM('BALANCE N-1'!F2:F11) | E6: =SUM('BALANCE N-1'!G2:G11)
B7: =IF(ROUND(B6-C6,0)=0,"Equilibre","Déséquilibre : écart de "&TEXT(B6-C6,"#,##0")) | D7: =IF(ROUND(D6-E6,0)=0,"Equilibre","Déséquilibre : écart de "&TEXT(D6-E6,"#,##0"))

Sheet Couverture
E26: PROJET EAU POTABLE RURALE
E31: LIASSE PROJETS DE DEVELOPPEMENT
E34: Exercice clos le 31-12-2025

Sheet Garde
B12: ETATS FINANCIERS NORMALISES DU SYSTEME COMPTABLE DES ENTITES A BUT NON LUCRATIF (SYCEBNL)
B13: Projets de développement et assimilés
C16: Exercice clos le 31-12-2025 - Durée (en mois) : 12
B20: DESIGNATION DE L'ENTITE
B22: DENOMINATION SOCIALE : | E22: PROJET EAU POTABLE RURALE
B24: SIGLE USUEL : | E24: PEPR
B26: ADRESSE COMPLETE :
B28: N° de compte contribuable (NCC) : | E28: PD-2023-017
B30: N° de télédéclarant (NTD) :
B32: PROJETS DE DEVELOPPEMENT
B34: Documents déposés | H34: Réservé à l'administration
B35: Fiche d'identification et renseignements divers | F35: X | H35: Date de dépôt
B36: Tableau emplois-ressources | F36: X
B37: Tableau d'exécution budgétaire | F37: X
B38: Tableau de réconciliation de trésorerie | F38: X
B39: Bilan (actif et passif) | F39: X | H39: Nom de l'agent ayant réceptionné le dépôt
B40: Compte d'exploitation | F40: X
B41: Notes annexes | F41: X
H43: Signature de l'agent et cachet du service
B48: Nombre de pages déposées par exemplaire :
B49: Nombre d'exemplaires déposés :

Sheet Fiche 1
A1: - 1 -
I2: FICHE 1
A3: Dénomination sociale : PROJET EAU POTABLE RURALE
A4: Adresse : | I4: Sigle usuel : | J4: PEPR
A5: N° de compte contribuable (NCC) : PD-2023-017 | G5: Exercice clos le 31-12-2025 | I5: Durée (en mois) : 12
A6: N° de télédéclarant (NTD) :
A7: FICHE D'IDENTIFICATION ET RENSEIGNEMENTS DIVERS
A8: SYCEBNL - Projets de développement et assimilés
A10: ZA | B10: EXERCICE COMPTABLE | G10: DU : 01-01-2025 AU : 31-12-2025
A11: ZB | B11: DATE D'ARRETE EFFECTIF DES COMPTES
A12: ZC | B12: EXERCICE PRECEDENT CLOS LE
A13: ZD | B13: DUREE DE L'EXERCICE PRECEDENT (EN MOIS)
A14: ZE | B14: N° REGISTRE (RCCM, F92, CONVENTION...) ET GREFFE
A15: ZF | B15: N° REPERTOIRE DES ENTITES
A16: ZG | B16: N° DE CAISSE SOCIALE
A17: ZH | B17: N° CODE IMPORTATEUR
A18: ZI | B18: CODE ACTIVITE PRINCIPALE
A19: ZJ | B19: DESIGNATION DE L'ENTITE ET SIGLE | G19: PROJET EAU POTABLE RURALE (PEPR)
A20: ZK | B20: N° DE TELEPHONE, ADRESSE E-MAIL, BOITE POSTALE, VILLE
A21: ZL | B21: ADRESSE GEOGRAPHIQUE COMPLETE (IMMEUBLE, RUE, QUARTIER, VILLE, PAYS)
A22: ZM | B22: DESIGNATION PRECISE DE L'ACTIVITE PRINCIPALE EXERCEE
A23: ZN | B23: % DE CAPACITE DE PRODUCTION UTILE
A24: ZO | B24: NOM, ADRESSE, TELEPHONE, E-MAIL ET QUALITE DE LA PERSONNE A CONTACTER EN CAS DE DEMANDE
A25: ZP | B25: NOM, ADRESSE, TELEPHONE ET E-MAIL DU SALARIE OU DU PROFESSIONNEL COMPTABLE AYANT ETABLI LES ETATS FINANCIERS
A26: ZQ | B26: NOM, ADRESSE, TELEPHONE, E-MAIL ET N° D'INSCRIPTION A L'ORDRE DE L'EXPERT-COMPTABLE AYANT DELIVRE L'ATTESTATION DE VISA
A27: ZR | B27: NOM, ADRESSE, TELEPHONE, E-MAIL ET N° D'INSCRIPTION DU COMMISSAIRE AUX COMPTES, LE CAS ECHEANT
A28: ZS | B28: ETATS FINANCIERS APPROUVES PAR L'ORGANE COMPETENT (OUI / NON)
A29: ZT | B29: NOM DU SIGNATAIRE DES ETATS FINANCIERS
A30: ZU | B30: QUALITE DU SIGNATAIRE DES ETATS FINANCIERS
A31: ZV | B31: DATE DE SIGNATURE
A32: ZW | B32: DOMICILIATIONS BANCAIRES (BANQUE ET NUMERO DE COMPTE)
B34: Signature

Sheet Fiche 2
A1: - 2 -
I2: FICHE 2
A3: Dénomination sociale : PROJET EAU POTABLE RURALE
A4: Adresse : | I4: Sigle usuel : | J4: PEPR
A5: N° de compte contribuable (NCC) : PD-2023-017 | G5: Exercice clos le 31-12-2025 | I5: Durée (en mois) : 12
A6: N° de télédéclarant (NTD) :
A7: FICHE D'IDENTIFICATION ET RENSEIGNEMENTS DIVERS
A8: EQUIPE DU PROJET
A10: Nom et Prénoms | C10: Nationalité | D10: Autres nationalités (à préciser) (2) | E10: Qualité | F10: N° d'identification fiscale | H10: Adresse (BP, ville, pays, adresse géographique et adresse e-mail)
A32: (2) Mentionner les autres nationalités le cas échéant.

Sheet Emplois-Ressources
A1: - 3 -
D2: EMPLOIS-RESSOURCES PROJETS DE DEVELOPPEMENT
A3: Dénomination sociale : PROJET EAU POTABLE RURALE
A4: Adresse : | D4: Sigle usuel : | E4: PEPR
A5: N° de compte contribuable (NCC) : PD-2023-017 | C5: Exercice clos le 31-12-2025 | D5: Durée (en mois) : 12
A6: N° de télédéclarant (NTD) :
A7: TABLEAU EMPLOIS-RESSOURCES
A8: REF | B8: DESIGNATION | C8: SOLDE CUMULE DEBUT EXERCICE N | D8: EXERCICE N | E8: SOLDE CUMULE FIN EXERCICE N
A9: FA | B9: Fonds reçus, Bailleurs | D9: =(SUMIF('BALANCE N'!$A$2:$A$50,"162*",'BALANCE N'!$G$2:$G$50)-SUMIF('BALANCE N'!$A$2:$A$50,"162*",'BALANCE N'!$F$2:$F$50)+SUMIF('BALANCE N'!$A$2:$A$50,"462*",'BALANCE N'!$G$2:$G$50)-SUMIF('BALANCE N'!$A$2:$A$50,"462*",'BALANCE N'!$F$2:$F$50))-(SUMIF('BALANCE N-1'!$A$2:$A$50,"162*",'BALANCE N-1'!$G$2:$G$50)-SUMIF('BALANCE N-1'!$A$2:$A$50,"162*",'BALANCE N-1'!$F$2:$F$50)+SUMIF('BALANCE N-1'!$A$2:$A$50,"462*",'BALANCE N-1'!$G$2:$G$50)-SUMIF('BALANCE N-1'!$A$2:$A$50,"462*",'BALANCE N-1'!$F$2:$F$50))+(SUMIF('BALANCE N'!$A$2:$A$50,"702*",'BALANCE N'!$G$2:$G$50)-SUMIF('BALANCE N'!$A$2:$A$50,"702*",'BALANCE N'!$F$2:$F$50)) | E9: =C9+D9
A10: FB | B10: Fonds reçus, Bailleurs (autres)
A11: FC | B11: Fonds contrepartie État | D11: =(SUMIF('BALANCE N'!$A$2:$A$50,"463*",'BALANCE N'!$G$2:$G$50)-SUMIF('BALANCE N'!$A$2:$A$50,"463*",'BALANCE N'!$F$2:$F$50)+SUMIF('BALANCE N'!$A$2:$A$50,"163*",'BALANCE N'!$G$2:$G$50)-SUMIF('BALANCE N'!$A$2:$A$50,"163*",'BALANCE N'!$F$2:$F$50))-(SUMIF('BALANCE N-1'!$A$2:$A$50,"463*",'BALANCE N-1'!$G$2:$G$50)-SUMIF('BALANCE N-1'!$A$2:$A$50,"463*",'BALANCE N-1'!$F$2:$F$50)+SUMIF('BALANCE N-1'!$A$2:$A$50,"163*",'BALANCE N-1'!$G$2:$G$50)-SUMIF('BALANCE N-1'!$A$2:$A$50,"163*",'BALANCE N-1'!$F$2:$F$50)) | E11: =C11+D11
A12: FD | B12: Autres fonds reçus | D12: =(SUMIF('BALANCE N'!$A$2:$A$50,"168*",'BALANCE N'!$G$2:$G$50)-SUMIF('BALANCE N'!$A$2:$A$50,"168*",'BALANCE N'!$F$2:$F$50)+SUMIF('BALANCE N'!$A$2:$A$50,"161*",'BALANCE N'!$G$2:$G$50)-SUMIF('BALANCE N'!$A$2:$A$50,"161*",'BALANCE N'!$F$2:$F$50)+SUMIF('BALANCE N'!$A$2:$A$50,"165*",'BALANCE N'!$G$2:$G$50)-SUMIF('BALANCE N'!$A$2:$A$50,"165*",'BALANCE N'!$F$2:$F$50)+SUMIF('BALANCE N'!$A$2:$A$50,"164*",'BALANCE N'!$G$2:$G$50)-SUMIF('BALANCE N'!$A$2:$A$50,"164*",'BALANCE N'!$F$2:$F$50)+SUMIF('BALANCE N'!$A$2:$A$50,"464*",'BALANCE N'!$G$2:$G$50)-SUMIF('BALANCE N'!$A$2:$A$50,"464*",'BALANCE N'!$F$2:$F$50))-(SUMIF('BALANCE N-1'!$A$2:$A$50,"168*",'BALANCE N-1'!$G$2:$G$50)-SUMIF('BALANCE N-1'!$A$2:$A$50,"168*",'BALANCE N-1'!$F$2:$F$50)+SUMIF('BALANCE N-1'!$A$2:$A$50,"161*",'BALANCE N-1'!$G$2:$G$50)-SUMIF('BALANCE N-1'!$A$2:$A$50,"161*",'BALANCE N-1'!$F$2:$F$50)+SUMIF('BALANCE N-1'!$A$2:$A$50,"165*",'BALANCE N-1'!$G$2:$G$50)-SUMIF('BALANCE N-1'!$A$2:$A$50,"165*",'BALANCE N-1'!$F$2:$F$50)+SUMIF('BALANCE N-1'!$A$2:$A$50,"164*",'BALANCE N-1'!$G$2:$G$50)-SUMIF('BALANCE N-1'!$A$2:$A$50,"164*",'BALANCE N-1'!$F$2:$F$50)+SUMIF('BALANCE N-1'!$A$2:$A$50,"464*",'BALANCE N-1'!$G$2:$G$50)-SUMIF('BALANCE N-1'!$A$2:$A$50,"464*",'BALANCE N-1'!$F$2:$F$50)) | E12: =C12+D12
A13: GR | B13: I. RESSOURCES | C13: =C9+C10+C11+C12 | D13: =D9+D10+D11+D12 | E13: =E9+E10+E11+E12
A14: FE | B14: Immobilisations incorporelles | C14: =SUMIF('BALANCE N-1'!$A$2:$A$50,"21*",'BALANCE N-1'!$F$2:$F$50)-SUMIF('BALANCE N-1'!$A$2:$A$50,"21*",'BALANCE N-1'!$G$2:$G$50)+SUMIF('BALANCE N-1'!$A$2:$A$50,"251*",'BALANCE N-1'!$F$2:$F$50)-SUMIF('BALANCE N-1'!$A$2:$A$50,"251*",'BALANCE N-1'!$G$2:$G$50) | D14: =E14-C14 | E14: =SUMIF('BALANCE N'!$A$2:$A$50,"21*",'BALANCE N'!$F$2:$F$50)-SUMIF('BALANCE N'!$A$2:$A$50,"21*",'BALANCE N'!$G$2:$G$50)+SUMIF('BALANCE N'!$A$2:$A$50,"251*",'BALANCE N'!$F$2:$F$50)-SUMIF('BALANCE N'!$A$2:$A$50,"251*",'BALANCE N'!$G$2:$G$50)
A15: FF | B15: Terrains | C15: =SUMIF('BALANCE N-1'!$A$2:$A$50,"22*",'BALANCE N-1'!$F$2:$F$50)-SUMIF('BALANCE N-1'!$A$2:$A$50,"22*",'BALANCE N-1'!$G$2:$G$50) | D15: =E15-C15 | E15: =SUMIF('BALANCE N'!$A$2:$A$50,"22*",'BALANCE N'!$F$2:$F$50)-SUMIF('BALANCE N'!$A$2:$A$50,"22*",'BALANCE N'!$G$2:$G$50)
A16: FG | B16: Bâtiments | C16: =SUMIF('BALANCE N-1'!$A$2:$A$50,"231*",'BALANCE N-1'!$F$2:$F$50)-SUMIF('BALANCE N-1'!$A$2:$A$50,"231*",'BALANCE N-1'!$G$2:$G$50)+SUMIF('BALANCE N-1'!$A$2:$A$50,"232*",'BALANCE N-1'!$F$2:$F$50)-SUMIF('BALANCE N-1'!$A$2:$A$50,"232*",'BALANCE N-1'!$G$2:$G$50)+SUMIF('BALANCE N-1'!$A$2:$A$50,"233*",'BALANCE N-1'!$F$2:$F$50)-SUMIF('BALANCE N-1'!$A$2:$A$50,"233*",'BALANCE N-1'!$G$2:$G$50)+SUMIF('BALANCE N-1'!$A$2:$A$50,"2393*",'BALANCE N-1'!$F$2:$F$50)-SUMIF('BALANCE N-1'!$A$2:$A$50,"2393*",'BALANCE N-1'!$G$2:$G$50)+SUMIF('BALANCE N-1'!$A$2:$A$50,"2396*",'BALANCE N-1'!$F$2:$F$50)-SUMIF('BALANCE N-1'!$A$2:$A$50,"2396*",'BALANCE N-1'!$G$2:$G$50)+SUMIF('BALANCE N-1'!$A$2:$A$50,"2391*",'BALANCE N-1'!$F$2:$F$50)-SUMIF('BALANCE N-1'!$A$2:$A$50,"2391*",'BALANCE N-1'!$G$2:$G$50)+SUMIF('BALANCE N-1'!$A$2:$A$50,"2392*",'BALANCE N-1'!$F$2:$F$50)-SUMIF('BALANCE N-1'!$A$2:$A$50,"2392*",'BALANCE N-1'!$G$2:$G$50) | D16: =E16-C16 | E16: =SUMIF('BALANCE N'!$A$2:$A$50,"231*",'BALANCE N'!$F$2:$F$50)-SUMIF('BALANCE N'!$A$2:$A$50,"231*",'BALANCE N'!$G$2:$G$50)+SUMIF('BALANCE N'!$A$2:$A$50,"232*",'BALANCE N'!$F$2:$F$50)-SUMIF('BALANCE N'!$A$2:$A$50,"232*",'BALANCE N'!$G$2:$G$50)+SUMIF('BALANCE N'!$A$2:$A$50,"233*",'BALANCE N'!$F$2:$F$50)-SUMIF('BALANCE N'!$A$2:$A$50,"233*",'BALANCE N'!$G$2:$G$50)+SUMIF('BALANCE N'!$A$2:$A$50,"2393*",'BALANCE N'!$F$2:$F$50)-SUMIF('BALANCE N'!$A$2:$A$50,"2393*",'BALANCE N'!$G$2:$G$50)+SUMIF('BALANCE N'!$A$2:$A$50,"2396*",'BALANCE N'!$F$2:$F$50)-SUMIF('BALANCE N'!$A$2:$A$50,"2396*",'BALANCE N'!$G$2:$G$50)+SUMIF('BALANCE N'!$A$2:$A$50,"2391*",'BALANCE N'!$F$2:$F$50)-SUMIF('BALANCE N'!$A$2:$A$50,"2391*",'BALANCE N'!$G$2:$G$50)+SUMIF('BALANCE N'!$A$2:$A$50,"2392*",'BALANCE N'!$F$2:$F$50)-SUMIF('BALANCE N'!$A$2:$A$50,"2392*",'BALANCE N'!$G$2:$G$50)
A17: FH | B17: Aménagements, agencements et installations | C17: =SUMIF('BALANCE N-1'!$A$2:$A$50,"238*",'BALANCE N-1'!$F$2:$F$50)-SUMIF('BALANCE N-1'!$A$2:$A$50,"238*",'BALANCE N-1'!$G$2:$G$50)+SUMIF('BALANCE N-1'!$A$2:$A$50,"234*",'BALANCE N-1'!$F$2:$F$50)-SUMIF('BALANCE N-1'!$A$2:$A$50,"234*",'BALANCE N-1'!$G$2:$G$50)+SUMIF('BALANCE N-1'!$A$2:$A$50,"235*",'BALANCE N-1'!$F$2:$F$50)-SUMIF('BALANCE N-1'!$A$2:$A$50,"235*",'BALANCE N-1'!$G$2:$G$50)+SUMIF('BALANCE N-1'!$A$2:$A$50,"2394*",'BALANCE N-1'!$F$2:$F$50)-SUMIF('BALANCE N-1'!$A$2:$A$50,"2394*",'BALANCE N-1'!$G$2:$G$50)+SUMIF('BALANCE N-1'!$A$2:$A$50,"2398*",'BALANCE N-1'!$F$2:$F$50)-SUMIF('BALANCE N-1'!$A$2:$A$50,"2398*",'BALANCE N-1'!$G$2:$G$50)+SUMIF('BALANCE N-1'!$A$2:$A$50,"2395*",'BALANCE N-1'!$F$2:$F$50)-SUMIF('BALANCE N-1'!$A$2:$A$50,"2395*",'BALANCE N-1'!$G$2:$G$50) | D17: =E17-C17 | E17: =SUMIF('BALANCE N'!$A$2:$A$50,"238*",'BALANCE N'!$F$2:$F$50)-SUMIF('BALANCE N'!$A$2:$A$50,"238*",'BALANCE N'!$G$2:$G$50)+SUMIF('BALANCE N'!$A$2:$A$50,"234*",'BALANCE N'!$F$2:$F$50)-SUMIF('BALANCE N'!$A$2:$A$50,"234*",'BALANCE N'!$G$2:$G$50)+SUMIF('BALANCE N'!$A$2:$A$50,"235*",'BALANCE N'!$F$2:$F$50)-SUMIF('BALANCE N'!$A$2:$A$50,"235*",'BALANCE N'!$G$2:$G$50)+SUMIF('BALANCE N'!$A$2:$A$50,"2394*",'BALANCE N'!$F$2:$F$50)-SUMIF('BALANCE N'!$A$2:$A$50,"2394*",'BALANCE N'!$G$2:$G$50)+SUMIF('BALANCE N'!$A$2:$A$50,"2398*",'BALANCE N'!$F$2:$F$50)-SUMIF('BALANCE N'!$A$2:$A$50,"2398*",'BALANCE N'!$G$2:$G$50)+SUMIF('BALANCE N'!$A$2:$A$50,"2395*",'BALANCE N'!$F$2:$F$50)-SUMIF('BALANCE N'!$A$2:$A$50,"2395*",'BALANCE N'!$G$2:$G$50)
A18: FI | B18: Matériel, mobilier et actifs biologiques | C18: =SUMIF('BALANCE N-1'!$A$2:$A$50,"24*",'BALANCE N-1'!$F$2:$F$50)-SUMIF('BALANCE N-1'!$A$2:$A$50,"24*",'BALANCE N-1'!$G$2:$G$50)-SUMIF('BALANCE N-1'!$A$2:$A$50,"245*",'BALANCE N-1'!$F$2:$F$50)+SUMIF('BALANCE N-1'!$A$2:$A$50,"245*",'BALANCE N-1'!$G$2:$G$50)-SUMIF('BALANCE N-1'!$A$2:$A$50,"2495*",'BALANCE N-1'!$F$2:$F$50)+SUMIF('BALANCE N-1'!$A$2:$A$50,"2495*",'BALANCE N-1'!$G$2:$G$50) | D18: =E18-C18 | E18: =SUMIF('BALANCE N'!$A$2:$A$50,"24*",'BALANCE N'!$F$2:$F$50)-SUMIF('BALANCE N'!$A$2:$A$50,"24*",'BALANCE N'!$G$2:$G$50)-SUMIF('BALANCE N'!$A$2:$A$50,"245*",'BALANCE N'!$F$2:$F$50)+SUMIF('BALANCE N'!$A$2:$A$50,"245*",'BALANCE N'!$G$2:$G$50)-SUMIF('BALANCE N'!$A$2:$A$50,"2495*",'BALANCE N'!$F$2:$F$50)+SUMIF('BALANCE N'!$A$2:$A$50,"2495*",'BALANCE N'!$G$2:$G$50)
A19: FJ | B19: Matériel de transport | C19: =SUMIF('BALANCE N-1'!$A$2:$A$50,"245*",'BALANCE N-1'!$F$2:$F$50)-SUMIF('BALANCE N-1'!$A$2:$A$50,"245*",'BALANCE N-1'!$G$2:$G$50)+SUMIF('BALANCE N-1'!$A$2:$A$50,"2495*",'BALANCE N-1'!$F$2:$F$50)-SUMIF('BALANCE N-1'!$A$2:$A$50,"2495*",'BALANCE N-1'!$G$2:$G$50) | D19: =E19-C19 | E19: =SUMIF('BALANCE N'!$A$2:$A$50,"245*",'BALANCE N'!$F$2:$F$50)-SUMIF('BALANCE N'!$A$2:$A$50,"245*",'BALANCE N'!$G$2:$G$50)+SUMIF('BALANCE N'!$A$2:$A$50,"2495*",'BALANCE N'!$F$2:$F$50)-SUMIF('BALANCE N'!$A$2:$A$50,"2495*",'BALANCE N'!$G$2:$G$50)
A20: FK | B20: Avances et acomptes sur immobilisations | C20: =SUMIF('BALANCE N-1'!$A$2:$A$50,"252*",'BALANCE N-1'!$F$2:$F$50)-SUMIF('BALANCE N-1'!$A$2:$A$50,"252*",'BALANCE N-1'!$G$2:$G$50) | D20: =E20-C20 | E20: =SUMIF('BALANCE N'!$A$2:$A$50,"252*",'BALANCE N'!$F$2:$F$50)-SUMIF('BALANCE N'!$A$2:$A$50,"252*",'BALANCE N'!$G$2:$G$50)
A21: FL | B21: Immobilisations financières | C21: =SUMIF('BALANCE N-1'!$A$2:$A$50,"26*",'BALANCE N-1'!$F$2:$F$50)-SUMIF('BALANCE N-1'!$A$2:$A$50,"26*",'BALANCE N-1'!$G$2:$G$50)+SUMIF('BALANCE N-1'!$A$2:$A$50,"27*",'BALANCE N-1'!$F$2:$F$50)-SUMIF('BALANCE N-1'!$A$2:$A$50,"27*",'BALANCE N-1'!$G$2:$G$50) | D21: =E21-C21 | E21: =SUMIF('BALANCE N'!$A$2:$A$50,"26*",'BALANCE N'!$F$2:$F$50)-SUMIF('BALANCE N'!$A$2:$A$50,"26*",'BALANCE N'!$G$2:$G$50)+SUMIF('BALANCE N'!$A$2:$A$50,"27*",'BALANCE N'!$F$2:$F$50)-SUMIF('BALANCE N'!$A$2:$A$50,"27*",'BALANCE N'!$G$2:$G$50)
A22: GS | B22: A - TOTAL DES IMMOBILISATIONS | C22: =C14+C15+C16+C17+C18+C19+C20+C21 | D22: =D14+D15+D16+D17+D18+D19+D20+D21 | E22: =E14+E15+E16+E17+E18+E19+E20+E21
A23: FM | B23: Achats de biens et services | D23: =SUMIF('BALANCE N'!$A$2:$A$50,"60*",'BALANCE N'!$F$2:$F$50)-SUMIF('BALANCE N'!$A$2:$A$50,"60*",'BALANCE N'!$G$2:$G$50) | E23: =C23+D23
A24: FN | B24: Transports | D24: =SUMIF('BALANCE N'!$A$2:$A$50,"61*",'BALANCE N'!$F$2:$F$50)-SUMIF('BALANCE N'!$A$2:$A$50,"61*",'BALANCE N'!$G$2:$G$50) | E24: =C24+D24
A25: FO | B25: Services extérieurs | D25: =SUMIF('BALANCE N'!$A$2:$A$50,"62*",'BALANCE N'!$F$2:$F$50)-SUMIF('BALANCE N'!$A$2:$A$50,"62*",'BALANCE N'!$G$2:$G$50)+SUMIF('BALANCE N'!$A$2:$A$50,"63*",'BALANCE N'!$F$2:$F$50)-SUMIF('BALANCE N'!$A$2:$A$50,"63*",'BALANCE N'!$G$2:$G$50) | E25: =C25+D25
A26: FP | B26: Impôts et taxes | D26: =SUMIF('BALANCE N'!$A$2:$A$50,"64*",'BALANCE N'!$F$2:$F$50)-SUMIF('BALANCE N'!$A$2:$A$50,"64*",'BALANCE N'!$G$2:$G$50) | E26: =C26+D26
A27: FQ | B27: Autres charges | D27: =SUMIF('BALANCE N'!$A$2:$A$50,"65*",'BALANCE N'!$F$2:$F$50)-SUMIF('BALANCE N'!$A$2:$A$50,"65*",'BALANCE N'!$G$2:$G$50) | E27: =C27+D27
A28: FR | B28: Charges de personnel | D28: =SUMIF('BALANCE N'!$A$2:$A$50,"66*",'BALANCE N'!$F$2:$F$50)-SUMIF('BALANCE N'!$A$2:$A$50,"66*",'BALANCE N'!$G$2:$G$50) | E28: =C28+D28
A29: FS | B29: Charges financières | D29: =SUMIF('BALANCE N'!$A$2:$A$50,"67*",'BALANCE N'!$F$2:$F$50)-SUMIF('BALANCE N'!$A$2:$A$50,"67*",'BALANCE N'!$G$2:$G$50) | E29: =C29+D29
A30: FT | B30: Avances sur charges (à justifier) | D30: =(SUMIF('BALANCE N'!$A$2:$A$50,"421*",'BALANCE N'!$F$2:$F$50))-(SUMIF('BALANCE N-1'!$A$2:$A$50,"421*",'BALANCE N-1'!$F$2:$F$50)) | E30: =C30+D30
A31: GT | B31: B - TOTAL DES CHARGES DE FONCTIONNEMENT | C31: =C23+C24+C25+C26+C27+C28+C29+C30 | D31: =D23+D24+D25+D26+D27+D28+D29+D30 | E31: =E23+E24+E25+E26+E27+E28+E29+E30
A32: GU | B32: II. EMPLOIS (A + B) | C32: =C22+C31 | D32: =D22+D31 | E32: =E22+E31
A33: GV | B33: III. EXCÉDENT / DÉFICIT DES FONDS REÇUS SUR LES EMPLOIS (I - II) | C33: =C13-C32 | D33: =D13-D32 | E33: =E13-E32
A34: FU | B34: Fonds Bailleur en début d'exercice N
A35: FV | B35: Fonds de contrepartie État en début d'exercice N
A36: FW | B36: Autres fonds en début d'exercice N
A37: GW | B37: IV. FONDS DISPONIBLE EN DÉBUT D'EXERCICE | C37: =C34+C35+C36 | D37: =D34+D35+D36 | E37: =E34+E35+E36
A38: GX | B38: V. MONTANT NET DE L'ENCAISSE DISPONIBLE (III + IV) | C38: =C33+C37 | D38: =D33+D37 | E38: =E33+E37
A39: FX | B39: Fonds Bailleur en fin d'exercice N
A40: FY | B40: Fonds de contrepartie État en fin d'exercice N
A41: FZ | B41: Autres fonds en fin d'exercice N
A42: GY | B42: VI. FONDS DISPONIBLE EN FIN D'EXERCICE | C42: =C39+C40+C41 | D42: =D39+D40+D41 | E42: =E39+E40+E41
A43: GZ | B43: VII. CONTRÔLE : TOTAL V = TOTAL VI (écart) | C43: =C38-C42 | D43: =D38-D42 | E43: =E38-E42
A45: Colonnes calculées depuis la balance : immobilisations (cumul = classe 2 brute), charges de l'exercice (classes 6), fonds reçus (variation des soldes 16x/46x + quote-part 702 consommée - approximation à ajuster depuis les avis de décaissement des bailleurs). Fonds disponibles début/fin (FU à FZ) : à ventiler par source ; rappel balance - trésorerie totale : voir CONTROLES.

Sheet Execution budgetaire
A1: - 4 -
G2: EXECUTION BUDGETAIRE PROJETS DE DEVELOPPEMENT
A3: Dénomination sociale : PROJET EAU POTABLE RURALE
A4: Adresse : | G4: Sigle usuel : | H4: PEPR
A5: N° de compte contribuable (NCC) : PD-2023-017 | E5: Exercice clos le 31-12-2025 | G5: Durée (en mois) : 12
A6: N° de télédéclarant (NTD) :
A7: TABLEAU DE SUIVI D'EXECUTION DU BUDGET
A8: Code | B8: Libellé | C8: Budget de l'exercice (1) | D8: Décaissement (2) | E8: Engagement (3) | F8: Réalisation (4 = 2 + 3) | G8: Crédit disponible (5 = 1 - 4) | H8: Exécution budget % (4/1)
F9: =D9+E9 | G9: =C9-F9 | H9: =IF(C9=0,"",F9/C9)
F10: =D10+E10 | G10: =C10-F10 | H10: =IF(C10=0,"",F10/C10)
F11: =D11+E11 | G11: =C11-F11 | H11: =IF(C11=0,"",F11/C11)
F12: =D12+E12 | G12: =C12-F12 | H12: =IF(C12=0,"",F12/C12)
F13: =D13+E13 | G13: =C13-F13 | H13: =IF(C13=0,"",F13/C13)
F14: =D14+E14 | G14: =C14-F14 | H14: =IF(C14=0,"",F14/C14)
F15: =D15+E15 | G15: =C15-F15 | H15: =IF(C15=0,"",F15/C15)
F16: =D16+E16 | G16: =C16-F16 | H16: =IF(C16=0,"",F16/C16)
F17: =D17+E17 | G17: =C17-F17 | H17: =IF(C17=0,"",F17/C17)
F18: =D18+E18 | G18: =C18-F18 | H18: =IF(C18=0,"",F18/C18)
F19: =D19+E19 | G19: =C19-F19 | H19: =IF(C19=0,"",F19/C19)
F20: =D20+E20 | G20: =C20-F20 | H20: =IF(C20=0,"",F20/C20)
... F22: =D22+E22 | G22: =C22-F22 | H22: =IF(C22=0,"",F22/C22)
B23: TOTAL | C23: =SUM(C9:C22) | D23: =SUM(D9:D22) | E23: =SUM(E9:E22) | F23: =SUM(F9:F22) | G23: =SUM(G9:G22) | H23: =IF(C23=0,"",F23/C23)
A25: Remplir code et libellé suivant la nomenclature budgétaire du projet.

Sheet Reconciliation tresorerie
A1: - 5 -
B2: RECONCILIATION PROJETS DE DEVELOPPEMENT
A3: Dénomination sociale : PROJET EAU POTABLE RURALE
A4: Adresse : | C4: PEPR
A5: N° de compte contribuable (NCC) : PD-2023-017 | C5: Durée (en mois) : 12
A6: N° de télédéclarant (NTD) :
A7: TABLEAU DE RECONCILIATION DE LA TRESORERIE
A8: LIBELLE | B8: REP. | C8: MONTANT
A9: TRÉSORERIE EN DÉBUT D'EXERCICE N | B9: A | C9: =SUMIF('BALANCE N-1'!$A$2:$A$50,"5*",'BALANCE N-1'!$F$2:$F$50)-SUMIF('BALANCE N-1'!$A$2:$A$50,"5*",'BALANCE N-1'!$G$2:$G$50)-SUMIF('BALANCE N-1'!$A$2:$A$50,"59*",'BALANCE N-1'!$F$2:$F$50)+SUMIF('BALANCE N-1'!$A$2:$A$50,"59*",'BALANCE N-1'!$G$2:$G$50)
A10: FONDS REÇUS DES BAILLEURS AU COURS DE L'EXERCICE N | B10: B | C10: ='Emplois-Ressources'!D9+'Emplois-Ressources'!D10+'Emplois-Ressources'!D11
A11: INTÉRÊTS REÇUS AU COURS DE L'EXERCICE N | B11: C | C11: =SUMIF('BALANCE N'!$A$2:$A$50,"77*",'BALANCE N'!$G$2:$G$50)-SUMIF('BALANCE N'!$A$2:$A$50,"77*",'BALANCE N'!$F$2:$F$50)
A12: AUTRES FONDS REÇUS AU COURS DE L'EXERCICE N | B12: D | C12: ='Emplois-Ressources'!D12
A13: VIREMENTS SUR COMPTES OPÉRATIONNELS | B13: E
A14: DÉPENSES DE L'EXERCICE N | B14: F | C14: ='Emplois-Ressources'!D32
A15: TRÉSORERIE EN FIN D'EXERCICE N (A+B+C+D-E-F) | B15: G | C15: =C9+C10+C11+C12-C13-C14
A16: PAIEMENTS EN INSTANCE | B16: H
A17: TRÉSORERIE NETTE DES PAIEMENTS EN INSTANCE (G-H) | B17: I | C17: =C15-C16
A19: Rappel balance - trésorerie de clôture (classe 5 nette) : | C19: =(SUMIF('BALANCE N'!$A$2:$A$50,"5*",'BALANCE N'!$F$2:$F$50)-SUMIF('BALANCE N'!$A$2:$A$50,"5*",'BALANCE N'!$G$2:$G$50)-SUMIF('BALANCE N'!$A$2:$A$50,"59*",'BALANCE N'!$F$2:$F$50)+SUMIF('BALANCE N'!$A$2:$A$50,"59*",'BALANCE N'!$G$2:$G$50))-(SUMIF('BALANCE N'!$A$2:$A$50,"59*",'BALANCE N'!$G$2:$G$50)-SUMIF('BALANCE N'!$A$2:$A$50,"599*",'BALANCE N'!$G$2:$G$50))
A20: Écart avec la ligne G (dépenses non décaissées, créances : à expliquer en NOTE 2) : | C20: =C15-C19

Sheet Bilan paysage
A1: - 6 -
I2: BILAN PAGE 1/1 PROJETS DE DEVELOPPEMENT
A3: Dénomination sociale : PROJET EAU POTABLE RURALE
A4: Adresse : | I4: Sigle usuel : | J4: PEPR
A5: N° de compte contribuable (NCC) : PD-2023-017 | G5: Exercice clos le 31-12-2025 | I5: Durée (en mois) : 12
A6: N° de télédéclarant (NTD) :
C7: BILAN
A8: REF | B8: ACTIF | C8: NOTE | D8: NET | E8: NET N-1 | F8: REF | G8: PASSIF | H8: NOTE | I8: NET | J8: NET N-1
A10: AA | B10: Immobilisations incorporelles | C10: 3A | D10: ='Bilan-Actif'!D9 | E10: ='Bilan-Actif'!E9 | F10: CA | G10: Fonds affectes aux investissements | H10: 9 | I10: ='Bilan-Passif'!D9 | J10: ='Bilan-Passif'!E9
A11: AB | B11: Terrains et batiments | C11: 3A | D11: ='Bilan-Actif'!D10 | E11: ='Bilan-Actif'!E10 | F11: CB | G11: Report a nouveau (+ ou -) | I11: ='Bilan-Passif'!D10 | J11: ='Bilan-Passif'!E10
A12: AC | B12: Amenagements, agencements et installations | C12: 3A | D12: ='Bilan-Actif'!D11 | E12: ='Bilan-Actif'!E11 | F12: CC | G12: Solde des operations de l'exercice | I12: ='Bilan-Passif'!D11 | J12: ='Bilan-Passif'!E11
A13: AD | B13: Materiel, mobilier et actifs biologiques | C13: 3A | D13: ='Bilan-Actif'!D12 | E13: ='Bilan-Actif'!E12 | F13: CD | G13: Subventions d'investissement | H13: 10 | I13: ='Bilan-Passif'!D12 | J13: ='Bilan-Passif'!E12
A14: AE | B14: Materiel de transport | C14: 3A | D14: ='Bilan-Actif'!D13 | E14: ='Bilan-Actif'!E13 | F14: CZ | G14: TOTAL RESSOURCES PROPRES ET ASSIMILEES | I14: ='Bilan-Passif'!D13 | J14: ='Bilan-Passif'!E13
A15: AF | B15: Avances et acomptes verses sur immobilisations | C15: 3A | D15: ='Bilan-Actif'!D14 | E15: ='Bilan-Actif'!E14 | F15: DA | G15: Emprunts et dettes assimilees | H15: 11 | I15: ='Bilan-Passif'!D14 | J15: ='Bilan-Passif'!E14
A16: AG | B16: Depots et cautionnements | C16: 3A | D16: ='Bilan-Actif'!D15 | E16: ='Bilan-Actif'!E15 | F16: DB | G16: Provisions pour risques et charges | H16: 11 | I16: ='Bilan-Passif'!D15 | J16: ='Bilan-Passif'!E15
A17: AH | B17: Autres immobilisations corporelles et financieres | C17: 3A | D17: ='Bilan-Actif'!D16 | E17: ='Bilan-Actif'!E16 | F17: DC | G17: TOTAL DETTES FINANCIERES ET RESSOURCES ASSIMILEES | I17: ='Bilan-Passif'!D16 | J17: ='Bilan-Passif'!E16
A18: AZ | B18: TOTAL ACTIF IMMOBILISE | D18: ='Bilan-Actif'!D17 | E18: ='Bilan-Actif'!E17 | F18: DD | G18: TOTAL RESSOURCES STABLES | I18: ='Bilan-Passif'!D17 | J18: ='Bilan-Passif'!E17
A19: BA | B19: Actif circulant HAO | C19: 4 | D19: ='Bilan-Actif'!D18 | E19: ='Bilan-Actif'!E18 | F19: DE | G19: Dettes circulantes HAO | H19: 4 | I19: ='Bilan-Passif'!D18 | J19: ='Bilan-Passif'!E18
A20: BB | B20: Stocks et encours | C20: 5 | D20: ='Bilan-Actif'!D19 | E20: ='Bilan-Actif'!E19 | F20: DF | G20: Fonds d'administration | H20: 9 | I20: ='Bilan-Passif'!D19 | J20: ='Bilan-Passif'!E19
A21: BC | B21: Fournisseurs debiteurs | C21: 6 | D21: ='Bilan-Actif'!D20 | E21: ='Bilan-Actif'!E20 | F21: DG | G21: Fournisseurs | H21: 12 | I21: ='Bilan-Passif'!D20 | J21: ='Bilan-Passif'!E20
A22: BD | B22: Clients-usagers | C22: 6 | D22: ='Bilan-Actif'!D21 | E22: ='Bilan-Actif'!E21 | F22: DH | G22: Autres dettes | H22: 12 | I22: ='Bilan-Passif'!D21 | J22: ='Bilan-Passif'!E21
A23: BE | B23: Autres creances | C23: 6 | D23: ='Bilan-Actif'!D22 | E23: ='Bilan-Actif'!E22 | F23: DI | G23: Provisions pour risques et charges a court terme | I23: ='Bilan-Passif'!D22 | J23: ='Bilan-Passif'!E22
A24: BF | B24: TOTAL ACTIF CIRCULANT | D24: ='Bilan-Actif'!D23 | E24: ='Bilan-Actif'!E23 | F24: DJ | G24: TOTAL PASSIF CIRCULANT | I24: ='Bilan-Passif'!D23 | J24: ='Bilan-Passif'!E23
A25: BV | B25: Valeurs a encaisser | C25: 7 | D25: ='Bilan-Actif'!D24 | E25: ='Bilan-Actif'!E24 | F25: DW | G25: Banques, etablissements financiers et credits de tresorerie | H25: 13 | I25: ='Bilan-Passif'!D24 | J25: ='Bilan-Passif'!E24
A26: BW | B26: Banques, etablissements financiers, caisses et assimiles | C26: 7 | D26: ='Bilan-Actif'!D25 | E26: ='Bilan-Actif'!E25 | F26: DX | G26: TOTAL TRESORERIE PASSIF | I26: ='Bilan-Passif'!D25 | J26: ='Bilan-Passif'!E25
A27: BX | B27: TOTAL TRESORERIE ACTIF | D27: ='Bilan-Actif'!D26 | E27: ='Bilan-Actif'!E26 | F27: DY | G27: Ecart de conversion-Passif | H27: 8 | I27: ='Bilan-Passif'!D26 | J27: ='Bilan-Passif'!E26
A28: BY | B28: Ecart de conversion-Actif | C28: 8 | D28: ='Bilan-Actif'!D27 | E28: ='Bilan-Actif'!E27 | F28: DZ | G28: TOTAL GENERAL | I28: ='Bilan-Passif'!D27 | J28: ='Bilan-Passif'!E27
A29: BZ | B29: TOTAL GENERAL | D29: ='Bilan-Actif'!D28 | E29: ='Bilan-Actif'!E28

Sheet Bilan-Actif
A1: - 7 -
D2: BILAN PAGE 1/2 PROJETS DE DEVELOPPEMENT
A3: Dénomination sociale : PROJET EAU POTABLE RURALE
A4: Adresse : | D4: Sigle usuel : | E4: PEPR
A5: N° de compte contribuable (NCC) : PD-2023-017 | C5: Exercice clos le 31-12-2025 | D5: Durée (en mois) : 12
A6: N° de télédéclarant (NTD) :
A7: BILAN (EN NET)
A8: REF | B8: ACTIF | C8: NOTE | D8: EXERCICE AU 31/12/N | E8: EXERCICE AU 31/12/N-1
A9: AA | B9: Immobilisations incorporelles | C9: 3A | D9: =((SUMIF('BALANCE N'!$A$2:$A$50,"21*",'BALANCE N'!$F$2:$F$50)-SUMIF('BALANCE N'!$A$2:$A$50,"21*",'BALANCE N'!$G$2:$G$50)))-((SUMIF('BALANCE N'!$A$2:$A$50,"291*",'BALANCE N'!$G$2:$G$50)-SUMIF('BALANCE N'!$A$2:$A$50,"291*",'BALANCE N'!$F$2:$F$50)+SUMIF('BALANCE N'!$A$2:$A$50,"281*",'BALANCE N'!$G$2:$G$50)-SUMIF('BALANCE N'!$A$2:$A$50,"281*",'BALANCE N'!$F$2:$F$50))) | E9: =((SUMIF('BALANCE N-1'!$A$2:$A$50,"21*",'BALANCE N-1'!$F$2:$F$50)-SUMIF('BALANCE N-1'!$A$2:$A$50,"21*",'BALANCE N-1'!$G$2:$G$50)))-((SUMIF('BALANCE N-1'!$A$2:$A$50,"291*",'BALANCE N-1'!$G$2:$G$50)-SUMIF('BALANCE N-1'!$A$2:$A$50,"291*",'BALANCE N-1'!$F$2:$F$50)+SUMIF('BALANCE N-1'!$A$2:$A$50,"281*",'BALANCE N-1'!$G$2:$G$50)-SUMIF('BALANCE N-1'!$A$2:$A$50,"281*",'BALANCE N-1'!$F$2:$F$50)))
A10: AB | B10: Terrains et batiments | C10: 3A | D10: =((SUMIF('BALANCE N'!$A$2:$A$50,"22*",'BALANCE N'!$F$2:$F$50)-SUMIF('BALANCE N'!$A$2:$A$50,"22*",'BALANCE N'!$G$2:$G$50)+SUMIF('BALANCE N'!$A$2:$A$50,"231*",'BALANCE N'!$F$2:$F$50)-SUMIF('BALANCE N'!$A$2:$A$50,"231*",'BALANCE N'!$G$2:$G$50)+SUMIF('BALANCE N'!$A$2:$A$50,"232*",'BALANCE N'!$F$2:$F$50)-SUMIF('BALANCE N'!$A$2:$A$50,"232*",'BALANCE N'!$G$2:$G$50)+SUMIF('BALANCE N'!$A$2:$A$50,"233*",'BALANCE N'!$F$2:$F$50)-SUMIF('BALANCE N'!$A$2:$A$50,"233*",'BALANCE N'!$G$2:$G$50)+SUMIF('BALANCE N'!$A$2:$A$50,"2393*",'BALANCE N'!$F$2:$F$50)-SUMIF('BALANCE N'!$A$2:$A$50,"2393*",'BALANCE N'!$G$2:$G$50)+SUMIF('BALANCE N'!$A$2:$A$50,"2396*",'BALANCE N'!$F$2:$F$50)-SUMIF('BALANCE N'!$A$2:$A$50,"2396*",'BALANCE N'!$G$2:$G$50)+SUMIF('BALANCE N'!$A$2:$A$50,"2391*",'BALANCE N'!$F$2:$F$50)-SUMIF('BALANCE N'!$A$2:$A$50,"2391*",'BALANCE N'!$G$2:$G$50)+SUMIF('BALANCE N'!$A$2:$A$50,"2392*",'BALANCE N'!$F$2:$F$50)-SUMIF('BALANCE N'!$A$2:$A$50,"2392*",'BALANCE N'!$G$2:$G$50)))-((SUMIF('BALANCE N'!$A$2:$A$50,"282*",'BALANCE N'!$G$2:$G$50)-SUMIF('BALANCE N'!$A$2:$A$50,"282*",'BALANCE N'!$F$2:$F$50)+SUMIF('BALANCE N'!$A$2:$A$50,"292*",'BALANCE N'!$G$2:$G$50)-SUMIF('BALANCE N'!$A$2:$A$50,"292*",'BALANCE N'!$F$2:$F$50)+SUMIF('BALANCE N'!$A$2:$A$50,"2933*",'BALANCE N'!$G$2:$G$50)-SUMIF('BALANCE N'!$A$2:$A$50,"2933*",'BALANCE N'!$F$2:$F$50)+SUMIF('BALANCE N'!$A$2:$A$50,"2932*",'BALANCE N'!$G$2:$G$50)-SUMIF('BALANCE N'!$A$2:$A$50,"2932*",'BALANCE N'!$F$2:$F$50)+SUMIF('BALANCE N'!$A$2:$A$50,"2832*",'BALANCE N'!$G$2:$G$50)-SUMIF('BALANCE N'!$A$2:$A$50,"2832*",'BALANCE N'!$F$2:$F$50)+SUMIF('BALANCE N'!$A$2:$A$50,"2831*",'BALANCE N'!$G$2:$G$50)-SUMIF('BALANCE N'!$A$2:$A$50,"2831*",'BALANCE N'!$F$2:$F$50)+SUMIF('BALANCE N'!$A$2:$A$50,"2833*",'BALANCE N'!$G$2:$G$50)-SUMIF('BALANCE N'!$A$2:$A$50,"2833*",'BALANCE N'!$F$2:$F$50)+SUMIF('BALANCE N'!$A$2:$A$50,"2931*",'BALANCE N'!$G$2:$G$50)-SUMIF('BALANCE N'!$A$2:$A$50,"2931*",'BALANCE N'!$F$2:$F$50)+SUMIF('BALANCE N'!$A$2:$A$50,"2939*",'BALANCE N'!$G$2:$G$50)-SUMIF('BALANCE N'!$A$2:$A$50,"2939*",'BALANCE N'!$F$2:$F$50))) | E10: =((SUMIF('BALANCE N-1'!$A$2:$A$50,"22*",'BALANCE N-1'!$F$2:$F$50)-SUMIF('BALANCE N-1'!$A$2:$A$50,"22*",'BALANCE N-1'!$G$2:$G$50)+SUMIF('BALANCE N-1'!$A$2:$A$50,"231*",'BALANCE N-1'!$F$2:$F$50)-SUMIF('BALANCE N-1'!$A$2:$A$50,"231*",'BALANCE N-1'!$G$2:$G$50)+SUMIF('BALANCE N-1'!$A$2:$A$50,"232*",'BALANCE N-1'!$F$2:$F$50)-SUMIF('BALANCE N-1'!$A$2:$A$50,"232*",'BALANCE N-1'!$G$2:$G$50)+SUMIF('BALANCE N-1'!$A$2:$A$50,"233*",'BALANCE N-1'!$F$2:$F$50)-SUMIF('BALANCE N-1'!$A$2:$A$50,"233*",'BALANCE N-1'!$G$2:$G$50)+SUMIF('BALANCE N-1'!$A$2:$A$50,"2393*",'BALANCE N-1'!$F$2:$F$50)-SUMIF('BALANCE N-1'!$A$2:$A$50,"2393*",'BALANCE N-1'!$G$2:$G$50)+SUMIF('BALANCE N-1'!$A$2:$A$50,"2396*",'BALANCE N-1'!$F$2:$F$50)-SUMIF('BALANCE N-1'!$A$2:$A$50,"2396*",'BALANCE N-1'!$G$2:$G$50)+SUMIF('BALANCE N-1'!$A$2:$A$50,"2391*",'BALANCE N-1'!$F$2:$F$50)-SUMIF('BALANCE N-1'!$A$2:$A$50,"2391*",'BALANCE N-1'!$G$2:$G$50)+SUMIF('BALANCE N-1'!$A$2:$A$50,"2392*",'BALANCE N-1'!$F$2:$F$50)-SUMIF('BALANCE N-1'!$A$2:$A$50,"2392*",'BALANCE N-1'!$G$2:$G$50)))-((SUMIF('BALANCE N-1'!$A$2:$A$50,"282*",'BALANCE N-1'!$G$2:$G$50)-SUMIF('BALANCE N-1'!$A$2:$A$50,"282*",'BALANCE N-1'!$F$2:$F$50)+SUMIF('BALANCE N-1'!$A$2:$A$50,"292*",'BALANCE N-1'!$G$2:$G$50)-SUMIF('BALANCE N-1'!$A$2:$A$50,"292*",'BALANCE N-1'!$F$2:$F$50)+SUMIF('BALANCE N-1'!$A$2:$A$50,"2933*",'BALANCE N-1'!$G$2:$G$50)-SUMIF('BALANCE N-1'!$A$2:$A$50,"2933*",'BALANCE N-1'!$F$2:$F$50)+SUMIF('BALANCE N-1'!$A$2:$A$50,"2932*",'BALANCE N-1'!$G$2:$G$50)-SUMIF('BALANCE N-1'!$A$2:$A$50,"2932*",'BALANCE N-1'!$F$2:$F$50)+SUMIF('BALANCE N-1'!$A$2:$A$50,"2832*",'BALANCE N-1'!$G$2:$G$50)-SUMIF('BALANCE N-1'!$A$2:$A$50,"2832*",'BALANCE N-1'!$F$2:$F$50)+SUMIF('BALANCE N-1'!$A$2:$A$50,"2831*",'BALANCE N-1'!$G$2:$G$50)-SUMIF('BALANCE N-1'!$A$2:$A$50,"2831*",'BALANCE N-1'!$F$2:$F$50)+SUMIF('BALANCE N-1'!$A$2:$A$50,"2833*",'BALANCE N-1'!$G$2:$G$50)-SUMIF('BALANCE N-1'!$A$2:$A$50,"2833*",'BALANCE N-1'!$F$2:$F$50)+SUMIF('BALANCE N-1'!$A$2:$A$50,"2931*",'BALANCE N-1'!$G$2:$G$50)-SUMIF('BALANCE N-1'!$A$2:$A$50,"2931*",'BALANCE N-1'!$F$2:$F$50)+SUMIF('BALANCE N-1'!$A$2:$A$50,"2939*",'BALANCE N-1'!$G$2:$G$50)-SUMIF('BALANCE N-1'!$A$2:$A$50,"2939*",'BALANCE N-1'!$F$2:$F$50)))
A11: AC | B11: Amenagements, agencements et installations | C11: 3A | D11: =((SUMIF('BALANCE N'!$A$2:$A$50,"238*",'BALANCE N'!$F$2:$F$50)-SUMIF('BALANCE N'!$A$2:$A$50,"238*",'BALANCE N'!$G$2:$G$50)+SUMIF('BALANCE N'!$A$2:$A$50,"234*",'BALANCE N'!$F$2:$F$50)-SUMIF('BALANCE N'!$A$2:$A$50,"234*",'BALANCE N'!$G$2:$G$50)+SUMIF('BALANCE N'!$A$2:$A$50,"235*",'BALANCE N'!$F$2:$F$50)-SUMIF('BALANCE N'!$A$2:$A$50,"235*",'BALANCE N'!$G$2:$G$50)+SUMIF('BALANCE N'!$A$2:$A$50,"2394*",'BALANCE N'!$F$2:$F$50)-SUMIF('BALANCE N'!$A$2:$A$50,"2394*",'BALANCE N'!$G$2:$G$50)+SUMIF('BALANCE N'!$A$2:$A$50,"2398*",'BALANCE N'!$F$2:$F$50)-SUMIF('BALANCE N'!$A$2:$A$50,"2398*",'BALANCE N'!$G$2:$G$50)+SUMIF('BALANCE N'!$A$2:$A$50,"2395*",'BALANCE N'!$F$2:$F$50)-SUMIF('BALANCE N'!$A$2:$A$50,"2395*",'BALANCE N'!$G$2:$G$50)))-((SUMIF('BALANCE N'!$A$2:$A$50,"2834*",'BALANCE N'!$G$2:$G$50)-SUMIF('BALANCE N'!$A$2:$A$50,"2834*",'BALANCE N'!$F$2:$F$50)+SUMIF('BALANCE N'!$A$2:$A$50,"2838*",'BALANCE N'!$G$2:$G$50)-SUMIF('BALANCE N'!$A$2:$A$50,"2838*",'BALANCE N'!$F$2:$F$50)+SUMIF('BALANCE N'!$A$2:$A$50,"2935*",'BALANCE N'!$G$2:$G$50)-SUMIF('BALANCE N'!$A$2:$A$50,"2935*",'BALANCE N'!$F$2:$F$50)+SUMIF('BALANCE N'!$A$2:$A$50,"2934*",'BALANCE N'!$G$2:$G$50)-SUMIF('BALANCE N'!$A$2:$A$50,"2934*",'BALANCE N'!$F$2:$F$50)+SUMIF('BALANCE N'!$A$2:$A$50,"2938*",'BALANCE N'!$G$2:$G$50)-SUMIF('BALANCE N'!$A$2:$A$50,"2938*",'BALANCE N'!$F$2:$F$50)+SUMIF('BALANCE N'!$A$2:$A$50,"2835*",'BALANCE N'!$G$2:$G$50)-SUMIF('BALANCE N'!$A$2:$A$50,"2835*",'BALANCE N'!$F$2:$F$50))) | E11: =((SUMIF('BALANCE N-1'!$A$2:$A$50,"238*",'BALANCE N-1'!$F$2:$F$50)-SUMIF('BALANCE N-1'!$A$2:$A$50,"238*",'BALANCE N-1'!$G$2:$G$50)+SUMIF('BALANCE N-1'!$A$2:$A$50,"234*",'BALANCE N-1'!$F$2:$F$50)-SUMIF('BALANCE N-1'!$A$2:$A$50,"234*",'BALANCE N-1'!$G$2:$G$50)+SUMIF('BALANCE N-1'!$A$2:$A$50,"235*",'BALANCE N-1'!$F$2:$F$50)-SUMIF('BALANCE N-1'!$A$2:$A$50,"235*",'BALANCE N-1'!$G$2:$G$50)+SUMIF('BALANCE N-1'!$A$2:$A$50,"2394*",'BALANCE N-1'!$F$2:$F$50)-SUMIF('BALANCE N-1'!$A$2:$A$50,"2394*",'BALANCE N-1'!$G$2:$G$50)+SUMIF('BALANCE N-1'!$A$2:$A$50,"2398*",'BALANCE N-1'!$F$2:$F$50)-SUMIF('BALANCE N-1'!$A$2:$A$50,"2398*",'BALANCE N-1'!$G$2:$G$50)+SUMIF('BALANCE N-1'!$A$2:$A$50,"2395*",'BALANCE N-1'!$F$2:$F$50)-SUMIF('BALANCE N-1'!$A$2:$A$50,"2395*",'BALANCE N-1'!$G$2:$G$50)))-((SUMIF('BALANCE N-1'!$A$2:$A$50,"2834*",'BALANCE N-1'!$G$2:$G$50)-SUMIF('BALANCE N-1'!$A$2:$A$50,"2834*",'BALANCE N-1'!$F$2:$F$50)+SUMIF('BALANCE N-1'!$A$2:$A$50,"2838*",'BALANCE N-1'!$G$2:$G$50)-SUMIF('BALANCE N-1'!$A$2:$A$50,"2838*",'BALANCE N-1'!$F$2:$F$50)+SUMIF('BALANCE N-1'!$A$2:$A$50,"2935*",'BALANCE N-1'!$G$2:$G$50)-SUMIF('BALANCE N-1'!$A$2:$A$50,"2935*",'BALANCE N-1'!$F$2:$F$50)+SUMIF('BALANCE N-1'!$A$2:$A$50,"2934*",'BALANCE N-1'!$G$2:$G$50)-SUMIF('BALANCE N-1'!$A$2:$A$50,"2934*",'BALANCE N-1'!$F$2:$F$50)+SUMIF('BALANCE N-1'!$A$2:$A$50,"2938*",'BALANCE N-1'!$G$2:$G$50)-SUMIF('BALANCE N-1'!$A$2:$A$50,"2938*",'BALANCE N-1'!$F$2:$F$50)+SUMIF('BALANCE N-1'!$A$2:$A$50,"2835*",'BALANCE N-1'!$G$2:$G$50)-SUMIF('BALANCE N-1'!$A$2:$A$50,"2835*",'BALANCE N-1'!$F$2:$F$50)))
A12: AD | B12: Materiel, mobilier et actifs biologiques | C12: 3A | D12: =((SUMIF('BALANCE N'!$A$2:$A$50,"24*",'BALANCE N'!$F$2:$F$50)-SUMIF('BALANCE N'!$A$2:$A$50,"24*",'BALANCE N'!$G$2:$G$50)-SUMIF('BALANCE N'!$A$2:$A$50,"245*",'BALANCE N'!$F$2:$F$50)+SUMIF('BALANCE N'!$A$2:$A$50,"245*",'BALANCE N'!$G$2:$G$50)-SUMIF('BALANCE N'!$A$2:$A$50,"2495*",'BALANCE N'!$F$2:$F$50)+SUMIF('BALANCE N'!$A$2:$A$50,"2495*",'BALANCE N'!$G$2:$G$50)))-((SUMIF('BALANCE N'!$A$2:$A$50,"284*",'BALANCE N'!$G$2:$G$50)-SUMIF('BALANCE N'!$A$2:$A$50,"284*",'BALANCE N'!$F$2:$F$50)+SUMIF('BALANCE N'!$A$2:$A$50,"294*",'BALANCE N'!$G$2:$G$50)-SUMIF('BALANCE N'!$A$2:$A$50,"294*",'BALANCE N'!$F$2:$F$50)-SUMIF('BALANCE N'!$A$2:$A$50,"2945*",'BALANCE N'!$G$2:$G$50)+SUMIF('BALANCE N'!$A$2:$A$50,"2945*",'BALANCE N'!$F$2:$F$50)-SUMIF('BALANCE N'!$A$2:$A$50,"2845*",'BALANCE N'!$G$2:$G$50)+SUMIF('BALANCE N'!$A$2:$A$50,"2845*",'BALANCE N'!$F$2:$F$50))) | E12: =((SUMIF('BALANCE N-1'!$A$2:$A$50,"24*",'BALANCE N-1'!$F$2:$F$50)-SUMIF('BALANCE N-1'!$A$2:$A$50,"24*",'BALANCE N-1'!$G$2:$G$50)-SUMIF('BALANCE N-1'!$A$2:$A$50,"245*",'BALANCE N-1'!$F$2:$F$50)+SUMIF('BALANCE N-1'!$A$2:$A$50,"245*",'BALANCE N-1'!$G$2:$G$50)-SUMIF('BALANCE N-1'!$A$2:$A$50,"2495*",'BALANCE N-1'!$F$2:$F$50)+SUMIF('BALANCE N-1'!$A$2:$A$50,"2495*",'BALANCE N-1'!$G$2:$G$50)))-((SUMIF('BALANCE N-1'!$A$2:$A$50,"284*",'BALANCE N-1'!$G$2:$G$50)-SUMIF('BALANCE N-1'!$A$2:$A$50,"284*",'BALANCE N-1'!$F$2:$F$50)+SUMIF('BALANCE N-1'!$A$2:$A$50,"294*",'BALANCE N-1'!$G$2:$G$50)-SUMIF('BALANCE N-1'!$A$2:$A$50,"294*",'BALANCE N-1'!$F$2:$F$50)-SUMIF('BALANCE N-1'!$A$2:$A$50,"2945*",'BALANCE N-1'!$G$2:$G$50)+SUMIF('BALANCE N-1'!$A$2:$A$50,"2945*",'BALANCE N-1'!$F$2:$F$50)-SUMIF('BALANCE N-1'!$A$2:$A$50,"2845*",'BALANCE N-1'!$G$2:$G$50)+SUMIF('BALANCE N-1'!$A$2:$A$50,"2845*",'BALANCE N-1'!$F$2:$F$50)))
A13: AE | B13: Materiel de transport | C13: 3A | D13: =((SUMIF('BALANCE N'!$A$2:$A$50,"245*",'BALANCE N'!$F$2:$F$50)-SUMIF('BALANCE N'!$A$2:$A$50,"245*",'BALANCE N'!$G$2:$G$50)+SUMIF('BALANCE N'!$A$2:$A$50,"2495*",'BALANCE N'!$F$2:$F$50)-SUMIF('BALANCE N'!$A$2:$A$50,"2495*",'BALANCE N'!$G$2:$G$50)))-((SUMIF('BALANCE N'!$A$2:$A$50,"2945*",'BALANCE N'!$G$2:$G$50)-SUMIF('BALANCE N'!$A$2:$A$50,"2945*",'BALANCE N'!$F$2:$F$50)+SUMIF('BALANCE N'!$A$2:$A$50,"2845*",'BALANCE N'!$G$2:$G$50)-SUMIF('BALANCE N'!$A$2:$A$50,"2845*",'BALANCE N'!$F$2:$F$50))) | E13: =((SUMIF('BALANCE N-1'!$A$2:$A$50,"245*",'BALANCE N-1'!$F$2:$F$50)-SUMIF('BALANCE N-1'!$A$2:$A$50,"245*",'BALANCE N-1'!$G$2:$G$50)+SUMIF('BALANCE N-1'!$A$2:$A$50,"2495*",'BALANCE N-1'!$F$2:$F$50)-SUMIF('BALANCE N-1'!$A$2:$A$50,"2495*",'BALANCE N-1'!$G$2:$G$50)))-((SUMIF('BALANCE N-1'!$A$2:$A$50,"2945*",'BALANCE N-1'!$G$2:$G$50)-SUMIF('BALANCE N-1'!$A$2:$A$50,"2945*",'BALANCE N-1'!$F$2:$F$50)+SUMIF('BALANCE N-1'!$A$2:$A$50,"2845*",'BALANCE N-1'!$G$2:$G$50)-SUMIF('BALANCE N-1'!$A$2:$A$50,"2845*",'BALANCE N-1'!$F$2:$F$50)))
A14: AF | B14: Avances et acomptes verses sur immobilisations | C14: 3A | D14: =((SUMIF('BALANCE N'!$A$2:$A$50,"25*",'BALANCE N'!$F$2:$F$50)-SUMIF('BALANCE N'!$A$2:$A$50,"25*",'BALANCE N'!$G$2:$G$50)))-((SUMIF('BALANCE N'!$A$2:$A$50,"295*",'BALANCE N'!$G$2:$G$50)-SUMIF('BALANCE N'!$A$2:$A$50,"295*",'BALANCE N'!$F$2:$F$50))) | E14: =((SUMIF('BALANCE N-1'!$A$2:$A$50,"25*",'BALANCE N-1'!$F$2:$F$50)-SUMIF('BALANCE N-1'!$A$2:$A$50,"25*",'BALANCE N-1'!$G$2:$G$50)))-((SUMIF('BALANCE N-1'!$A$2:$A$50,"295*",'BALANCE N-1'!$G$2:$G$50)-SUMIF('BALANCE N-1'!$A$2:$A$50,"295*",'BALANCE N-1'!$F$2:$F$50)))
A15: AG | B15: Depots et cautionnements | C15: 3A | D15: =((SUMIF('BALANCE N'!$A$2:$A$50,"275*",'BALANCE N'!$F$2:$F$50)-SUMIF('BALANCE N'!$A$2:$A$50,"275*",'BALANCE N'!$G$2:$G$50)))-((SUMIF('BALANCE N'!$A$2:$A$50,"2975*",'BALANCE N'!$G$2:$G$50)-SUMIF('BALANCE N'!$A$2:$A$50,"2975*",'BALANCE N'!$F$2:$F$50))) | E15: =((SUMIF('BALANCE N-1'!$A$2:$A$50,"275*",'BALANCE N-1'!$F$2:$F$50)-SUMIF('BALANCE N-1'!$A$2:$A$50,"275*",'BALANCE N-1'!$G$2:$G$50)))-((SUMIF('BALANCE N-1'!$A$2:$A$50,"2975*",'BALANCE N-1'!$G$2:$G$50)-SUMIF('BALANCE N-1'!$A$2:$A$50,"2975*",'BALANCE N-1'!$F$2:$F$50)))
A16: AH | B16: Autres immobilisations corporelles et financieres | C16: 3A | D16: =((SUMIF('BALANCE N'!$A$2:$A$50,"26*",'BALANCE N'!$F$2:$F$50)-SUMIF('BALANCE N'!$A$2:$A$50,"26*",'BALANCE N'!$G$2:$G$50)+SUMIF('BALANCE N'!$A$2:$A$50,"27*",'BALANCE N'!$F$2:$F$50)-SUMIF('BALANCE N'!$A$2:$A$50,"27*",'BALANCE N'!$G$2:$G$50)-SUMIF('BALANCE N'!$A$2:$A$50,"275*",'BALANCE N'!$F$2:$F$50)+SUMIF('BALANCE N'!$A$2:$A$50,"275*",'BALANCE N'!$G$2:$G$50)))-((SUMIF('BALANCE N'!$A$2:$A$50,"296*",'BALANCE N'!$G$2:$G$50)-SUMIF('BALANCE N'!$A$2:$A$50,"296*",'BALANCE N'!$F$2:$F$50)+SUMIF('BALANCE N'!$A$2:$A$50,"297*",'BALANCE N'!$G$2:$G$50)-SUMIF('BALANCE N'!$A$2:$A$50,"297*",'BALANCE N'!$F$2:$F$50)-SUMIF('BALANCE N'!$A$2:$A$50,"2975*",'BALANCE N'!$G$2:$G$50)+SUMIF('BALANCE N'!$A$2:$A$50,"2975*",'BALANCE N'!$F$2:$F$50))) | E16: =((SUMIF('BALANCE N-1'!$A$2:$A$50,"26*",'BALANCE N-1'!$F$2:$F$50)-SUMIF('BALANCE N-1'!$A$2:$A$50,"26*",'BALANCE N-1'!$G$2:$G$50)+SUMIF('BALANCE N-1'!$A$2:$A$50,"27*",'BALANCE N-1'!$F$2:$F$50)-SUMIF('BALANCE N-1'!$A$2:$A$50,"27*",'BALANCE N-1'!$G$2:$G$50)-SUMIF('BALANCE N-1'!$A$2:$A$50,"275*",'BALANCE N-1'!$F$2:$F$50)+SUMIF('BALANCE N-1'!$A$2:$A$50,"275*",'BALANCE N-1'!$G$2:$G$50)))-((SUMIF('BALANCE N-1'!$A$2:$A$50,"296*",'BALANCE N-1'!$G$2:$G$50)-SUMIF('BALANCE N-1'!$A$2:$A$50,"296*",'BALANCE N-1'!$F$2:$F$50)+SUMIF('BALANCE N-1'!$A$2:$A$50,"297*",'BALANCE N-1'!$G$2:$G$50)-SUMIF('BALANCE N-1'!$A$2:$A$50,"297*",'BALANCE N-1'!$F$2:$F$50)-SUMIF('BALANCE N-1'!$A$2:$A$50,"2975*",'BALANCE N-1'!$G$2:$G$50)+SUMIF('BALANCE N-1'!$A$2:$A$50,"2975*",'BALANCE N-1'!$F$2:$F$50)))
A17: AZ | B17: TOTAL ACTIF IMMOBILISE | D17: =D9+D10+D11+D12+D13+D14+D15+D16 | E17: =E9+E10+E11+E12+E13+E14+E15+E16
A18: BA | B18: Actif circulant HAO | C18: 4 | D18: =((SUMIF('BALANCE N'!$A$2:$A$50,"485*",'BALANCE N'!$F$2:$F$50)-SUMIF('BALANCE N'!$A$2:$A$50,"485*",'BALANCE N'!$G$2:$G$50)))-((SUMIF('BALANCE N'!$A$2:$A$50,"498*",'BALANCE N'!$G$2:$G$50)-SUMIF('BALANCE N'!$A$2:$A$50,"498*",'BALANCE N'!$F$2:$F$50))) | E18: =((SUMIF('BALANCE N-1'!$A$2:$A$50,"485*",'BALANCE N-1'!$F$2:$F$50)-SUMIF('BALANCE N-1'!$A$2:$A$50,"485*",'BALANCE N-1'!$G$2:$G$50)))-((SUMIF('BALANCE N-1'!$A$2:$A$50,"498*",'BALANCE N-1'!$G$2:$G$50)-SUMIF('BALANCE N-1'!$A$2:$A$50,"498*",'BALANCE N-1'!$F$2:$F$50)))
A19: BB | B19: Stocks et encours | C19: 5 | D19: =((SUMIF('BALANCE N'!$A$2:$A$50,"36*",'BALANCE N'!$F$2:$F$50)-SUMIF('BALANCE N'!$A$2:$A$50,"36*",'BALANCE N'!$G$2:$G$50)+SUMIF('BALANCE N'!$A$2:$A$50,"31*",'BALANCE N'!$F$2:$F$50)-SUMIF('BALANCE N'!$A$2:$A$50,"31*",'BALANCE N'!$G$2:$G$50)+SUMIF('BALANCE N'!$A$2:$A$50,"38*",'BALANCE N'!$F$2:$F$50)-SUMIF('BALANCE N'!$A$2:$A$50,"38*",'BALANCE N'!$G$2:$G$50)+SUMIF('BALANCE N'!$A$2:$A$50,"34*",'BALANCE N'!$F$2:$F$50)-SUMIF('BALANCE N'!$A$2:$A$50,"34*",'BALANCE N'!$G$2:$G$50)+SUMIF('BALANCE N'!$A$2:$A$50,"33*",'BALANCE N'!$F$2:$F$50)-SUMIF('BALANCE N'!$A$2:$A$50,"33*",'BALANCE N'!$G$2:$G$50)+SUMIF('BALANCE N'!$A$2:$A$50,"37*",'BALANCE N'!$F$2:$F$50)-SUMIF('BALANCE N'!$A$2:$A$50,"37*",'BALANCE N'!$G$2:$G$50)+SUMIF('BALANCE N'!$A$2:$A$50,"32*",'BALANCE N'!$F$2:$F$50)-SUMIF('BALANCE N'!$A$2:$A$50,"32*",'BALANCE N'!$G$2:$G$50)))-((SUMIF('BALANCE N'!$A$2:$A$50,"39*",'BALANCE N'!$G$2:$G$50)-SUMIF('BALANCE N'!$A$2:$A$50,"39*",'BALANCE N'!$F$2:$F$50))) | E19: =((SUMIF('BALANCE N-1'!$A$2:$A$50,"36*",'BALANCE N-1'!$F$2:$F$50)-SUMIF('BALANCE N-1'!$A$2:$A$50,"36*",'BALANCE N-1'!$G$2:$G$50)+SUMIF('BALANCE N-1'!$A$2:$A$50,"31*",'BALANCE N-1'!$F$2:$F$50)-SUMIF('BALANCE N-1'!$A$2:$A$50,"31*",'BALANCE N-1'!$G$2:$G$50)+SUMIF('BALANCE N-1'!$A$2:$A$50,"38*",'BALANCE N-1'!$F$2:$F$50)-SUMIF('BALANCE N-1'!$A$2:$A$50,"38*",'BALANCE N-1'!$G$2:$G$50)+SUMIF('BALANCE N-1'!$A$2:$A$50,"34*",'BALANCE N-1'!$F$2:$F$50)-SUMIF('BALANCE N-1'!$A$2:$A$50,"34*",'BALANCE N-1'!$G$2:$G$50)+SUMIF('BALANCE N-1'!$A$2:$A$50,"33*",'BALANCE N-1'!$F$2:$F$50)-SUMIF('BALANCE N-1'!$A$2:$A$50,"33*",'BALANCE N-1'!$G$2:$G$50)+SUMIF('BALANCE N-1'!$A$2:$A$50,"37*",'BALANCE N-1'!$F$2:$F$50)-SUMIF('BALANCE N-1'!$A$2:$A$50,"37*",'BALANCE N-1'!$G$2:$G$50)+SUMIF('BALANCE N-1'!$A$2:$A$50,"32*",'BALANCE N-1'!$F$2:$F$50)-SUMIF('BALANCE N-1'!$A$2:$A$50,"32*",'BALANCE N-1'!$G$2:$G$50)))-((SUMIF('BALANCE N-1'!$A$2:$A$50,"39*",'BALANCE N-1'!$G$2:$G$50)-SUMIF('BALANCE N-1'!$A$2:$A$50,"39*",'BALANCE N-1'!$F$2:$F$50)))
A20: BC | B20: Fournisseurs debiteurs | C20: 6 | D20: =((SUMIF('BALANCE N'!$A$2:$A$50,"409*",'BALANCE N'!$F$2:$F$50)-SUMIF('BALANCE N'!$A$2:$A$50,"409*",'BALANCE N'!$G$2:$G$50)))-((SUMIF('BALANCE N'!$A$2:$A$50,"490*",'BALANCE N'!$G$2:$G$50)-SUMIF('BALANCE N'!$A$2:$A$50,"490*",'BALANCE N'!$F$2:$F$50))) | E20: =((SUMIF('BALANCE N-1'!$A$2:$A$50,"409*",'BALANCE N-1'!$F$2:$F$50)-SUMIF('BALANCE N-1'!$A$2:$A$50,"409*",'BALANCE N-1'!$G$2:$G$50)))-((SUMIF('BALANCE N-1'!$A$2:$A$50,"490*",'BALANCE N-1'!$G$2:$G$50)-SUMIF('BALANCE N-1'!$A$2:$A$50,"490*",'BALANCE N-1'!$F$2:$F$50)))
A21: BD | B21: Clients-usagers | C21: 6 | D21: =((SUMIF('BALANCE N'!$A$2:$A$50,"41*",'BALANCE N'!$F$2:$F$50)-SUMIF('BALANCE N'!$A$2:$A$50,"41*",'BALANCE N'!$G$2:$G$50)-SUMIF('BALANCE N'!$A$2:$A$50,"411*",'BALANCE N'!$F$2:$F$50)+SUMIF('BALANCE N'!$A$2:$A$50,"411*",'BALANCE N'!$G$2:$G$50)-SUMIF('BALANCE N'!$A$2:$A$50,"419*",'BALANCE N'!$F$2:$F$50)+SUMIF('BALANCE N'!$A$2:$A$50,"419*",'BALANCE N'!$G$2:$G$50)))-((SUMIF('BALANCE N'!$A$2:$A$50,"491*",'BALANCE N'!$G$2:$G$50)-SUMIF('BALANCE N'!$A$2:$A$50,"491*",'BALANCE N'!$F$2:$F$50))) | E21: =((SUMIF('BALANCE N-1'!$A$2:$A$50,"41*",'BALANCE N-1'!$F$2:$F$50)-SUMIF('BALANCE N-1'!$A$2:$A$50,"41*",'BALANCE N-1'!$G$2:$G$50)-SUMIF('BALANCE N-1'!$A$2:$A$50,"411*",'BALANCE N-1'!$F$2:$F$50)+SUMIF('BALANCE N-1'!$A$2:$A$50,"411*",'BALANCE N-1'!$G$2:$G$50)-SUMIF('BALANCE N-1'!$A$2:$A$50,"419*",'BALANCE N-1'!$F$2:$F$50)+SUMIF('BALANCE N-1'!$A$2:$A$50,"419*",'BALANCE N-1'!$G$2:$G$50)))-((SUMIF('BALANCE N-1'!$A$2:$A$50,"491*",'BALANCE N-1'!$G$2:$G$50)-SUMIF('BALANCE N-1'!$A$2:$A$50,"491*",'BALANCE N-1'!$F$2:$F$50)))
A22: BE | B22: Autres creances | C22: 6 | D22: =((SUMIF('BALANCE N'!$A$2:$A$50,"43*",'BALANCE N'!$F$2:$F$50)+SUMIF('BALANCE N'!$A$2:$A$50,"47*",'BALANCE N'!$F$2:$F$50)+SUMIF('BALANCE N'!$A$2:$A$50,"44*",'BALANCE N'!$F$2:$F$50)+SUMIF('BALANCE N'!$A$2:$A$50,"42*",'BALANCE N'!$F$2:$F$50)-SUMIF('BALANCE N'!$A$2:$A$50,"478*",'BALANCE N'!$F$2:$F$50)))-((SUMIF('BALANCE N'!$A$2:$A$50,"493*",'BALANCE N'!$G$2:$G$50)-SUMIF('BALANCE N'!$A$2:$A$50,"493*",'BALANCE N'!$F$2:$F$50)+SUMIF('BALANCE N'!$A$2:$A$50,"492*",'BALANCE N'!$G$2:$G$50)-SUMIF('BALANCE N'!$A$2:$A$50,"492*",'BALANCE N'!$F$2:$F$50)+SUMIF('BALANCE N'!$A$2:$A$50,"497*",'BALANCE N'!$G$2:$G$50)-SUMIF('BALANCE N'!$A$2:$A$50,"497*",'BALANCE N'!$F$2:$F$50)+SUMIF('BALANCE N'!$A$2:$A$50,"494*",'BALANCE N'!$G$2:$G$50)-SUMIF('BALANCE N'!$A$2:$A$50,"494*",'BALANCE N'!$F$2:$F$50))) | E22: =((SUMIF('BALANCE N-1'!$A$2:$A$50,"43*",'BALANCE N-1'!$F$2:$F$50)+SUMIF('BALANCE N-1'!$A$2:$A$50,"47*",'BALANCE N-1'!$F$2:$F$50)+SUMIF('BALANCE N-1'!$A$2:$A$50,"44*",'BALANCE N-1'!$F$2:$F$50)+SUMIF('BALANCE N-1'!$A$2:$A$50,"42*",'BALANCE N-1'!$F$2:$F$50)-SUMIF('BALANCE N-1'!$A$2:$A$50,"478*",'BALANCE N-1'!$F$2:$F$50)))-((SUMIF('BALANCE N-1'!$A$2:$A$50,"493*",'BALANCE N-1'!$G$2:$G$50)-SUMIF('BALANCE N-1'!$A$2:$A$50,"493*",'BALANCE N-1'!$F$2:$F$50)+SUMIF('BALANCE N-1'!$A$2:$A$50,"492*",'BALANCE N-1'!$G$2:$G$50)-SUMIF('BALANCE N-1'!$A$2:$A$50,"492*",'BALANCE N-1'!$F$2:$F$50)+SUMIF('BALANCE N-1'!$A$2:$A$50,"497*",'BALANCE N-1'!$G$2:$G$50)-SUMIF('BALANCE N-1'!$A$2:$A$50,"497*",'BALANCE N-1'!$F$2:$F$50)+SUMIF('BALANCE N-1'!$A$2:$A$50,"494*",'BALANCE N-1'!$G$2:$G$50)-SUMIF('BALANCE N-1'!$A$2:$A$50,"494*",'BALANCE N-1'!$F$2:$F$50)))
A23: BF | B23: TOTAL ACTIF CIRCULANT | D23: =D18+D19+D20+D21+D22 | E23: =E18+E19+E20+E21+E22
A24: BV | B24: Valeurs a encaisser | C24: 7 | D24: =((SUMIF('BALANCE N'!$A$2:$A$50,"51*",'BALANCE N'!$F$2:$F$50)-SUMIF('BALANCE N'!$A$2:$A$50,"51*",'BALANCE N'!$G$2:$G$50)))-((SUMIF('BALANCE N'!$A$2:$A$50,"591*",'BALANCE N'!$G$2:$G$50)-SUMIF('BALANCE N'!$A$2:$A$50,"591*",'BALANCE N'!$F$2:$F$50))) | E24: =((SUMIF('BALANCE N-1'!$A$2:$A$50,"51*",'BALANCE N-1'!$F$2:$F$50)-SUMIF('BALANCE N-1'!$A$2:$A$50,"51*",'BALANCE N-1'!$G$2:$G$50)))-((SUMIF('BALANCE N-1'!$A$2:$A$50,"591*",'BALANCE N-1'!$G$2:$G$50)-SUMIF('BALANCE N-1'!$A$2:$A$50,"591*",'BALANCE N-1'!$F$2:$F$50)))
A25: BW | B25: Banques, etablissements financiers, caisses et assimiles | C25: 7 | D25: =((SUMIF('BALANCE N'!$A$2:$A$50,"57*",'BALANCE N'!$F$2:$F$50)-SUMIF('BALANCE N'!$A$2:$A$50,"57*",'BALANCE N'!$G$2:$G$50)+SUMIF('BALANCE N'!$A$2:$A$50,"55*",'BALANCE N'!$F$2:$F$50)-SUMIF('BALANCE N'!$A$2:$A$50,"55*",'BALANCE N'!$G$2:$G$50)+SUMIF('BALANCE N'!$A$2:$A$50,"53*",'BALANCE N'!$F$2:$F$50)-SUMIF('BALANCE N'!$A$2:$A$50,"53*",'BALANCE N'!$G$2:$G$50)+SUMIF('BALANCE N'!$A$2:$A$50,"52*",'BALANCE N'!$F$2:$F$50)-SUMIF('BALANCE N'!$A$2:$A$50,"52*",'BALANCE N'!$G$2:$G$50)))-((SUMIF('BALANCE N'!$A$2:$A$50,"592*",'BALANCE N'!$G$2:$G$50)-SUMIF('BALANCE N'!$A$2:$A$50,"592*",'BALANCE N'!$F$2:$F$50)+SUMIF('BALANCE N'!$A$2:$A$50,"595*",'BALANCE N'!$G$2:$G$50)-SUMIF('BALANCE N'!$A$2:$A$50,"595*",'BALANCE N'!$F$2:$F$50)+SUMIF('BALANCE N'!$A$2:$A$50,"593*",'BALANCE N'!$G$2:$G$50)-SUMIF('BALANCE N'!$A$2:$A$50,"593*",'BALANCE N'!$F$2:$F$50))) | E25: =((SUMIF('BALANCE N-1'!$A$2:$A$50,"57*",'BALANCE N-1'!$F$2:$F$50)-SUMIF('BALANCE N-1'!$A$2:$A$50,"57*",'BALANCE N-1'!$G$2:$G$50)+SUMIF('BALANCE N-1'!$A$2:$A$50,"55*",'BALANCE N-1'!$F$2:$F$50)-SUMIF('BALANCE N-1'!$A$2:$A$50,"55*",'BALANCE N-1'!$G$2:$G$50)+SUMIF('BALANCE N-1'!$A$2:$A$50,"53*",'BALANCE N-1'!$F$2:$F$50)-SUMIF('BALANCE N-1'!$A$2:$A$50,"53*",'BALANCE N-1'!$G$2:$G$50)+SUMIF('BALANCE N-1'!$A$2:$A$50,"52*",'BALANCE N-1'!$F$2:$F$50)-SUMIF('BALANCE N-1'!$A$2:$A$50,"52*",'BALANCE N-1'!$G$2:$G$50)))-((SUMIF('BALANCE N-1'!$A$2:$A$50,"592*",'BALANCE N-1'!$G$2:$G$50)-SUMIF('BALANCE N-1'!$A$2:$A$50,"592*",'BALANCE N-1'!$F$2:$F$50)+SUMIF('BALANCE N-1'!$A$2:$A$50,"595*",'BALANCE N-1'!$G$2:$G$50)-SUMIF('BALANCE N-1'!$A$2:$A$50,"595*",'BALANCE N-1'!$F$2:$F$50)+SUMIF('BALANCE N-1'!$A$2:$A$50,"593*",'BALANCE N-1'!$G$2:$G$50)-SUMIF('BALANCE N-1'!$A$2:$A$50,"593*",'BALANCE N-1'!$F$2:$F$50)))
A26: BX | B26: TOTAL TRESORERIE ACTIF | D26: =D24+D25 | E26: =E24+E25
A27: BY | B27: Ecart de conversion-Actif | C27: 8 | D27: =(SUMIF('BALANCE N'!$A$2:$A$50,"478*",'BALANCE N'!$F$2:$F$50)-SUMIF('BALANCE N'!$A$2:$A$50,"478*",'BALANCE N'!$G$2:$G$50)) | E27: =(SUMIF('BALANCE N-1'!$A$2:$A$50,"478*",'BALANCE N-1'!$F$2:$F$50)-SUMIF('BALANCE N-1'!$A$2:$A$50,"478*",'BALANCE N-1'!$G$2:$G$50))
A28: BZ | B28: TOTAL GENERAL | D28: =D17+D23+D26+D27 | E28: =E17+E23+E26+E27

Sheet Bilan-Passif
A1: - 8 -
D2: BILAN PAGE 2/2 PROJETS DE DEVELOPPEMENT
A3: Dénomination sociale : PROJET EAU POTABLE RURALE
A4: Adresse : | D4: Sigle usuel : | E4: PEPR
A5: N° de compte contribuable (NCC) : PD-2023-017 | C5: Exercice clos le 31-12-2025 | D5: Durée (en mois) : 12
A6: N° de télédéclarant (NTD) :
A7: BILAN (EN NET)
A8: REF | B8: PASSIF | C8: NOTE | D8: EXERCICE AU 31/12/N | E8: EXERCICE AU 31/12/N-1
A9: CA | B9: Fonds affectes aux investissements | C9: 9 | D9: =(SUMIF('BALANCE N'!$A$2:$A$50,"16*",'BALANCE N'!$G$2:$G$50)-SUMIF('BALANCE N'!$A$2:$A$50,"16*",'BALANCE N'!$F$2:$F$50)) | E9: =(SUMIF('BALANCE N-1'!$A$2:$A$50,"16*",'BALANCE N-1'!$G$2:$G$50)-SUMIF('BALANCE N-1'!$A$2:$A$50,"16*",'BALANCE N-1'!$F$2:$F$50))
A10: CB | B10: Report a nouveau (+ ou -) | D10: =(SUMIF('BALANCE N'!$A$2:$A$50,"12*",'BALANCE N'!$G$2:$G$50)-SUMIF('BALANCE N'!$A$2:$A$50,"12*",'BALANCE N'!$F$2:$F$50)) | E10: =(SUMIF('BALANCE N-1'!$A$2:$A$50,"12*",'BALANCE N-1'!$G$2:$G$50)-SUMIF('BALANCE N-1'!$A$2:$A$50,"12*",'BALANCE N-1'!$F$2:$F$50))
A11: CC | B11: Solde des operations de l'exercice | D11: ='Compte Exploitation'!D28+(SUMIF('BALANCE N'!$A$2:$A$50,"13*",'BALANCE N'!$G$2:$G$50)-SUMIF('BALANCE N'!$A$2:$A$50,"13*",'BALANCE N'!$F$2:$F$50)) | E11: ='Compte Exploitation'!E28+(SUMIF('BALANCE N-1'!$A$2:$A$50,"13*",'BALANCE N-1'!$G$2:$G$50)-SUMIF('BALANCE N-1'!$A$2:$A$50,"13*",'BALANCE N-1'!$F$2:$F$50))
A12: CD | B12: Subventions d'investissement | C12: 10 | D12: =(SUMIF('BALANCE N'!$A$2:$A$50,"14*",'BALANCE N'!$G$2:$G$50)-SUMIF('BALANCE N'!$A$2:$A$50,"14*",'BALANCE N'!$F$2:$F$50)) | E12: =(SUMIF('BALANCE N-1'!$A$2:$A$50,"14*",'BALANCE N-1'!$G$2:$G$50)-SUMIF('BALANCE N-1'!$A$2:$A$50,"14*",'BALANCE N-1'!$F$2:$F$50))
A13: CZ | B13: TOTAL RESSOURCES PROPRES ET ASSIMILEES | D13: =D9+D10+D11+D12 | E13: =E9+E10+E11+E12
A14: DA | B14: Emprunts et dettes assimilees | C14: 11 | D14: =(SUMIF('BALANCE N'!$A$2:$A$50,"18*",'BALANCE N'!$G$2:$G$50)-SUMIF('BALANCE N'!$A$2:$A$50,"18*",'BALANCE N'!$F$2:$F$50)) | E14: =(SUMIF('BALANCE N-1'!$A$2:$A$50,"18*",'BALANCE N-1'!$G$2:$G$50)-SUMIF('BALANCE N-1'!$A$2:$A$50,"18*",'BALANCE N-1'!$F$2:$F$50))
A15: DB | B15: Provisions pour risques et charges | C15: 11 | D15: =(SUMIF('BALANCE N'!$A$2:$A$50,"19*",'BALANCE N'!$G$2:$G$50)-SUMIF('BALANCE N'!$A$2:$A$50,"19*",'BALANCE N'!$F$2:$F$50)) | E15: =(SUMIF('BALANCE N-1'!$A$2:$A$50,"19*",'BALANCE N-1'!$G$2:$G$50)-SUMIF('BALANCE N-1'!$A$2:$A$50,"19*",'BALANCE N-1'!$F$2:$F$50))
A16: DC | B16: TOTAL DETTES FINANCIERES ET RESSOURCES ASSIMILEES | D16: =D14+D15 | E16: =E14+E15
A17: DD | B17: TOTAL RESSOURCES STABLES | D17: =D13+D16 | E17: =E13+E16
A18: DE | B18: Dettes circulantes HAO | C18: 4 | D18: =(SUMIF('BALANCE N'!$A$2:$A$50,"484*",'BALANCE N'!$G$2:$G$50)-SUMIF('BALANCE N'!$A$2:$A$50,"484*",'BALANCE N'!$F$2:$F$50)+SUMIF('BALANCE N'!$A$2:$A$50,"481*",'BALANCE N'!$G$2:$G$50)-SUMIF('BALANCE N'!$A$2:$A$50,"481*",'BALANCE N'!$F$2:$F$50)+SUMIF('BALANCE N'!$A$2:$A$50,"4998*",'BALANCE N'!$G$2:$G$50)-SUMIF('BALANCE N'!$A$2:$A$50,"4998*",'BALANCE N'!$F$2:$F$50)) | E18: =(SUMIF('BALANCE N-1'!$A$2:$A$50,"484*",'BALANCE N-1'!$G$2:$G$50)-SUMIF('BALANCE N-1'!$A$2:$A$50,"484*",'BALANCE N-1'!$F$2:$F$50)+SUMIF('BALANCE N-1'!$A$2:$A$50,"481*",'BALANCE N-1'!$G$2:$G$50)-SUMIF('BALANCE N-1'!$A$2:$A$50,"481*",'BALANCE N-1'!$F$2:$F$50)+SUMIF('BALANCE N-1'!$A$2:$A$50,"4998*",'BALANCE N-1'!$G$2:$G$50)-SUMIF('BALANCE N-1'!$A$2:$A$50,"4998*",'BALANCE N-1'!$F$2:$F$50))
A19: DF | B19: Fonds d'administration | C19: 9 | D19: =(SUMIF('BALANCE N'!$A$2:$A$50,"46*",'BALANCE N'!$G$2:$G$50)-SUMIF('BALANCE N'!$A$2:$A$50,"46*",'BALANCE N'!$F$2:$F$50)) | E19: =(SUMIF('BALANCE N-1'!$A$2:$A$50,"46*",'BALANCE N-1'!$G$2:$G$50)-SUMIF('BALANCE N-1'!$A$2:$A$50,"46*",'BALANCE N-1'!$F$2:$F$50))
A20: DG | B20: Fournisseurs | C20: 12 | D20: =(SUMIF('BALANCE N'!$A$2:$A$50,"40*",'BALANCE N'!$G$2:$G$50)-SUMIF('BALANCE N'!$A$2:$A$50,"40*",'BALANCE N'!$F$2:$F$50)-SUMIF('BALANCE N'!$A$2:$A$50,"409*",'BALANCE N'!$G$2:$G$50)+SUMIF('BALANCE N'!$A$2:$A$50,"409*",'BALANCE N'!$F$2:$F$50)) | E20: =(SUMIF('BALANCE N-1'!$A$2:$A$50,"40*",'BALANCE N-1'!$G$2:$G$50)-SUMIF('BALANCE N-1'!$A$2:$A$50,"40*",'BALANCE N-1'!$F$2:$F$50)-SUMIF('BALANCE N-1'!$A$2:$A$50,"409*",'BALANCE N-1'!$G$2:$G$50)+SUMIF('BALANCE N-1'!$A$2:$A$50,"409*",'BALANCE N-1'!$F$2:$F$50))
A21: DH | B21: Autres dettes | C21: 12 | D21: =(SUMIF('BALANCE N'!$A$2:$A$50,"419*",'BALANCE N'!$G$2:$G$50)-SUMIF('BALANCE N'!$A$2:$A$50,"419*",'BALANCE N'!$F$2:$F$50)-SUMIF('BALANCE N'!$A$2:$A$50,"479*",'BALANCE N'!$G$2:$G$50)+SUMIF('BALANCE N'!$A$2:$A$50,"479*",'BALANCE N'!$F$2:$F$50))+(SUMIF('BALANCE N'!$A$2:$A$50,"43*",'BALANCE N'!$G$2:$G$50)+SUMIF('BALANCE N'!$A$2:$A$50,"47*",'BALANCE N'!$G$2:$G$50)+SUMIF('BALANCE N'!$A$2:$A$50,"44*",'BALANCE N'!$G$2:$G$50)+SUMIF('BALANCE N'!$A$2:$A$50,"42*",'BALANCE N'!$G$2:$G$50)-SUMIF('BALANCE N'!$A$2:$A$50,"479*",'BALANCE N'!$G$2:$G$50)) | E21: =(SUMIF('BALANCE N-1'!$A$2:$A$50,"419*",'BALANCE N-1'!$G$2:$G$50)-SUMIF('BALANCE N-1'!$A$2:$A$50,"419*",'BALANCE N-1'!$F$2:$F$50)-SUMIF('BALANCE N-1'!$A$2:$A$50,"479*",'BALANCE N-1'!$G$2:$G$50)+SUMIF('BALANCE N-1'!$A$2:$A$50,"479*",'BALANCE N-1'!$F$2:$F$50))+(SUMIF('BALANCE N-1'!$A$2:$A$50,"43*",'BALANCE N-1'!$G$2:$G$50)+SUMIF('BALANCE N-1'!$A$2:$A$50,"47*",'BALANCE N-1'!$G$2:$G$50)+SUMIF('BALANCE N-1'!$A$2:$A$50,"44*",'BALANCE N-1'!$G$2:$G$50)+SUMIF('BALANCE N-1'!$A$2:$A$50,"42*",'BALANCE N-1'!$G$2:$G$50)-SUMIF('BALANCE N-1'!$A$2:$A$50,"479*",'BALANCE N-1'!$G$2:$G$50))
A22: DI | B22: Provisions pour risques et charges a court terme | D22: =(SUMIF('BALANCE N'!$A$2:$A$50,"499*",'BALANCE N'!$G$2:$G$50)-SUMIF('BALANCE N'!$A$2:$A$50,"499*",'BALANCE N'!$F$2:$F$50)+SUMIF('BALANCE N'!$A$2:$A$50,"599*",'BALANCE N'!$G$2:$G$50)-SUMIF('BALANCE N'!$A$2:$A$50,"599*",'BALANCE N'!$F$2:$F$50)-SUMIF('BALANCE N'!$A$2:$A$50,"4998*",'BALANCE N'!$G$2:$G$50)+SUMIF('BALANCE N'!$A$2:$A$50,"4998*",'BALANCE N'!$F$2:$F$50)) | E22: =(SUMIF('BALANCE N-1'!$A$2:$A$50,"499*",'BALANCE N-1'!$G$2:$G$50)-SUMIF('BALANCE N-1'!$A$2:$A$50,"499*",'BALANCE N-1'!$F$2:$F$50)+SUMIF('BALANCE N-1'!$A$2:$A$50,"599*",'BALANCE N-1'!$G$2:$G$50)-SUMIF('BALANCE N-1'!$A$2:$A$50,"599*",'BALANCE N-1'!$F$2:$F$50)-SUMIF('BALANCE N-1'!$A$2:$A$50,"4998*",'BALANCE N-1'!$G$2:$G$50)+SUMIF('BALANCE N-1'!$A$2:$A$50,"4998*",'BALANCE N-1'!$F$2:$F$50))
A23: DJ | B23: TOTAL PASSIF CIRCULANT | D23: =D18+D19+D20+D21+D22 | E23: =E18+E19+E20+E21+E22
A24: DW | B24: Banques, etablissements financiers et credits de tresorerie | C24: 13 | D24: =(SUMIF('BALANCE N'!$A$2:$A$50,"56*",'BALANCE N'!$G$2:$G$50)-SUMIF('BALANCE N'!$A$2:$A$50,"56*",'BALANCE N'!$F$2:$F$50))+(SUMIF('BALANCE N'!$A$2:$A$50,"53*",'BALANCE N'!$G$2:$G$50)+SUMIF('BALANCE N'!$A$2:$A$50,"52*",'BALANCE N'!$G$2:$G$50)) | E24: =(SUMIF('BALANCE N-1'!$A$2:$A$50,"56*",'BALANCE N-1'!$G$2:$G$50)-SUMIF('BALANCE N-1'!$A$2:$A$50,"56*",'BALANCE N-1'!$F$2:$F$50))+(SUMIF('BALANCE N-1'!$A$2:$A$50,"53*",'BALANCE N-1'!$G$2:$G$50)+SUMIF('BALANCE N-1'!$A$2:$A$50,"52*",'BALANCE N-1'!$G$2:$G$50))
A25: DX | B25: TOTAL TRESORERIE PASSIF | D25: =D24 | E25: =E24
A26: DY | B26: Ecart de conversion-Passif | C26: 8 | D26: =(SUMIF('BALANCE N'!$A$2:$A$50,"479*",'BALANCE N'!$G$2:$G$50)-SUMIF('BALANCE N'!$A$2:$A$50,"479*",'BALANCE N'!$F$2:$F$50)) | E26: =(SUMIF('BALANCE N-1'!$A$2:$A$50,"479*",'BALANCE N-1'!$G$2:$G$50)-SUMIF('BALANCE N-1'!$A$2:$A$50,"479*",'BALANCE N-1'!$F$2:$F$50))
A27: DZ | B27: TOTAL GENERAL | D27: =D17+D23+D25+D26 | E27: =E17+E23+E25+E26

Sheet Compte Exploitation
A1: - 9 -
D2: COMPTE D'EXPLOITATION PROJETS DE DEVELOPPEMENT
A3: Dénomination sociale : PROJET EAU POTABLE RURALE
A4: Adresse : | D4: Sigle usuel : | E4: PEPR
A5: N° de compte contribuable (NCC) : PD-2023-017 | C5: Exercice clos le 31-12-2025 | D5: Durée (en mois) : 12
A6: N° de télédéclarant (NTD) :
A7: COMPTE D'EXPLOITATION
A8: REF | B8: LIBELLES | C8: NOTE | D8: EXERCICE AU 31/12/N | E8: EXERCICE AU 31/12/N-1
A9: RA | B9: Fonds d'administration consommes | C9: 9 et 14 | D9: =(SUMIF('BALANCE N'!$A$2:$A$50,"702*",'BALANCE N'!$G$2:$G$50)-SUMIF('BALANCE N'!$A$2:$A$50,"702*",'BALANCE N'!$F$2:$F$50)) | E9: =(SUMIF('BALANCE N-1'!$A$2:$A$50,"702*",'BALANCE N-1'!$G$2:$G$50)-SUMIF('BALANCE N-1'!$A$2:$A$50,"702*",'BALANCE N-1'!$F$2:$F$50))
A10: RB | B10: Ventes de marchandises, produits finis et prestations de services | C10: 14 | D10: =(SUMIF('BALANCE N'!$A$2:$A$50,"705*",'BALANCE N'!$G$2:$G$50)-SUMIF('BALANCE N'!$A$2:$A$50,"705*",'BALANCE N'!$F$2:$F$50)) | E10: =(SUMIF('BALANCE N-1'!$A$2:$A$50,"705*",'BALANCE N-1'!$G$2:$G$50)-SUMIF('BALANCE N-1'!$A$2:$A$50,"705*",'BALANCE N-1'!$F$2:$F$50))
A11: RC | B11: Subventions d'exploitation | C11: 14 | D11: =(SUMIF('BALANCE N'!$A$2:$A$50,"71*",'BALANCE N'!$G$2:$G$50)-SUMIF('BALANCE N'!$A$2:$A$50,"71*",'BALANCE N'!$F$2:$F$50)) | E11: =(SUMIF('BALANCE N-1'!$A$2:$A$50,"71*",'BALANCE N-1'!$G$2:$G$50)-SUMIF('BALANCE N-1'!$A$2:$A$50,"71*",'BALANCE N-1'!$F$2:$F$50))
A12: RD | B12: Autres produits et transferts de charges | C12: 14 | D12: =(SUMIF('BALANCE N'!$A$2:$A$50,"75*",'BALANCE N'!$G$2:$G$50)-SUMIF('BALANCE N'!$A$2:$A$50,"75*",'BALANCE N'!$F$2:$F$50)+SUMIF('BALANCE N'!$A$2:$A$50,"72*",'BALANCE N'!$G$2:$G$50)-SUMIF('BALANCE N'!$A$2:$A$50,"72*",'BALANCE N'!$F$2:$F$50)+SUMIF('BALANCE N'!$A$2:$A$50,"78*",'BALANCE N'!$G$2:$G$50)-SUMIF('BALANCE N'!$A$2:$A$50,"78*",'BALANCE N'!$F$2:$F$50)+SUMIF('BALANCE N'!$A$2:$A$50,"73*",'BALANCE N'!$G$2:$G$50)-SUMIF('BALANCE N'!$A$2:$A$50,"73*",'BALANCE N'!$F$2:$F$50)+SUMIF('BALANCE N'!$A$2:$A$50,"77*",'BALANCE N'!$G$2:$G$50)-SUMIF('BALANCE N'!$A$2:$A$50,"77*",'BALANCE N'!$F$2:$F$50)+SUMIF('BALANCE N'!$A$2:$A$50,"706*",'BALANCE N'!$G$2:$G$50)-SUMIF('BALANCE N'!$A$2:$A$50,"706*",'BALANCE N'!$F$2:$F$50)+SUMIF('BALANCE N'!$A$2:$A$50,"707*",'BALANCE N'!$G$2:$G$50)-SUMIF('BALANCE N'!$A$2:$A$50,"707*",'BALANCE N'!$F$2:$F$50)+SUMIF('BALANCE N'!$A$2:$A$50,"708*",'BALANCE N'!$G$2:$G$50)-SUMIF('BALANCE N'!$A$2:$A$50,"708*",'BALANCE N'!$F$2:$F$50)) | E12: =(SUMIF('BALANCE N-1'!$A$2:$A$50,"75*",'BALANCE N-1'!$G$2:$G$50)-SUMIF('BALANCE N-1'!$A$2:$A$50,"75*",'BALANCE N-1'!$F$2:$F$50)+SUMIF('BALANCE N-1'!$A$2:$A$50,"72*",'BALANCE N-1'!$G$2:$G$50)-SUMIF('BALANCE N-1'!$A$2:$A$50,"72*",'BALANCE N-1'!$F$2:$F$50)+SUMIF('BALANCE N-1'!$A$2:$A$50,"78*",'BALANCE N-1'!$G$2:$G$50)-SUMIF('BALANCE N-1'!$A$2:$A$50,"78*",'BALANCE N-1'!$F$2:$F$50)+SUMIF('BALANCE N-1'!$A$2:$A$50,"73*",'BALANCE N-1'!$G$2:$G$50)-SUMIF('BALANCE N-1'!$A$2:$A$50,"73*",'BALANCE N-1'!$F$2:$F$50)+SUMIF('BALANCE N-1'!$A$2:$A$50,"77*",'BALANCE N-1'!$G$2:$G$50)-SUMIF('BALANCE N-1'!$A$2:$A$50,"77*",'BALANCE N-1'!$F$2:$F$50)+SUMIF('BALANCE N-1'!$A$2:$A$50,"706*",'BALANCE N-1'!$G$2:$G$50)-SUMIF('BALANCE N-1'!$A$2:$A$50,"706*",'BALANCE N-1'!$F$2:$F$50)+SUMIF('BALANCE N-1'!$A$2:$A$50,"707*",'BALANCE N-1'!$G$2:$G$50)-SUMIF('BALANCE N-1'!$A$2:$A$50,"707*",'BALANCE N-1'!$F$2:$F$50)+SUMIF('BALANCE N-1'!$A$2:$A$50,"708*",'BALANCE N-1'!$G$2:$G$50)-SUMIF('BALANCE N-1'!$A$2:$A$50,"708*",'BALANCE N-1'!$F$2:$F$50))
A13: RE | B13: Reprises de provisions | C13: 22 | D13: =(SUMIF('BALANCE N'!$A$2:$A$50,"79*",'BALANCE N'!$G$2:$G$50)-SUMIF('BALANCE N'!$A$2:$A$50,"79*",'BALANCE N'!$F$2:$F$50)) | E13: =(SUMIF('BALANCE N-1'!$A$2:$A$50,"79*",'BALANCE N-1'!$G$2:$G$50)-SUMIF('BALANCE N-1'!$A$2:$A$50,"79*",'BALANCE N-1'!$F$2:$F$50))
A14: XA | B14: REVENUS | D14: =D9+D10+D11+D12+D13 | E14: =E9+E10+E11+E12+E13
A15: TA | B15: Achats de biens, marchandises, matieres premieres et fournitures liees | C15: 15 | D15: =(SUMIF('BALANCE N'!$A$2:$A$50,"602*",'BALANCE N'!$G$2:$G$50)-SUMIF('BALANCE N'!$A$2:$A$50,"602*",'BALANCE N'!$F$2:$F$50)+SUMIF('BALANCE N'!$A$2:$A$50,"601*",'BALANCE N'!$G$2:$G$50)-SUMIF('BALANCE N'!$A$2:$A$50,"601*",'BALANCE N'!$F$2:$F$50)) | E15: =(SUMIF('BALANCE N-1'!$A$2:$A$50,"602*",'BALANCE N-1'!$G$2:$G$50)-SUMIF('BALANCE N-1'!$A$2:$A$50,"602*",'BALANCE N-1'!$F$2:$F$50)+SUMIF('BALANCE N-1'!$A$2:$A$50,"601*",'BALANCE N-1'!$G$2:$G$50)-SUMIF('BALANCE N-1'!$A$2:$A$50,"601*",'BALANCE N-1'!$F$2:$F$50))
A16: TB | B16: Autres achats | C16: 15 | D16: =(SUMIF('BALANCE N'!$A$2:$A$50,"604*",'BALANCE N'!$G$2:$G$50)-SUMIF('BALANCE N'!$A$2:$A$50,"604*",'BALANCE N'!$F$2:$F$50)+SUMIF('BALANCE N'!$A$2:$A$50,"608*",'BALANCE N'!$G$2:$G$50)-SUMIF('BALANCE N'!$A$2:$A$50,"608*",'BALANCE N'!$F$2:$F$50)+SUMIF('BALANCE N'!$A$2:$A$50,"605*",'BALANCE N'!$G$2:$G$50)-SUMIF('BALANCE N'!$A$2:$A$50,"605*",'BALANCE N'!$F$2:$F$50)+SUMIF('BALANCE N'!$A$2:$A$50,"606*",'BALANCE N'!$G$2:$G$50)-SUMIF('BALANCE N'!$A$2:$A$50,"606*",'BALANCE N'!$F$2:$F$50)) | E16: =(SUMIF('BALANCE N-1'!$A$2:$A$50,"604*",'BALANCE N-1'!$G$2:$G$50)-SUMIF('BALANCE N-1'!$A$2:$A$50,"604*",'BALANCE N-1'!$F$2:$F$50)+SUMIF('BALANCE N-1'!$A$2:$A$50,"608*",'BALANCE N-1'!$G$2:$G$50)-SUMIF('BALANCE N-1'!$A$2:$A$50,"608*",'BALANCE N-1'!$F$2:$F$50)+SUMIF('BALANCE N-1'!$A$2:$A$50,"605*",'BALANCE N-1'!$G$2:$G$50)-SUMIF('BALANCE N-1'!$A$2:$A$50,"605*",'BALANCE N-1'!$F$2:$F$50)+SUMIF('BALANCE N-1'!$A$2:$A$50,"606*",'BALANCE N-1'!$G$2:$G$50)-SUMIF('BALANCE N-1'!$A$2:$A$50,"606*",'BALANCE N-1'!$F$2:$F$50))
A17: TC | B17: Variation de stocks de biens, marchandises, matieres et fournitures | C17: 5 | D17: =(SUMIF('BALANCE N'!$A$2:$A$50,"603*",'BALANCE N'!$G$2:$G$50)-SUMIF('BALANCE N'!$A$2:$A$50,"603*",'BALANCE N'!$F$2:$F$50)) | E17: =(SUMIF('BALANCE N-1'!$A$2:$A$50,"603*",'BALANCE N-1'!$G$2:$G$50)-SUMIF('BALANCE N-1'!$A$2:$A$50,"603*",'BALANCE N-1'!$F$2:$F$50))
A18: TD | B18: Transports | C18: 16 | D18: =(SUMIF('BALANCE N'!$A$2:$A$50,"61*",'BALANCE N'!$G$2:$G$50)-SUMIF('BALANCE N'!$A$2:$A$50,"61*",'BALANCE N'!$F$2:$F$50)) | E18: =(SUMIF('BALANCE N-1'!$A$2:$A$50,"61*",'BALANCE N-1'!$G$2:$G$50)-SUMIF('BALANCE N-1'!$A$2:$A$50,"61*",'BALANCE N-1'!$F$2:$F$50))
A19: TG | B19: Services exterieurs | C19: 17 | D19: =(SUMIF('BALANCE N'!$A$2:$A$50,"62*",'BALANCE N'!$G$2:$G$50)-SUMIF('BALANCE N'!$A$2:$A$50,"62*",'BALANCE N'!$F$2:$F$50)+SUMIF('BALANCE N'!$A$2:$A$50,"63*",'BALANCE N'!$G$2:$G$50)-SUMIF('BALANCE N'!$A$2:$A$50,"63*",'BALANCE N'!$F$2:$F$50)) | E19: =(SUMIF('BALANCE N-1'!$A$2:$A$50,"62*",'BALANCE N-1'!$G$2:$G$50)-SUMIF('BALANCE N-1'!$A$2:$A$50,"62*",'BALANCE N-1'!$F$2:$F$50)+SUMIF('BALANCE N-1'!$A$2:$A$50,"63*",'BALANCE N-1'!$G$2:$G$50)-SUMIF('BALANCE N-1'!$A$2:$A$50,"63*",'BALANCE N-1'!$F$2:$F$50))
A20: TH | B20: Impots et taxes | C20: 18 | D20: =(SUMIF('BALANCE N'!$A$2:$A$50,"64*",'BALANCE N'!$G$2:$G$50)-SUMIF('BALANCE N'!$A$2:$A$50,"64*",'BALANCE N'!$F$2:$F$50)) | E20: =(SUMIF('BALANCE N-1'!$A$2:$A$50,"64*",'BALANCE N-1'!$G$2:$G$50)-SUMIF('BALANCE N-1'!$A$2:$A$50,"64*",'BALANCE N-1'!$F$2:$F$50))
A21: TI | B21: Autres charges | C21: 19 | D21: =(SUMIF('BALANCE N'!$A$2:$A$50,"65*",'BALANCE N'!$G$2:$G$50)-SUMIF('BALANCE N'!$A$2:$A$50,"65*",'BALANCE N'!$F$2:$F$50)) | E21: =(SUMIF('BALANCE N-1'!$A$2:$A$50,"65*",'BALANCE N-1'!$G$2:$G$50)-SUMIF('BALANCE N-1'!$A$2:$A$50,"65*",'BALANCE N-1'!$F$2:$F$50))
A22: TJ | B22: Charges de personnel | C22: 20A | D22: =(SUMIF('BALANCE N'!$A$2:$A$50,"66*",'BALANCE N'!$G$2:$G$50)-SUMIF('BALANCE N'!$A$2:$A$50,"66*",'BALANCE N'!$F$2:$F$50)) | E22: =(SUMIF('BALANCE N-1'!$A$2:$A$50,"66*",'BALANCE N-1'!$G$2:$G$50)-SUMIF('BALANCE N-1'!$A$2:$A$50,"66*",'BALANCE N-1'!$F$2:$F$50))
A23: TK | B23: Frais financiers et charges assimilees | C23: 21 | D23: =(SUMIF('BALANCE N'!$A$2:$A$50,"67*",'BALANCE N'!$G$2:$G$50)-SUMIF('BALANCE N'!$A$2:$A$50,"67*",'BALANCE N'!$F$2:$F$50)) | E23: =(SUMIF('BALANCE N-1'!$A$2:$A$50,"67*",'BALANCE N-1'!$G$2:$G$50)-SUMIF('BALANCE N-1'!$A$2:$A$50,"67*",'BALANCE N-1'!$F$2:$F$50))
A24: TJ | B24: Dotations aux amortissements et aux provisions | C24: 22 | D24: =(SUMIF('BALANCE N'!$A$2:$A$50,"68*",'BALANCE N'!$G$2:$G$50)-SUMIF('BALANCE N'!$A$2:$A$50,"68*",'BALANCE N'!$F$2:$F$50)+SUMIF('BALANCE N'!$A$2:$A$50,"69*",'BALANCE N'!$G$2:$G$50)-SUMIF('BALANCE N'!$A$2:$A$50,"69*",'BALANCE N'!$F$2:$F$50)) | E24: =(SUMIF('BALANCE N-1'!$A$2:$A$50,"68*",'BALANCE N-1'!$G$2:$G$50)-SUMIF('BALANCE N-1'!$A$2:$A$50,"68*",'BALANCE N-1'!$F$2:$F$50)+SUMIF('BALANCE N-1'!$A$2:$A$50,"69*",'BALANCE N-1'!$G$2:$G$50)-SUMIF('BALANCE N-1'!$A$2:$A$50,"69*",'BALANCE N-1'!$F$2:$F$50))
A25: TK | B25: Produits H.A.O. | C25: 23 | D25: =(SUMIF('BALANCE N'!$A$2:$A$50,"84*",'BALANCE N'!$G$2:$G$50)-SUMIF('BALANCE N'!$A$2:$A$50,"84*",'BALANCE N'!$F$2:$F$50)+SUMIF('BALANCE N'!$A$2:$A$50,"86*",'BALANCE N'!$G$2:$G$50)-SUMIF('BALANCE N'!$A$2:$A$50,"86*",'BALANCE N'!$F$2:$F$50)+SUMIF('BALANCE N'!$A$2:$A$50,"88*",'BALANCE N'!$G$2:$G$50)-SUMIF('BALANCE N'!$A$2:$A$50,"88*",'BALANCE N'!$F$2:$F$50)+SUMIF('BALANCE N'!$A$2:$A$50,"82*",'BALANCE N'!$G$2:$G$50)-SUMIF('BALANCE N'!$A$2:$A$50,"82*",'BALANCE N'!$F$2:$F$50)) | E25: =(SUMIF('BALANCE N-1'!$A$2:$A$50,"84*",'BALANCE N-1'!$G$2:$G$50)-SUMIF('BALANCE N-1'!$A$2:$A$50,"84*",'BALANCE N-1'!$F$2:$F$50)+SUMIF('BALANCE N-1'!$A$2:$A$50,"86*",'BALANCE N-1'!$G$2:$G$50)-SUMIF('BALANCE N-1'!$A$2:$A$50,"86*",'BALANCE N-1'!$F$2:$F$50)+SUMIF('BALANCE N-1'!$A$2:$A$50,"88*",'BALANCE N-1'!$G$2:$G$50)-SUMIF('BALANCE N-1'!$A$2:$A$50,"88*",'BALANCE N-1'!$F$2:$F$50)+SUMIF('BALANCE N-1'!$A$2:$A$50,"82*",'BALANCE N-1'!$G$2:$G$50)-SUMIF('BALANCE N-1'!$A$2:$A$50,"82*",'BALANCE N-1'!$F$2:$F$50))
A26: TL | B26: Charges H.A.O. | C26: 23 | D26: =(SUMIF('BALANCE N'!$A$2:$A$50,"81*",'BALANCE N'!$G$2:$G$50)-SUMIF('BALANCE N'!$A$2:$A$50,"81*",'BALANCE N'!$F$2:$F$50)+SUMIF('BALANCE N'!$A$2:$A$50,"87*",'BALANCE N'!$G$2:$G$50)-SUMIF('BALANCE N'!$A$2:$A$50,"87*",'BALANCE N'!$F$2:$F$50)+SUMIF('BALANCE N'!$A$2:$A$50,"85*",'BALANCE N'!$G$2:$G$50)-SUMIF('BALANCE N'!$A$2:$A$50,"85*",'BALANCE N'!$F$2:$F$50)+SUMIF('BALANCE N'!$A$2:$A$50,"83*",'BALANCE N'!$G$2:$G$50)-SUMIF('BALANCE N'!$A$2:$A$50,"83*",'BALANCE N'!$F$2:$F$50)) | E26: =(SUMIF('BALANCE N-1'!$A$2:$A$50,"81*",'BALANCE N-1'!$G$2:$G$50)-SUMIF('BALANCE N-1'!$A$2:$A$50,"81*",'BALANCE N-1'!$F$2:$F$50)+SUMIF('BALANCE N-1'!$A$2:$A$50,"87*",'BALANCE N-1'!$G$2:$G$50)-SUMIF('BALANCE N-1'!$A$2:$A$50,"87*",'BALANCE N-1'!$F$2:$F$50)+SUMIF('BALANCE N-1'!$A$2:$A$50,"85*",'BALANCE N-1'!$G$2:$G$50)-SUMIF('BALANCE N-1'!$A$2:$A$50,"85*",'BALANCE N-1'!$F$2:$F$50)+SUMIF('BALANCE N-1'!$A$2:$A$50,"83*",'BALANCE N-1'!$G$2:$G$50)-SUMIF('BALANCE N-1'!$A$2:$A$50,"83*",'BALANCE N-1'!$F$2:$F$50))
A27: XB | B27: CHARGES DE FONCTIONNEMENT | D27: =D15+D16+D17+D18+D19+D20+D21+D22+D23+D24+D25+D26 | E27: =E15+E16+E17+E18+E19+E20+E21+E22+E23+E24+E25+E26
A28: XC | B28: SOLDE DES OPERATIONS DE L'EXERCICE | D28: =D14+D27 | E28: =E14+E27

Sheet NOTES ANNEXES
A1: - 10 -
I2: NOTES ANNEXES
A3: Dénomination sociale : PROJET EAU POTABLE RURALE
A4: Adresse : | I4: Sigle usuel : | J4: PEPR
A5: N° de compte contribuable (NCC) : PD-2023-017 | G5: Exercice clos le 31-12-2025 | I5: Durée (en mois) : 12
A6: N° de télédéclarant (NTD) :
A7: FICHE RECAPITULATIVE NOTES ANNEXES PRESENTEES (1)
A8: NOTES | B8: INTITULES | I8: A (2) | J8: N/A (2)
A9: Partie 1 : Informations générales
A10: Note 1 | B10: INFORMATIONS OBLIGATOIRES
A11: Partie 2 : Notes sur le tableau emplois-ressources, le tableau d'exécution budgétaire et la réconciliation de trésorerie
A12: Note 2 | B12: INFORMATIONS SPÉCIFIQUES
A13: Partie 3 : Notes sur le bilan
A14: Note 3A | B14: IMMOBILISATIONS BRUTES
A15: Note 3B | B15: BIENS PRIS EN LOCATION-ACQUISITION
A16: Note 4 | B16: ACTIF CIRCULANT ET DETTES CIRCULANTES HAO
A17: Note 5 | B17: STOCKS ET ENCOURS
A18: Note 6 | B18: CLIENTS-USAGERS ET AUTRES CRÉANCES
A19: Note 7 | B19: DISPONIBILITÉS
A20: Note 8 | B20: ÉCARTS DE CONVERSION
A21: Note 9 | B21: FONDS DU BAILLEUR
A22: Note 10 | B22: SUBVENTIONS
A23: Note 11 | B23: DETTES FINANCIÈRES ET RESSOURCES ASSIMILÉES
A24: Note 12 | B24: DETTES FOURNISSEURS ET ASSIMILÉES, FISCALES ET SOCIALES
A25: Note 13 | B25: BANQUES, CRÉDIT D'ESCOMPTE ET DE TRÉSORERIE
A26: Partie 4 : Notes sur le compte d'exploitation
A27: Note 14 | B27: REVENUS ET AUTRES PRODUITS
A28: Note 15 | B28: ACHATS
A29: Note 16 | B29: TRANSPORTS
A30: Note 17 | B30: SERVICES EXTÉRIEURS
A31: Note 18 | B31: IMPÔTS ET TAXES
A32: Note 19 | B32: AUTRES CHARGES
A33: Note 20A | B33: CHARGES DE PERSONNEL
A34: Note 20B | B34: EFFECTIFS, MASSE SALARIALE ET PERSONNEL EXTÉRIEUR
A35: Note 21 | B35: CHARGES ET REVENUS FINANCIERS
A36: Note 22 | B36: DOTATIONS ET CHARGES POUR PROVISIONS
A37: Note 23 | B37: AUTRES CHARGES ET PRODUITS HAO
A38: Note 24 | B38: TABLEAU D'EXÉCUTION BUDGÉTAIRE
A40: (1) Les notes non documentées ne doivent pas être jointes aux états financiers ; dans une note, les lignes non chiffrées doivent être supprimées.
A41: (2) A : applicable ; N/A : non applicable. Cocher la colonne correspondante pour chaque note.

Sheet NOTE 1
A1: - 11 -
E2: NOTE 1 PROJETS DE DEVELOPPEMENT
A3: Dénomination sociale : PROJET EAU POTABLE RURALE
A4: Adresse : | E4: Sigle usuel : | F4: PEPR
A5: N° de compte contribuable (NCC) : PD-2023-017 | C5: Exercice clos le 31-12-2025 | E5: Durée (en mois) : 12
A6: N° de télédéclarant (NTD) :
A7: NOTE 1 : INFORMATIONS OBLIGATOIRES
A9: A - IDENTITÉ, ORGANISATION : date de début du projet, nature du projet de développement, activité ou mission réalisée, données chiffrées (effectifs, total des ressources affectées, moyens utilisés).
A12: B - DÉCLARATION DE CONFORMITÉ AU SYSTÈME COMPTABLE DES ENTITÉS À BUT NON LUCRATIF ET FAITS MARQUANTS DE L'EXERCICE.
A15: C - RÈGLES, MÉTHODES COMPTABLES ET DÉROGATION AUX PRINCIPES COMPTABLES.
A18: D - INFORMATIONS COMPLÉMENTAIRES RELATIVES AU BILAN ET AU COMPTE D'EXPLOITATION.

Sheet NOTE 2
A1: - 12 -
E2: NOTE 2 PROJETS DE DEVELOPPEMENT
A3: Dénomination sociale : PROJET EAU POTABLE RURALE
A4: Adresse : | E4: Sigle usuel : | F4: PEPR
A5: N° de compte contribuable (NCC) : PD-2023-017 | C5: Exercice clos le 31-12-2025 | E5: Durée (en mois) : 12
A6: N° de télédéclarant (NTD) :
A7: NOTE 2 : INFORMATIONS SPÉCIFIQUES
A9: A - TABLEAU EMPLOIS RESSOURCES : faits marquants.
A12: B - TABLEAU D'EXÉCUTION BUDGÉTAIRE : expliquer les écarts significatifs entre budget et réalisation.
A15: C - TABLEAU DE RÉCONCILIATION DE TRÉSORERIE : faits marquants.

Sheet NOTE 3A
A1: - 13 -
D2: NOTE 3A PROJETS DE DEVELOPPEMENT
A3: Dénomination sociale : PROJET EAU POTABLE RURALE
A4: Adresse : | D4: Sigle usuel : | E4: PEPR
A5: N° de compte contribuable (NCC) : PD-2023-017 | C5: Exercice clos le 31-12-2025 | D5: Durée (en mois) : 12
A6: N° de télédéclarant (NTD) :
A7: NOTE 3A : IMMOBILISATIONS BRUTES
A8: RUBRIQUES | B8: Montant brut à l'ouverture (A) | C8: Augmentations (B) | D8: Diminutions (C) | E8: Montant brut à la clôture (D = A + B - C)
A9: IMMOBILISATIONS INCORPORELLES
A10: Brevets, licences, logiciels et droits similaires | B10: =SUMIF('BALANCE N-1'!$A$2:$A$50,"212*",'BALANCE N-1'!$F$2:$F$50)-SUMIF('BALANCE N-1'!$A$2:$A$50,"212*",'BALANCE N-1'!$G$2:$G$50)+SUMIF('BALANCE N-1'!$A$2:$A$50,"214*",'BALANCE N-1'!$F$2:$F$50)-SUMIF('BALANCE N-1'!$A$2:$A$50,"214*",'BALANCE N-1'!$G$2:$G$50)+SUMIF('BALANCE N-1'!$A$2:$A$50,"213*",'BALANCE N-1'!$F$2:$F$50)-SUMIF('BALANCE N-1'!$A$2:$A$50,"213*",'BALANCE N-1'!$G$2:$G$50) | C10: =MAX(0,(SUMIF('BALANCE N'!$A$2:$A$50,"212*",'BALANCE N'!$F$2:$F$50)-SUMIF('BALANCE N'!$A$2:$A$50,"212*",'BALANCE N'!$G$2:$G$50)+SUMIF('BALANCE N'!$A$2:$A$50,"214*",'BALANCE N'!$F$2:$F$50)-SUMIF('BALANCE N'!$A$2:$A$50,"214*",'BALANCE N'!$G$2:$G$50)+SUMIF('BALANCE N'!$A$2:$A$50,"213*",'BALANCE N'!$F$2:$F$50)-SUMIF('BALANCE N'!$A$2:$A$50,"213*",'BALANCE N'!$G$2:$G$50))-(SUMIF('BALANCE N-1'!$A$2:$A$50,"212*",'BALANCE N-1'!$F$2:$F$50)-SUMIF('BALANCE N-1'!$A$2:$A$50,"212*",'BALANCE N-1'!$G$2:$G$50)+SUMIF('BALANCE N-1'!$A$2:$A$50,"214*",'BALANCE N-1'!$F$2:$F$50)-SUMIF('BALANCE N-1'!$A$2:$A$50,"214*",'BALANCE N-1'!$G$2:$G$50)+SUMIF('BALANCE N-1'!$A$2:$A$50,"213*",'BALANCE N-1'!$F$2:$F$50)-SUMIF('BALANCE N-1'!$A$2:$A$50,"213*",'BALANCE N-1'!$G$2:$G$50))) | D10: =MAX(0,(SUMIF('BALANCE N-1'!$A$2:$A$50,"212*",'BALANCE N-1'!$F$2:$F$50)-SUMIF('BALANCE N-1'!$A$2:$A$50,"212*",'BALANCE N-1'!$G$2:$G$50)+SUMIF('BALANCE N-1'!$A$2:$A$50,"214*",'BALANCE N-1'!$F$2:$F$50)-SUMIF('BALANCE N-1'!$A$2:$A$50,"214*",'BALANCE N-1'!$G$2:$G$50)+SUMIF('BALANCE N-1'!$A$2:$A$50,"213*",'BALANCE N-1'!$F$2:$F$50)-SUMIF('BALANCE N-1'!$A$2:$A$50,"213*",'BALANCE N-1'!$G$2:$G$50))-(SUMIF('BALANCE N'!$A$2:$A$50,"212*",'BALANCE N'!$F$2:$F$50)-SUMIF('BALANCE N'!$A$2:$A$50,"212*",'BALANCE N'!$G$2:$G$50)+SUMIF('BALANCE N'!$A$2:$A$50,"214*",'BALANCE N'!$F$2:$F$50)-SUMIF('BALANCE N'!$A$2:$A$50,"214*",'BALANCE N'!$G$2:$G$50)+SUMIF('BALANCE N'!$A$2:$A$50,"213*",'BALANCE N'!$F$2:$F$50)-SUMIF('BALANCE N'!$A$2:$A$50,"213*",'BALANCE N'!$G$2:$G$50))) | E10: =B10+C10-D10
A11: Avances et acomptes sur immobilisations incorporelles | B11: =SUMIF('BALANCE N-1'!$A$2:$A$50,"251*",'BALANCE N-1'!$F$2:$F$50)-SUMIF('BALANCE N-1'!$A$2:$A$50,"251*",'BALANCE N-1'!$G$2:$G$50) | C11: =MAX(0,(SUMIF('BALANCE N'!$A$2:$A$50,"251*",'BALANCE N'!$F$2:$F$50)-SUMIF('BALANCE N'!$A$2:$A$50,"251*",'BALANCE N'!$G$2:$G$50))-(SUMIF('BALANCE N-1'!$A$2:$A$50,"251*",'BALANCE N-1'!$F$2:$F$50)-SUMIF('BALANCE N-1'!$A$2:$A$50,"251*",'BALANCE N-1'!$G$2:$G$50))) | D11: =MAX(0,(SUMIF('BALANCE N-1'!$A$2:$A$50,"251*",'BALANCE N-1'!$F$2:$F$50)-SUMIF('BALANCE N-1'!$A$2:$A$50,"251*",'BALANCE N-1'!$G$2:$G$50))-(SUMIF('BALANCE N'!$A$2:$A$50,"251*",'BALANCE N'!$F$2:$F$50)-SUMIF('BALANCE N'!$A$2:$A$50,"251*",'BALANCE N'!$G$2:$G$50))) | E11: =B11+C11-D11
A12: Autres immobilisations incorporelles | B12: =SUMIF('BALANCE N-1'!$A$2:$A$50,"219*",'BALANCE N-1'!$F$2:$F$50)-SUMIF('BALANCE N-1'!$A$2:$A$50,"219*",'BALANCE N-1'!$G$2:$G$50)+SUMIF('BALANCE N-1'!$A$2:$A$50,"218*",'BALANCE N-1'!$F$2:$F$50)-SUMIF('BALANCE N-1'!$A$2:$A$50,"218*",'BALANCE N-1'!$G$2:$G$50) | C12: =MAX(0,(SUMIF('BALANCE N'!$A$2:$A$50,"219*",'BALANCE N'!$F$2:$F$50)-SUMIF('BALANCE N'!$A$2:$A$50,"219*",'BALANCE N'!$G$2:$G$50)+SUMIF('BALANCE N'!$A$2:$A$50,"218*",'BALANCE N'!$F$2:$F$50)-SUMIF('BALANCE N'!$A$2:$A$50,"218*",'BALANCE N'!$G$2:$G$50))-(SUMIF('BALANCE N-1'!$A$2:$A$50,"219*",'BALANCE N-1'!$F$2:$F$50)-SUMIF('BALANCE N-1'!$A$2:$A$50,"219*",'BALANCE N-1'!$G$2:$G$50)+SUMIF('BALANCE N-1'!$A$2:$A$50,"218*",'BALANCE N-1'!$F$2:$F$50)-SUMIF('BALANCE N-1'!$A$2:$A$50,"218*",'BALANCE N-1'!$G$2:$G$50))) | D12: =MAX(0,(SUMIF('BALANCE N-1'!$A$2:$A$50,"219*",'BALANCE N-1'!$F$2:$F$50)-SUMIF('BALANCE N-1'!$A$2:$A$50,"219*",'BALANCE N-1'!$G$2:$G$50)+SUMIF('BALANCE N-1'!$A$2:$A$50,"218*",'BALANCE N-1'!$F$2:$F$50)-SUMIF('BALANCE N-1'!$A$2:$A$50,"218*",'BALANCE N-1'!$G$2:$G$50))-(SUMIF('BALANCE N'!$A$2:$A$50,"219*",'BALANCE N'!$F$2:$F$50)-SUMIF('BALANCE N'!$A$2:$A$50,"219*",'BALANCE N'!$G$2:$G$50)+SUMIF('BALANCE N'!$A$2:$A$50,"218*",'BALANCE N'!$F$2:$F$50)-SUMIF('BALANCE N'!$A$2:$A$50,"218*",'BALANCE N'!$G$2:$G$50))) | E12: =B12+C12-D12
A13: IMMOBILISATIONS CORPORELLES
A14: Terrains hors immeuble de placement | B14: =SUMIF('BALANCE N-1'!$A$2:$A$50,"22*",'BALANCE N-1'!$F$2:$F$50)-SUMIF('BALANCE N-1'!$A$2:$A$50,"22*",'BALANCE N-1'!$G$2:$G$50)-SUMIF('BALANCE N-1'!$A$2:$A$50,"2281*",'BALANCE N-1'!$F$2:$F$50)+SUMIF('BALANCE N-1'!$A$2:$A$50,"2281*",'BALANCE N-1'!$G$2:$G$50) | C14: =MAX(0,(SUMIF('BALANCE N'!$A$2:$A$50,"22*",'BALANCE N'!$F$2:$F$50)-SUMIF('BALANCE N'!$A$2:$A$50,"22*",'BALANCE N'!$G$2:$G$50)-SUMIF('BALANCE N'!$A$2:$A$50,"2281*",'BALANCE N'!$F$2:$F$50)+SUMIF('BALANCE N'!$A$2:$A$50,"2281*",'BALANCE N'!$G$2:$G$50))-(SUMIF('BALANCE N-1'!$A$2:$A$50,"22*",'BALANCE N-1'!$F$2:$F$50)-SUMIF('BALANCE N-1'!$A$2:$A$50,"22*",'BALANCE N-1'!$G$2:$G$50)-SUMIF('BALANCE N-1'!$A$2:$A$50,"2281*",'BALANCE N-1'!$F$2:$F$50)+SUMIF('BALANCE N-1'!$A$2:$A$50,"2281*",'BALANCE N-1'!$G$2:$G$50))) | D14: =MAX(0,(SUMIF('BALANCE N-1'!$A$2:$A$50,"22*",'BALANCE N-1'!$F$2:$F$50)-SUMIF('BALANCE N-1'!$A$2:$A$50,"22*",'BALANCE N-1'!$G$2:$G$50)-SUMIF('BALANCE N-1'!$A$2:$A$50,"2281*",'BALANCE N-1'!$F$2:$F$50)+SUMIF('BALANCE N-1'!$A$2:$A$50,"2281*",'BALANCE N-1'!$G$2:$G$50))-(SUMIF('BALANCE N'!$A$2:$A$50,"22*",'BALANCE N'!$F$2:$F$50)-SUMIF('BALANCE N'!$A$2:$A$50,"22*",'BALANCE N'!$G$2:$G$50)-SUMIF('BALANCE N'!$A$2:$A$50,"2281*",'BALANCE N'!$F$2:$F$50)+SUMIF('BALANCE N'!$A$2:$A$50,"2281*",'BALANCE N'!$G$2:$G$50))) | E14: =B14+C14-D14
A15: Terrains - immeuble de placement | B15: =SUMIF('BALANCE N-1'!$A$2:$A$50,"2281*",'BALANCE N-1'!$F$2:$F$50)-SUMIF('BALANCE N-1'!$A$2:$A$50,"2281*",'BALANCE N-1'!$G$2:$G$50) | C15: =MAX(0,(SUMIF('BALANCE N'!$A$2:$A$50,"2281*",'BALANCE N'!$F$2:$F$50)-SUMIF('BALANCE N'!$A$2:$A$50,"2281*",'BALANCE N'!$G$2:$G$50))-(SUMIF('BALANCE N-1'!$A$2:$A$50,"2281*",'BALANCE N-1'!$F$2:$F$50)-SUMIF('BALANCE N-1'!$A$2:$A$50,"2281*",'BALANCE N-1'!$G$2:$G$50))) | D15: =MAX(0,(SUMIF('BALANCE N-1'!$A$2:$A$50,"2281*",'BALANCE N-1'!$F$2:$F$50)-SUMIF('BALANCE N-1'!$A$2:$A$50,"2281*",'BALANCE N-1'!$G$2:$G$50))-(SUMIF('BALANCE N'!$A$2:$A$50,"2281*",'BALANCE N'!$F$2:$F$50)-SUMIF('BALANCE N'!$A$2:$A$50,"2281*",'BALANCE N'!$G$2:$G$50))) | E15: =B15+C15-D15
A16: Bâtiments hors immeuble de placement | B16: =SUMIF('BALANCE N-1'!$A$2:$A$50,"231*",'BALANCE N-1'!$F$2:$F$50)-SUMIF('BALANCE N-1'!$A$2:$A$50,"231*",'BALANCE N-1'!$G$2:$G$50)+SUMIF('BALANCE N-1'!$A$2:$A$50,"232*",'BALANCE N-1'!$F$2:$F$50)-SUMIF('BALANCE N-1'!$A$2:$A$50,"232*",'BALANCE N-1'!$G$2:$G$50)+SUMIF('BALANCE N-1'!$A$2:$A$50,"233*",'BALANCE N-1'!$F$2:$F$50)-SUMIF('BALANCE N-1'!$A$2:$A$50,"233*",'BALANCE N-1'!$G$2:$G$50)+SUMIF('BALANCE N-1'!$A$2:$A$50,"2393*",'BALANCE N-1'!$F$2:$F$50)-SUMIF('BALANCE N-1'!$A$2:$A$50,"2393*",'BALANCE N-1'!$G$2:$G$50)+SUMIF('BALANCE N-1'!$A$2:$A$50,"2391*",'BALANCE N-1'!$F$2:$F$50)-SUMIF('BALANCE N-1'!$A$2:$A$50,"2391*",'BALANCE N-1'!$G$2:$G$50)+SUMIF('BALANCE N-1'!$A$2:$A$50,"2392*",'BALANCE N-1'!$F$2:$F$50)-SUMIF('BALANCE N-1'!$A$2:$A$50,"2392*",'BALANCE N-1'!$G$2:$G$50)-SUMIF('BALANCE N-1'!$A$2:$A$50,"2325*",'BALANCE N-1'!$F$2:$F$50)+SUMIF('BALANCE N-1'!$A$2:$A$50,"2325*",'BALANCE N-1'!$G$2:$G$50)-SUMIF('BALANCE N-1'!$A$2:$A$50,"2315*",'BALANCE N-1'!$F$2:$F$50)+SUMIF('BALANCE N-1'!$A$2:$A$50,"2315*",'BALANCE N-1'!$G$2:$G$50) | C16: =MAX(0,(SUMIF('BALANCE N'!$A$2:$A$50,"231*",'BALANCE N'!$F$2:$F$50)-SUMIF('BALANCE N'!$A$2:$A$50,"231*",'BALANCE N'!$G$2:$G$50)+SUMIF('BALANCE N'!$A$2:$A$50,"232*",'BALANCE N'!$F$2:$F$50)-SUMIF('BALANCE N'!$A$2:$A$50,"232*",'BALANCE N'!$G$2:$G$50)+SUMIF('BALANCE N'!$A$2:$A$50,"233*",'BALANCE N'!$F$2:$F$50)-SUMIF('BALANCE N'!$A$2:$A$50,"233*",'BALANCE N'!$G$2:$G$50)+SUMIF('BALANCE N'!$A$2:$A$50,"2393*",'BALANCE N'!$F$2:$F$50)-SUMIF('BALANCE N'!$A$2:$A$50,"2393*",'BALANCE N'!$G$2:$G$50)+SUMIF('BALANCE N'!$A$2:$A$50,"2391*",'BALANCE N'!$F$2:$F$50)-SUMIF('BALANCE N'!$A$2:$A$50,"2391*",'BALANCE N'!$G$2:$G$50)+SUMIF('BALANCE N'!$A$2:$A$50,"2392*",'BALANCE N'!$F$2:$F$50)-SUMIF('BALANCE N'!$A$2:$A$50,"2392*",'BALANCE N'!$G$2:$G$50)-SUMIF('BALANCE N'!$A$2:$A$50,"2325*",'BALANCE N'!$F$2:$F$50)+SUMIF('BALANCE N'!$A$2:$A$50,"2325*",'BALANCE N'!$G$2:$G$50)-SUMIF('BALANCE N'!$A$2:$A$50,"2315*",'BALANCE N'!$F$2:$F$50)+SUMIF('BALANCE N'!$A$2:$A$50,"2315*",'BALANCE N'!$G$2:$G$50))-(SUMIF('BALANCE N-1'!$A$2:$A$50,"231*",'BALANCE N-1'!$F$2:$F$50)-SUMIF('BALANCE N-1'!$A$2:$A$50,"231*",'BALANCE N-1'!$G$2:$G$50)+SUMIF('BALANCE N-1'!$A$2:$A$50,"232*",'BALANCE N-1'!$F$2:$F$50)-SUMIF('BALANCE N-1'!$A$2:$A$50,"232*",'BALANCE N-1'!$G$2:$G$50)+SUMIF('BALANCE N-1'!$A$2:$A$50,"233*",'BALANCE N-1'!$F$2:$F$50)-SUMIF('BALANCE N-1'!$A$2:$A$50,"233*",'BALANCE N-1'!$G$2:$G$50)+SUMIF('BALANCE N-1'!$A$2:$A$50,"2393*",'BALANCE N-1'!$F$2:$F$50)-SUMIF('BALANCE N-1'!$A$2:$A$50,"2393*",'BALANCE N-1'!$G$2:$G$50)+SUMIF('BALANCE N-1'!$A$2:$A$50,"2391*",'BALANCE N-1'!$F$2:$F$50)-SUMIF('BALANCE N-1'!$A$2:$A$50,"2391*",'BALANCE N-1'!$G$2:$G$50)+SUMIF('BALANCE N-1'!$A$2:$A$50,"2392*",'BALANCE N-1'!$F$2:$F$50)-SUMIF('BALANCE N-1'!$A$2:$A$50,"2392*",'BALANCE N-1'!$G$2:$G$50)-SUMIF('BALANCE N-1'!$A$2:$A$50,"2325*",'BALANCE N-1'!$F$2:$F$50)+SUMIF('BALANCE N-1'!$A$2:$A$50,"2325*",'BALANCE N-1'!$G$2:$G$50)-SUMIF('BALANCE N-1'!$A$2:$A$50,"2315*",'BALANCE N-1'!$F$2:$F$50)+SUMIF('BALANCE N-1'!$A$2:$A$50,"2315*",'BALANCE N-1'!$G$2:$G$50))) | D16: =MAX(0,(SUMIF('BALANCE N-1'!$A$2:$A$50,"231*",'BALANCE N-1'!$F$2:$F$50)-SUMIF('BALANCE N-1'!$A$2:$A$50,"231*",'BALANCE N-1'!$G$2:$G$50)+SUMIF('BALANCE N-1'!$A$2:$A$50,"232*",'BALANCE N-1'!$F$2:$F$50)-SUMIF('BALANCE N-1'!$A$2:$A$50,"232*",'BALANCE N-1'!$G$2:$G$50)+SUMIF('BALANCE N-1'!$A$2:$A$50,"233*",'BALANCE N-1'!$F$2:$F$50)-SUMIF('BALANCE N-1'!$A$2:$A$50,"233*",'BALANCE N-1'!$G$2:$G$50)+SUMIF('BALANCE N-1'!$A$2:$A$50,"2393*",'BALANCE N-1'!$F$2:$F$50)-SUMIF('BALANCE N-1'!$A$2:$A$50,"2393*",'BALANCE N-1'!$G$2:$G$50)+SUMIF('BALANCE N-1'!$A$2:$A$50,"2391*",'BALANCE N-1'!$F$2:$F$50)-SUMIF('BALANCE N-1'!$A$2:$A$50,"2391*",'BALANCE N-1'!$G$2:$G$50)+SUMIF('BALANCE N-1'!$A$2:$A$50,"2392*",'BALANCE N-1'!$F$2:$F$50)-SUMIF('BALANCE N-1'!$A$2:$A$50,"2392*",'BALANCE N-1'!$G$2:$G$50)-SUMIF('BALANCE N-1'!$A$2:$A$50,"2325*",'BALANCE N-1'!$F$2:$F$50)+SUMIF('BALANCE N-1'!$A$2:$A$50,"2325*",'BALANCE N-1'!$G$2:$G$50)-SUMIF('BALANCE N-1'!$A$2:$A$50,"2315*",'BALANCE N-1'!$F$2:$F$50)+SUMIF('BALANCE N-1'!$A$2:$A$50,"2315*",'BALANCE N-1'!$G$2:$G$50))-(SUMIF('BALANCE N'!$A$2:$A$50,"231*",'BALANCE N'!$F$2:$F$50)-SUMIF('BALANCE N'!$A$2:$A$50,"231*",'BALANCE N'!$G$2:$G$50)+SUMIF('BALANCE N'!$A$2:$A$50,"232*",'BALANCE N'!$F$2:$F$50)-SUMIF('BALANCE N'!$A$2:$A$50,"232*",'BALANCE N'!$G$2:$G$50)+SUMIF('BALANCE N'!$A$2:$A$50,"233*",'BALANCE N'!$F$2:$F$50)-SUMIF('BALANCE N'!$A$2:$A$50,"233*",'BALANCE N'!$G$2:$G$50)+SUMIF('BALANCE N'!$A$2:$A$50,"2393*",'BALANCE N'!$F$2:$F$50)-SUMIF('BALANCE N'!$A$2:$A$50,"2393*",'BALANCE N'!$G$2:$G$50)+SUMIF('BALANCE N'!$A$2:$A$50,"2391*",'BALANCE N'!$F$2:$F$50)-SUMIF('BALANCE N'!$A$2:$A$50,"2391*",'BALANCE N'!$G$2:$G$50)+SUMIF('BALANCE N'!$A$2:$A$50,"2392*",'BALANCE N'!$F$2:$F$50)-SUMIF('BALANCE N'!$A$2:$A$50,"2392*",'BALANCE N'!$G$2:$G$50)-SUMIF('BALANCE N'!$A$2:$A$50,"2325*",'BALANCE N'!$F$2:$F$50)+SUMIF('BALANCE N'!$A$2:$A$50,"2325*",'BALANCE N'!$G$2:$G$50)-SUMIF('BALANCE N'!$A$2:$A$50,"2315*",'BALANCE N'!$F$2:$F$50)+SUMIF('BALANCE N'!$A$2:$A$50,"2315*",'BALANCE N'!$G$2:$G$50))) | E16: =B16+C16-D16
A17: Bâtiments - immeuble de placement | B17: =SUMIF('BALANCE N-1'!$A$2:$A$50,"2325*",'BALANCE N-1'!$F$2:$F$50)-SUMIF('BALANCE N-1'!$A$2:$A$50,"2325*",'BALANCE N-1'!$G$2:$G$50)+SUMIF('BALANCE N-1'!$A$2:$A$50,"2396*",'BALANCE N-1'!$F$2:$F$50)-SUMIF('BALANCE N-1'!$A$2:$A$50,"2396*",'BALANCE N-1'!$G$2:$G$50)+SUMIF('BALANCE N-1'!$A$2:$A$50,"2315*",'BALANCE N-1'!$F$2:$F$50)-SUMIF('BALANCE N-1'!$A$2:$A$50,"2315*",'BALANCE N-1'!$G$2:$G$50) | C17: =MAX(0,(SUMIF('BALANCE N'!$A$2:$A$50,"2325*",'BALANCE N'!$F$2:$F$50)-SUMIF('BALANCE N'!$A$2:$A$50,"2325*",'BALANCE N'!$G$2:$G$50)+SUMIF('BALANCE N'!$A$2:$A$50,"2396*",'BALANCE N'!$F$2:$F$50)-SUMIF('BALANCE N'!$A$2:$A$50,"2396*",'BALANCE N'!$G$2:$G$50)+SUMIF('BALANCE N'!$A$2:$A$50,"2315*",'BALANCE N'!$F$2:$F$50)-SUMIF('BALANCE N'!$A$2:$A$50,"2315*",'BALANCE N'!$G$2:$G$50))-(SUMIF('BALANCE N-1'!$A$2:$A$50,"2325*",'BALANCE N-1'!$F$2:$F$50)-SUMIF('BALANCE N-1'!$A$2:$A$50,"2325*",'BALANCE N-1'!$G$2:$G$50)+SUMIF('BALANCE N-1'!$A$2:$A$50,"2396*",'BALANCE N-1'!$F$2:$F$50)-SUMIF('BALANCE N-1'!$A$2:$A$50,"2396*",'BALANCE N-1'!$G$2:$G$50)+SUMIF('BALANCE N-1'!$A$2:$A$50,"2315*",'BALANCE N-1'!$F$2:$F$50)-SUMIF('BALANCE N-1'!$A$2:$A$50,"2315*",'BALANCE N-1'!$G$2:$G$50))) | D17: =MAX(0,(SUMIF('BALANCE N-1'!$A$2:$A$50,"2325*",'BALANCE N-1'!$F$2:$F$50)-SUMIF('BALANCE N-1'!$A$2:$A$50,"2325*",'BALANCE N-1'!$G$2:$G$50)+SUMIF('BALANCE N-1'!$A$2:$A$50,"2396*",'BALANCE N-1'!$F$2:$F$50)-SUMIF('BALANCE N-1'!$A$2:$A$50,"2396*",'BALANCE N-1'!$G$2:$G$50)+SUMIF('BALANCE N-1'!$A$2:$A$50,"2315*",'BALANCE N-1'!$F$2:$F$50)-SUMIF('BALANCE N-1'!$A$2:$A$50,"2315*",'BALANCE N-1'!$G$2:$G$50))-(SUMIF('BALANCE N'!$A$2:$A$50,"2325*",'BALANCE N'!$F$2:$F$50)-SUMIF('BALANCE N'!$A$2:$A$50,"2325*",'BALANCE N'!$G$2:$G$50)+SUMIF('BALANCE N'!$A$2:$A$50,"2396*",'BALANCE N'!$F$2:$F$50)-SUMIF('BALANCE N'!$A$2:$A$50,"2396*",'BALANCE N'!$G$2:$G$50)+SUMIF('BALANCE N'!$A$2:$A$50,"2315*",'BALANCE N'!$F$2:$F$50)-SUMIF('BALANCE N'!$A$2:$A$50,"2315*",'BALANCE N'!$G$2:$G$50))) | E17: =B17+C17-D17
A18: Aménagements, agencements et installations | B18: =SUMIF('BALANCE N-1'!$A$2:$A$50,"238*",'BALANCE N-1'!$F$2:$F$50)-SUMIF('BALANCE N-1'!$A$2:$A$50,"238*",'BALANCE N-1'!$G$2:$G$50)+SUMIF('BALANCE N-1'!$A$2:$A$50,"234*",'BALANCE N-1'!$F$2:$F$50)-SUMIF('BALANCE N-1'!$A$2:$A$50,"234*",'BALANCE N-1'!$G$2:$G$50)+SUMIF('BALANCE N-1'!$A$2:$A$50,"235*",'BALANCE N-1'!$F$2:$F$50)-SUMIF('BALANCE N-1'!$A$2:$A$50,"235*",'BALANCE N-1'!$G$2:$G$50)+SUMIF('BALANCE N-1'!$A$2:$A$50,"2394*",'BALANCE N-1'!$F$2:$F$50)-SUMIF('BALANCE N-1'!$A$2:$A$50,"2394*",'BALANCE N-1'!$G$2:$G$50)+SUMIF('BALANCE N-1'!$A$2:$A$50,"2398*",'BALANCE N-1'!$F$2:$F$50)-SUMIF('BALANCE N-1'!$A$2:$A$50,"2398*",'BALANCE N-1'!$G$2:$G$50)+SUMIF('BALANCE N-1'!$A$2:$A$50,"2395*",'BALANCE N-1'!$F$2:$F$50)-SUMIF('BALANCE N-1'!$A$2:$A$50,"2395*",'BALANCE N-1'!$G$2:$G$50) | C18: =MAX(0,(SUMIF('BALANCE N'!$A$2:$A$50,"238*",'BALANCE N'!$F$2:$F$50)-SUMIF('BALANCE N'!$A$2:$A$50,"238*",'BALANCE N'!$G$2:$G$50)+SUMIF('BALANCE N'!$A$2:$A$50,"234*",'BALANCE N'!$F$2:$F$50)-SUMIF('BALANCE N'!$A$2:$A$50,"234*",'BALANCE N'!$G$2:$G$50)+SUMIF('BALANCE N'!$A$2:$A$50,"235*",'BALANCE N'!$F$2:$F$50)-SUMIF('BALANCE N'!$A$2:$A$50,"235*",'BALANCE N'!$G$2:$G$50)+SUMIF('BALANCE N'!$A$2:$A$50,"2394*",'BALANCE N'!$F$2:$F$50)-SUMIF('BALANCE N'!$A$2:$A$50,"2394*",'BALANCE N'!$G$2:$G$50)+SUMIF('BALANCE N'!$A$2:$A$50,"2398*",'BALANCE N'!$F$2:$F$50)-SUMIF('BALANCE N'!$A$2:$A$50,"2398*",'BALANCE N'!$G$2:$G$50)+SUMIF('BALANCE N'!$A$2:$A$50,"2395*",'BALANCE N'!$F$2:$F$50)-SUMIF('BALANCE N'!$A$2:$A$50,"2395*",'BALANCE N'!$G$2:$G$50))-(SUMIF('BALANCE N-1'!$A$2:$A$50,"238*",'BALANCE N-1'!$F$2:$F$50)-SUMIF('BALANCE N-1'!$A$2:$A$50,"238*",'BALANCE N-1'!$G$2:$G$50)+SUMIF('BALANCE N-1'!$A$2:$A$50,"234*",'BALANCE N-1'!$F$2:$F$50)-SUMIF('BALANCE N-1'!$A$2:$A$50,"234*",'BALANCE N-1'!$G$2:$G$50)+SUMIF('BALANCE N-1'!$A$2:$A$50,"235*",'BALANCE N-1'!$F$2:$F$50)-SUMIF('BALANCE N-1'!$A$2:$A$50,"235*",'BALANCE N-1'!$G$2:$G$50)+SUMIF('BALANCE N-1'!$A$2:$A$50,"2394*",'BALANCE N-1'!$F$2:$F$50)-SUMIF('BALANCE N-1'!$A$2:$A$50,"2394*",'BALANCE N-1'!$G$2:$G$50)+SUMIF('BALANCE N-1'!$A$2:$A$50,"2398*",'BALANCE N-1'!$F$2:$F$50)-SUMIF('BALANCE N-1'!$A$2:$A$50,"2398*",'BALANCE N-1'!$G$2:$G$50)+SUMIF('BALANCE N-1'!$A$2:$A$50,"2395*",'BALANCE N-1'!$F$2:$F$50)-SUMIF('BALANCE N-1'!$A$2:$A$50,"2395*",'BALANCE N-1'!$G$2:$G$50))) | D18: =MAX(0,(SUMIF('BALANCE N-1'!$A$2:$A$50,"238*",'BALANCE N-1'!$F$2:$F$50)-SUMIF('BALANCE N-1'!$A$2:$A$50,"238*",'BALANCE N-1'!$G$2:$G$50)+SUMIF('BALANCE N-1'!$A$2:$A$50,"234*",'BALANCE N-1'!$F$2:$F$50)-SUMIF('BALANCE N-1'!$A$2:$A$50,"234*",'BALANCE N-1'!$G$2:$G$50)+SUMIF('BALANCE N-1'!$A$2:$A$50,"235*",'BALANCE N-1'!$F$2:$F$50)-SUMIF('BALANCE N-1'!$A$2:$A$50,"235*",'BALANCE N-1'!$G$2:$G$50)+SUMIF('BALANCE N-1'!$A$2:$A$50,"2394*",'BALANCE N-1'!$F$2:$F$50)-SUMIF('BALANCE N-1'!$A$2:$A$50,"2394*",'BALANCE N-1'!$G$2:$G$50)+SUMIF('BALANCE N-1'!$A$2:$A$50,"2398*",'BALANCE N-1'!$F$2:$F$50)-SUMIF('BALANCE N-1'!$A$2:$A$50,"2398*",'BALANCE N-1'!$G$2:$G$50)+SUMIF('BALANCE N-1'!$A$2:$A$50,"2395*",'BALANCE N-1'!$F$2:$F$50)-SUMIF('BALANCE N-1'!$A$2:$A$50,"2395*",'BALANCE N-1'!$G$2:$G$50))-(SUMIF('BALANCE N'!$A$2:$A$50,"238*",'BALANCE N'!$F$2:$F$50)-SUMIF('BALANCE N'!$A$2:$A$50,"238*",'BALANCE N'!$G$2:$G$50)+SUMIF('BALANCE N'!$A$2:$A$50,"234*",'BALANCE N'!$F$2:$F$50)-SUMIF('BALANCE N'!$A$2:$A$50,"234*",'BALANCE N'!$G$2:$G$50)+SUMIF('BALANCE N'!$A$2:$A$50,"235*",'BALANCE N'!$F$2:$F$50)-SUMIF('BALANCE N'!$A$2:$A$50,"235*",'BALANCE N'!$G$2:$G$50)+SUMIF('BALANCE N'!$A$2:$A$50,"2394*",'BALANCE N'!$F$2:$F$50)-SUMIF('BALANCE N'!$A$2:$A$50,"2394*",'BALANCE N'!$G$2:$G$50)+SUMIF('BALANCE N'!$A$2:$A$50,"2398*",'BALANCE N'!$F$2:$F$50)-SUMIF('BALANCE N'!$A$2:$A$50,"2398*",'BALANCE N'!$G$2:$G$50)+SUMIF('BALANCE N'!$A$2:$A$50,"2395*",'BALANCE N'!$F$2:$F$50)-SUMIF('BALANCE N'!$A$2:$A$50,"2395*",'BALANCE N'!$G$2:$G$50))) | E18: =B18+C18-D18
A19: Matériel, mobilier et actifs biologiques | B19: =SUMIF('BALANCE N-1'!$A$2:$A$50,"24*",'BALANCE N-1'!$F$2:$F$50)-SUMIF('BALANCE N-1'!$A$2:$A$50,"24*",'BALANCE N-1'!$G$2:$G$50)-SUMIF('BALANCE N-1'!$A$2:$A$50,"245*",'BALANCE N-1'!$F$2:$F$50)+SUMIF('BALANCE N-1'!$A$2:$A$50,"245*",'BALANCE N-1'!$G$2:$G$50)-SUMIF('BALANCE N-1'!$A$2:$A$50,"2495*",'BALANCE N-1'!$F$2:$F$50)+SUMIF('BALANCE N-1'!$A$2:$A$50,"2495*",'BALANCE N-1'!$G$2:$G$50) | C19: =MAX(0,(SUMIF('BALANCE N'!$A$2:$A$50,"24*",'BALANCE N'!$F$2:$F$50)-SUMIF('BALANCE N'!$A$2:$A$50,"24*",'BALANCE N'!$G$2:$G$50)-SUMIF('BALANCE N'!$A$2:$A$50,"245*",'BALANCE N'!$F$2:$F$50)+SUMIF('BALANCE N'!$A$2:$A$50,"245*",'BALANCE N'!$G$2:$G$50)-SUMIF('BALANCE N'!$A$2:$A$50,"2495*",'BALANCE N'!$F$2:$F$50)+SUMIF('BALANCE N'!$A$2:$A$50,"2495*",'BALANCE N'!$G$2:$G$50))-(SUMIF('BALANCE N-1'!$A$2:$A$50,"24*",'BALANCE N-1'!$F$2:$F$50)-SUMIF('BALANCE N-1'!$A$2:$A$50,"24*",'BALANCE N-1'!$G$2:$G$50)-SUMIF('BALANCE N-1'!$A$2:$A$50,"245*",'BALANCE N-1'!$F$2:$F$50)+SUMIF('BALANCE N-1'!$A$2:$A$50,"245*",'BALANCE N-1'!$G$2:$G$50)-SUMIF('BALANCE N-1'!$A$2:$A$50,"2495*",'BALANCE N-1'!$F$2:$F$50)+SUMIF('BALANCE N-1'!$A$2:$A$50,"2495*",'BALANCE N-1'!$G$2:$G$50))) | D19: =MAX(0,(SUMIF('BALANCE N-1'!$A$2:$A$50,"24*",'BALANCE N-1'!$F$2:$F$50)-SUMIF('BALANCE N-1'!$A$2:$A$50,"24*",'BALANCE N-1'!$G$2:$G$50)-SUMIF('BALANCE N-1'!$A$2:$A$50,"245*",'BALANCE N-1'!$F$2:$F$50)+SUMIF('BALANCE N-1'!$A$2:$A$50,"245*",'BALANCE N-1'!$G$2:$G$50)-SUMIF('BALANCE N-1'!$A$2:$A$50,"2495*",'BALANCE N-1'!$F$2:$F$50)+SUMIF('BALANCE N-1'!$A$2:$A$50,"2495*",'BALANCE N-1'!$G$2:$G$50))-(SUMIF('BALANCE N'!$A$2:$A$50,"24*",'BALANCE N'!$F$2:$F$50)-SUMIF('BALANCE N'!$A$2:$A$50,"24*",'BALANCE N'!$G$2:$G$50)-SUMIF('BALANCE N'!$A$2:$A$50,"245*",'BALANCE N'!$F$2:$F$50)+SUMIF('BALANCE N'!$A$2:$A$50,"245*",'BALANCE N'!$G$2:$G$50)-SUMIF('BALANCE N'!$A$2:$A$50,"2495*",'BALANCE N'!$F$2:$F$50)+SUMIF('BALANCE N'!$A$2:$A$50,"2495*",'BALANCE N'!$G$2:$G$50))) | E19: =B19+C19-D19
A20: Matériel de transport | B20: =SUMIF('BALANCE N-1'!$A$2:$A$50,"245*",'BALANCE N-1'!$F$2:$F$50)-SUMIF('BALANCE N-1'!$A$2:$A$50,"245*",'BALANCE N-1'!$G$2:$G$50)+SUMIF('BALANCE N-1'!$A$2:$A$50,"2495*",'BALANCE N-1'!$F$2:$F$50)-SUMIF('BALANCE N-1'!$A$2:$A$50,"2495*",'BALANCE N-1'!$G$2:$G$50) | C20: =MAX(0,(SUMIF('BALANCE N'!$A$2:$A$50,"245*",'BALANCE N'!$F$2:$F$50)-SUMIF('BALANCE N'!$A$2:$A$50,"245*",'BALANCE N'!$G$2:$G$50)+SUMIF('BALANCE N'!$A$2:$A$50,"2495*",'BALANCE N'!$F$2:$F$50)-SUMIF('BALANCE N'!$A$2:$A$50,"2495*",'BALANCE N'!$G$2:$G$50))-(SUMIF('BALANCE N-1'!$A$2:$A$50,"245*",'BALANCE N-1'!$F$2:$F$50)-SUMIF('BALANCE N-1'!$A$2:$A$50,"245*",'BALANCE N-1'!$G$2:$G$50)+SUMIF('BALANCE N-1'!$A$2:$A$50,"2495*",'BALANCE N-1'!$F$2:$F$50)-SUMIF('BALANCE N-1'!$A$2:$A$50,"2495*",'BALANCE N-1'!$G$2:$G$50))) | D20: =MAX(0,(SUMIF('BALANCE N-1'!$A$2:$A$50,"245*",'BALANCE N-1'!$F$2:$F$50)-SUMIF('BALANCE N-1'!$A$2:$A$50,"245*",'BALANCE N-1'!$G$2:$G$50)+SUMIF('BALANCE N-1'!$A$2:$A$50,"2495*",'BALANCE N-1'!$F$2:$F$50)-SUMIF('BALANCE N-1'!$A$2:$A$50,"2495*",'BALANCE N-1'!$G$2:$G$50))-(SUMIF('BALANCE N'!$A$2:$A$50,"245*",'BALANCE N'!$F$2:$F$50)-SUMIF('BALANCE N'!$A$2:$A$50,"245*",'BALANCE N'!$G$2:$G$50)+SUMIF('BALANCE N'!$A$2:$A$50,"2495*",'BALANCE N'!$F$2:$F$50)-SUMIF('BALANCE N'!$A$2:$A$50,"2495*",'BALANCE N'!$G$2:$G$50))) | E20: =B20+C20-D20
A21: Avances et acomptes sur immobilisations corporelles | B21: =SUMIF('BALANCE N-1'!$A$2:$A$50,"252*",'BALANCE N-1'!$F$2:$F$50)-SUMIF('BALANCE N-1'!$A$2:$A$50,"252*",'BALANCE N-1'!$G$2:$G$50) | C21: =MAX(0,(SUMIF('BALANCE N'!$A$2:$A$50,"252*",'BALANCE N'!$F$2:$F$50)-SUMIF('BALANCE N'!$A$2:$A$50,"252*",'BALANCE N'!$G$2:$G$50))-(SUMIF('BALANCE N-1'!$A$2:$A$50,"252*",'BALANCE N-1'!$F$2:$F$50)-SUMIF('BALANCE N-1'!$A$2:$A$50,"252*",'BALANCE N-1'!$G$2:$G$50))) | D21: =MAX(0,(SUMIF('BALANCE N-1'!$A$2:$A$50,"252*",'BALANCE N-1'!$F$2:$F$50)-SUMIF('BALANCE N-1'!$A$2:$A$50,"252*",'BALANCE N-1'!$G$2:$G$50))-(SUMIF('BALANCE N'!$A$2:$A$50,"252*",'BALANCE N'!$F$2:$F$50)-SUMIF('BALANCE N'!$A$2:$A$50,"252*",'BALANCE N'!$G$2:$G$50))) | E21: =B21+C21-D21
A22: IMMOBILISATIONS FINANCIÈRES
A23: Dépôts et cautionnements | B23: =SUMIF('BALANCE N-1'!$A$2:$A$50,"275*",'BALANCE N-1'!$F$2:$F$50)-SUMIF('BALANCE N-1'!$A$2:$A$50,"275*",'BALANCE N-1'!$G$2:$G$50) | C23: =MAX(0,(SUMIF('BALANCE N'!$A$2:$A$50,"275*",'BALANCE N'!$F$2:$F$50)-SUMIF('BALANCE N'!$A$2:$A$50,"275*",'BALANCE N'!$G$2:$G$50))-(SUMIF('BALANCE N-1'!$A$2:$A$50,"275*",'BALANCE N-1'!$F$2:$F$50)-SUMIF('BALANCE N-1'!$A$2:$A$50,"275*",'BALANCE N-1'!$G$2:$G$50))) | D23: =MAX(0,(SUMIF('BALANCE N-1'!$A$2:$A$50,"275*",'BALANCE N-1'!$F$2:$F$50)-SUMIF('BALANCE N-1'!$A$2:$A$50,"275*",'BALANCE N-1'!$G$2:$G$50))-(SUMIF('BALANCE N'!$A$2:$A$50,"275*",'BALANCE N'!$F$2:$F$50)-SUMIF('BALANCE N'!$A$2:$A$50,"275*",'BALANCE N'!$G$2:$G$50))) | E23: =B23+C23-D23
A24: Autres immobilisations financières | B24: =SUMIF('BALANCE N-1'!$A$2:$A$50,"26*",'BALANCE N-1'!$F$2:$F$50)-SUMIF('BALANCE N-1'!$A$2:$A$50,"26*",'BALANCE N-1'!$G$2:$G$50)+SUMIF('BALANCE N-1'!$A$2:$A$50,"27*",'BALANCE N-1'!$F$2:$F$50)-SUMIF('BALANCE N-1'!$A$2:$A$50,"27*",'BALANCE N-1'!$G$2:$G$50)-SUMIF('BALANCE N-1'!$A$2:$A$50,"275*",'BALANCE N-1'!$F$2:$F$50)+SUMIF('BALANCE N-1'!$A$2:$A$50,"275*",'BALANCE N-1'!$G$2:$G$50) | C24: =MAX(0,(SUMIF('BALANCE N'!$A$2:$A$50,"26*",'BALANCE N'!$F$2:$F$50)-SUMIF('BALANCE N'!$A$2:$A$50,"26*",'BALANCE N'!$G$2:$G$50)+SUMIF('BALANCE N'!$A$2:$A$50,"27*",'BALANCE N'!$F$2:$F$50)-SUMIF('BALANCE N'!$A$2:$A$50,"27*",'BALANCE N'!$G$2:$G$50)-SUMIF('BALANCE N'!$A$2:$A$50,"275*",'BALANCE N'!$F$2:$F$50)+SUMIF('BALANCE N'!$A$2:$A$50,"275*",'BALANCE N'!$G$2:$G$50))-(SUMIF('BALANCE N-1'!$A$2:$A$50,"26*",'BALANCE N-1'!$F$2:$F$50)-SUMIF('BALANCE N-1'!$A$2:$A$50,"26*",'BALANCE N-1'!$G$2:$G$50)+SUMIF('BALANCE N-1'!$A$2:$A$50,"27*",'BALANCE N-1'!$F$2:$F$50)-SUMIF('BALANCE N-1'!$A$2:$A$50,"27*",'BALANCE N-1'!$G$2:$G$50)-SUMIF('BALANCE N-1'!$A$2:$A$50,"275*",'BALANCE N-1'!$F$2:$F$50)+SUMIF('BALANCE N-1'!$A$2:$A$50,"275*",'BALANCE N-1'!$G$2:$G$50))) | D24: =MAX(0,(SUMIF('BALANCE N-1'!$A$2:$A$50,"26*",'BALANCE N-1'!$F$2:$F$50)-SUMIF('BALANCE N-1'!$A$2:$A$50,"26*",'BALANCE N-1'!$G$2:$G$50)+SUMIF('BALANCE N-1'!$A$2:$A$50,"27*",'BALANCE N-1'!$F$2:$F$50)-SUMIF('BALANCE N-1'!$A$2:$A$50,"27*",'BALANCE N-1'!$G$2:$G$50)-SUMIF('BALANCE N-1'!$A$2:$A$50,"275*",'BALANCE N-1'!$F$2:$F$50)+SUMIF('BALANCE N-1'!$A$2:$A$50,"275*",'BALANCE N-1'!$G$2:$G$50))-(SUMIF('BALANCE N'!$A$2:$A$50,"26*",'BALANCE N'!$F$2:$F$50)-SUMIF('BALANCE N'!$A$2:$A$50,"26*",'BALANCE N'!$G$2:$G$50)+SUMIF('BALANCE N'!$A$2:$A$50,"27*",'BALANCE N'!$F$2:$F$50)-SUMIF('BALANCE N'!$A$2:$A$50,"27*",'BALANCE N'!$G$2:$G$50)-SUMIF('BALANCE N'!$A$2:$A$50,"275*",'BALANCE N'!$F$2:$F$50)+SUMIF('BALANCE N'!$A$2:$A$50,"275*",'BALANCE N'!$G$2:$G$50))) | E24: =B24+C24-D24
A25: TOTAL GÉNÉRAL | B25: =B10+B11+B12+B14+B15+B16+B17+B18+B19+B20+B21+B23+B24 | C25: =C10+C11+C12+C14+C15+C16+C17+C18+C19+C20+C21+C23+C24 | D25: =D10+D11+D12+D14+D15+D16+D17+D18+D19+D20+D21+D23+D24 | E25: =E10+E11+E12+E14+E15+E16+E17+E18+E19+E20+E21+E23+E24
A27: Sans balance N-1, seule la colonne de clôture est servie ; avec N-1, les mouvements sont posés en variation nette (augmentation ou diminution) faute d'état des mouvements - à ajuster depuis l'inventaire des immobilisations.
A29: Commentaires :
A30: • Toute variation significative doit être commentée ; joindre l'inventaire physique des immobilisations.

Sheet NOTE 3B
A1: - 14 -
D2: NOTE 3B PROJETS DE DEVELOPPEMENT
A3: Dénomination sociale : PROJET EAU POTABLE RURALE
A4: Adresse : | D4: Sigle usuel : | E4: PEPR
A5: N° de compte contribuable (NCC) : PD-2023-017 | C5: Exercice clos le 31-12-2025 | D5: Durée (en mois) : 12
A6: N° de télédéclarant (NTD) :
A7: NOTE 3B : BIENS PRIS EN LOCATION-ACQUISITION
A8: I : crédit-bail immobilier ; M : crédit-bail mobilier ; A : autres contrats
A9: RUBRIQUES | B9: Montant brut à l'ouverture (A) | C9: Augmentations (B) | D9: Diminutions (C) | E9: Montant brut à la clôture (D = A + B - C)
A10: Terrains | B10: =SUMIF('BALANCE N-1'!$A$2:$A$50,"2286*",'BALANCE N-1'!$F$2:$F$50)-SUMIF('BALANCE N-1'!$A$2:$A$50,"2286*",'BALANCE N-1'!$G$2:$G$50) | C10: =MAX(0,(SUMIF('BALANCE N'!$A$2:$A$50,"2286*",'BALANCE N'!$F$2:$F$50)-SUMIF('BALANCE N'!$A$2:$A$50,"2286*",'BALANCE N'!$G$2:$G$50))-(SUMIF('BALANCE N-1'!$A$2:$A$50,"2286*",'BALANCE N-1'!$F$2:$F$50)-SUMIF('BALANCE N-1'!$A$2:$A$50,"2286*",'BALANCE N-1'!$G$2:$G$50))) | D10: =MAX(0,(SUMIF('BALANCE N-1'!$A$2:$A$50,"2286*",'BALANCE N-1'!$F$2:$F$50)-SUMIF('BALANCE N-1'!$A$2:$A$50,"2286*",'BALANCE N-1'!$G$2:$G$50))-(SUMIF('BALANCE N'!$A$2:$A$50,"2286*",'BALANCE N'!$F$2:$F$50)-SUMIF('BALANCE N'!$A$2:$A$50,"2286*",'BALANCE N'!$G$2:$G$50))) | E10: =B10+C10-D10
A11: Bâtiments | B11: =SUMIF('BALANCE N-1'!$A$2:$A$50,"2316*",'BALANCE N-1'!$F$2:$F$50)-SUMIF('BALANCE N-1'!$A$2:$A$50,"2316*",'BALANCE N-1'!$G$2:$G$50) | C11: =MAX(0,(SUMIF('BALANCE N'!$A$2:$A$50,"2316*",'BALANCE N'!$F$2:$F$50)-SUMIF('BALANCE N'!$A$2:$A$50,"2316*",'BALANCE N'!$G$2:$G$50))-(SUMIF('BALANCE N-1'!$A$2:$A$50,"2316*",'BALANCE N-1'!$F$2:$F$50)-SUMIF('BALANCE N-1'!$A$2:$A$50,"2316*",'BALANCE N-1'!$G$2:$G$50))) | D11: =MAX(0,(SUMIF('BALANCE N-1'!$A$2:$A$50,"2316*",'BALANCE N-1'!$F$2:$F$50)-SUMIF('BALANCE N-1'!$A$2:$A$50,"2316*",'BALANCE N-1'!$G$2:$G$50))-(SUMIF('BALANCE N'!$A$2:$A$50,"2316*",'BALANCE N'!$F$2:$F$50)-SUMIF('BALANCE N'!$A$2:$A$50,"2316*",'BALANCE N'!$G$2:$G$50))) | E11: =B11+C11-D11
A12: Matériel, mobilier | B12: =SUMIF('BALANCE N-1'!$A$2:$A$50,"2416*",'BALANCE N-1'!$F$2:$F$50)-SUMIF('BALANCE N-1'!$A$2:$A$50,"2416*",'BALANCE N-1'!$G$2:$G$50)+SUMIF('BALANCE N-1'!$A$2:$A$50,"2446*",'BALANCE N-1'!$F$2:$F$50)-SUMIF('BALANCE N-1'!$A$2:$A$50,"2446*",'BALANCE N-1'!$G$2:$G$50)+SUMIF('BALANCE N-1'!$A$2:$A$50,"2426*",'BALANCE N-1'!$F$2:$F$50)-SUMIF('BALANCE N-1'!$A$2:$A$50,"2426*",'BALANCE N-1'!$G$2:$G$50) | C12: =MAX(0,(SUMIF('BALANCE N'!$A$2:$A$50,"2416*",'BALANCE N'!$F$2:$F$50)-SUMIF('BALANCE N'!$A$2:$A$50,"2416*",'BALANCE N'!$G$2:$G$50)+SUMIF('BALANCE N'!$A$2:$A$50,"2446*",'BALANCE N'!$F$2:$F$50)-SUMIF('BALANCE N'!$A$2:$A$50,"2446*",'BALANCE N'!$G$2:$G$50)+SUMIF('BALANCE N'!$A$2:$A$50,"2426*",'BALANCE N'!$F$2:$F$50)-SUMIF('BALANCE N'!$A$2:$A$50,"2426*",'BALANCE N'!$G$2:$G$50))-(SUMIF('BALANCE N-1'!$A$2:$A$50,"2416*",'BALANCE N-1'!$F$2:$F$50)-SUMIF('BALANCE N-1'!$A$2:$A$50,"2416*",'BALANCE N-1'!$G$2:$G$50)+SUMIF('BALANCE N-1'!$A$2:$A$50,"2446*",'BALANCE N-1'!$F$2:$F$50)-SUMIF('BALANCE N-1'!$A$2:$A$50,"2446*",'BALANCE N-1'!$G$2:$G$50)+SUMIF('BALANCE N-1'!$A$2:$A$50,"2426*",'BALANCE N-1'!$F$2:$F$50)-SUMIF('BALANCE N-1'!$A$2:$A$50,"2426*",'BALANCE N-1'!$G$2:$G$50))) | D12: =MAX(0,(SUMIF('BALANCE N-1'!$A$2:$A$50,"2416*",'BALANCE N-1'!$F$2:$F$50)-SUMIF('BALANCE N-1'!$A$2:$A$50,"2416*",'BALANCE N-1'!$G$2:$G$50)+SUMIF('BALANCE N-1'!$A$2:$A$50,"2446*",'BALANCE N-1'!$F$2:$F$50)-SUMIF('BALANCE N-1'!$A$2:$A$50,"2446*",'BALANCE N-1'!$G$2:$G$50)+SUMIF('BALANCE N-1'!$A$2:$A$50,"2426*",'BALANCE N-1'!$F$2:$F$50)-SUMIF('BALANCE N-1'!$A$2:$A$50,"2426*",'BALANCE N-1'!$G$2:$G$50))-(SUMIF('BALANCE N'!$A$2:$A$50,"2416*",'BALANCE N'!$F$2:$F$50)-SUMIF('BALANCE N'!$A$2:$A$50,"2416*",'BALANCE N'!$G$2:$G$50)+SUMIF('BALANCE N'!$A$2:$A$50,"2446*",'BALANCE N'!$F$2:$F$50)-SUMIF('BALANCE N'!$A$2:$A$50,"2446*",'BALANCE N'!$G$2:$G$50)+SUMIF('BALANCE N'!$A$2:$A$50,"2426*",'BALANCE N'!$F$2:$F$50)-SUMIF('BALANCE N'!$A$2:$A$50,"2426*",'BALANCE N'!$G$2:$G$50))) | E12: =B12+C12-D12
A13: Matériel de transport | B13: =SUMIF('BALANCE N-1'!$A$2:$A$50,"2456*",'BALANCE N-1'!$F$2:$F$50)-SUMIF('BALANCE N-1'!$A$2:$A$50,"2456*",'BALANCE N-1'!$G$2:$G$50) | C13: =MAX(0,(SUMIF('BALANCE N'!$A$2:$A$50,"2456*",'BALANCE N'!$F$2:$F$50)-SUMIF('BALANCE N'!$A$2:$A$50,"2456*",'BALANCE N'!$G$2:$G$50))-(SUMIF('BALANCE N-1'!$A$2:$A$50,"2456*",'BALANCE N-1'!$F$2:$F$50)-SUMIF('BALANCE N-1'!$A$2:$A$50,"2456*",'BALANCE N-1'!$G$2:$G$50))) | D13: =MAX(0,(SUMIF('BALANCE N-1'!$A$2:$A$50,"2456*",'BALANCE N-1'!$F$2:$F$50)-SUMIF('BALANCE N-1'!$A$2:$A$50,"2456*",'BALANCE N-1'!$G$2:$G$50))-(SUMIF('BALANCE N'!$A$2:$A$50,"2456*",'BALANCE N'!$F$2:$F$50)-SUMIF('BALANCE N'!$A$2:$A$50,"2456*",'BALANCE N'!$G$2:$G$50))) | E13: =B13+C13-D13
A14: TOTAL GÉNÉRAL | B14: =B10+B11+B12+B13 | C14: =C10+C11+C12+C13 | D14: =D10+D11+D12+D13 | E14: =E10+E11+E12+E13
A16: Sans balance N-1, seule la colonne de clôture est servie ; avec N-1, les mouvements sont posés en variation nette (augmentation ou diminution) faute d'état des mouvements - à ajuster depuis l'inventaire des immobilisations.
A18: Commentaires :
A19: • Indiquer la nature du bien, le nom du bailleur et la durée du bail.

Sheet NOTE 4
A1: - 15 -
D2: NOTE 4 PROJETS DE DEVELOPPEMENT
A3: Dénomination sociale : PROJET EAU POTABLE RURALE
A4: Adresse : | D4: Sigle usuel : | E4: PEPR
A5: N° de compte contribuable (NCC) : PD-2023-017 | C5: Exercice clos le 31-12-2025 | D5: Durée (en mois) : 12
A6: N° de télédéclarant (NTD) :
A7: NOTE 4 : ACTIF CIRCULANT ET DETTES CIRCULANTES HAO
A8: Libellés | B8: Année N | C8: Année N-1 | D8: Variation en valeur | E8: Variation en %
A9: ACTIF CIRCULANT HAO
A10: Créances sur cessions d'immobilisations | B10: =SUMIF('BALANCE N'!$A$2:$A$50,"485*",'BALANCE N'!$F$2:$F$50)-SUMIF('BALANCE N'!$A$2:$A$50,"485*",'BALANCE N'!$G$2:$G$50) | C10: =SUMIF('BALANCE N-1'!$A$2:$A$50,"485*",'BALANCE N-1'!$F$2:$F$50)-SUMIF('BALANCE N-1'!$A$2:$A$50,"485*",'BALANCE N-1'!$G$2:$G$50) | D10: =B10-C10 | E10: =IF(C10=0,"",(B10-C10)/C10)
A11: TOTAL BRUT | B11: =SUM(B10:B10) | C11: =SUM(C10:C10) | D11: =B11-C11 | E11: =IF(C11=0,"",(B11-C11)/C11)
A12: Dépréciations des créances HAO | B12: =SUMIF('BALANCE N'!$A$2:$A$50,"498*",'BALANCE N'!$G$2:$G$50)-SUMIF('BALANCE N'!$A$2:$A$50,"498*",'BALANCE N'!$F$2:$F$50) | C12: =SUMIF('BALANCE N-1'!$A$2:$A$50,"498*",'BALANCE N-1'!$G$2:$G$50)-SUMIF('BALANCE N-1'!$A$2:$A$50,"498*",'BALANCE N-1'!$F$2:$F$50) | D12: =B12-C12 | E12: =IF(C12=0,"",(B12-C12)/C12)
B13: =SUM(B12:B12) | C13: =SUM(C12:C12) | D13: =B13-C13 | E13: =IF(C13=0,"",(B13-C13)/C13)
A14: TOTAL NET DE DÉPRÉCIATIONS | B14: =B11-B13 | C14: =C11-C13 | D14: =B14-C14 | E14: =IF(C14=0,"",(B14-C14)/C14)
A16: DETTES CIRCULANTES HAO
A17: Fournisseurs d'investissements | B17: =SUMIF('BALANCE N'!$A$2:$A$50,"481*",'BALANCE N'!$G$2:$G$50)-SUMIF('BALANCE N'!$A$2:$A$50,"481*",'BALANCE N'!$F$2:$F$50) | C17: =SUMIF('BALANCE N-1'!$A$2:$A$50,"481*",'BALANCE N-1'!$G$2:$G$50)-SUMIF('BALANCE N-1'!$A$2:$A$50,"481*",'BALANCE N-1'!$F$2:$F$50) | D17: =B17-C17 | E17: =IF(C17=0,"",(B17-C17)/C17)
A18: Autres dettes hors activités ordinaires | B18: =SUMIF('BALANCE N'!$A$2:$A$50,"484*",'BALANCE N'!$G$2:$G$50)-SUMIF('BALANCE N'!$A$2:$A$50,"484*",'BALANCE N'!$F$2:$F$50)+SUMIF('BALANCE N'!$A$2:$A$50,"4998*",'BALANCE N'!$G$2:$G$50)-SUMIF('BALANCE N'!$A$2:$A$50,"4998*",'BALANCE N'!$F$2:$F$50) | C18: =SUMIF('BALANCE N-1'!$A$2:$A$50,"484*",'BALANCE N-1'!$G$2:$G$50)-SUMIF('BALANCE N-1'!$A$2:$A$50,"484*",'BALANCE N-1'!$F$2:$F$50)+SUMIF('BALANCE N-1'!$A$2:$A$50,"4998*",'BALANCE N-1'!$G$2:$G$50)-SUMIF('BALANCE N-1'!$A$2:$A$50,"4998*",'BALANCE N-1'!$F$2:$F$50) | D18: =B18-C18 | E18: =IF(C18=0,"",(B18-C18)/C18)
A19: TOTAL | B19: =SUM(B17:B18) | C19: =SUM(C17:C18) | D19: =B19-C19 | E19: =IF(C19=0,"",(B19-C19)/C19)
A21: Commentaires :
A22: • Indiquer la date et la nature de l'immobilisation achetée et/ou cédée.

Sheet NOTE 5
A1: - 16 -
D2: NOTE 5 PROJETS DE DEVELOPPEMENT
A3: Dénomination sociale : PROJET EAU POTABLE RURALE
A4: Adresse : | D4: Sigle usuel : | E4: PEPR
A5: N° de compte contribuable (NCC) : PD-2023-017 | C5: Exercice clos le 31-12-2025 | D5: Durée (en mois) : 12
A6: N° de télédéclarant (NTD) :
A7: NOTE 5 : STOCKS ET ENCOURS
A8: Libellés | B8: Année N | C8: Année N-1 | D8: Variation en valeur | E8: Variation en %
A9: Biens liés à l'activité | B9: =SUMIF('BALANCE N'!$A$2:$A$50,"31*",'BALANCE N'!$F$2:$F$50)-SUMIF('BALANCE N'!$A$2:$A$50,"31*",'BALANCE N'!$G$2:$G$50) | C9: =SUMIF('BALANCE N-1'!$A$2:$A$50,"31*",'BALANCE N-1'!$F$2:$F$50)-SUMIF('BALANCE N-1'!$A$2:$A$50,"31*",'BALANCE N-1'!$G$2:$G$50) | D9: =B9-C9 | E9: =IF(C9=0,"",(B9-C9)/C9)
A10: Marchandises, matières premières et fournitures liées | B10: =SUMIF('BALANCE N'!$A$2:$A$50,"32*",'BALANCE N'!$F$2:$F$50)-SUMIF('BALANCE N'!$A$2:$A$50,"32*",'BALANCE N'!$G$2:$G$50) | C10: =SUMIF('BALANCE N-1'!$A$2:$A$50,"32*",'BALANCE N-1'!$F$2:$F$50)-SUMIF('BALANCE N-1'!$A$2:$A$50,"32*",'BALANCE N-1'!$G$2:$G$50) | D10: =B10-C10 | E10: =IF(C10=0,"",(B10-C10)/C10)
A11: Autres approvisionnements | B11: =SUMIF('BALANCE N'!$A$2:$A$50,"33*",'BALANCE N'!$F$2:$F$50)-SUMIF('BALANCE N'!$A$2:$A$50,"33*",'BALANCE N'!$G$2:$G$50) | C11: =SUMIF('BALANCE N-1'!$A$2:$A$50,"33*",'BALANCE N-1'!$F$2:$F$50)-SUMIF('BALANCE N-1'!$A$2:$A$50,"33*",'BALANCE N-1'!$G$2:$G$50) | D11: =B11-C11 | E11: =IF(C11=0,"",(B11-C11)/C11)
A12: Dons en nature | B12: =SUMIF('BALANCE N'!$A$2:$A$50,"34*",'BALANCE N'!$F$2:$F$50)-SUMIF('BALANCE N'!$A$2:$A$50,"34*",'BALANCE N'!$G$2:$G$50) | C12: =SUMIF('BALANCE N-1'!$A$2:$A$50,"34*",'BALANCE N-1'!$F$2:$F$50)-SUMIF('BALANCE N-1'!$A$2:$A$50,"34*",'BALANCE N-1'!$G$2:$G$50) | D12: =B12-C12 | E12: =IF(C12=0,"",(B12-C12)/C12)
A13: Produits finis et intermédiaires | B13: =SUMIF('BALANCE N'!$A$2:$A$50,"36*",'BALANCE N'!$F$2:$F$50)-SUMIF('BALANCE N'!$A$2:$A$50,"36*",'BALANCE N'!$G$2:$G$50) | C13: =SUMIF('BALANCE N-1'!$A$2:$A$50,"36*",'BALANCE N-1'!$F$2:$F$50)-SUMIF('BALANCE N-1'!$A$2:$A$50,"36*",'BALANCE N-1'!$G$2:$G$50) | D13: =B13-C13 | E13: =IF(C13=0,"",(B13-C13)/C13)
A14: Stocks HAO | B14: =SUMIF('BALANCE N'!$A$2:$A$50,"38*",'BALANCE N'!$F$2:$F$50)-SUMIF('BALANCE N'!$A$2:$A$50,"38*",'BALANCE N'!$G$2:$G$50) | C14: =SUMIF('BALANCE N-1'!$A$2:$A$50,"38*",'BALANCE N-1'!$F$2:$F$50)-SUMIF('BALANCE N-1'!$A$2:$A$50,"38*",'BALANCE N-1'!$G$2:$G$50) | D14: =B14-C14 | E14: =IF(C14=0,"",(B14-C14)/C14)
A15: Stocks en cours de route, en consignation ou en dépôt | B15: =SUMIF('BALANCE N'!$A$2:$A$50,"37*",'BALANCE N'!$F$2:$F$50)-SUMIF('BALANCE N'!$A$2:$A$50,"37*",'BALANCE N'!$G$2:$G$50) | C15: =SUMIF('BALANCE N-1'!$A$2:$A$50,"37*",'BALANCE N-1'!$F$2:$F$50)-SUMIF('BALANCE N-1'!$A$2:$A$50,"37*",'BALANCE N-1'!$G$2:$G$50) | D15: =B15-C15 | E15: =IF(C15=0,"",(B15-C15)/C15)
A16: TOTAL STOCKS ET ENCOURS | B16: =SUM(B9:B15) | C16: =SUM(C9:C15) | D16: =B16-C16 | E16: =IF(C16=0,"",(B16-C16)/C16)
A17: Dépréciations des stocks | B17: =SUMIF('BALANCE N'!$A$2:$A$50,"39*",'BALANCE N'!$G$2:$G$50)-SUMIF('BALANCE N'!$A$2:$A$50,"39*",'BALANCE N'!$F$2:$F$50) | C17: =SUMIF('BALANCE N-1'!$A$2:$A$50,"39*",'BALANCE N-1'!$G$2:$G$50)-SUMIF('BALANCE N-1'!$A$2:$A$50,"39*",'BALANCE N-1'!$F$2:$F$50) | D17: =B17-C17 | E17: =IF(C17=0,"",(B17-C17)/C17)
B18: =SUM(B17:B17) | C18: =SUM(C17:C17) | D18: =B18-C18 | E18: =IF(C18=0,"",(B18-C18)/C18)
A19: TOTAL NET DE DÉPRÉCIATIONS | B19: =B16-B18 | C19: =C16-C18 | D19: =B19-C19 | E19: =IF(C19=0,"",(B19-C19)/C19)

Sheet NOTE 6
A1: - 17 -
G2: NOTE 6 PROJETS DE DEVELOPPEMENT
A3: Dénomination sociale : PROJET EAU POTABLE RURALE
A4: Adresse : | G4: Sigle usuel : | H4: PEPR
A5: N° de compte contribuable (NCC) : PD-2023-017 | E5: Exercice clos le 31-12-2025 | G5: Durée (en mois) : 12
A6: N° de télédéclarant (NTD) :
A7: NOTE 6 : CLIENTS-USAGERS ET AUTRES CRÉANCES
A8: Libellés | B8: Année N | C8: Année N-1 | D8: Variation en valeur | E8: Variation en % | F8: À un an au plus | G8: À plus d'un an et deux ans au plus | H8: À plus de deux ans
A9: Fournisseurs, débiteurs | B9: =SUMIF('BALANCE N'!$A$2:$A$50,"409*",'BALANCE N'!$F$2:$F$50)-SUMIF('BALANCE N'!$A$2:$A$50,"409*",'BALANCE N'!$G$2:$G$50) | C9: =SUMIF('BALANCE N-1'!$A$2:$A$50,"409*",'BALANCE N-1'!$F$2:$F$50)-SUMIF('BALANCE N-1'!$A$2:$A$50,"409*",'BALANCE N-1'!$G$2:$G$50) | D9: =B9-C9 | E9: =IF(C9=0,"",(B9-C9)/C9)
A10: Clients-usagers | B10: =SUMIF('BALANCE N'!$A$2:$A$50,"41*",'BALANCE N'!$F$2:$F$50)-SUMIF('BALANCE N'!$A$2:$A$50,"41*",'BALANCE N'!$G$2:$G$50)-SUMIF('BALANCE N'!$A$2:$A$50,"411*",'BALANCE N'!$F$2:$F$50)+SUMIF('BALANCE N'!$A$2:$A$50,"411*",'BALANCE N'!$G$2:$G$50)-SUMIF('BALANCE N'!$A$2:$A$50,"419*",'BALANCE N'!$F$2:$F$50)+SUMIF('BALANCE N'!$A$2:$A$50,"419*",'BALANCE N'!$G$2:$G$50) | C10: =SUMIF('BALANCE N-1'!$A$2:$A$50,"41*",'BALANCE N-1'!$F$2:$F$50)-SUMIF('BALANCE N-1'!$A$2:$A$50,"41*",'BALANCE N-1'!$G$2:$G$50)-SUMIF('BALANCE N-1'!$A$2:$A$50,"411*",'BALANCE N-1'!$F$2:$F$50)+SUMIF('BALANCE N-1'!$A$2:$A$50,"411*",'BALANCE N-1'!$G$2:$G$50)-SUMIF('BALANCE N-1'!$A$2:$A$50,"419*",'BALANCE N-1'!$F$2:$F$50)+SUMIF('BALANCE N-1'!$A$2:$A$50,"419*",'BALANCE N-1'!$G$2:$G$50) | D10: =B10-C10 | E10: =IF(C10=0,"",(B10-C10)/C10)
A11: Personnel | B11: =SUMIF('BALANCE N'!$A$2:$A$50,"42*",'BALANCE N'!$F$2:$F$50) | C11: =SUMIF('BALANCE N-1'!$A$2:$A$50,"42*",'BALANCE N-1'!$F$2:$F$50) | D11: =B11-C11 | E11: =IF(C11=0,"",(B11-C11)/C11)
A12: Organismes sociaux | B12: =SUMIF('BALANCE N'!$A$2:$A$50,"43*",'BALANCE N'!$F$2:$F$50) | C12: =SUMIF('BALANCE N-1'!$A$2:$A$50,"43*",'BALANCE N-1'!$F$2:$F$50) | D12: =B12-C12 | E12: =IF(C12=0,"",(B12-C12)/C12)
A13: État et collectivités publiques | B13: =SUMIF('BALANCE N'!$A$2:$A$50,"44*",'BALANCE N'!$F$2:$F$50) | C13: =SUMIF('BALANCE N-1'!$A$2:$A$50,"44*",'BALANCE N-1'!$F$2:$F$50) | D13: =B13-C13 | E13: =IF(C13=0,"",(B13-C13)/C13)
A14: Autres débiteurs divers | B14: =SUMIF('BALANCE N'!$A$2:$A$50,"47*",'BALANCE N'!$F$2:$F$50)-SUMIF('BALANCE N'!$A$2:$A$50,"478*",'BALANCE N'!$F$2:$F$50) | C14: =SUMIF('BALANCE N-1'!$A$2:$A$50,"47*",'BALANCE N-1'!$F$2:$F$50)-SUMIF('BALANCE N-1'!$A$2:$A$50,"478*",'BALANCE N-1'!$F$2:$F$50) | D14: =B14-C14 | E14: =IF(C14=0,"",(B14-C14)/C14)
A15: TOTAL BRUT | B15: =SUM(B9:B14) | C15: =SUM(C9:C14) | D15: =B15-C15 | E15: =IF(C15=0,"",(B15-C15)/C15)
A16: Dépréciations des créances | B16: =SUMIF('BALANCE N'!$A$2:$A$50,"494*",'BALANCE N'!$G$2:$G$50)-SUMIF('BALANCE N'!$A$2:$A$50,"494*",'BALANCE N'!$F$2:$F$50)+SUMIF('BALANCE N'!$A$2:$A$50,"490*",'BALANCE N'!$G$2:$G$50)-SUMIF('BALANCE N'!$A$2:$A$50,"490*",'BALANCE N'!$F$2:$F$50)+SUMIF('BALANCE N'!$A$2:$A$50,"492*",'BALANCE N'!$G$2:$G$50)-SUMIF('BALANCE N'!$A$2:$A$50,"492*",'BALANCE N'!$F$2:$F$50)+SUMIF('BALANCE N'!$A$2:$A$50,"497*",'BALANCE N'!$G$2:$G$50)-SUMIF('BALANCE N'!$A$2:$A$50,"497*",'BALANCE N'!$F$2:$F$50)+SUMIF('BALANCE N'!$A$2:$A$50,"491*",'BALANCE N'!$G$2:$G$50)-SUMIF('BALANCE N'!$A$2:$A$50,"491*",'BALANCE N'!$F$2:$F$50)+SUMIF('BALANCE N'!$A$2:$A$50,"493*",'BALANCE N'!$G$2:$G$50)-SUMIF('BALANCE N'!$A$2:$A$50,"493*",'BALANCE N'!$F$2:$F$50) | C16: =SUMIF('BALANCE N-1'!$A$2:$A$50,"494*",'BALANCE N-1'!$G$2:$G$50)-SUMIF('BALANCE N-1'!$A$2:$A$50,"494*",'BALANCE N-1'!$F$2:$F$50)+SUMIF('BALANCE N-1'!$A$2:$A$50,"490*",'BALANCE N-1'!$G$2:$G$50)-SUMIF('BALANCE N-1'!$A$2:$A$50,"490*",'BALANCE N-1'!$F$2:$F$50)+SUMIF('BALANCE N-1'!$A$2:$A$50,"492*",'BALANCE N-1'!$G$2:$G$50)-SUMIF('BALANCE N-1'!$A$2:$A$50,"492*",'BALANCE N-1'!$F$2:$F$50)+SUMIF('BALANCE N-1'!$A$2:$A$50,"497*",'BALANCE N-1'!$G$2:$G$50)-SUMIF('BALANCE N-1'!$A$2:$A$50,"497*",'BALANCE N-1'!$F$2:$F$50)+SUMIF('BALANCE N-1'!$A$2:$A$50,"491*",'BALANCE N-1'!$G$2:$G$50)-SUMIF('BALANCE N-1'!$A$2:$A$50,"491*",'BALANCE N-1'!$F$2:$F$50)+SUMIF('BALANCE N-1'!$A$2:$A$50,"493*",'BALANCE N-1'!$G$2:$G$50)-SUMIF('BALANCE N-1'!$A$2:$A$50,"493*",'BALANCE N-1'!$F$2:$F$50) | D16: =B16-C16 | E16: =IF(C16=0,"",(B16-C16)/C16)
B17: =SUM(B16:B16) | C17: =SUM(C16:C16) | D17: =B17-C17 | E17: =IF(C17=0,"",(B17-C17)/C17)
A18: TOTAL NET DE DÉPRÉCIATIONS | B18: =B15-B17 | C18: =C15-C17 | D18: =B18-C18 | E18: =IF(C18=0,"",(B18-C18)/C18)
A20: Commentaires :
A21: • Justifier toute variation significative et les créances anciennes.

Sheet NOTE 7
A1: - 18 -
D2: NOTE 7 PROJETS DE DEVELOPPEMENT
A3: Dénomination sociale : PROJET EAU POTABLE RURALE
A4: Adresse : | D4: Sigle usuel : | E4: PEPR
A5: N° de compte contribuable (NCC) : PD-2023-017 | C5: Exercice clos le 31-12-2025 | D5: Durée (en mois) : 12
A6: N° de télédéclarant (NTD) :
A7: NOTE 7 : DISPONIBILITÉS
A8: Libellés | B8: Année N | C8: Année N-1 | D8: Variation en valeur | E8: Variation en %
A9: Chèques à encaisser | B9: =SUMIF('BALANCE N'!$A$2:$A$50,"513*",'BALANCE N'!$F$2:$F$50)-SUMIF('BALANCE N'!$A$2:$A$50,"513*",'BALANCE N'!$G$2:$G$50) | C9: =SUMIF('BALANCE N-1'!$A$2:$A$50,"513*",'BALANCE N-1'!$F$2:$F$50)-SUMIF('BALANCE N-1'!$A$2:$A$50,"513*",'BALANCE N-1'!$G$2:$G$50) | D9: =B9-C9 | E9: =IF(C9=0,"",(B9-C9)/C9)
A10: Chèques à l'encaissement | B10: =SUMIF('BALANCE N'!$A$2:$A$50,"514*",'BALANCE N'!$F$2:$F$50)-SUMIF('BALANCE N'!$A$2:$A$50,"514*",'BALANCE N'!$G$2:$G$50) | C10: =SUMIF('BALANCE N-1'!$A$2:$A$50,"514*",'BALANCE N-1'!$F$2:$F$50)-SUMIF('BALANCE N-1'!$A$2:$A$50,"514*",'BALANCE N-1'!$G$2:$G$50) | D10: =B10-C10 | E10: =IF(C10=0,"",(B10-C10)/C10)
A11: Cartes de crédit à encaisser | B11: =SUMIF('BALANCE N'!$A$2:$A$50,"515*",'BALANCE N'!$F$2:$F$50)-SUMIF('BALANCE N'!$A$2:$A$50,"515*",'BALANCE N'!$G$2:$G$50) | C11: =SUMIF('BALANCE N-1'!$A$2:$A$50,"515*",'BALANCE N-1'!$F$2:$F$50)-SUMIF('BALANCE N-1'!$A$2:$A$50,"515*",'BALANCE N-1'!$G$2:$G$50) | D11: =B11-C11 | E11: =IF(C11=0,"",(B11-C11)/C11)
A12: Autres valeurs à encaisser | B12: =SUMIF('BALANCE N'!$A$2:$A$50,"518*",'BALANCE N'!$F$2:$F$50)-SUMIF('BALANCE N'!$A$2:$A$50,"518*",'BALANCE N'!$G$2:$G$50) | C12: =SUMIF('BALANCE N-1'!$A$2:$A$50,"518*",'BALANCE N-1'!$F$2:$F$50)-SUMIF('BALANCE N-1'!$A$2:$A$50,"518*",'BALANCE N-1'!$G$2:$G$50) | D12: =B12-C12 | E12: =IF(C12=0,"",(B12-C12)/C12)
A13: TOTAL VALEURS À ENCAISSER | B13: =SUM(B9:B12) | C13: =SUM(C9:C12) | D13: =B13-C13 | E13: =IF(C13=0,"",(B13-C13)/C13)
A14: Banques locales | B14: =SUMIF('BALANCE N'!$A$2:$A$50,"521*",'BALANCE N'!$F$2:$F$50) | C14: =SUMIF('BALANCE N-1'!$A$2:$A$50,"521*",'BALANCE N-1'!$F$2:$F$50) | D14: =B14-C14 | E14: =IF(C14=0,"",(B14-C14)/C14)
A15: Banques autres États région | B15: =SUMIF('BALANCE N'!$A$2:$A$50,"522*",'BALANCE N'!$F$2:$F$50) | C15: =SUMIF('BALANCE N-1'!$A$2:$A$50,"522*",'BALANCE N-1'!$F$2:$F$50) | D15: =B15-C15 | E15: =IF(C15=0,"",(B15-C15)/C15)
A16: Banques, dépôt à terme et assimilés | B16: =SUMIF('BALANCE N'!$A$2:$A$50,"525*",'BALANCE N'!$F$2:$F$50) | C16: =SUMIF('BALANCE N-1'!$A$2:$A$50,"525*",'BALANCE N-1'!$F$2:$F$50) | D16: =B16-C16 | E16: =IF(C16=0,"",(B16-C16)/C16)
A17: Autres banques | B17: =SUMIF('BALANCE N'!$A$2:$A$50,"524*",'BALANCE N'!$F$2:$F$50)+SUMIF('BALANCE N'!$A$2:$A$50,"523*",'BALANCE N'!$F$2:$F$50) | C17: =SUMIF('BALANCE N-1'!$A$2:$A$50,"524*",'BALANCE N-1'!$F$2:$F$50)+SUMIF('BALANCE N-1'!$A$2:$A$50,"523*",'BALANCE N-1'!$F$2:$F$50) | D17: =B17-C17 | E17: =IF(C17=0,"",(B17-C17)/C17)
A18: Banques intérêts courus | B18: =SUMIF('BALANCE N'!$A$2:$A$50,"526*",'BALANCE N'!$F$2:$F$50)-SUMIF('BALANCE N'!$A$2:$A$50,"526*",'BALANCE N'!$G$2:$G$50) | C18: =SUMIF('BALANCE N-1'!$A$2:$A$50,"526*",'BALANCE N-1'!$F$2:$F$50)-SUMIF('BALANCE N-1'!$A$2:$A$50,"526*",'BALANCE N-1'!$G$2:$G$50) | D18: =B18-C18 | E18: =IF(C18=0,"",(B18-C18)/C18)
A19: Banques postales | B19: =SUMIF('BALANCE N'!$A$2:$A$50,"531*",'BALANCE N'!$F$2:$F$50) | C19: =SUMIF('BALANCE N-1'!$A$2:$A$50,"531*",'BALANCE N-1'!$F$2:$F$50) | D19: =B19-C19 | E19: =IF(C19=0,"",(B19-C19)/C19)
A20: Autres établissements financiers | B20: =SUMIF('BALANCE N'!$A$2:$A$50,"538*",'BALANCE N'!$F$2:$F$50)+SUMIF('BALANCE N'!$A$2:$A$50,"533*",'BALANCE N'!$F$2:$F$50)+SUMIF('BALANCE N'!$A$2:$A$50,"532*",'BALANCE N'!$F$2:$F$50) | C20: =SUMIF('BALANCE N-1'!$A$2:$A$50,"538*",'BALANCE N-1'!$F$2:$F$50)+SUMIF('BALANCE N-1'!$A$2:$A$50,"533*",'BALANCE N-1'!$F$2:$F$50)+SUMIF('BALANCE N-1'!$A$2:$A$50,"532*",'BALANCE N-1'!$F$2:$F$50) | D20: =B20-C20 | E20: =IF(C20=0,"",(B20-C20)/C20)
A21: Établissements financiers intérêts courus | B21: =SUMIF('BALANCE N'!$A$2:$A$50,"536*",'BALANCE N'!$F$2:$F$50)-SUMIF('BALANCE N'!$A$2:$A$50,"536*",'BALANCE N'!$G$2:$G$50) | C21: =SUMIF('BALANCE N-1'!$A$2:$A$50,"536*",'BALANCE N-1'!$F$2:$F$50)-SUMIF('BALANCE N-1'!$A$2:$A$50,"536*",'BALANCE N-1'!$G$2:$G$50) | D21: =B21-C21 | E21: =IF(C21=0,"",(B21-C21)/C21)
A22: Instruments de monnaie électronique | B22: =SUMIF('BALANCE N'!$A$2:$A$50,"55*",'BALANCE N'!$F$2:$F$50)-SUMIF('BALANCE N'!$A$2:$A$50,"55*",'BALANCE N'!$G$2:$G$50) | C22: =SUMIF('BALANCE N-1'!$A$2:$A$50,"55*",'BALANCE N-1'!$F$2:$F$50)-SUMIF('BALANCE N-1'!$A$2:$A$50,"55*",'BALANCE N-1'!$G$2:$G$50) | D22: =B22-C22 | E22: =IF(C22=0,"",(B22-C22)/C22)
A23: Caisse | B23: =SUMIF('BALANCE N'!$A$2:$A$50,"57*",'BALANCE N'!$F$2:$F$50)-SUMIF('BALANCE N'!$A$2:$A$50,"57*",'BALANCE N'!$G$2:$G$50) | C23: =SUMIF('BALANCE N-1'!$A$2:$A$50,"57*",'BALANCE N-1'!$F$2:$F$50)-SUMIF('BALANCE N-1'!$A$2:$A$50,"57*",'BALANCE N-1'!$G$2:$G$50) | D23: =B23-C23 | E23: =IF(C23=0,"",(B23-C23)/C23)
A24: TOTAL BANQUES ET CAISSES | B24: =SUM(B14:B23) | C24: =SUM(C14:C23) | D24: =B24-C24 | E24: =IF(C24=0,"",(B24-C24)/C24)
A25: Dépréciations | B25: =SUMIF('BALANCE N'!$A$2:$A$50,"591*",'BALANCE N'!$G$2:$G$50)-SUMIF('BALANCE N'!$A$2:$A$50,"591*",'BALANCE N'!$F$2:$F$50)+SUMIF('BALANCE N'!$A$2:$A$50,"592*",'BALANCE N'!$G$2:$G$50)-SUMIF('BALANCE N'!$A$2:$A$50,"592*",'BALANCE N'!$F$2:$F$50)+SUMIF('BALANCE N'!$A$2:$A$50,"595*",'BALANCE N'!$G$2:$G$50)-SUMIF('BALANCE N'!$A$2:$A$50,"595*",'BALANCE N'!$F$2:$F$50)+SUMIF('BALANCE N'!$A$2:$A$50,"593*",'BALANCE N'!$G$2:$G$50)-SUMIF('BALANCE N'!$A$2:$A$50,"593*",'BALANCE N'!$F$2:$F$50) | C25: =SUMIF('BALANCE N-1'!$A$2:$A$50,"591*",'BALANCE N-1'!$G$2:$G$50)-SUMIF('BALANCE N-1'!$A$2:$A$50,"591*",'BALANCE N-1'!$F$2:$F$50)+SUMIF('BALANCE N-1'!$A$2:$A$50,"592*",'BALANCE N-1'!$G$2:$G$50)-SUMIF('BALANCE N-1'!$A$2:$A$50,"592*",'BALANCE N-1'!$F$2:$F$50)+SUMIF('BALANCE N-1'!$A$2:$A$50,"595*",'BALANCE N-1'!$G$2:$G$50)-SUMIF('BALANCE N-1'!$A$2:$A$50,"595*",'BALANCE N-1'!$F$2:$F$50)+SUMIF('BALANCE N-1'!$A$2:$A$50,"593*",'BALANCE N-1'!$G$2:$G$50)-SUMIF('BALANCE N-1'!$A$2:$A$50,"593*",'BALANCE N-1'!$F$2:$F$50) | D25: =B25-C25 | E25: =IF(C25=0,"",(B25-C25)/C25)
B26: =SUM(B25:B25) | C26: =SUM(C25:C25) | D26: =B26-C26 | E26: =IF(C26=0,"",(B26-C26)/C26)
A27: TOTAL NET DE DÉPRÉCIATIONS | B27: =B13+B24-B26 | C27: =C13+C24-C26 | D27: =B27-C27 | E27: =IF(C27=0,"",(B27-C27)/C27)
A29: Commentaires :
A30: • Indiquer la date de rapprochement des comptes bancaires et la date d'inventaire de la caisse.

Sheet NOTE 8
A1: - 19 -
D2: NOTE 8 PROJETS DE DEVELOPPEMENT
A3: Dénomination sociale : PROJET EAU POTABLE RURALE
A4: Adresse : | D4: Sigle usuel : | E4: PEPR
A5: N° de compte contribuable (NCC) : PD-2023-017 | C5: Exercice clos le 31-12-2025 | D5: Durée (en mois) : 12
A6: N° de télédéclarant (NTD) :
A7: NOTE 8 : ÉCARTS DE CONVERSION
A8: Libellés | B8: Année N | C8: Année N-1 | D8: Variation en valeur | E8: Variation en %
A9: Écarts de conversion-actif (détailler les créances et dettes concernées) | B9: =SUMIF('BALANCE N'!$A$2:$A$50,"478*",'BALANCE N'!$F$2:$F$50)-SUMIF('BALANCE N'!$A$2:$A$50,"478*",'BALANCE N'!$G$2:$G$50) | C9: =SUMIF('BALANCE N-1'!$A$2:$A$50,"478*",'BALANCE N-1'!$F$2:$F$50)-SUMIF('BALANCE N-1'!$A$2:$A$50,"478*",'BALANCE N-1'!$G$2:$G$50) | D9: =B9-C9 | E9: =IF(C9=0,"",(B9-C9)/C9)
A10: …
A11: Écart de conversion-passif (détailler les créances et dettes concernées) | B11: =SUMIF('BALANCE N'!$A$2:$A$50,"479*",'BALANCE N'!$G$2:$G$50)-SUMIF('BALANCE N'!$A$2:$A$50,"479*",'BALANCE N'!$F$2:$F$50) | C11: =SUMIF('BALANCE N-1'!$A$2:$A$50,"479*",'BALANCE N-1'!$G$2:$G$50)-SUMIF('BALANCE N-1'!$A$2:$A$50,"479*",'BALANCE N-1'!$F$2:$F$50) | D11: =B11-C11 | E11: =IF(C11=0,"",(B11-C11)/C11)
A12: …

Sheet NOTE 9
A1: - 20 -
F2: NOTE 9 PROJETS DE DEVELOPPEMENT
A3: Dénomination sociale : PROJET EAU POTABLE RURALE
A4: Adresse : | F4: Sigle usuel : | G4: PEPR
A5: N° de compte contribuable (NCC) : PD-2023-017 | D5: Exercice clos le 31-12-2025 | F5: Durée (en mois) : 12
A6: N° de télédéclarant (NTD) :
A7: NOTE 9 : FONDS DU BAILLEUR
A8: Date des décaissements | B8: Bailleur / sous-projet 1 : montant décaissé | C8: Montant consommé | D8: Solde restant | E8: Bailleur / sous-projet 2 : montant décaissé | F8: Montant consommé | G8: Solde restant
A9: FONDS D'INVESTISSEMENT
D10: =B10-C10 | G10: =E10-F10
D11: =B11-C11 | G11: =E11-F11
D12: =B12-C12 | G12: =E12-F12
D13: =B13-C13 | G13: =E13-F13
A14: TOTAL FONDS D'INVESTISSEMENT | B14: =SUM(B10:B13) | C14: =SUM(C10:C13) | D14: =SUM(D10:D13) | E14: =SUM(E10:E13) | F14: =SUM(F10:F13) | G14: =SUM(G10:G13)
A15: FONDS D'ADMINISTRATION (2)
D16: =B16-C16 | G16: =E16-F16
D17: =B17-C17 | G17: =E17-F17
D18: =B18-C18 | G18: =E18-F18
D19: =B19-C19 | G19: =E19-F19
A20: TOTAL FONDS D'ADMINISTRATION (2) | B20: =SUM(B16:B19) | C20: =SUM(C16:C19) | D20: =SUM(D16:D19) | E20: =SUM(E16:E19) | F20: =SUM(F16:F19) | G20: =SUM(G16:G19)
A22: Rappels balance (formules) - à ventiler par bailleur :
A23: Fonds affectés aux investissements non consommés (soldes 162-164) | B23: =SUMIF('BALANCE N'!$A$2:$A$50,"162*",'BALANCE N'!$G$2:$G$50)-SUMIF('BALANCE N'!$A$2:$A$50,"162*",'BALANCE N'!$F$2:$F$50)+SUMIF('BALANCE N'!$A$2:$A$50,"163*",'BALANCE N'!$G$2:$G$50)-SUMIF('BALANCE N'!$A$2:$A$50,"163*",'BALANCE N'!$F$2:$F$50)+SUMIF('BALANCE N'!$A$2:$A$50,"164*",'BALANCE N'!$G$2:$G$50)-SUMIF('BALANCE N'!$A$2:$A$50,"164*",'BALANCE N'!$F$2:$F$50)
A24: Fonds d'administration non consommés (soldes 462-464) | B24: =SUMIF('BALANCE N'!$A$2:$A$50,"463*",'BALANCE N'!$G$2:$G$50)-SUMIF('BALANCE N'!$A$2:$A$50,"463*",'BALANCE N'!$F$2:$F$50)+SUMIF('BALANCE N'!$A$2:$A$50,"464*",'BALANCE N'!$G$2:$G$50)-SUMIF('BALANCE N'!$A$2:$A$50,"464*",'BALANCE N'!$F$2:$F$50)+SUMIF('BALANCE N'!$A$2:$A$50,"462*",'BALANCE N'!$G$2:$G$50)-SUMIF('BALANCE N'!$A$2:$A$50,"462*",'BALANCE N'!$F$2:$F$50)
A25: Quote-part de fonds d'administration consommée de l'exercice (702) | B25: =SUMIF('BALANCE N'!$A$2:$A$50,"702*",'BALANCE N'!$G$2:$G$50)-SUMIF('BALANCE N'!$A$2:$A$50,"702*",'BALANCE N'!$F$2:$F$50)
A27: (1) une colonne par bailleur et/ou sous-projet. (2) le montant consommé d'un exercice = solde du compte 702, à subdiviser par nature de projet. Indiquer le niveau d'utilisation des fonds en % et expliquer les retards d'exécution éventuels.

Sheet NOTE 10
A1: - 21 -
F2: NOTE 10 PROJETS DE DEVELOPPEMENT
A3: Dénomination sociale : PROJET EAU POTABLE RURALE
A4: Adresse : | F4: Sigle usuel : | G4: PEPR
A5: N° de compte contribuable (NCC) : PD-2023-017 | D5: Exercice clos le 31-12-2025 | F5: Durée (en mois) : 12
A6: N° de télédéclarant (NTD) :
A7: NOTE 10 : SUBVENTIONS
A8: Libellés | B8: Année N | C8: Année N-1 | D8: Variation en valeur | E8: Variation en % | F8: Régime fiscal | G8: Échéances
A9: État | B9: =SUMIF('BALANCE N'!$A$2:$A$50,"1411*",'BALANCE N'!$G$2:$G$50)-SUMIF('BALANCE N'!$A$2:$A$50,"1411*",'BALANCE N'!$F$2:$F$50) | C9: =SUMIF('BALANCE N-1'!$A$2:$A$50,"1411*",'BALANCE N-1'!$G$2:$G$50)-SUMIF('BALANCE N-1'!$A$2:$A$50,"1411*",'BALANCE N-1'!$F$2:$F$50) | D9: =B9-C9 | E9: =IF(C9=0,"",(B9-C9)/C9)
A10: Régions | B10: =SUMIF('BALANCE N'!$A$2:$A$50,"1412*",'BALANCE N'!$G$2:$G$50)-SUMIF('BALANCE N'!$A$2:$A$50,"1412*",'BALANCE N'!$F$2:$F$50) | C10: =SUMIF('BALANCE N-1'!$A$2:$A$50,"1412*",'BALANCE N-1'!$G$2:$G$50)-SUMIF('BALANCE N-1'!$A$2:$A$50,"1412*",'BALANCE N-1'!$F$2:$F$50) | D10: =B10-C10 | E10: =IF(C10=0,"",(B10-C10)/C10)
A11: Départements | B11: =SUMIF('BALANCE N'!$A$2:$A$50,"1413*",'BALANCE N'!$G$2:$G$50)-SUMIF('BALANCE N'!$A$2:$A$50,"1413*",'BALANCE N'!$F$2:$F$50) | C11: =SUMIF('BALANCE N-1'!$A$2:$A$50,"1413*",'BALANCE N-1'!$G$2:$G$50)-SUMIF('BALANCE N-1'!$A$2:$A$50,"1413*",'BALANCE N-1'!$F$2:$F$50) | D11: =B11-C11 | E11: =IF(C11=0,"",(B11-C11)/C11)
A12: Communes et collectivités publiques décentralisées | B12: =SUMIF('BALANCE N'!$A$2:$A$50,"1414*",'BALANCE N'!$G$2:$G$50)-SUMIF('BALANCE N'!$A$2:$A$50,"1414*",'BALANCE N'!$F$2:$F$50) | C12: =SUMIF('BALANCE N-1'!$A$2:$A$50,"1414*",'BALANCE N-1'!$G$2:$G$50)-SUMIF('BALANCE N-1'!$A$2:$A$50,"1414*",'BALANCE N-1'!$F$2:$F$50) | D12: =B12-C12 | E12: =IF(C12=0,"",(B12-C12)/C12)
A13: Entités publiques ou mixtes | B13: =SUMIF('BALANCE N'!$A$2:$A$50,"1415*",'BALANCE N'!$G$2:$G$50)-SUMIF('BALANCE N'!$A$2:$A$50,"1415*",'BALANCE N'!$F$2:$F$50) | C13: =SUMIF('BALANCE N-1'!$A$2:$A$50,"1415*",'BALANCE N-1'!$G$2:$G$50)-SUMIF('BALANCE N-1'!$A$2:$A$50,"1415*",'BALANCE N-1'!$F$2:$F$50) | D13: =B13-C13 | E13: =IF(C13=0,"",(B13-C13)/C13)
A14: Entités et organismes privés | B14: =SUMIF('BALANCE N'!$A$2:$A$50,"1416*",'BALANCE N'!$G$2:$G$50)-SUMIF('BALANCE N'!$A$2:$A$50,"1416*",'BALANCE N'!$F$2:$F$50) | C14: =SUMIF('BALANCE N-1'!$A$2:$A$50,"1416*",'BALANCE N-1'!$G$2:$G$50)-SUMIF('BALANCE N-1'!$A$2:$A$50,"1416*",'BALANCE N-1'!$F$2:$F$50) | D14: =B14-C14 | E14: =IF(C14=0,"",(B14-C14)/C14)
A15: Organismes internationaux | B15: =SUMIF('BALANCE N'!$A$2:$A$50,"1417*",'BALANCE N'!$G$2:$G$50)-SUMIF('BALANCE N'!$A$2:$A$50,"1417*",'BALANCE N'!$F$2:$F$50) | C15: =SUMIF('BALANCE N-1'!$A$2:$A$50,"1417*",'BALANCE N-1'!$G$2:$G$50)-SUMIF('BALANCE N-1'!$A$2:$A$50,"1417*",'BALANCE N-1'!$F$2:$F$50) | D15: =B15-C15 | E15: =IF(C15=0,"",(B15-C15)/C15)
A16: Autres | B16: =SUMIF('BALANCE N'!$A$2:$A$50,"148*",'BALANCE N'!$G$2:$G$50)-SUMIF('BALANCE N'!$A$2:$A$50,"148*",'BALANCE N'!$F$2:$F$50)+SUMIF('BALANCE N'!$A$2:$A$50,"1418*",'BALANCE N'!$G$2:$G$50)-SUMIF('BALANCE N'!$A$2:$A$50,"1418*",'BALANCE N'!$F$2:$F$50) | C16: =SUMIF('BALANCE N-1'!$A$2:$A$50,"148*",'BALANCE N-1'!$G$2:$G$50)-SUMIF('BALANCE N-1'!$A$2:$A$50,"148*",'BALANCE N-1'!$F$2:$F$50)+SUMIF('BALANCE N-1'!$A$2:$A$50,"1418*",'BALANCE N-1'!$G$2:$G$50)-SUMIF('BALANCE N-1'!$A$2:$A$50,"1418*",'BALANCE N-1'!$F$2:$F$50) | D16: =B16-C16 | E16: =IF(C16=0,"",(B16-C16)/C16)
A17: TOTAL SUBVENTIONS | B17: =SUM(B9:B16) | C17: =SUM(C9:C16) | D17: =B17-C17 | E17: =IF(C17=0,"",(B17-C17)/C17)

Sheet NOTE 11
A1: - 22 -
G2: NOTE 11 PROJETS DE DEVELOPPEMENT
A3: Dénomination sociale : PROJET EAU POTABLE RURALE
A4: Adresse : | G4: Sigle usuel : | H4: PEPR
A5: N° de compte contribuable (NCC) : PD-2023-017 | E5: Exercice clos le 31-12-2025 | G5: Durée (en mois) : 12
A6: N° de télédéclarant (NTD) :
A7: NOTE 11 : DETTES FINANCIÈRES ET RESSOURCES ASSIMILÉES
A8: Libellés | B8: Année N | C8: Année N-1 | D8: Variation en valeur | E8: Variation en % | F8: À un an au plus | G8: À plus d'un an et deux ans au plus | H8: À plus de deux ans
A9: Emprunts et dettes auprès des établissements de crédit | B9: =SUMIF('BALANCE N'!$A$2:$A$50,"182*",'BALANCE N'!$G$2:$G$50)-SUMIF('BALANCE N'!$A$2:$A$50,"182*",'BALANCE N'!$F$2:$F$50) | C9: =SUMIF('BALANCE N-1'!$A$2:$A$50,"182*",'BALANCE N-1'!$G$2:$G$50)-SUMIF('BALANCE N-1'!$A$2:$A$50,"182*",'BALANCE N-1'!$F$2:$F$50) | D9: =B9-C9 | E9: =IF(C9=0,"",(B9-C9)/C9)
A10: Avances reçues de l'État | B10: =SUMIF('BALANCE N'!$A$2:$A$50,"183*",'BALANCE N'!$G$2:$G$50)-SUMIF('BALANCE N'!$A$2:$A$50,"183*",'BALANCE N'!$F$2:$F$50) | C10: =SUMIF('BALANCE N-1'!$A$2:$A$50,"183*",'BALANCE N-1'!$G$2:$G$50)-SUMIF('BALANCE N-1'!$A$2:$A$50,"183*",'BALANCE N-1'!$F$2:$F$50) | D10: =B10-C10 | E10: =IF(C10=0,"",(B10-C10)/C10)
A11: Dépôts et cautionnements reçus | B11: =SUMIF('BALANCE N'!$A$2:$A$50,"185*",'BALANCE N'!$G$2:$G$50)-SUMIF('BALANCE N'!$A$2:$A$50,"185*",'BALANCE N'!$F$2:$F$50) | C11: =SUMIF('BALANCE N-1'!$A$2:$A$50,"185*",'BALANCE N-1'!$G$2:$G$50)-SUMIF('BALANCE N-1'!$A$2:$A$50,"185*",'BALANCE N-1'!$F$2:$F$50) | D11: =B11-C11 | E11: =IF(C11=0,"",(B11-C11)/C11)
A12: Intérêts courus | B12: =SUMIF('BALANCE N'!$A$2:$A$50,"186*",'BALANCE N'!$G$2:$G$50)-SUMIF('BALANCE N'!$A$2:$A$50,"186*",'BALANCE N'!$F$2:$F$50) | C12: =SUMIF('BALANCE N-1'!$A$2:$A$50,"186*",'BALANCE N-1'!$G$2:$G$50)-SUMIF('BALANCE N-1'!$A$2:$A$50,"186*",'BALANCE N-1'!$F$2:$F$50) | D12: =B12-C12 | E12: =IF(C12=0,"",(B12-C12)/C12)
A13: Autres emprunts et dettes | B13: =SUMIF('BALANCE N'!$A$2:$A$50,"188*",'BALANCE N'!$G$2:$G$50)-SUMIF('BALANCE N'!$A$2:$A$50,"188*",'BALANCE N'!$F$2:$F$50)+SUMIF('BALANCE N'!$A$2:$A$50,"181*",'BALANCE N'!$G$2:$G$50)-SUMIF('BALANCE N'!$A$2:$A$50,"181*",'BALANCE N'!$F$2:$F$50) | C13: =SUMIF('BALANCE N-1'!$A$2:$A$50,"188*",'BALANCE N-1'!$G$2:$G$50)-SUMIF('BALANCE N-1'!$A$2:$A$50,"188*",'BALANCE N-1'!$F$2:$F$50)+SUMIF('BALANCE N-1'!$A$2:$A$50,"181*",'BALANCE N-1'!$G$2:$G$50)-SUMIF('BALANCE N-1'!$A$2:$A$50,"181*",'BALANCE N-1'!$F$2:$F$50) | D13: =B13-C13 | E13: =IF(C13=0,"",(B13-C13)/C13)
A14: TOTAL EMPRUNTS ET DETTES FINANCIÈRES | B14: =SUM(B9:B13) | C14: =SUM(C9:C13) | D14: =B14-C14 | E14: =IF(C14=0,"",(B14-C14)/C14)
A15: Crédit-bail immobilier | B15: =SUMIF('BALANCE N'!$A$2:$A$50,"1871*",'BALANCE N'!$G$2:$G$50)-SUMIF('BALANCE N'!$A$2:$A$50,"1871*",'BALANCE N'!$F$2:$F$50) | C15: =SUMIF('BALANCE N-1'!$A$2:$A$50,"1871*",'BALANCE N-1'!$G$2:$G$50)-SUMIF('BALANCE N-1'!$A$2:$A$50,"1871*",'BALANCE N-1'!$F$2:$F$50) | D15: =B15-C15 | E15: =IF(C15=0,"",(B15-C15)/C15)
A16: Crédit-bail mobilier | B16: =SUMIF('BALANCE N'!$A$2:$A$50,"1872*",'BALANCE N'!$G$2:$G$50)-SUMIF('BALANCE N'!$A$2:$A$50,"1872*",'BALANCE N'!$F$2:$F$50) | C16: =SUMIF('BALANCE N-1'!$A$2:$A$50,"1872*",'BALANCE N-1'!$G$2:$G$50)-SUMIF('BALANCE N-1'!$A$2:$A$50,"1872*",'BALANCE N-1'!$F$2:$F$50) | D16: =B16-C16 | E16: =IF(C16=0,"",(B16-C16)/C16)
A17: Location-vente | B17: =SUMIF('BALANCE N'!$A$2:$A$50,"1873*",'BALANCE N'!$G$2:$G$50)-SUMIF('BALANCE N'!$A$2:$A$50,"1873*",'BALANCE N'!$F$2:$F$50) | C17: =SUMIF('BALANCE N-1'!$A$2:$A$50,"1873*",'BALANCE N-1'!$G$2:$G$50)-SUMIF('BALANCE N-1'!$A$2:$A$50,"1873*",'BALANCE N-1'!$F$2:$F$50) | D17: =B17-C17 | E17: =IF(C17=0,"",(B17-C17)/C17)
A18: Intérêts courus (location-acquisition) | B18: =SUMIF('BALANCE N'!$A$2:$A$50,"1876*",'BALANCE N'!$G$2:$G$50)-SUMIF('BALANCE N'!$A$2:$A$50,"1876*",'BALANCE N'!$F$2:$F$50) | C18: =SUMIF('BALANCE N-1'!$A$2:$A$50,"1876*",'BALANCE N-1'!$G$2:$G$50)-SUMIF('BALANCE N-1'!$A$2:$A$50,"1876*",'BALANCE N-1'!$F$2:$F$50) | D18: =B18-C18 | E18: =IF(C18=0,"",(B18-C18)/C18)
A19: Autres dettes de location-acquisition | B19: =SUMIF('BALANCE N'!$A$2:$A$50,"187*",'BALANCE N'!$G$2:$G$50)-SUMIF('BALANCE N'!$A$2:$A$50,"187*",'BALANCE N'!$F$2:$F$50)-SUMIF('BALANCE N'!$A$2:$A$50,"1873*",'BALANCE N'!$G$2:$G$50)+SUMIF('BALANCE N'!$A$2:$A$50,"1873*",'BALANCE N'!$F$2:$F$50)-SUMIF('BALANCE N'!$A$2:$A$50,"1876*",'BALANCE N'!$G$2:$G$50)+SUMIF('BALANCE N'!$A$2:$A$50,"1876*",'BALANCE N'!$F$2:$F$50)-SUMIF('BALANCE N'!$A$2:$A$50,"1872*",'BALANCE N'!$G$2:$G$50)+SUMIF('BALANCE N'!$A$2:$A$50,"1872*",'BALANCE N'!$F$2:$F$50)-SUMIF('BALANCE N'!$A$2:$A$50,"1871*",'BALANCE N'!$G$2:$G$50)+SUMIF('BALANCE N'!$A$2:$A$50,"1871*",'BALANCE N'!$F$2:$F$50) | C19: =SUMIF('BALANCE N-1'!$A$2:$A$50,"187*",'BALANCE N-1'!$G$2:$G$50)-SUMIF('BALANCE N-1'!$A$2:$A$50,"187*",'BALANCE N-1'!$F$2:$F$50)-SUMIF('BALANCE N-1'!$A$2:$A$50,"1873*",'BALANCE N-1'!$G$2:$G$50)+SUMIF('BALANCE N-1'!$A$2:$A$50,"1873*",'BALANCE N-1'!$F$2:$F$50)-SUMIF('BALANCE N-1'!$A$2:$A$50,"1876*",'BALANCE N-1'!$G$2:$G$50)+SUMIF('BALANCE N-1'!$A$2:$A$50,"1876*",'BALANCE N-1'!$F$2:$F$50)-SUMIF('BALANCE N-1'!$A$2:$A$50,"1872*",'BALANCE N-1'!$G$2:$G$50)+SUMIF('BALANCE N-1'!$A$2:$A$50,"1872*",'BALANCE N-1'!$F$2:$F$50)-SUMIF('BALANCE N-1'!$A$2:$A$50,"1871*",'BALANCE N-1'!$G$2:$G$50)+SUMIF('BALANCE N-1'!$A$2:$A$50,"1871*",'BALANCE N-1'!$F$2:$F$50) | D19: =B19-C19 | E19: =IF(C19=0,"",(B19-C19)/C19)
A20: TOTAL DETTES DE LOCATION-ACQUISITION | B20: =SUM(B15:B19) | C20: =SUM(C15:C19) | D20: =B20-C20 | E20: =IF(C20=0,"",(B20-C20)/C20)
A21: Provisions pour litiges | B21: =SUMIF('BALANCE N'!$A$2:$A$50,"191*",'BALANCE N'!$G$2:$G$50)-SUMIF('BALANCE N'!$A$2:$A$50,"191*",'BALANCE N'!$F$2:$F$50) | C21: =SUMIF('BALANCE N-1'!$A$2:$A$50,"191*",'BALANCE N-1'!$G$2:$G$50)-SUMIF('BALANCE N-1'!$A$2:$A$50,"191*",'BALANCE N-1'!$F$2:$F$50) | D21: =B21-C21 | E21: =IF(C21=0,"",(B21-C21)/C21)
A22: Provisions pour pertes de change | B22: =SUMIF('BALANCE N'!$A$2:$A$50,"194*",'BALANCE N'!$G$2:$G$50)-SUMIF('BALANCE N'!$A$2:$A$50,"194*",'BALANCE N'!$F$2:$F$50) | C22: =SUMIF('BALANCE N-1'!$A$2:$A$50,"194*",'BALANCE N-1'!$G$2:$G$50)-SUMIF('BALANCE N-1'!$A$2:$A$50,"194*",'BALANCE N-1'!$F$2:$F$50) | D22: =B22-C22 | E22: =IF(C22=0,"",(B22-C22)/C22)
A23: Provisions pour pensions et obligations assimilées | B23: =SUMIF('BALANCE N'!$A$2:$A$50,"196*",'BALANCE N'!$G$2:$G$50)-SUMIF('BALANCE N'!$A$2:$A$50,"196*",'BALANCE N'!$F$2:$F$50) | C23: =SUMIF('BALANCE N-1'!$A$2:$A$50,"196*",'BALANCE N-1'!$G$2:$G$50)-SUMIF('BALANCE N-1'!$A$2:$A$50,"196*",'BALANCE N-1'!$F$2:$F$50) | D23: =B23-C23 | E23: =IF(C23=0,"",(B23-C23)/C23)
A24: Autres provisions pour risques et charges | B24: =SUMIF('BALANCE N'!$A$2:$A$50,"198*",'BALANCE N'!$G$2:$G$50)-SUMIF('BALANCE N'!$A$2:$A$50,"198*",'BALANCE N'!$F$2:$F$50)+SUMIF('BALANCE N'!$A$2:$A$50,"192*",'BALANCE N'!$G$2:$G$50)-SUMIF('BALANCE N'!$A$2:$A$50,"192*",'BALANCE N'!$F$2:$F$50) | C24: =SUMIF('BALANCE N-1'!$A$2:$A$50,"198*",'BALANCE N-1'!$G$2:$G$50)-SUMIF('BALANCE N-1'!$A$2:$A$50,"198*",'BALANCE N-1'!$F$2:$F$50)+SUMIF('BALANCE N-1'!$A$2:$A$50,"192*",'BALANCE N-1'!$G$2:$G$50)-SUMIF('BALANCE N-1'!$A$2:$A$50,"192*",'BALANCE N-1'!$F$2:$F$50) | D24: =B24-C24 | E24: =IF(C24=0,"",(B24-C24)/C24)
A25: TOTAL PROVISIONS FINANCIÈRES POUR RISQUES ET CHARGES | B25: =SUM(B21:B24) | C25: =SUM(C21:C24) | D25: =B25-C25 | E25: =IF(C25=0,"",(B25-C25)/C25)
A26: TOTAL DETTES FINANCIÈRES ET RESSOURCES ASSIMILÉES | B26: =B14+B20+B25 | C26: =C14+C20+C25 | D26: =B26-C26 | E26: =IF(C26=0,"",(B26-C26)/C26)
A28: Commentaires :
A29: • Pour chaque emprunt : date d'octroi, organisme, montant initial, durée, garanties données.

Sheet NOTE 12
A1: - 23 -
G2: NOTE 12 PROJETS DE DEVELOPPEMENT
A3: Dénomination sociale : PROJET EAU POTABLE RURALE
A4: Adresse : | G4: Sigle usuel : | H4: PEPR
A5: N° de compte contribuable (NCC) : PD-2023-017 | E5: Exercice clos le 31-12-2025 | G5: Durée (en mois) : 12
A6: N° de télédéclarant (NTD) :
A7: NOTE 12 : DETTES FOURNISSEURS ET ASSIMILÉES, FISCALES ET SOCIALES
A8: Libellés | B8: Année N | C8: Année N-1 | D8: Variation en valeur | E8: Variation en % | F8: À un an au plus | G8: À plus d'un an et deux ans au plus | H8: À plus de deux ans
A9: Fournisseurs | B9: =SUMIF('BALANCE N'!$A$2:$A$50,"40*",'BALANCE N'!$G$2:$G$50)-SUMIF('BALANCE N'!$A$2:$A$50,"40*",'BALANCE N'!$F$2:$F$50)-SUMIF('BALANCE N'!$A$2:$A$50,"409*",'BALANCE N'!$G$2:$G$50)+SUMIF('BALANCE N'!$A$2:$A$50,"409*",'BALANCE N'!$F$2:$F$50) | C9: =SUMIF('BALANCE N-1'!$A$2:$A$50,"40*",'BALANCE N-1'!$G$2:$G$50)-SUMIF('BALANCE N-1'!$A$2:$A$50,"40*",'BALANCE N-1'!$F$2:$F$50)-SUMIF('BALANCE N-1'!$A$2:$A$50,"409*",'BALANCE N-1'!$G$2:$G$50)+SUMIF('BALANCE N-1'!$A$2:$A$50,"409*",'BALANCE N-1'!$F$2:$F$50) | D9: =B9-C9 | E9: =IF(C9=0,"",(B9-C9)/C9)
A10: Clients-usagers créditeurs | B10: =SUMIF('BALANCE N'!$A$2:$A$50,"419*",'BALANCE N'!$G$2:$G$50)-SUMIF('BALANCE N'!$A$2:$A$50,"419*",'BALANCE N'!$F$2:$F$50) | C10: =SUMIF('BALANCE N-1'!$A$2:$A$50,"419*",'BALANCE N-1'!$G$2:$G$50)-SUMIF('BALANCE N-1'!$A$2:$A$50,"419*",'BALANCE N-1'!$F$2:$F$50) | D10: =B10-C10 | E10: =IF(C10=0,"",(B10-C10)/C10)
A11: DETTES FOURNISSEURS ET ASSIMILÉES | B11: =SUM(B9:B10) | C11: =SUM(C9:C10) | D11: =B11-C11 | E11: =IF(C11=0,"",(B11-C11)/C11)
A12: Personnel, rémunérations dues | B12: =SUMIF('BALANCE N'!$A$2:$A$50,"422*",'BALANCE N'!$G$2:$G$50) | C12: =SUMIF('BALANCE N-1'!$A$2:$A$50,"422*",'BALANCE N-1'!$G$2:$G$50) | D12: =B12-C12 | E12: =IF(C12=0,"",(B12-C12)/C12)
A13: Personnel, congés à payer | B13: =SUMIF('BALANCE N'!$A$2:$A$50,"4281*",'BALANCE N'!$G$2:$G$50) | C13: =SUMIF('BALANCE N-1'!$A$2:$A$50,"4281*",'BALANCE N-1'!$G$2:$G$50) | D13: =B13-C13 | E13: =IF(C13=0,"",(B13-C13)/C13)
A14: Charges sociales sur congés à payer | B14: =SUMIF('BALANCE N'!$A$2:$A$50,"4382*",'BALANCE N'!$G$2:$G$50) | C14: =SUMIF('BALANCE N-1'!$A$2:$A$50,"4382*",'BALANCE N-1'!$G$2:$G$50) | D14: =B14-C14 | E14: =IF(C14=0,"",(B14-C14)/C14)
A15: Autres personnel | B15: =SUMIF('BALANCE N'!$A$2:$A$50,"421*",'BALANCE N'!$G$2:$G$50)+SUMIF('BALANCE N'!$A$2:$A$50,"423*",'BALANCE N'!$G$2:$G$50)+SUMIF('BALANCE N'!$A$2:$A$50,"427*",'BALANCE N'!$G$2:$G$50)+SUMIF('BALANCE N'!$A$2:$A$50,"424*",'BALANCE N'!$G$2:$G$50)+SUMIF('BALANCE N'!$A$2:$A$50,"425*",'BALANCE N'!$G$2:$G$50)+SUMIF('BALANCE N'!$A$2:$A$50,"428*",'BALANCE N'!$G$2:$G$50)-SUMIF('BALANCE N'!$A$2:$A$50,"4281*",'BALANCE N'!$G$2:$G$50) | C15: =SUMIF('BALANCE N-1'!$A$2:$A$50,"421*",'BALANCE N-1'!$G$2:$G$50)+SUMIF('BALANCE N-1'!$A$2:$A$50,"423*",'BALANCE N-1'!$G$2:$G$50)+SUMIF('BALANCE N-1'!$A$2:$A$50,"427*",'BALANCE N-1'!$G$2:$G$50)+SUMIF('BALANCE N-1'!$A$2:$A$50,"424*",'BALANCE N-1'!$G$2:$G$50)+SUMIF('BALANCE N-1'!$A$2:$A$50,"425*",'BALANCE N-1'!$G$2:$G$50)+SUMIF('BALANCE N-1'!$A$2:$A$50,"428*",'BALANCE N-1'!$G$2:$G$50)-SUMIF('BALANCE N-1'!$A$2:$A$50,"4281*",'BALANCE N-1'!$G$2:$G$50) | D15: =B15-C15 | E15: =IF(C15=0,"",(B15-C15)/C15)
A16: Caisse de sécurité sociale | B16: =SUMIF('BALANCE N'!$A$2:$A$50,"431*",'BALANCE N'!$G$2:$G$50) | C16: =SUMIF('BALANCE N-1'!$A$2:$A$50,"431*",'BALANCE N-1'!$G$2:$G$50) | D16: =B16-C16 | E16: =IF(C16=0,"",(B16-C16)/C16)
A17: Caisse de retraite | B17: =SUMIF('BALANCE N'!$A$2:$A$50,"432*",'BALANCE N'!$G$2:$G$50) | C17: =SUMIF('BALANCE N-1'!$A$2:$A$50,"432*",'BALANCE N-1'!$G$2:$G$50) | D17: =B17-C17 | E17: =IF(C17=0,"",(B17-C17)/C17)
A18: Mutuelle de santé | B18: =SUMIF('BALANCE N'!$A$2:$A$50,"4331*",'BALANCE N'!$G$2:$G$50) | C18: =SUMIF('BALANCE N-1'!$A$2:$A$50,"4331*",'BALANCE N-1'!$G$2:$G$50) | D18: =B18-C18 | E18: =IF(C18=0,"",(B18-C18)/C18)
A19: Assurance retraite | B19: =SUMIF('BALANCE N'!$A$2:$A$50,"4332*",'BALANCE N'!$G$2:$G$50) | C19: =SUMIF('BALANCE N-1'!$A$2:$A$50,"4332*",'BALANCE N-1'!$G$2:$G$50) | D19: =B19-C19 | E19: =IF(C19=0,"",(B19-C19)/C19)
A20: Autres charges sociales et cotisations | B20: =SUMIF('BALANCE N'!$A$2:$A$50,"438*",'BALANCE N'!$G$2:$G$50)+SUMIF('BALANCE N'!$A$2:$A$50,"4333*",'BALANCE N'!$G$2:$G$50)-SUMIF('BALANCE N'!$A$2:$A$50,"4382*",'BALANCE N'!$G$2:$G$50) | C20: =SUMIF('BALANCE N-1'!$A$2:$A$50,"438*",'BALANCE N-1'!$G$2:$G$50)+SUMIF('BALANCE N-1'!$A$2:$A$50,"4333*",'BALANCE N-1'!$G$2:$G$50)-SUMIF('BALANCE N-1'!$A$2:$A$50,"4382*",'BALANCE N-1'!$G$2:$G$50) | D20: =B20-C20 | E20: =IF(C20=0,"",(B20-C20)/C20)
A21: TOTAL DETTES SOCIALES | B21: =SUM(B12:B20) | C21: =SUM(C12:C20) | D21: =B21-C21 | E21: =IF(C21=0,"",(B21-C21)/C21)
A22: État, autres impôts et taxes | B22: =SUMIF('BALANCE N'!$A$2:$A$50,"446*",'BALANCE N'!$G$2:$G$50)+SUMIF('BALANCE N'!$A$2:$A$50,"442*",'BALANCE N'!$G$2:$G$50) | C22: =SUMIF('BALANCE N-1'!$A$2:$A$50,"446*",'BALANCE N-1'!$G$2:$G$50)+SUMIF('BALANCE N-1'!$A$2:$A$50,"442*",'BALANCE N-1'!$G$2:$G$50) | D22: =B22-C22 | E22: =IF(C22=0,"",(B22-C22)/C22)
A23: État, TVA | B23: =SUMIF('BALANCE N'!$A$2:$A$50,"443*",'BALANCE N'!$G$2:$G$50)+SUMIF('BALANCE N'!$A$2:$A$50,"444*",'BALANCE N'!$G$2:$G$50)+SUMIF('BALANCE N'!$A$2:$A$50,"445*",'BALANCE N'!$G$2:$G$50) | C23: =SUMIF('BALANCE N-1'!$A$2:$A$50,"443*",'BALANCE N-1'!$G$2:$G$50)+SUMIF('BALANCE N-1'!$A$2:$A$50,"444*",'BALANCE N-1'!$G$2:$G$50)+SUMIF('BALANCE N-1'!$A$2:$A$50,"445*",'BALANCE N-1'!$G$2:$G$50) | D23: =B23-C23 | E23: =IF(C23=0,"",(B23-C23)/C23)
A24: État, impôts retenus à la source | B24: =SUMIF('BALANCE N'!$A$2:$A$50,"447*",'BALANCE N'!$G$2:$G$50) | C24: =SUMIF('BALANCE N-1'!$A$2:$A$50,"447*",'BALANCE N-1'!$G$2:$G$50) | D24: =B24-C24 | E24: =IF(C24=0,"",(B24-C24)/C24)
A25: Autres dettes État | B25: =SUMIF('BALANCE N'!$A$2:$A$50,"448*",'BALANCE N'!$G$2:$G$50)+SUMIF('BALANCE N'!$A$2:$A$50,"449*",'BALANCE N'!$G$2:$G$50) | C25: =SUMIF('BALANCE N-1'!$A$2:$A$50,"448*",'BALANCE N-1'!$G$2:$G$50)+SUMIF('BALANCE N-1'!$A$2:$A$50,"449*",'BALANCE N-1'!$G$2:$G$50) | D25: =B25-C25 | E25: =IF(C25=0,"",(B25-C25)/C25)
A26: TOTAL DETTES FISCALES | B26: =SUM(B22:B25) | C26: =SUM(C22:C25) | D26: =B26-C26 | E26: =IF(C26=0,"",(B26-C26)/C26)
A27: TOTAL DETTES FOURNISSEURS ET ASSIMILÉES, FISCALES ET SOCIALES | B27: =B11+B21+B26 | C27: =C11+C21+C26 | D27: =B27-C27 | E27: =IF(C27=0,"",(B27-C27)/C27)

Sheet NOTE 13
A1: - 24 -
D2: NOTE 13 PROJETS DE DEVELOPPEMENT
A3: Dénomination sociale : PROJET EAU POTABLE RURALE
A4: Adresse : | D4: Sigle usuel : | E4: PEPR
A5: N° de compte contribuable (NCC) : PD-2023-017 | C5: Exercice clos le 31-12-2025 | D5: Durée (en mois) : 12
A6: N° de télédéclarant (NTD) :
A7: NOTE 13 : BANQUES, CRÉDIT D'ESCOMPTE ET DE TRÉSORERIE
A8: Libellés | B8: Année N | C8: Année N-1 | D8: Variation en valeur | E8: Variation en %
A9: Escomptes de crédits ordinaires | B9: =SUMIF('BALANCE N'!$A$2:$A$50,"565*",'BALANCE N'!$G$2:$G$50) | C9: =SUMIF('BALANCE N-1'!$A$2:$A$50,"565*",'BALANCE N-1'!$G$2:$G$50) | D9: =B9-C9 | E9: =IF(C9=0,"",(B9-C9)/C9)
A10: TOTAL : BANQUES, CRÉDITS D'ESCOMPTE | B10: =SUM(B9:B9) | C10: =SUM(C9:C9) | D10: =B10-C10 | E10: =IF(C10=0,"",(B10-C10)/C10)
A11: Banques locales | B11: =SUMIF('BALANCE N'!$A$2:$A$50,"521*",'BALANCE N'!$G$2:$G$50) | C11: =SUMIF('BALANCE N-1'!$A$2:$A$50,"521*",'BALANCE N-1'!$G$2:$G$50) | D11: =B11-C11 | E11: =IF(C11=0,"",(B11-C11)/C11)
A12: Banques autres États région | B12: =SUMIF('BALANCE N'!$A$2:$A$50,"522*",'BALANCE N'!$G$2:$G$50) | C12: =SUMIF('BALANCE N-1'!$A$2:$A$50,"522*",'BALANCE N-1'!$G$2:$G$50) | D12: =B12-C12 | E12: =IF(C12=0,"",(B12-C12)/C12)
A13: Autres banques | B13: =SUMIF('BALANCE N'!$A$2:$A$50,"524*",'BALANCE N'!$G$2:$G$50)+SUMIF('BALANCE N'!$A$2:$A$50,"525*",'BALANCE N'!$G$2:$G$50)+SUMIF('BALANCE N'!$A$2:$A$50,"523*",'BALANCE N'!$G$2:$G$50) | C13: =SUMIF('BALANCE N-1'!$A$2:$A$50,"524*",'BALANCE N-1'!$G$2:$G$50)+SUMIF('BALANCE N-1'!$A$2:$A$50,"525*",'BALANCE N-1'!$G$2:$G$50)+SUMIF('BALANCE N-1'!$A$2:$A$50,"523*",'BALANCE N-1'!$G$2:$G$50) | D13: =B13-C13 | E13: =IF(C13=0,"",(B13-C13)/C13)
A14: Banques, intérêts courus | B14: =SUMIF('BALANCE N'!$A$2:$A$50,"566*",'BALANCE N'!$G$2:$G$50)+SUMIF('BALANCE N'!$A$2:$A$50,"526*",'BALANCE N'!$G$2:$G$50) | C14: =SUMIF('BALANCE N-1'!$A$2:$A$50,"566*",'BALANCE N-1'!$G$2:$G$50)+SUMIF('BALANCE N-1'!$A$2:$A$50,"526*",'BALANCE N-1'!$G$2:$G$50) | D14: =B14-C14 | E14: =IF(C14=0,"",(B14-C14)/C14)
A15: Crédit de trésorerie | B15: =SUMIF('BALANCE N'!$A$2:$A$50,"561*",'BALANCE N'!$G$2:$G$50) | C15: =SUMIF('BALANCE N-1'!$A$2:$A$50,"561*",'BALANCE N-1'!$G$2:$G$50) | D15: =B15-C15 | E15: =IF(C15=0,"",(B15-C15)/C15)
A16: TOTAL : BANQUES, CRÉDITS DE TRÉSORERIE | B16: =SUM(B11:B15) | C16: =SUM(C11:C15) | D16: =B16-C16 | E16: =IF(C16=0,"",(B16-C16)/C16)
A17: TOTAL GÉNÉRAL | B17: =B10+B16 | C17: =C10+C16 | D17: =B17-C17 | E17: =IF(C17=0,"",(B17-C17)/C17)

Sheet NOTE 14
A1: - 25 -
D2: NOTE 14 PROJETS DE DEVELOPPEMENT
A3: Dénomination sociale : PROJET EAU POTABLE RURALE
A4: Adresse : | D4: Sigle usuel : | E4: PEPR
A5: N° de compte contribuable (NCC) : PD-2023-017 | C5: Exercice clos le 31-12-2025 | D5: Durée (en mois) : 12
A6: N° de télédéclarant (NTD) :
A7: NOTE 14 : REVENUS ET AUTRES PRODUITS
A8: Libellés | B8: Année N | C8: Année N-1 | D8: Variation en valeur | E8: Variation en %
A9: Fonds d'administration consommés | B9: =SUMIF('BALANCE N'!$A$2:$A$50,"702*",'BALANCE N'!$G$2:$G$50)-SUMIF('BALANCE N'!$A$2:$A$50,"702*",'BALANCE N'!$F$2:$F$50) | C9: =SUMIF('BALANCE N-1'!$A$2:$A$50,"702*",'BALANCE N-1'!$G$2:$G$50)-SUMIF('BALANCE N-1'!$A$2:$A$50,"702*",'BALANCE N-1'!$F$2:$F$50) | D9: =B9-C9 | E9: =IF(C9=0,"",(B9-C9)/C9)
A10: Ventes de marchandises, produits fabriqués, travaux et services | B10: =SUMIF('BALANCE N'!$A$2:$A$50,"705*",'BALANCE N'!$G$2:$G$50)-SUMIF('BALANCE N'!$A$2:$A$50,"705*",'BALANCE N'!$F$2:$F$50) | C10: =SUMIF('BALANCE N-1'!$A$2:$A$50,"705*",'BALANCE N-1'!$G$2:$G$50)-SUMIF('BALANCE N-1'!$A$2:$A$50,"705*",'BALANCE N-1'!$F$2:$F$50) | D10: =B10-C10 | E10: =IF(C10=0,"",(B10-C10)/C10)
A11: Produits accessoires | B11: =SUMIF('BALANCE N'!$A$2:$A$50,"707*",'BALANCE N'!$G$2:$G$50)-SUMIF('BALANCE N'!$A$2:$A$50,"707*",'BALANCE N'!$F$2:$F$50) | C11: =SUMIF('BALANCE N-1'!$A$2:$A$50,"707*",'BALANCE N-1'!$G$2:$G$50)-SUMIF('BALANCE N-1'!$A$2:$A$50,"707*",'BALANCE N-1'!$F$2:$F$50) | D11: =B11-C11 | E11: =IF(C11=0,"",(B11-C11)/C11)
A12: Production immobilisée | B12: =SUMIF('BALANCE N'!$A$2:$A$50,"72*",'BALANCE N'!$G$2:$G$50)-SUMIF('BALANCE N'!$A$2:$A$50,"72*",'BALANCE N'!$F$2:$F$50) | C12: =SUMIF('BALANCE N-1'!$A$2:$A$50,"72*",'BALANCE N-1'!$G$2:$G$50)-SUMIF('BALANCE N-1'!$A$2:$A$50,"72*",'BALANCE N-1'!$F$2:$F$50) | D12: =B12-C12 | E12: =IF(C12=0,"",(B12-C12)/C12)
A13: Subventions d'exploitation | B13: =SUMIF('BALANCE N'!$A$2:$A$50,"71*",'BALANCE N'!$G$2:$G$50)-SUMIF('BALANCE N'!$A$2:$A$50,"71*",'BALANCE N'!$F$2:$F$50) | C13: =SUMIF('BALANCE N-1'!$A$2:$A$50,"71*",'BALANCE N-1'!$G$2:$G$50)-SUMIF('BALANCE N-1'!$A$2:$A$50,"71*",'BALANCE N-1'!$F$2:$F$50) | D13: =B13-C13 | E13: =IF(C13=0,"",(B13-C13)/C13)
A14: Autres produits et transferts de charges d'exploitation | B14: =SUMIF('BALANCE N'!$A$2:$A$50,"75*",'BALANCE N'!$G$2:$G$50)-SUMIF('BALANCE N'!$A$2:$A$50,"75*",'BALANCE N'!$F$2:$F$50)+SUMIF('BALANCE N'!$A$2:$A$50,"78*",'BALANCE N'!$G$2:$G$50)-SUMIF('BALANCE N'!$A$2:$A$50,"78*",'BALANCE N'!$F$2:$F$50)+SUMIF('BALANCE N'!$A$2:$A$50,"73*",'BALANCE N'!$G$2:$G$50)-SUMIF('BALANCE N'!$A$2:$A$50,"73*",'BALANCE N'!$F$2:$F$50)+SUMIF('BALANCE N'!$A$2:$A$50,"77*",'BALANCE N'!$G$2:$G$50)-SUMIF('BALANCE N'!$A$2:$A$50,"77*",'BALANCE N'!$F$2:$F$50)+SUMIF('BALANCE N'!$A$2:$A$50,"706*",'BALANCE N'!$G$2:$G$50)-SUMIF('BALANCE N'!$A$2:$A$50,"706*",'BALANCE N'!$F$2:$F$50)+SUMIF('BALANCE N'!$A$2:$A$50,"708*",'BALANCE N'!$G$2:$G$50)-SUMIF('BALANCE N'!$A$2:$A$50,"708*",'BALANCE N'!$F$2:$F$50) | C14: =SUMIF('BALANCE N-1'!$A$2:$A$50,"75*",'BALANCE N-1'!$G$2:$G$50)-SUMIF('BALANCE N-1'!$A$2:$A$50,"75*",'BALANCE N-1'!$F$2:$F$50)+SUMIF('BALANCE N-1'!$A$2:$A$50,"78*",'BALANCE N-1'!$G$2:$G$50)-SUMIF('BALANCE N-1'!$A$2:$A$50,"78*",'BALANCE N-1'!$F$2:$F$50)+SUMIF('BALANCE N-1'!$A$2:$A$50,"73*",'BALANCE N-1'!$G$2:$G$50)-SUMIF('BALANCE N-1'!$A$2:$A$50,"73*",'BALANCE N-1'!$F$2:$F$50)+SUMIF('BALANCE N-1'!$A$2:$A$50,"77*",'BALANCE N-1'!$G$2:$G$50)-SUMIF('BALANCE N-1'!$A$2:$A$50,"77*",'BALANCE N-1'!$F$2:$F$50)+SUMIF('BALANCE N-1'!$A$2:$A$50,"706*",'BALANCE N-1'!$G$2:$G$50)-SUMIF('BALANCE N-1'!$A$2:$A$50,"706*",'BALANCE N-1'!$F$2:$F$50)+SUMIF('BALANCE N-1'!$A$2:$A$50,"708*",'BALANCE N-1'!$G$2:$G$50)-SUMIF('BALANCE N-1'!$A$2:$A$50,"708*",'BALANCE N-1'!$F$2:$F$50) | D14: =B14-C14 | E14: =IF(C14=0,"",(B14-C14)/C14)
A15: TOTAL : REVENUS ET AUTRES PRODUITS | B15: =SUM(B9:B14) | C15: =SUM(C9:C14) | D15: =B15-C15 | E15: =IF(C15=0,"",(B15-C15)/C15)

Sheet NOTE 15
A1: - 26 -
D2: NOTE 15 PROJETS DE DEVELOPPEMENT
A3: Dénomination sociale : PROJET EAU POTABLE RURALE
A4: Adresse : | D4: Sigle usuel : | E4: PEPR
A5: N° de compte contribuable (NCC) : PD-2023-017 | C5: Exercice clos le 31-12-2025 | D5: Durée (en mois) : 12
A6: N° de télédéclarant (NTD) :
A7: NOTE 15 : ACHATS
A8: Libellés | B8: Année N | C8: Année N-1 | D8: Variation en valeur | E8: Variation en %
A9: Achats de biens et services liés à l'activité | B9: =SUMIF('BALANCE N'!$A$2:$A$50,"601*",'BALANCE N'!$F$2:$F$50)-SUMIF('BALANCE N'!$A$2:$A$50,"601*",'BALANCE N'!$G$2:$G$50) | C9: =SUMIF('BALANCE N-1'!$A$2:$A$50,"601*",'BALANCE N-1'!$F$2:$F$50)-SUMIF('BALANCE N-1'!$A$2:$A$50,"601*",'BALANCE N-1'!$G$2:$G$50) | D9: =B9-C9 | E9: =IF(C9=0,"",(B9-C9)/C9)
A10: Achats de marchandises et matières premières | B10: =SUMIF('BALANCE N'!$A$2:$A$50,"602*",'BALANCE N'!$F$2:$F$50)-SUMIF('BALANCE N'!$A$2:$A$50,"602*",'BALANCE N'!$G$2:$G$50) | C10: =SUMIF('BALANCE N-1'!$A$2:$A$50,"602*",'BALANCE N-1'!$F$2:$F$50)-SUMIF('BALANCE N-1'!$A$2:$A$50,"602*",'BALANCE N-1'!$G$2:$G$50) | D10: =B10-C10 | E10: =IF(C10=0,"",(B10-C10)/C10)
A11: Matières et fournitures consommables | B11: =SUMIF('BALANCE N'!$A$2:$A$50,"604*",'BALANCE N'!$F$2:$F$50)-SUMIF('BALANCE N'!$A$2:$A$50,"604*",'BALANCE N'!$G$2:$G$50) | C11: =SUMIF('BALANCE N-1'!$A$2:$A$50,"604*",'BALANCE N-1'!$F$2:$F$50)-SUMIF('BALANCE N-1'!$A$2:$A$50,"604*",'BALANCE N-1'!$G$2:$G$50) | D11: =B11-C11 | E11: =IF(C11=0,"",(B11-C11)/C11)
A12: Eau, électricité, énergies et fournitures non stockées | B12: =SUMIF('BALANCE N'!$A$2:$A$50,"605*",'BALANCE N'!$F$2:$F$50)-SUMIF('BALANCE N'!$A$2:$A$50,"605*",'BALANCE N'!$G$2:$G$50) | C12: =SUMIF('BALANCE N-1'!$A$2:$A$50,"605*",'BALANCE N-1'!$F$2:$F$50)-SUMIF('BALANCE N-1'!$A$2:$A$50,"605*",'BALANCE N-1'!$G$2:$G$50) | D12: =B12-C12 | E12: =IF(C12=0,"",(B12-C12)/C12)
A13: Achats autres activités | B13: =SUMIF('BALANCE N'!$A$2:$A$50,"606*",'BALANCE N'!$F$2:$F$50)-SUMIF('BALANCE N'!$A$2:$A$50,"606*",'BALANCE N'!$G$2:$G$50) | C13: =SUMIF('BALANCE N-1'!$A$2:$A$50,"606*",'BALANCE N-1'!$F$2:$F$50)-SUMIF('BALANCE N-1'!$A$2:$A$50,"606*",'BALANCE N-1'!$G$2:$G$50) | D13: =B13-C13 | E13: =IF(C13=0,"",(B13-C13)/C13)
A14: Achats d'emballages | B14: =SUMIF('BALANCE N'!$A$2:$A$50,"608*",'BALANCE N'!$F$2:$F$50)-SUMIF('BALANCE N'!$A$2:$A$50,"608*",'BALANCE N'!$G$2:$G$50) | C14: =SUMIF('BALANCE N-1'!$A$2:$A$50,"608*",'BALANCE N-1'!$F$2:$F$50)-SUMIF('BALANCE N-1'!$A$2:$A$50,"608*",'BALANCE N-1'!$G$2:$G$50) | D14: =B14-C14 | E14: =IF(C14=0,"",(B14-C14)/C14)
A15: TOTAL ACHATS | B15: =SUM(B9:B14) | C15: =SUM(C9:C14) | D15: =B15-C15 | E15: =IF(C15=0,"",(B15-C15)/C15)

Sheet NOTE 16
A1: - 27 -
D2: NOTE 16 PROJETS DE DEVELOPPEMENT
A3: Dénomination sociale : PROJET EAU POTABLE RURALE
A4: Adresse : | D4: Sigle usuel : | E4: PEPR
A5: N° de compte contribuable (NCC) : PD-2023-017 | C5: Exercice clos le 31-12-2025 | D5: Durée (en mois) : 12
A6: N° de télédéclarant (NTD) :
A7: NOTE 16 : TRANSPORTS
A8: Libellés | B8: Année N | C8: Année N-1 | D8: Variation en valeur | E8: Variation en %
A9: Transports sur ventes | B9: =SUMIF('BALANCE N'!$A$2:$A$50,"612*",'BALANCE N'!$F$2:$F$50)-SUMIF('BALANCE N'!$A$2:$A$50,"612*",'BALANCE N'!$G$2:$G$50) | C9: =SUMIF('BALANCE N-1'!$A$2:$A$50,"612*",'BALANCE N-1'!$F$2:$F$50)-SUMIF('BALANCE N-1'!$A$2:$A$50,"612*",'BALANCE N-1'!$G$2:$G$50) | D9: =B9-C9 | E9: =IF(C9=0,"",(B9-C9)/C9)
A10: Transports pour le compte de tiers | B10: =SUMIF('BALANCE N'!$A$2:$A$50,"613*",'BALANCE N'!$F$2:$F$50)-SUMIF('BALANCE N'!$A$2:$A$50,"613*",'BALANCE N'!$G$2:$G$50) | C10: =SUMIF('BALANCE N-1'!$A$2:$A$50,"613*",'BALANCE N-1'!$F$2:$F$50)-SUMIF('BALANCE N-1'!$A$2:$A$50,"613*",'BALANCE N-1'!$G$2:$G$50) | D10: =B10-C10 | E10: =IF(C10=0,"",(B10-C10)/C10)
A11: Transport du personnel | B11: =SUMIF('BALANCE N'!$A$2:$A$50,"614*",'BALANCE N'!$F$2:$F$50)-SUMIF('BALANCE N'!$A$2:$A$50,"614*",'BALANCE N'!$G$2:$G$50) | C11: =SUMIF('BALANCE N-1'!$A$2:$A$50,"614*",'BALANCE N-1'!$F$2:$F$50)-SUMIF('BALANCE N-1'!$A$2:$A$50,"614*",'BALANCE N-1'!$G$2:$G$50) | D11: =B11-C11 | E11: =IF(C11=0,"",(B11-C11)/C11)
A12: Transports de plis | B12: =SUMIF('BALANCE N'!$A$2:$A$50,"616*",'BALANCE N'!$F$2:$F$50)-SUMIF('BALANCE N'!$A$2:$A$50,"616*",'BALANCE N'!$G$2:$G$50) | C12: =SUMIF('BALANCE N-1'!$A$2:$A$50,"616*",'BALANCE N-1'!$F$2:$F$50)-SUMIF('BALANCE N-1'!$A$2:$A$50,"616*",'BALANCE N-1'!$G$2:$G$50) | D12: =B12-C12 | E12: =IF(C12=0,"",(B12-C12)/C12)
A13: Voyages, déplacements et autres frais de transport | B13: =SUMIF('BALANCE N'!$A$2:$A$50,"618*",'BALANCE N'!$F$2:$F$50)-SUMIF('BALANCE N'!$A$2:$A$50,"618*",'BALANCE N'!$G$2:$G$50)+SUMIF('BALANCE N'!$A$2:$A$50,"619*",'BALANCE N'!$F$2:$F$50)-SUMIF('BALANCE N'!$A$2:$A$50,"619*",'BALANCE N'!$G$2:$G$50) | C13: =SUMIF('BALANCE N-1'!$A$2:$A$50,"618*",'BALANCE N-1'!$F$2:$F$50)-SUMIF('BALANCE N-1'!$A$2:$A$50,"618*",'BALANCE N-1'!$G$2:$G$50)+SUMIF('BALANCE N-1'!$A$2:$A$50,"619*",'BALANCE N-1'!$F$2:$F$50)-SUMIF('BALANCE N-1'!$A$2:$A$50,"619*",'BALANCE N-1'!$G$2:$G$50) | D13: =B13-C13 | E13: =IF(C13=0,"",(B13-C13)/C13)
A14: TOTAL | B14: =SUM(B9:B13) | C14: =SUM(C9:C13) | D14: =B14-C14 | E14: =IF(C14=0,"",(B14-C14)/C14)

Sheet NOTE 17
A1: - 28 -
D2: NOTE 17 PROJETS DE DEVELOPPEMENT
A3: Dénomination sociale : PROJET EAU POTABLE RURALE
A4: Adresse : | D4: Sigle usuel : | E4: PEPR
A5: N° de compte contribuable (NCC) : PD-2023-017 | C5: Exercice clos le 31-12-2025 | D5: Durée (en mois) : 12
A6: N° de télédéclarant (NTD) :
A7: NOTE 17 : SERVICES EXTÉRIEURS
A8: Libellés | B8: Année N | C8: Année N-1 | D8: Variation en valeur | E8: Variation en %
A9: Sous-traitance générale | B9: =SUMIF('BALANCE N'!$A$2:$A$50,"621*",'BALANCE N'!$F$2:$F$50)-SUMIF('BALANCE N'!$A$2:$A$50,"621*",'BALANCE N'!$G$2:$G$50) | C9: =SUMIF('BALANCE N-1'!$A$2:$A$50,"621*",'BALANCE N-1'!$F$2:$F$50)-SUMIF('BALANCE N-1'!$A$2:$A$50,"621*",'BALANCE N-1'!$G$2:$G$50) | D9: =B9-C9 | E9: =IF(C9=0,"",(B9-C9)/C9)
A10: Locations et charges locatives | B10: =SUMIF('BALANCE N'!$A$2:$A$50,"622*",'BALANCE N'!$F$2:$F$50)-SUMIF('BALANCE N'!$A$2:$A$50,"622*",'BALANCE N'!$G$2:$G$50) | C10: =SUMIF('BALANCE N-1'!$A$2:$A$50,"622*",'BALANCE N-1'!$F$2:$F$50)-SUMIF('BALANCE N-1'!$A$2:$A$50,"622*",'BALANCE N-1'!$G$2:$G$50) | D10: =B10-C10 | E10: =IF(C10=0,"",(B10-C10)/C10)
A11: Redevances de location-acquisition | B11: =SUMIF('BALANCE N'!$A$2:$A$50,"623*",'BALANCE N'!$F$2:$F$50)-SUMIF('BALANCE N'!$A$2:$A$50,"623*",'BALANCE N'!$G$2:$G$50) | C11: =SUMIF('BALANCE N-1'!$A$2:$A$50,"623*",'BALANCE N-1'!$F$2:$F$50)-SUMIF('BALANCE N-1'!$A$2:$A$50,"623*",'BALANCE N-1'!$G$2:$G$50) | D11: =B11-C11 | E11: =IF(C11=0,"",(B11-C11)/C11)
A12: Entretien, réparations et maintenance | B12: =SUMIF('BALANCE N'!$A$2:$A$50,"624*",'BALANCE N'!$F$2:$F$50)-SUMIF('BALANCE N'!$A$2:$A$50,"624*",'BALANCE N'!$G$2:$G$50) | C12: =SUMIF('BALANCE N-1'!$A$2:$A$50,"624*",'BALANCE N-1'!$F$2:$F$50)-SUMIF('BALANCE N-1'!$A$2:$A$50,"624*",'BALANCE N-1'!$G$2:$G$50) | D12: =B12-C12 | E12: =IF(C12=0,"",(B12-C12)/C12)
A13: Primes d'assurance | B13: =SUMIF('BALANCE N'!$A$2:$A$50,"625*",'BALANCE N'!$F$2:$F$50)-SUMIF('BALANCE N'!$A$2:$A$50,"625*",'BALANCE N'!$G$2:$G$50) | C13: =SUMIF('BALANCE N-1'!$A$2:$A$50,"625*",'BALANCE N-1'!$F$2:$F$50)-SUMIF('BALANCE N-1'!$A$2:$A$50,"625*",'BALANCE N-1'!$G$2:$G$50) | D13: =B13-C13 | E13: =IF(C13=0,"",(B13-C13)/C13)
A14: Études, recherches et documentation | B14: =SUMIF('BALANCE N'!$A$2:$A$50,"626*",'BALANCE N'!$F$2:$F$50)-SUMIF('BALANCE N'!$A$2:$A$50,"626*",'BALANCE N'!$G$2:$G$50) | C14: =SUMIF('BALANCE N-1'!$A$2:$A$50,"626*",'BALANCE N-1'!$F$2:$F$50)-SUMIF('BALANCE N-1'!$A$2:$A$50,"626*",'BALANCE N-1'!$G$2:$G$50) | D14: =B14-C14 | E14: =IF(C14=0,"",(B14-C14)/C14)
A15: Publicité, publications, relations publiques | B15: =SUMIF('BALANCE N'!$A$2:$A$50,"627*",'BALANCE N'!$F$2:$F$50)-SUMIF('BALANCE N'!$A$2:$A$50,"627*",'BALANCE N'!$G$2:$G$50) | C15: =SUMIF('BALANCE N-1'!$A$2:$A$50,"627*",'BALANCE N-1'!$F$2:$F$50)-SUMIF('BALANCE N-1'!$A$2:$A$50,"627*",'BALANCE N-1'!$G$2:$G$50) | D15: =B15-C15 | E15: =IF(C15=0,"",(B15-C15)/C15)
A16: Frais de télécommunications | B16: =SUMIF('BALANCE N'!$A$2:$A$50,"628*",'BALANCE N'!$F$2:$F$50)-SUMIF('BALANCE N'!$A$2:$A$50,"628*",'BALANCE N'!$G$2:$G$50) | C16: =SUMIF('BALANCE N-1'!$A$2:$A$50,"628*",'BALANCE N-1'!$F$2:$F$50)-SUMIF('BALANCE N-1'!$A$2:$A$50,"628*",'BALANCE N-1'!$G$2:$G$50) | D16: =B16-C16 | E16: =IF(C16=0,"",(B16-C16)/C16)
A17: Frais bancaires | B17: =SUMIF('BALANCE N'!$A$2:$A$50,"631*",'BALANCE N'!$F$2:$F$50)-SUMIF('BALANCE N'!$A$2:$A$50,"631*",'BALANCE N'!$G$2:$G$50) | C17: =SUMIF('BALANCE N-1'!$A$2:$A$50,"631*",'BALANCE N-1'!$F$2:$F$50)-SUMIF('BALANCE N-1'!$A$2:$A$50,"631*",'BALANCE N-1'!$G$2:$G$50) | D17: =B17-C17 | E17: =IF(C17=0,"",(B17-C17)/C17)
A18: Rémunérations d'intermédiaires et de conseils | B18: =SUMIF('BALANCE N'!$A$2:$A$50,"632*",'BALANCE N'!$F$2:$F$50)-SUMIF('BALANCE N'!$A$2:$A$50,"632*",'BALANCE N'!$G$2:$G$50) | C18: =SUMIF('BALANCE N-1'!$A$2:$A$50,"632*",'BALANCE N-1'!$F$2:$F$50)-SUMIF('BALANCE N-1'!$A$2:$A$50,"632*",'BALANCE N-1'!$G$2:$G$50) | D18: =B18-C18 | E18: =IF(C18=0,"",(B18-C18)/C18)
A19: Frais de formation du personnel | B19: =SUMIF('BALANCE N'!$A$2:$A$50,"633*",'BALANCE N'!$F$2:$F$50)-SUMIF('BALANCE N'!$A$2:$A$50,"633*",'BALANCE N'!$G$2:$G$50) | C19: =SUMIF('BALANCE N-1'!$A$2:$A$50,"633*",'BALANCE N-1'!$F$2:$F$50)-SUMIF('BALANCE N-1'!$A$2:$A$50,"633*",'BALANCE N-1'!$G$2:$G$50) | D19: =B19-C19 | E19: =IF(C19=0,"",(B19-C19)/C19)
A20: Redevances pour brevets, licences, logiciels | B20: =SUMIF('BALANCE N'!$A$2:$A$50,"634*",'BALANCE N'!$F$2:$F$50)-SUMIF('BALANCE N'!$A$2:$A$50,"634*",'BALANCE N'!$G$2:$G$50) | C20: =SUMIF('BALANCE N-1'!$A$2:$A$50,"634*",'BALANCE N-1'!$F$2:$F$50)-SUMIF('BALANCE N-1'!$A$2:$A$50,"634*",'BALANCE N-1'!$G$2:$G$50) | D20: =B20-C20 | E20: =IF(C20=0,"",(B20-C20)/C20)
A21: Cotisations | B21: =SUMIF('BALANCE N'!$A$2:$A$50,"635*",'BALANCE N'!$F$2:$F$50)-SUMIF('BALANCE N'!$A$2:$A$50,"635*",'BALANCE N'!$G$2:$G$50) | C21: =SUMIF('BALANCE N-1'!$A$2:$A$50,"635*",'BALANCE N-1'!$F$2:$F$50)-SUMIF('BALANCE N-1'!$A$2:$A$50,"635*",'BALANCE N-1'!$G$2:$G$50) | D21: =B21-C21 | E21: =IF(C21=0,"",(B21-C21)/C21)
A22: Frais de recherche de fonds | B22: =SUMIF('BALANCE N'!$A$2:$A$50,"636*",'BALANCE N'!$F$2:$F$50)-SUMIF('BALANCE N'!$A$2:$A$50,"636*",'BALANCE N'!$G$2:$G$50) | C22: =SUMIF('BALANCE N-1'!$A$2:$A$50,"636*",'BALANCE N-1'!$F$2:$F$50)-SUMIF('BALANCE N-1'!$A$2:$A$50,"636*",'BALANCE N-1'!$G$2:$G$50) | D22: =B22-C22 | E22: =IF(C22=0,"",(B22-C22)/C22)
A23: Rémunérations de personnel extérieur à l'entité | B23: =SUMIF('BALANCE N'!$A$2:$A$50,"637*",'BALANCE N'!$F$2:$F$50)-SUMIF('BALANCE N'!$A$2:$A$50,"637*",'BALANCE N'!$G$2:$G$50) | C23: =SUMIF('BALANCE N-1'!$A$2:$A$50,"637*",'BALANCE N-1'!$F$2:$F$50)-SUMIF('BALANCE N-1'!$A$2:$A$50,"637*",'BALANCE N-1'!$G$2:$G$50) | D23: =B23-C23 | E23: =IF(C23=0,"",(B23-C23)/C23)
A24: Autres charges externes | B24: =SUMIF('BALANCE N'!$A$2:$A$50,"638*",'BALANCE N'!$F$2:$F$50)-SUMIF('BALANCE N'!$A$2:$A$50,"638*",'BALANCE N'!$G$2:$G$50) | C24: =SUMIF('BALANCE N-1'!$A$2:$A$50,"638*",'BALANCE N-1'!$F$2:$F$50)-SUMIF('BALANCE N-1'!$A$2:$A$50,"638*",'BALANCE N-1'!$G$2:$G$50) | D24: =B24-C24 | E24: =IF(C24=0,"",(B24-C24)/C24)
A25: TOTAL | B25: =SUM(B9:B24) | C25: =SUM(C9:C24) | D25: =B25-C25 | E25: =IF(C25=0,"",(B25-C25)/C25)

Sheet NOTE 18
A1: - 29 -
D2: NOTE 18 PROJETS DE DEVELOPPEMENT
A3: Dénomination sociale : PROJET EAU POTABLE RURALE
A4: Adresse : | D4: Sigle usuel : | E4: PEPR
A5: N° de compte contribuable (NCC) : PD-2023-017 | C5: Exercice clos le 31-12-2025 | D5: Durée (en mois) : 12
A6: N° de télédéclarant (NTD) :
A7: NOTE 18 : IMPÔTS ET TAXES
A8: Libellés | B8: Année N | C8: Année N-1 | D8: Variation en valeur | E8: Variation en %
A9: Impôts et taxes directs | B9: =SUMIF('BALANCE N'!$A$2:$A$50,"641*",'BALANCE N'!$F$2:$F$50)-SUMIF('BALANCE N'!$A$2:$A$50,"641*",'BALANCE N'!$G$2:$G$50) | C9: =SUMIF('BALANCE N-1'!$A$2:$A$50,"641*",'BALANCE N-1'!$F$2:$F$50)-SUMIF('BALANCE N-1'!$A$2:$A$50,"641*",'BALANCE N-1'!$G$2:$G$50) | D9: =B9-C9 | E9: =IF(C9=0,"",(B9-C9)/C9)
A10: Impôts et taxes indirects | B10: =SUMIF('BALANCE N'!$A$2:$A$50,"645*",'BALANCE N'!$F$2:$F$50)-SUMIF('BALANCE N'!$A$2:$A$50,"645*",'BALANCE N'!$G$2:$G$50) | C10: =SUMIF('BALANCE N-1'!$A$2:$A$50,"645*",'BALANCE N-1'!$F$2:$F$50)-SUMIF('BALANCE N-1'!$A$2:$A$50,"645*",'BALANCE N-1'!$G$2:$G$50) | D10: =B10-C10 | E10: =IF(C10=0,"",(B10-C10)/C10)
A11: Droits d'enregistrement | B11: =SUMIF('BALANCE N'!$A$2:$A$50,"646*",'BALANCE N'!$F$2:$F$50)-SUMIF('BALANCE N'!$A$2:$A$50,"646*",'BALANCE N'!$G$2:$G$50) | C11: =SUMIF('BALANCE N-1'!$A$2:$A$50,"646*",'BALANCE N-1'!$F$2:$F$50)-SUMIF('BALANCE N-1'!$A$2:$A$50,"646*",'BALANCE N-1'!$G$2:$G$50) | D11: =B11-C11 | E11: =IF(C11=0,"",(B11-C11)/C11)
A12: Pénalités et amendes fiscales | B12: =SUMIF('BALANCE N'!$A$2:$A$50,"647*",'BALANCE N'!$F$2:$F$50)-SUMIF('BALANCE N'!$A$2:$A$50,"647*",'BALANCE N'!$G$2:$G$50) | C12: =SUMIF('BALANCE N-1'!$A$2:$A$50,"647*",'BALANCE N-1'!$F$2:$F$50)-SUMIF('BALANCE N-1'!$A$2:$A$50,"647*",'BALANCE N-1'!$G$2:$G$50) | D12: =B12-C12 | E12: =IF(C12=0,"",(B12-C12)/C12)
A13: Autres impôts et taxes | B13: =SUMIF('BALANCE N'!$A$2:$A$50,"648*",'BALANCE N'!$F$2:$F$50)-SUMIF('BALANCE N'!$A$2:$A$50,"648*",'BALANCE N'!$G$2:$G$50) | C13: =SUMIF('BALANCE N-1'!$A$2:$A$50,"648*",'BALANCE N-1'!$F$2:$F$50)-SUMIF('BALANCE N-1'!$A$2:$A$50,"648*",'BALANCE N-1'!$G$2:$G$50) | D13: =B13-C13 | E13: =IF(C13=0,"",(B13-C13)/C13)
A14: Dégrèvements et annulations des impôts et taxes (-) | B14: =SUMIF('BALANCE N'!$A$2:$A$50,"649*",'BALANCE N'!$F$2:$F$50)-SUMIF('BALANCE N'!$A$2:$A$50,"649*",'BALANCE N'!$G$2:$G$50) | C14: =SUMIF('BALANCE N-1'!$A$2:$A$50,"649*",'BALANCE N-1'!$F$2:$F$50)-SUMIF('BALANCE N-1'!$A$2:$A$50,"649*",'BALANCE N-1'!$G$2:$G$50) | D14: =B14-C14 | E14: =IF(C14=0,"",(B14-C14)/C14)
A15: TOTAL | B15: =SUM(B9:B14) | C15: =SUM(C9:C14) | D15: =B15-C15 | E15: =IF(C15=0,"",(B15-C15)/C15)

Sheet NOTE 19
A1: - 30 -
D2: NOTE 19 PROJETS DE DEVELOPPEMENT
A3: Dénomination sociale : PROJET EAU POTABLE RURALE
A4: Adresse : | D4: Sigle usuel : | E4: PEPR
A5: N° de compte contribuable (NCC) : PD-2023-017 | C5: Exercice clos le 31-12-2025 | D5: Durée (en mois) : 12
A6: N° de télédéclarant (NTD) :
A7: NOTE 19 : AUTRES CHARGES
A8: Libellés | B8: Année N | C8: Année N-1 | D8: Variation en valeur | E8: Variation en %
A9: Pertes sur créances | B9: =SUMIF('BALANCE N'!$A$2:$A$50,"651*",'BALANCE N'!$F$2:$F$50)-SUMIF('BALANCE N'!$A$2:$A$50,"651*",'BALANCE N'!$G$2:$G$50) | C9: =SUMIF('BALANCE N-1'!$A$2:$A$50,"651*",'BALANCE N-1'!$F$2:$F$50)-SUMIF('BALANCE N-1'!$A$2:$A$50,"651*",'BALANCE N-1'!$G$2:$G$50) | D9: =B9-C9 | E9: =IF(C9=0,"",(B9-C9)/C9)
A10: Subventions accordées | B10: =SUMIF('BALANCE N'!$A$2:$A$50,"652*",'BALANCE N'!$F$2:$F$50)-SUMIF('BALANCE N'!$A$2:$A$50,"652*",'BALANCE N'!$G$2:$G$50) | C10: =SUMIF('BALANCE N-1'!$A$2:$A$50,"652*",'BALANCE N-1'!$F$2:$F$50)-SUMIF('BALANCE N-1'!$A$2:$A$50,"652*",'BALANCE N-1'!$G$2:$G$50) | D10: =B10-C10 | E10: =IF(C10=0,"",(B10-C10)/C10)
A11: Dons en nature courants à distribuer | B11: =SUMIF('BALANCE N'!$A$2:$A$50,"654*",'BALANCE N'!$F$2:$F$50)-SUMIF('BALANCE N'!$A$2:$A$50,"654*",'BALANCE N'!$G$2:$G$50) | C11: =SUMIF('BALANCE N-1'!$A$2:$A$50,"654*",'BALANCE N-1'!$F$2:$F$50)-SUMIF('BALANCE N-1'!$A$2:$A$50,"654*",'BALANCE N-1'!$G$2:$G$50) | D11: =B11-C11 | E11: =IF(C11=0,"",(B11-C11)/C11)
A12: Pénalités et amendes pénales | B12: =SUMIF('BALANCE N'!$A$2:$A$50,"657*",'BALANCE N'!$F$2:$F$50)-SUMIF('BALANCE N'!$A$2:$A$50,"657*",'BALANCE N'!$G$2:$G$50) | C12: =SUMIF('BALANCE N-1'!$A$2:$A$50,"657*",'BALANCE N-1'!$F$2:$F$50)-SUMIF('BALANCE N-1'!$A$2:$A$50,"657*",'BALANCE N-1'!$G$2:$G$50) | D12: =B12-C12 | E12: =IF(C12=0,"",(B12-C12)/C12)
A13: Autres charges diverses | B13: =SUMIF('BALANCE N'!$A$2:$A$50,"658*",'BALANCE N'!$F$2:$F$50)-SUMIF('BALANCE N'!$A$2:$A$50,"658*",'BALANCE N'!$G$2:$G$50) | C13: =SUMIF('BALANCE N-1'!$A$2:$A$50,"658*",'BALANCE N-1'!$F$2:$F$50)-SUMIF('BALANCE N-1'!$A$2:$A$50,"658*",'BALANCE N-1'!$G$2:$G$50) | D13: =B13-C13 | E13: =IF(C13=0,"",(B13-C13)/C13)
A14: Charges pour provisions pour risques à court terme d'exploitation | B14: =SUMIF('BALANCE N'!$A$2:$A$50,"659*",'BALANCE N'!$F$2:$F$50)-SUMIF('BALANCE N'!$A$2:$A$50,"659*",'BALANCE N'!$G$2:$G$50) | C14: =SUMIF('BALANCE N-1'!$A$2:$A$50,"659*",'BALANCE N-1'!$F$2:$F$50)-SUMIF('BALANCE N-1'!$A$2:$A$50,"659*",'BALANCE N-1'!$G$2:$G$50) | D14: =B14-C14 | E14: =IF(C14=0,"",(B14-C14)/C14)
A15: TOTAL | B15: =SUM(B9:B14) | C15: =SUM(C9:C14) | D15: =B15-C15 | E15: =IF(C15=0,"",(B15-C15)/C15)
A17: Commentaires :
A18: • Indiquer les organismes bénéficiaires des dons.

Sheet NOTE 20A
A1: - 31 -
D2: NOTE 20A PROJETS DE DEVELOPPEMENT
A3: Dénomination sociale : PROJET EAU POTABLE RURALE
A4: Adresse : | D4: Sigle usuel : | E4: PEPR
A5: N° de compte contribuable (NCC) : PD-2023-017 | C5: Exercice clos le 31-12-2025 | D5: Durée (en mois) : 12
A6: N° de télédéclarant (NTD) :
A7: NOTE 20A : CHARGES DE PERSONNEL
A8: Libellés | B8: Année N | C8: Année N-1 | D8: Variation en valeur | E8: Variation en %
A9: Rémunérations directes versées au personnel national | B9: =SUMIF('BALANCE N'!$A$2:$A$50,"661*",'BALANCE N'!$F$2:$F$50)-SUMIF('BALANCE N'!$A$2:$A$50,"661*",'BALANCE N'!$G$2:$G$50) | C9: =SUMIF('BALANCE N-1'!$A$2:$A$50,"661*",'BALANCE N-1'!$F$2:$F$50)-SUMIF('BALANCE N-1'!$A$2:$A$50,"661*",'BALANCE N-1'!$G$2:$G$50) | D9: =B9-C9 | E9: =IF(C9=0,"",(B9-C9)/C9)
A10: Rémunérations directes versées au personnel non national | B10: =SUMIF('BALANCE N'!$A$2:$A$50,"662*",'BALANCE N'!$F$2:$F$50)-SUMIF('BALANCE N'!$A$2:$A$50,"662*",'BALANCE N'!$G$2:$G$50) | C10: =SUMIF('BALANCE N-1'!$A$2:$A$50,"662*",'BALANCE N-1'!$F$2:$F$50)-SUMIF('BALANCE N-1'!$A$2:$A$50,"662*",'BALANCE N-1'!$G$2:$G$50) | D10: =B10-C10 | E10: =IF(C10=0,"",(B10-C10)/C10)
A11: Indemnités forfaitaires versées au personnel | B11: =SUMIF('BALANCE N'!$A$2:$A$50,"663*",'BALANCE N'!$F$2:$F$50)-SUMIF('BALANCE N'!$A$2:$A$50,"663*",'BALANCE N'!$G$2:$G$50) | C11: =SUMIF('BALANCE N-1'!$A$2:$A$50,"663*",'BALANCE N-1'!$F$2:$F$50)-SUMIF('BALANCE N-1'!$A$2:$A$50,"663*",'BALANCE N-1'!$G$2:$G$50) | D11: =B11-C11 | E11: =IF(C11=0,"",(B11-C11)/C11)
A12: Charges sociales | B12: =SUMIF('BALANCE N'!$A$2:$A$50,"664*",'BALANCE N'!$F$2:$F$50)-SUMIF('BALANCE N'!$A$2:$A$50,"664*",'BALANCE N'!$G$2:$G$50) | C12: =SUMIF('BALANCE N-1'!$A$2:$A$50,"664*",'BALANCE N-1'!$F$2:$F$50)-SUMIF('BALANCE N-1'!$A$2:$A$50,"664*",'BALANCE N-1'!$G$2:$G$50) | D12: =B12-C12 | E12: =IF(C12=0,"",(B12-C12)/C12)
A13: Habillement et équipement du personnel | B13: =SUMIF('BALANCE N'!$A$2:$A$50,"665*",'BALANCE N'!$F$2:$F$50)-SUMIF('BALANCE N'!$A$2:$A$50,"665*",'BALANCE N'!$G$2:$G$50) | C13: =SUMIF('BALANCE N-1'!$A$2:$A$50,"665*",'BALANCE N-1'!$F$2:$F$50)-SUMIF('BALANCE N-1'!$A$2:$A$50,"665*",'BALANCE N-1'!$G$2:$G$50) | D13: =B13-C13 | E13: =IF(C13=0,"",(B13-C13)/C13)
A14: Rémunération transférée de personnel extérieur | B14: =SUMIF('BALANCE N'!$A$2:$A$50,"667*",'BALANCE N'!$F$2:$F$50)-SUMIF('BALANCE N'!$A$2:$A$50,"667*",'BALANCE N'!$G$2:$G$50) | C14: =SUMIF('BALANCE N-1'!$A$2:$A$50,"667*",'BALANCE N-1'!$F$2:$F$50)-SUMIF('BALANCE N-1'!$A$2:$A$50,"667*",'BALANCE N-1'!$G$2:$G$50) | D14: =B14-C14 | E14: =IF(C14=0,"",(B14-C14)/C14)
A15: Autres charges sociales | B15: =SUMIF('BALANCE N'!$A$2:$A$50,"668*",'BALANCE N'!$F$2:$F$50)-SUMIF('BALANCE N'!$A$2:$A$50,"668*",'BALANCE N'!$G$2:$G$50) | C15: =SUMIF('BALANCE N-1'!$A$2:$A$50,"668*",'BALANCE N-1'!$F$2:$F$50)-SUMIF('BALANCE N-1'!$A$2:$A$50,"668*",'BALANCE N-1'!$G$2:$G$50) | D15: =B15-C15 | E15: =IF(C15=0,"",(B15-C15)/C15)
A16: Dégrèvements et annulations des charges sociales (-) | B16: =SUMIF('BALANCE N'!$A$2:$A$50,"669*",'BALANCE N'!$F$2:$F$50)-SUMIF('BALANCE N'!$A$2:$A$50,"669*",'BALANCE N'!$G$2:$G$50) | C16: =SUMIF('BALANCE N-1'!$A$2:$A$50,"669*",'BALANCE N-1'!$F$2:$F$50)-SUMIF('BALANCE N-1'!$A$2:$A$50,"669*",'BALANCE N-1'!$G$2:$G$50) | D16: =B16-C16 | E16: =IF(C16=0,"",(B16-C16)/C16)
A17: TOTAL | B17: =SUM(B9:B16) | C17: =SUM(C9:C16) | D17: =B17-C17 | E17: =IF(C17=0,"",(B17-C17)/C17)

Sheet NOTE 20B
A1: - 32 -
H2: NOTE 20B PROJETS DE DEVELOPPEMENT
A3: Dénomination sociale : PROJET EAU POTABLE RURALE
A4: Adresse : | H4: Sigle usuel : | I4: PEPR
A5: N° de compte contribuable (NCC) : PD-2023-017 | F5: Exercice clos le 31-12-2025 | H5: Durée (en mois) : 12
A6: N° de télédéclarant (NTD) :
A7: NOTE 20B : EFFECTIFS, MASSE SALARIALE ET PERSONNEL EXTÉRIEUR
A8: 1. PERSONNEL PROPRE
A9: QUALIFICATIONS | B9: Effectifs Nationaux (M/F) | C9: Effectifs Autres États Région (M/F) | D9: Effectifs Hors Région (M/F) | E9: Effectifs Total | F9: Masse salariale Nationaux | G9: Masse salariale Autres États | H9: Masse salariale Hors Région | I9: Masse salariale Total
A10: YA. 1. Cadres supérieurs
A11: YB. 2. Techniciens supérieurs et cadres moyens
A12: YC. 3. Techniciens, agents de maîtrise et ouvriers qualifiés
A13: YD. 4. Employés, manœuvres, ouvriers et apprentis
A14: YE. TOTAL (1) | B14: =SUM(B10:B13) | C14: =SUM(C10:C13) | D14: =SUM(D10:D13) | E14: =SUM(E10:E13) | F14: =SUM(F10:F13) | G14: =SUM(G10:G13) | H14: =SUM(H10:H13) | I14: =SUM(I10:I13)
A15: YF. Permanents
A16: YG. Saisonniers
A18: 2. PERSONNEL EXTÉRIEUR ET BÉNÉVOLE - facturation à l'entité
A20: YH. 1. Cadres supérieurs
A21: YI. 2. Techniciens supérieurs et cadres moyens
A22: YJ. 3. Techniciens, agents de maîtrise et ouvriers qualifiés
A23: YK. 4. Employés, manœuvres, ouvriers et apprentis
A24: YL. TOTAL (2) | B24: =SUM(B20:B23)
A25: YO. TOTAL (1 + 2) : à rapprocher de la note 29A et du compte 637

Sheet NOTE 21
A1: - 33 -
D2: NOTE 21 PROJETS DE DEVELOPPEMENT
A3: Dénomination sociale : PROJET EAU POTABLE RURALE
A4: Adresse : | D4: Sigle usuel : | E4: PEPR
A5: N° de compte contribuable (NCC) : PD-2023-017 | C5: Exercice clos le 31-12-2025 | D5: Durée (en mois) : 12
A6: N° de télédéclarant (NTD) :
A7: NOTE 21 : CHARGES ET REVENUS FINANCIERS
A8: Libellés | B8: Année N | C8: Année N-1 | D8: Variation en valeur | E8: Variation en %
A9: Intérêts des emprunts | B9: =SUMIF('BALANCE N'!$A$2:$A$50,"671*",'BALANCE N'!$F$2:$F$50)-SUMIF('BALANCE N'!$A$2:$A$50,"671*",'BALANCE N'!$G$2:$G$50) | C9: =SUMIF('BALANCE N-1'!$A$2:$A$50,"671*",'BALANCE N-1'!$F$2:$F$50)-SUMIF('BALANCE N-1'!$A$2:$A$50,"671*",'BALANCE N-1'!$G$2:$G$50) | D9: =B9-C9 | E9: =IF(C9=0,"",(B9-C9)/C9)
A10: Intérêts dans loyers de location-acquisition | B10: =SUMIF('BALANCE N'!$A$2:$A$50,"672*",'BALANCE N'!$F$2:$F$50)-SUMIF('BALANCE N'!$A$2:$A$50,"672*",'BALANCE N'!$G$2:$G$50) | C10: =SUMIF('BALANCE N-1'!$A$2:$A$50,"672*",'BALANCE N-1'!$F$2:$F$50)-SUMIF('BALANCE N-1'!$A$2:$A$50,"672*",'BALANCE N-1'!$G$2:$G$50) | D10: =B10-C10 | E10: =IF(C10=0,"",(B10-C10)/C10)
A11: Escomptes accordés | B11: =SUMIF('BALANCE N'!$A$2:$A$50,"673*",'BALANCE N'!$F$2:$F$50)-SUMIF('BALANCE N'!$A$2:$A$50,"673*",'BALANCE N'!$G$2:$G$50) | C11: =SUMIF('BALANCE N-1'!$A$2:$A$50,"673*",'BALANCE N-1'!$F$2:$F$50)-SUMIF('BALANCE N-1'!$A$2:$A$50,"673*",'BALANCE N-1'!$G$2:$G$50) | D11: =B11-C11 | E11: =IF(C11=0,"",(B11-C11)/C11)
A12: Autres intérêts | B12: =SUMIF('BALANCE N'!$A$2:$A$50,"674*",'BALANCE N'!$F$2:$F$50)-SUMIF('BALANCE N'!$A$2:$A$50,"674*",'BALANCE N'!$G$2:$G$50) | C12: =SUMIF('BALANCE N-1'!$A$2:$A$50,"674*",'BALANCE N-1'!$F$2:$F$50)-SUMIF('BALANCE N-1'!$A$2:$A$50,"674*",'BALANCE N-1'!$G$2:$G$50) | D12: =B12-C12 | E12: =IF(C12=0,"",(B12-C12)/C12)
A13: Pertes de change financières | B13: =SUMIF('BALANCE N'!$A$2:$A$50,"676*",'BALANCE N'!$F$2:$F$50)-SUMIF('BALANCE N'!$A$2:$A$50,"676*",'BALANCE N'!$G$2:$G$50) | C13: =SUMIF('BALANCE N-1'!$A$2:$A$50,"676*",'BALANCE N-1'!$F$2:$F$50)-SUMIF('BALANCE N-1'!$A$2:$A$50,"676*",'BALANCE N-1'!$G$2:$G$50) | D13: =B13-C13 | E13: =IF(C13=0,"",(B13-C13)/C13)
A14: Pertes sur cessions de titres de placement | B14: =SUMIF('BALANCE N'!$A$2:$A$50,"677*",'BALANCE N'!$F$2:$F$50)-SUMIF('BALANCE N'!$A$2:$A$50,"677*",'BALANCE N'!$G$2:$G$50) | C14: =SUMIF('BALANCE N-1'!$A$2:$A$50,"677*",'BALANCE N-1'!$F$2:$F$50)-SUMIF('BALANCE N-1'!$A$2:$A$50,"677*",'BALANCE N-1'!$G$2:$G$50) | D14: =B14-C14 | E14: =IF(C14=0,"",(B14-C14)/C14)
A15: Charges pour provisions à court terme à caractère financier | B15: =SUMIF('BALANCE N'!$A$2:$A$50,"678*",'BALANCE N'!$F$2:$F$50)-SUMIF('BALANCE N'!$A$2:$A$50,"678*",'BALANCE N'!$G$2:$G$50)+SUMIF('BALANCE N'!$A$2:$A$50,"679*",'BALANCE N'!$F$2:$F$50)-SUMIF('BALANCE N'!$A$2:$A$50,"679*",'BALANCE N'!$G$2:$G$50) | C15: =SUMIF('BALANCE N-1'!$A$2:$A$50,"678*",'BALANCE N-1'!$F$2:$F$50)-SUMIF('BALANCE N-1'!$A$2:$A$50,"678*",'BALANCE N-1'!$G$2:$G$50)+SUMIF('BALANCE N-1'!$A$2:$A$50,"679*",'BALANCE N-1'!$F$2:$F$50)-SUMIF('BALANCE N-1'!$A$2:$A$50,"679*",'BALANCE N-1'!$G$2:$G$50) | D15: =B15-C15 | E15: =IF(C15=0,"",(B15-C15)/C15)
A16: TOTAL : FRAIS FINANCIERS | B16: =SUM(B9:B15) | C16: =SUM(C9:C15) | D16: =B16-C16 | E16: =IF(C16=0,"",(B16-C16)/C16)
A17: Intérêts de prêts et créances diverses | B17: =SUMIF('BALANCE N'!$A$2:$A$50,"771*",'BALANCE N'!$G$2:$G$50)-SUMIF('BALANCE N'!$A$2:$A$50,"771*",'BALANCE N'!$F$2:$F$50) | C17: =SUMIF('BALANCE N-1'!$A$2:$A$50,"771*",'BALANCE N-1'!$G$2:$G$50)-SUMIF('BALANCE N-1'!$A$2:$A$50,"771*",'BALANCE N-1'!$F$2:$F$50) | D17: =B17-C17 | E17: =IF(C17=0,"",(B17-C17)/C17)
A18: Revenus de participations et autres titres immobilisés | B18: =SUMIF('BALANCE N'!$A$2:$A$50,"772*",'BALANCE N'!$G$2:$G$50)-SUMIF('BALANCE N'!$A$2:$A$50,"772*",'BALANCE N'!$F$2:$F$50) | C18: =SUMIF('BALANCE N-1'!$A$2:$A$50,"772*",'BALANCE N-1'!$G$2:$G$50)-SUMIF('BALANCE N-1'!$A$2:$A$50,"772*",'BALANCE N-1'!$F$2:$F$50) | D18: =B18-C18 | E18: =IF(C18=0,"",(B18-C18)/C18)
A19: Escomptes obtenus | B19: =SUMIF('BALANCE N'!$A$2:$A$50,"773*",'BALANCE N'!$G$2:$G$50)-SUMIF('BALANCE N'!$A$2:$A$50,"773*",'BALANCE N'!$F$2:$F$50) | C19: =SUMIF('BALANCE N-1'!$A$2:$A$50,"773*",'BALANCE N-1'!$G$2:$G$50)-SUMIF('BALANCE N-1'!$A$2:$A$50,"773*",'BALANCE N-1'!$F$2:$F$50) | D19: =B19-C19 | E19: =IF(C19=0,"",(B19-C19)/C19)
A20: Revenus de placement | B20: =SUMIF('BALANCE N'!$A$2:$A$50,"774*",'BALANCE N'!$G$2:$G$50)-SUMIF('BALANCE N'!$A$2:$A$50,"774*",'BALANCE N'!$F$2:$F$50) | C20: =SUMIF('BALANCE N-1'!$A$2:$A$50,"774*",'BALANCE N-1'!$G$2:$G$50)-SUMIF('BALANCE N-1'!$A$2:$A$50,"774*",'BALANCE N-1'!$F$2:$F$50) | D20: =B20-C20 | E20: =IF(C20=0,"",(B20-C20)/C20)
A21: Gains de change financiers | B21: =SUMIF('BALANCE N'!$A$2:$A$50,"776*",'BALANCE N'!$G$2:$G$50)-SUMIF('BALANCE N'!$A$2:$A$50,"776*",'BALANCE N'!$F$2:$F$50) | C21: =SUMIF('BALANCE N-1'!$A$2:$A$50,"776*",'BALANCE N-1'!$G$2:$G$50)-SUMIF('BALANCE N-1'!$A$2:$A$50,"776*",'BALANCE N-1'!$F$2:$F$50) | D21: =B21-C21 | E21: =IF(C21=0,"",(B21-C21)/C21)
A22: Gains sur cessions de titres de placement | B22: =SUMIF('BALANCE N'!$A$2:$A$50,"777*",'BALANCE N'!$G$2:$G$50)-SUMIF('BALANCE N'!$A$2:$A$50,"777*",'BALANCE N'!$F$2:$F$50)+SUMIF('BALANCE N'!$A$2:$A$50,"778*",'BALANCE N'!$G$2:$G$50)-SUMIF('BALANCE N'!$A$2:$A$50,"778*",'BALANCE N'!$F$2:$F$50) | C22: =SUMIF('BALANCE N-1'!$A$2:$A$50,"777*",'BALANCE N-1'!$G$2:$G$50)-SUMIF('BALANCE N-1'!$A$2:$A$50,"777*",'BALANCE N-1'!$F$2:$F$50)+SUMIF('BALANCE N-1'!$A$2:$A$50,"778*",'BALANCE N-1'!$G$2:$G$50)-SUMIF('BALANCE N-1'!$A$2:$A$50,"778*",'BALANCE N-1'!$F$2:$F$50) | D22: =B22-C22 | E22: =IF(C22=0,"",(B22-C22)/C22)
A23: Transferts de charges financières | B23: =SUMIF('BALANCE N'!$A$2:$A$50,"787*",'BALANCE N'!$G$2:$G$50)-SUMIF('BALANCE N'!$A$2:$A$50,"787*",'BALANCE N'!$F$2:$F$50) | C23: =SUMIF('BALANCE N-1'!$A$2:$A$50,"787*",'BALANCE N-1'!$G$2:$G$50)-SUMIF('BALANCE N-1'!$A$2:$A$50,"787*",'BALANCE N-1'!$F$2:$F$50) | D23: =B23-C23 | E23: =IF(C23=0,"",(B23-C23)/C23)
A24: Reprises de charges pour provisions à court terme à caractère financier | B24: =SUMIF('BALANCE N'!$A$2:$A$50,"779*",'BALANCE N'!$G$2:$G$50)-SUMIF('BALANCE N'!$A$2:$A$50,"779*",'BALANCE N'!$F$2:$F$50) | C24: =SUMIF('BALANCE N-1'!$A$2:$A$50,"779*",'BALANCE N-1'!$G$2:$G$50)-SUMIF('BALANCE N-1'!$A$2:$A$50,"779*",'BALANCE N-1'!$F$2:$F$50) | D24: =B24-C24 | E24: =IF(C24=0,"",(B24-C24)/C24)
A25: TOTAL : REVENUS FINANCIERS | B25: =SUM(B17:B24) | C25: =SUM(C17:C24) | D25: =B25-C25 | E25: =IF(C25=0,"",(B25-C25)/C25)
A26: TOTAL (revenus - frais) | B26: =B25-B16 | C26: =C25-C16 | D26: =B26-C26 | E26: =IF(C26=0,"",(B26-C26)/C26)

Sheet NOTE 22
A1: - 34 -
H2: NOTE 22 PROJETS DE DEVELOPPEMENT
A3: Dénomination sociale : PROJET EAU POTABLE RURALE
A4: Adresse : | H4: Sigle usuel : | I4: PEPR
A5: N° de compte contribuable (NCC) : PD-2023-017 | F5: Exercice clos le 31-12-2025 | H5: Durée (en mois) : 12
A6: N° de télédéclarant (NTD) :
A7: NOTE 22 : DOTATIONS ET CHARGES POUR PROVISIONS
A8: NATURE | B8: Provisions à l'ouverture (A) | C8: Dotations exploitation | D8: Dotations financières | E8: Dotations HAO | F8: Reprises exploitation | G8: Reprises financières | H8: Reprises HAO | I8: Provisions à la clôture (D = A + B - C)
A9: Provisions pour risques et charges | B9: =SUMIF('BALANCE N-1'!$A$2:$A$50,"19*",'BALANCE N-1'!$G$2:$G$50)-SUMIF('BALANCE N-1'!$A$2:$A$50,"19*",'BALANCE N-1'!$F$2:$F$50) | D9: =MAX(0,(SUMIF('BALANCE N'!$A$2:$A$50,"19*",'BALANCE N'!$G$2:$G$50)-SUMIF('BALANCE N'!$A$2:$A$50,"19*",'BALANCE N'!$F$2:$F$50))-(SUMIF('BALANCE N-1'!$A$2:$A$50,"19*",'BALANCE N-1'!$G$2:$G$50)-SUMIF('BALANCE N-1'!$A$2:$A$50,"19*",'BALANCE N-1'!$F$2:$F$50))) | G9: =MAX(0,(SUMIF('BALANCE N-1'!$A$2:$A$50,"19*",'BALANCE N-1'!$G$2:$G$50)-SUMIF('BALANCE N-1'!$A$2:$A$50,"19*",'BALANCE N-1'!$F$2:$F$50))-(SUMIF('BALANCE N'!$A$2:$A$50,"19*",'BALANCE N'!$G$2:$G$50)-SUMIF('BALANCE N'!$A$2:$A$50,"19*",'BALANCE N'!$F$2:$F$50))) | I9: =B9+C9+D9+E9-F9-G9-H9
A10: Dépréciations des immobilisations | B10: =SUMIF('BALANCE N-1'!$A$2:$A$50,"29*",'BALANCE N-1'!$G$2:$G$50)-SUMIF('BALANCE N-1'!$A$2:$A$50,"29*",'BALANCE N-1'!$F$2:$F$50) | C10: =MAX(0,(SUMIF('BALANCE N'!$A$2:$A$50,"29*",'BALANCE N'!$G$2:$G$50)-SUMIF('BALANCE N'!$A$2:$A$50,"29*",'BALANCE N'!$F$2:$F$50))-(SUMIF('BALANCE N-1'!$A$2:$A$50,"29*",'BALANCE N-1'!$G$2:$G$50)-SUMIF('BALANCE N-1'!$A$2:$A$50,"29*",'BALANCE N-1'!$F$2:$F$50))) | F10: =MAX(0,(SUMIF('BALANCE N-1'!$A$2:$A$50,"29*",'BALANCE N-1'!$G$2:$G$50)-SUMIF('BALANCE N-1'!$A$2:$A$50,"29*",'BALANCE N-1'!$F$2:$F$50))-(SUMIF('BALANCE N'!$A$2:$A$50,"29*",'BALANCE N'!$G$2:$G$50)-SUMIF('BALANCE N'!$A$2:$A$50,"29*",'BALANCE N'!$F$2:$F$50))) | I10: =B10+C10+D10+E10-F10-G10-H10
A11: TOTAL : DOTATIONS | B11: =SUM(B9:B10) | C11: =SUM(C9:C10) | D11: =SUM(D9:D10) | E11: =SUM(E9:E10) | F11: =SUM(F9:F10) | G11: =SUM(G9:G10) | H11: =SUM(H9:H10) | I11: =SUM(I9:I10)
A12: Dépréciations des stocks et en-cours | B12: =SUMIF('BALANCE N-1'!$A$2:$A$50,"39*",'BALANCE N-1'!$G$2:$G$50)-SUMIF('BALANCE N-1'!$A$2:$A$50,"39*",'BALANCE N-1'!$F$2:$F$50) | C12: =MAX(0,(SUMIF('BALANCE N'!$A$2:$A$50,"39*",'BALANCE N'!$G$2:$G$50)-SUMIF('BALANCE N'!$A$2:$A$50,"39*",'BALANCE N'!$F$2:$F$50))-(SUMIF('BALANCE N-1'!$A$2:$A$50,"39*",'BALANCE N-1'!$G$2:$G$50)-SUMIF('BALANCE N-1'!$A$2:$A$50,"39*",'BALANCE N-1'!$F$2:$F$50))) | F12: =MAX(0,(SUMIF('BALANCE N-1'!$A$2:$A$50,"39*",'BALANCE N-1'!$G$2:$G$50)-SUMIF('BALANCE N-1'!$A$2:$A$50,"39*",'BALANCE N-1'!$F$2:$F$50))-(SUMIF('BALANCE N'!$A$2:$A$50,"39*",'BALANCE N'!$G$2:$G$50)-SUMIF('BALANCE N'!$A$2:$A$50,"39*",'BALANCE N'!$F$2:$F$50))) | I12: =B12+C12+D12+E12-F12-G12-H12
A13: Dépréciations des comptes de tiers | B13: =SUMIF('BALANCE N-1'!$A$2:$A$50,"494*",'BALANCE N-1'!$G$2:$G$50)-SUMIF('BALANCE N-1'!$A$2:$A$50,"494*",'BALANCE N-1'!$F$2:$F$50)+SUMIF('BALANCE N-1'!$A$2:$A$50,"490*",'BALANCE N-1'!$G$2:$G$50)-SUMIF('BALANCE N-1'!$A$2:$A$50,"490*",'BALANCE N-1'!$F$2:$F$50)+SUMIF('BALANCE N-1'!$A$2:$A$50,"492*",'BALANCE N-1'!$G$2:$G$50)-SUMIF('BALANCE N-1'!$A$2:$A$50,"492*",'BALANCE N-1'!$F$2:$F$50)+SUMIF('BALANCE N-1'!$A$2:$A$50,"497*",'BALANCE N-1'!$G$2:$G$50)-SUMIF('BALANCE N-1'!$A$2:$A$50,"497*",'BALANCE N-1'!$F$2:$F$50)+SUMIF('BALANCE N-1'!$A$2:$A$50,"491*",'BALANCE N-1'!$G$2:$G$50)-SUMIF('BALANCE N-1'!$A$2:$A$50,"491*",'BALANCE N-1'!$F$2:$F$50)+SUMIF('BALANCE N-1'!$A$2:$A$50,"493*",'BALANCE N-1'!$G$2:$G$50)-SUMIF('BALANCE N-1'!$A$2:$A$50,"493*",'BALANCE N-1'!$F$2:$F$50) | C13: =MAX(0,(SUMIF('BALANCE N'!$A$2:$A$50,"494*",'BALANCE N'!$G$2:$G$50)-SUMIF('BALANCE N'!$A$2:$A$50,"494*",'BALANCE N'!$F$2:$F$50)+SUMIF('BALANCE N'!$A$2:$A$50,"490*",'BALANCE N'!$G$2:$G$50)-SUMIF('BALANCE N'!$A$2:$A$50,"490*",'BALANCE N'!$F$2:$F$50)+SUMIF('BALANCE N'!$A$2:$A$50,"492*",'BALANCE N'!$G$2:$G$50)-SUMIF('BALANCE N'!$A$2:$A$50,"492*",'BALANCE N'!$F$2:$F$50)+SUMIF('BALANCE N'!$A$2:$A$50,"497*",'BALANCE N'!$G$2:$G$50)-SUMIF('BALANCE N'!$A$2:$A$50,"497*",'BALANCE N'!$F$2:$F$50)+SUMIF('BALANCE N'!$A$2:$A$50,"491*",'BALANCE N'!$G$2:$G$50)-SUMIF('BALANCE N'!$A$2:$A$50,"491*",'BALANCE N'!$F$2:$F$50)+SUMIF('BALANCE N'!$A$2:$A$50,"493*",'BALANCE N'!$G$2:$G$50)-SUMIF('BALANCE N'!$A$2:$A$50,"493*",'BALANCE N'!$F$2:$F$50))-(SUMIF('BALANCE N-1'!$A$2:$A$50,"494*",'BALANCE N-1'!$G$2:$G$50)-SUMIF('BALANCE N-1'!$A$2:$A$50,"494*",'BALANCE N-1'!$F$2:$F$50)+SUMIF('BALANCE N-1'!$A$2:$A$50,"490*",'BALANCE N-1'!$G$2:$G$50)-SUMIF('BALANCE N-1'!$A$2:$A$50,"490*",'BALANCE N-1'!$F$2:$F$50)+SUMIF('BALANCE N-1'!$A$2:$A$50,"492*",'BALANCE N-1'!$G$2:$G$50)-SUMIF('BALANCE N-1'!$A$2:$A$50,"492*",'BALANCE N-1'!$F$2:$F$50)+SUMIF('BALANCE N-1'!$A$2:$A$50,"497*",'BALANCE N-1'!$G$2:$G$50)-SUMIF('BALANCE N-1'!$A$2:$A$50,"497*",'BALANCE N-1'!$F$2:$F$50)+SUMIF('BALANCE N-1'!$A$2:$A$50,"491*",'BALANCE N-1'!$G$2:$G$50)-SUMIF('BALANCE N-1'!$A$2:$A$50,"491*",'BALANCE N-1'!$F$2:$F$50)+SUMIF('BALANCE N-1'!$A$2:$A$50,"493*",'BALANCE N-1'!$G$2:$G$50)-SUMIF('BALANCE N-1'!$A$2:$A$50,"493*",'BALANCE N-1'!$F$2:$F$50))) | F13: =MAX(0,(SUMIF('BALANCE N-1'!$A$2:$A$50,"494*",'BALANCE N-1'!$G$2:$G$50)-SUMIF('BALANCE N-1'!$A$2:$A$50,"494*",'BALANCE N-1'!$F$2:$F$50)+SUMIF('BALANCE N-1'!$A$2:$A$50,"490*",'BALANCE N-1'!$G$2:$G$50)-SUMIF('BALANCE N-1'!$A$2:$A$50,"490*",'BALANCE N-1'!$F$2:$F$50)+SUMIF('BALANCE N-1'!$A$2:$A$50,"492*",'BALANCE N-1'!$G$2:$G$50)-SUMIF('BALANCE N-1'!$A$2:$A$50,"492*",'BALANCE N-1'!$F$2:$F$50)+SUMIF('BALANCE N-1'!$A$2:$A$50,"497*",'BALANCE N-1'!$G$2:$G$50)-SUMIF('BALANCE N-1'!$A$2:$A$50,"497*",'BALANCE N-1'!$F$2:$F$50)+SUMIF('BALANCE N-1'!$A$2:$A$50,"491*",'BALANCE N-1'!$G$2:$G$50)-SUMIF('BALANCE N-1'!$A$2:$A$50,"491*",'BALANCE N-1'!$F$2:$F$50)+SUMIF('BALANCE N-1'!$A$2:$A$50,"493*",'BALANCE N-1'!$G$2:$G$50)-SUMIF('BALANCE N-1'!$A$2:$A$50,"493*",'BALANCE N-1'!$F$2:$F$50))-(SUMIF('BALANCE N'!$A$2:$A$50,"494*",'BALANCE N'!$G$2:$G$50)-SUMIF('BALANCE N'!$A$2:$A$50,"494*",'BALANCE N'!$F$2:$F$50)+SUMIF('BALANCE N'!$A$2:$A$50,"490*",'BALANCE N'!$G$2:$G$50)-SUMIF('BALANCE N'!$A$2:$A$50,"490*",'BALANCE N'!$F$2:$F$50)+SUMIF('BALANCE N'!$A$2:$A$50,"492*",'BALANCE N'!$G$2:$G$50)-SUMIF('BALANCE N'!$A$2:$A$50,"492*",'BALANCE N'!$F$2:$F$50)+SUMIF('BALANCE N'!$A$2:$A$50,"497*",'BALANCE N'!$G$2:$G$50)-SUMIF('BALANCE N'!$A$2:$A$50,"497*",'BALANCE N'!$F$2:$F$50)+SUMIF('BALANCE N'!$A$2:$A$50,"491*",'BALANCE N'!$G$2:$G$50)-SUMIF('BALANCE N'!$A$2:$A$50,"491*",'BALANCE N'!$F$2:$F$50)+SUMIF('BALANCE N'!$A$2:$A$50,"493*",'BALANCE N'!$G$2:$G$50)-SUMIF('BALANCE N'!$A$2:$A$50,"493*",'BALANCE N'!$F$2:$F$50))) | I13: =B13+C13+D13+E13-F13-G13-H13
A14: Dépréciations des comptes de créances HAO | B14: =SUMIF('BALANCE N-1'!$A$2:$A$50,"498*",'BALANCE N-1'!$G$2:$G$50)-SUMIF('BALANCE N-1'!$A$2:$A$50,"498*",'BALANCE N-1'!$F$2:$F$50) | E14: =MAX(0,(SUMIF('BALANCE N'!$A$2:$A$50,"498*",'BALANCE N'!$G$2:$G$50)-SUMIF('BALANCE N'!$A$2:$A$50,"498*",'BALANCE N'!$F$2:$F$50))-(SUMIF('BALANCE N-1'!$A$2:$A$50,"498*",'BALANCE N-1'!$G$2:$G$50)-SUMIF('BALANCE N-1'!$A$2:$A$50,"498*",'BALANCE N-1'!$F$2:$F$50))) | H14: =MAX(0,(SUMIF('BALANCE N-1'!$A$2:$A$50,"498*",'BALANCE N-1'!$G$2:$G$50)-SUMIF('BALANCE N-1'!$A$2:$A$50,"498*",'BALANCE N-1'!$F$2:$F$50))-(SUMIF('BALANCE N'!$A$2:$A$50,"498*",'BALANCE N'!$G$2:$G$50)-SUMIF('BALANCE N'!$A$2:$A$50,"498*",'BALANCE N'!$F$2:$F$50))) | I14: =B14+C14+D14+E14-F14-G14-H14
A15: Dépréciations de trésorerie | B15: =SUMIF('BALANCE N-1'!$A$2:$A$50,"591*",'BALANCE N-1'!$G$2:$G$50)-SUMIF('BALANCE N-1'!$A$2:$A$50,"591*",'BALANCE N-1'!$F$2:$F$50)+SUMIF('BALANCE N-1'!$A$2:$A$50,"592*",'BALANCE N-1'!$G$2:$G$50)-SUMIF('BALANCE N-1'!$A$2:$A$50,"592*",'BALANCE N-1'!$F$2:$F$50)+SUMIF('BALANCE N-1'!$A$2:$A$50,"595*",'BALANCE N-1'!$G$2:$G$50)-SUMIF('BALANCE N-1'!$A$2:$A$50,"595*",'BALANCE N-1'!$F$2:$F$50)+SUMIF('BALANCE N-1'!$A$2:$A$50,"593*",'BALANCE N-1'!$G$2:$G$50)-SUMIF('BALANCE N-1'!$A$2:$A$50,"593*",'BALANCE N-1'!$F$2:$F$50) | D15: =MAX(0,(SUMIF('BALANCE N'!$A$2:$A$50,"591*",'BALANCE N'!$G$2:$G$50)-SUMIF('BALANCE N'!$A$2:$A$50,"591*",'BALANCE N'!$F$2:$F$50)+SUMIF('BALANCE N'!$A$2:$A$50,"592*",'BALANCE N'!$G$2:$G$50)-SUMIF('BALANCE N'!$A$2:$A$50,"592*",'BALANCE N'!$F$2:$F$50)+SUMIF('BALANCE N'!$A$2:$A$50,"595*",'BALANCE N'!$G$2:$G$50)-SUMIF('BALANCE N'!$A$2:$A$50,"595*",'BALANCE N'!$F$2:$F$50)+SUMIF('BALANCE N'!$A$2:$A$50,"593*",'BALANCE N'!$G$2:$G$50)-SUMIF('BALANCE N'!$A$2:$A$50,"593*",'BALANCE N'!$F$2:$F$50))-(SUMIF('BALANCE N-1'!$A$2:$A$50,"591*",'BALANCE N-1'!$G$2:$G$50)-SUMIF('BALANCE N-1'!$A$2:$A$50,"591*",'BALANCE N-1'!$F$2:$F$50)+SUMIF('BALANCE N-1'!$A$2:$A$50,"592*",'BALANCE N-1'!$G$2:$G$50)-SUMIF('BALANCE N-1'!$A$2:$A$50,"592*",'BALANCE N-1'!$F$2:$F$50)+SUMIF('BALANCE N-1'!$A$2:$A$50,"595*",'BALANCE N-1'!$G$2:$G$50)-SUMIF('BALANCE N-1'!$A$2:$A$50,"595*",'BALANCE N-1'!$F$2:$F$50)+SUMIF('BALANCE N-1'!$A$2:$A$50,"593*",'BALANCE N-1'!$G$2:$G$50)-SUMIF('BALANCE N-1'!$A$2:$A$50,"593*",'BALANCE N-1'!$F$2:$F$50))) | G15: =MAX(0,(SUMIF('BALANCE N-1'!$A$2:$A$50,"591*",'BALANCE N-1'!$G$2:$G$50)-SUMIF('BALANCE N-1'!$A$2:$A$50,"591*",'BALANCE N-1'!$F$2:$F$50)+SUMIF('BALANCE N-1'!$A$2:$A$50,"592*",'BALANCE N-1'!$G$2:$G$50)-SUMIF('BALANCE N-1'!$A$2:$A$50,"592*",'BALANCE N-1'!$F$2:$F$50)+SUMIF('BALANCE N-1'!$A$2:$A$50,"595*",'BALANCE N-1'!$G$2:$G$50)-SUMIF('BALANCE N-1'!$A$2:$A$50,"595*",'BALANCE N-1'!$F$2:$F$50)+SUMIF('BALANCE N-1'!$A$2:$A$50,"593*",'BALANCE N-1'!$G$2:$G$50)-SUMIF('BALANCE N-1'!$A$2:$A$50,"593*",'BALANCE N-1'!$F$2:$F$50))-(SUMIF('BALANCE N'!$A$2:$A$50,"591*",'BALANCE N'!$G$2:$G$50)-SUMIF('BALANCE N'!$A$2:$A$50,"591*",'BALANCE N'!$F$2:$F$50)+SUMIF('BALANCE N'!$A$2:$A$50,"592*",'BALANCE N'!$G$2:$G$50)-SUMIF('BALANCE N'!$A$2:$A$50,"592*",'BALANCE N'!$F$2:$F$50)+SUMIF('BALANCE N'!$A$2:$A$50,"595*",'BALANCE N'!$G$2:$G$50)-SUMIF('BALANCE N'!$A$2:$A$50,"595*",'BALANCE N'!$F$2:$F$50)+SUMIF('BALANCE N'!$A$2:$A$50,"593*",'BALANCE N'!$G$2:$G$50)-SUMIF('BALANCE N'!$A$2:$A$50,"593*",'BALANCE N'!$F$2:$F$50))) | I15: =B15+C15+D15+E15-F15-G15-H15
A16: Provisions pour risques à court terme | B16: =SUMIF('BALANCE N-1'!$A$2:$A$50,"499*",'BALANCE N-1'!$G$2:$G$50)-SUMIF('BALANCE N-1'!$A$2:$A$50,"499*",'BALANCE N-1'!$F$2:$F$50)+SUMIF('BALANCE N-1'!$A$2:$A$50,"599*",'BALANCE N-1'!$G$2:$G$50)-SUMIF('BALANCE N-1'!$A$2:$A$50,"599*",'BALANCE N-1'!$F$2:$F$50)-SUMIF('BALANCE N-1'!$A$2:$A$50,"4998*",'BALANCE N-1'!$G$2:$G$50)+SUMIF('BALANCE N-1'!$A$2:$A$50,"4998*",'BALANCE N-1'!$F$2:$F$50) | C16: =MAX(0,(SUMIF('BALANCE N'!$A$2:$A$50,"499*",'BALANCE N'!$G$2:$G$50)-SUMIF('BALANCE N'!$A$2:$A$50,"499*",'BALANCE N'!$F$2:$F$50)+SUMIF('BALANCE N'!$A$2:$A$50,"599*",'BALANCE N'!$G$2:$G$50)-SUMIF('BALANCE N'!$A$2:$A$50,"599*",'BALANCE N'!$F$2:$F$50)-SUMIF('BALANCE N'!$A$2:$A$50,"4998*",'BALANCE N'!$G$2:$G$50)+SUMIF('BALANCE N'!$A$2:$A$50,"4998*",'BALANCE N'!$F$2:$F$50))-(SUMIF('BALANCE N-1'!$A$2:$A$50,"499*",'BALANCE N-1'!$G$2:$G$50)-SUMIF('BALANCE N-1'!$A$2:$A$50,"499*",'BALANCE N-1'!$F$2:$F$50)+SUMIF('BALANCE N-1'!$A$2:$A$50,"599*",'BALANCE N-1'!$G$2:$G$50)-SUMIF('BALANCE N-1'!$A$2:$A$50,"599*",'BALANCE N-1'!$F$2:$F$50)-SUMIF('BALANCE N-1'!$A$2:$A$50,"4998*",'BALANCE N-1'!$G$2:$G$50)+SUMIF('BALANCE N-1'!$A$2:$A$50,"4998*",'BALANCE N-1'!$F$2:$F$50))) | F16: =MAX(0,(SUMIF('BALANCE N-1'!$A$2:$A$50,"499*",'BALANCE N-1'!$G$2:$G$50)-SUMIF('BALANCE N-1'!$A$2:$A$50,"499*",'BALANCE N-1'!$F$2:$F$50)+SUMIF('BALANCE N-1'!$A$2:$A$50,"599*",'BALANCE N-1'!$G$2:$G$50)-SUMIF('BALANCE N-1'!$A$2:$A$50,"599*",'BALANCE N-1'!$F$2:$F$50)-SUMIF('BALANCE N-1'!$A$2:$A$50,"4998*",'BALANCE N-1'!$G$2:$G$50)+SUMIF('BALANCE N-1'!$A$2:$A$50,"4998*",'BALANCE N-1'!$F$2:$F$50))-(SUMIF('BALANCE N'!$A$2:$A$50,"499*",'BALANCE N'!$G$2:$G$50)-SUMIF('BALANCE N'!$A$2:$A$50,"499*",'BALANCE N'!$F$2:$F$50)+SUMIF('BALANCE N'!$A$2:$A$50,"599*",'BALANCE N'!$G$2:$G$50)-SUMIF('BALANCE N'!$A$2:$A$50,"599*",'BALANCE N'!$F$2:$F$50)-SUMIF('BALANCE N'!$A$2:$A$50,"4998*",'BALANCE N'!$G$2:$G$50)+SUMIF('BALANCE N'!$A$2:$A$50,"4998*",'BALANCE N'!$F$2:$F$50))) | I16: =B16+C16+D16+E16-F16-G16-H16
A17: TOTAL : CHARGES POUR DÉPRÉCIATIONS ET PROVISIONS | B17: =SUM(B12:B16) | C17: =SUM(C12:C16) | D17: =SUM(D12:D16) | E17: =SUM(E12:E16) | F17: =SUM(F12:F16) | G17: =SUM(G12:G16) | H17: =SUM(H12:H16) | I17: =SUM(I12:I16)
A18: TOTAL | B18: =B11+B17 | C18: =C11+C17 | D18: =D11+D17 | E18: =E11+E17 | F18: =F11+F17 | G18: =G11+G17 | H18: =H11+H17 | I18: =I11+I17
A20: À défaut d'échéancier, dotations et reprises sont posées en variation nette N/N-1 par nature - indiquer les évènements et circonstances de chaque constitution et reprise.

Sheet NOTE 23
A1: - 35 -
D2: NOTE 23 PROJETS DE DEVELOPPEMENT
A3: Dénomination sociale : PROJET EAU POTABLE RURALE
A4: Adresse : | D4: Sigle usuel : | E4: PEPR
A5: N° de compte contribuable (NCC) : PD-2023-017 | C5: Exercice clos le 31-12-2025 | D5: Durée (en mois) : 12
A6: N° de télédéclarant (NTD) :
A7: NOTE 23 : AUTRES CHARGES ET PRODUITS HAO
A8: Libellés | B8: Année N | C8: Année N-1 | D8: Variation en valeur | E8: Variation en %
A9: Charges H.A.O. constatées (compte 831) | B9: =SUMIF('BALANCE N'!$A$2:$A$50,"831*",'BALANCE N'!$F$2:$F$50)-SUMIF('BALANCE N'!$A$2:$A$50,"831*",'BALANCE N'!$G$2:$G$50) | C9: =SUMIF('BALANCE N-1'!$A$2:$A$50,"831*",'BALANCE N-1'!$F$2:$F$50)-SUMIF('BALANCE N-1'!$A$2:$A$50,"831*",'BALANCE N-1'!$G$2:$G$50) | D9: =B9-C9 | E9: =IF(C9=0,"",(B9-C9)/C9)
A10: Dons en nature H.A.O. (compte 832) | B10: =SUMIF('BALANCE N'!$A$2:$A$50,"832*",'BALANCE N'!$F$2:$F$50)-SUMIF('BALANCE N'!$A$2:$A$50,"832*",'BALANCE N'!$G$2:$G$50) | C10: =SUMIF('BALANCE N-1'!$A$2:$A$50,"832*",'BALANCE N-1'!$F$2:$F$50)-SUMIF('BALANCE N-1'!$A$2:$A$50,"832*",'BALANCE N-1'!$G$2:$G$50) | D10: =B10-C10 | E10: =IF(C10=0,"",(B10-C10)/C10)
A11: Pertes sur créances HAO | B11: =SUMIF('BALANCE N'!$A$2:$A$50,"834*",'BALANCE N'!$F$2:$F$50)-SUMIF('BALANCE N'!$A$2:$A$50,"834*",'BALANCE N'!$G$2:$G$50) | C11: =SUMIF('BALANCE N-1'!$A$2:$A$50,"834*",'BALANCE N-1'!$F$2:$F$50)-SUMIF('BALANCE N-1'!$A$2:$A$50,"834*",'BALANCE N-1'!$G$2:$G$50) | D11: =B11-C11 | E11: =IF(C11=0,"",(B11-C11)/C11)
A12: Abandons de créances consentis | B12: =SUMIF('BALANCE N'!$A$2:$A$50,"836*",'BALANCE N'!$F$2:$F$50)-SUMIF('BALANCE N'!$A$2:$A$50,"836*",'BALANCE N'!$G$2:$G$50) | C12: =SUMIF('BALANCE N-1'!$A$2:$A$50,"836*",'BALANCE N-1'!$F$2:$F$50)-SUMIF('BALANCE N-1'!$A$2:$A$50,"836*",'BALANCE N-1'!$G$2:$G$50) | D12: =B12-C12 | E12: =IF(C12=0,"",(B12-C12)/C12)
A13: Charges pour provisions pour risques à court terme HAO | B13: =SUMIF('BALANCE N'!$A$2:$A$50,"838*",'BALANCE N'!$F$2:$F$50)-SUMIF('BALANCE N'!$A$2:$A$50,"838*",'BALANCE N'!$G$2:$G$50)+SUMIF('BALANCE N'!$A$2:$A$50,"839*",'BALANCE N'!$F$2:$F$50)-SUMIF('BALANCE N'!$A$2:$A$50,"839*",'BALANCE N'!$G$2:$G$50) | C13: =SUMIF('BALANCE N-1'!$A$2:$A$50,"838*",'BALANCE N-1'!$F$2:$F$50)-SUMIF('BALANCE N-1'!$A$2:$A$50,"838*",'BALANCE N-1'!$G$2:$G$50)+SUMIF('BALANCE N-1'!$A$2:$A$50,"839*",'BALANCE N-1'!$F$2:$F$50)-SUMIF('BALANCE N-1'!$A$2:$A$50,"839*",'BALANCE N-1'!$G$2:$G$50) | D13: =B13-C13 | E13: =IF(C13=0,"",(B13-C13)/C13)
A14: Dotations hors activités ordinaires | B14: =SUMIF('BALANCE N'!$A$2:$A$50,"85*",'BALANCE N'!$F$2:$F$50)-SUMIF('BALANCE N'!$A$2:$A$50,"85*",'BALANCE N'!$G$2:$G$50) | C14: =SUMIF('BALANCE N-1'!$A$2:$A$50,"85*",'BALANCE N-1'!$F$2:$F$50)-SUMIF('BALANCE N-1'!$A$2:$A$50,"85*",'BALANCE N-1'!$G$2:$G$50) | D14: =B14-C14 | E14: =IF(C14=0,"",(B14-C14)/C14)
A15: Valeurs comptables des cessions d'immobilisations | B15: =SUMIF('BALANCE N'!$A$2:$A$50,"81*",'BALANCE N'!$F$2:$F$50)-SUMIF('BALANCE N'!$A$2:$A$50,"81*",'BALANCE N'!$G$2:$G$50) | C15: =SUMIF('BALANCE N-1'!$A$2:$A$50,"81*",'BALANCE N-1'!$F$2:$F$50)-SUMIF('BALANCE N-1'!$A$2:$A$50,"81*",'BALANCE N-1'!$G$2:$G$50) | D15: =B15-C15 | E15: =IF(C15=0,"",(B15-C15)/C15)
A16: Variations de stocks de dons en nature HAO (+/-) | B16: =SUMIF('BALANCE N'!$A$2:$A$50,"87*",'BALANCE N'!$F$2:$F$50)-SUMIF('BALANCE N'!$A$2:$A$50,"87*",'BALANCE N'!$G$2:$G$50) | C16: =SUMIF('BALANCE N-1'!$A$2:$A$50,"87*",'BALANCE N-1'!$F$2:$F$50)-SUMIF('BALANCE N-1'!$A$2:$A$50,"87*",'BALANCE N-1'!$G$2:$G$50) | D16: =B16-C16 | E16: =IF(C16=0,"",(B16-C16)/C16)
A17: TOTAL : AUTRES CHARGES HAO | B17: =SUM(B9:B16) | C17: =SUM(C9:C16) | D17: =B17-C17 | E17: =IF(C17=0,"",(B17-C17)/C17)
A18: Produits H.A.O. constatés (compte 841) | B18: =SUMIF('BALANCE N'!$A$2:$A$50,"841*",'BALANCE N'!$G$2:$G$50)-SUMIF('BALANCE N'!$A$2:$A$50,"841*",'BALANCE N'!$F$2:$F$50) | C18: =SUMIF('BALANCE N-1'!$A$2:$A$50,"841*",'BALANCE N-1'!$G$2:$G$50)-SUMIF('BALANCE N-1'!$A$2:$A$50,"841*",'BALANCE N-1'!$F$2:$F$50) | D18: =B18-C18 | E18: =IF(C18=0,"",(B18-C18)/C18)
A19: Contributions volontaires en nature (compte 842) | B19: =SUMIF('BALANCE N'!$A$2:$A$50,"842*",'BALANCE N'!$G$2:$G$50)-SUMIF('BALANCE N'!$A$2:$A$50,"842*",'BALANCE N'!$F$2:$F$50) | C19: =SUMIF('BALANCE N-1'!$A$2:$A$50,"842*",'BALANCE N-1'!$G$2:$G$50)-SUMIF('BALANCE N-1'!$A$2:$A$50,"842*",'BALANCE N-1'!$F$2:$F$50) | D19: =B19-C19 | E19: =IF(C19=0,"",(B19-C19)/C19)
A20: Contributions volontaires en numéraire | B20: =SUMIF('BALANCE N'!$A$2:$A$50,"843*",'BALANCE N'!$G$2:$G$50)-SUMIF('BALANCE N'!$A$2:$A$50,"843*",'BALANCE N'!$F$2:$F$50) | C20: =SUMIF('BALANCE N-1'!$A$2:$A$50,"843*",'BALANCE N-1'!$G$2:$G$50)-SUMIF('BALANCE N-1'!$A$2:$A$50,"843*",'BALANCE N-1'!$F$2:$F$50) | D20: =B20-C20 | E20: =IF(C20=0,"",(B20-C20)/C20)
A21: Abandons de créances obtenus | B21: =SUMIF('BALANCE N'!$A$2:$A$50,"846*",'BALANCE N'!$G$2:$G$50)-SUMIF('BALANCE N'!$A$2:$A$50,"846*",'BALANCE N'!$F$2:$F$50) | C21: =SUMIF('BALANCE N-1'!$A$2:$A$50,"846*",'BALANCE N-1'!$G$2:$G$50)-SUMIF('BALANCE N-1'!$A$2:$A$50,"846*",'BALANCE N-1'!$F$2:$F$50) | D21: =B21-C21 | E21: =IF(C21=0,"",(B21-C21)/C21)
A22: Transferts de produits H.A.O. | B22: =SUMIF('BALANCE N'!$A$2:$A$50,"848*",'BALANCE N'!$G$2:$G$50)-SUMIF('BALANCE N'!$A$2:$A$50,"848*",'BALANCE N'!$F$2:$F$50) | C22: =SUMIF('BALANCE N-1'!$A$2:$A$50,"848*",'BALANCE N-1'!$G$2:$G$50)-SUMIF('BALANCE N-1'!$A$2:$A$50,"848*",'BALANCE N-1'!$F$2:$F$50) | D22: =B22-C22 | E22: =IF(C22=0,"",(B22-C22)/C22)
A23: Reprises de charges et provisions à court terme HAO | B23: =SUMIF('BALANCE N'!$A$2:$A$50,"849*",'BALANCE N'!$G$2:$G$50)-SUMIF('BALANCE N'!$A$2:$A$50,"849*",'BALANCE N'!$F$2:$F$50) | C23: =SUMIF('BALANCE N-1'!$A$2:$A$50,"849*",'BALANCE N-1'!$G$2:$G$50)-SUMIF('BALANCE N-1'!$A$2:$A$50,"849*",'BALANCE N-1'!$F$2:$F$50) | D23: =B23-C23 | E23: =IF(C23=0,"",(B23-C23)/C23)
A24: Reprises d'amortissements, provisions et dépréciations H.A.O. | B24: =SUMIF('BALANCE N'!$A$2:$A$50,"86*",'BALANCE N'!$G$2:$G$50)-SUMIF('BALANCE N'!$A$2:$A$50,"86*",'BALANCE N'!$F$2:$F$50) | C24: =SUMIF('BALANCE N-1'!$A$2:$A$50,"86*",'BALANCE N-1'!$G$2:$G$50)-SUMIF('BALANCE N-1'!$A$2:$A$50,"86*",'BALANCE N-1'!$F$2:$F$50) | D24: =B24-C24 | E24: =IF(C24=0,"",(B24-C24)/C24)
A25: Produits des cessions d'immobilisations | B25: =SUMIF('BALANCE N'!$A$2:$A$50,"82*",'BALANCE N'!$G$2:$G$50)-SUMIF('BALANCE N'!$A$2:$A$50,"82*",'BALANCE N'!$F$2:$F$50) | C25: =SUMIF('BALANCE N-1'!$A$2:$A$50,"82*",'BALANCE N-1'!$G$2:$G$50)-SUMIF('BALANCE N-1'!$A$2:$A$50,"82*",'BALANCE N-1'!$F$2:$F$50) | D25: =B25-C25 | E25: =IF(C25=0,"",(B25-C25)/C25)
A26: Subventions d'équilibre | B26: =SUMIF('BALANCE N'!$A$2:$A$50,"88*",'BALANCE N'!$G$2:$G$50)-SUMIF('BALANCE N'!$A$2:$A$50,"88*",'BALANCE N'!$F$2:$F$50) | C26: =SUMIF('BALANCE N-1'!$A$2:$A$50,"88*",'BALANCE N-1'!$G$2:$G$50)-SUMIF('BALANCE N-1'!$A$2:$A$50,"88*",'BALANCE N-1'!$F$2:$F$50) | D26: =B26-C26 | E26: =IF(C26=0,"",(B26-C26)/C26)
A27: TOTAL : AUTRES PRODUITS HAO | B27: =SUM(B18:B26) | C27: =SUM(C18:C26) | D27: =B27-C27 | E27: =IF(C27=0,"",(B27-C27)/C27)
A28: TOTAL (produits - charges) | B28: =B27-B17 | C28: =C27-C17 | D28: =B28-C28 | E28: =IF(C28=0,"",(B28-C28)/C28)

Sheet NOTE 24
A1: - 36 -
G2: NOTE 24 PROJETS DE DEVELOPPEMENT
A3: Dénomination sociale : PROJET EAU POTABLE RURALE
A4: Adresse : | G4: Sigle usuel : | H4: PEPR
A5: N° de compte contribuable (NCC) : PD-2023-017 | E5: Exercice clos le 31-12-2025 | G5: Durée (en mois) : 12
A6: N° de télédéclarant (NTD) :
A7: NOTE 24 : TABLEAU D'EXÉCUTION BUDGÉTAIRE
A8: Code | B8: Libellé | C8: Budget de l'exercice (1) | D8: Décaissement (2) | E8: Engagement (3) | F8: Réalisation (4 = 2 + 3) | G8: Crédit disponible (5 = 1 - 4) | H8: Exécution budget % (4/1)
F9: =D9+E9 | G9: =C9-F9 | H9: =IF(C9=0,"",F9/C9)
F10: =D10+E10 | G10: =C10-F10 | H10: =IF(C10=0,"",F10/C10)
F11: =D11+E11 | G11: =C11-F11 | H11: =IF(C11=0,"",F11/C11)
F12: =D12+E12 | G12: =C12-F12 | H12: =IF(C12=0,"",F12/C12)
F13: =D13+E13 | G13: =C13-F13 | H13: =IF(C13=0,"",F13/C13)
F14: =D14+E14 | G14: =C14-F14 | H14: =IF(C14=0,"",F14/C14)
F15: =D15+E15 | G15: =C15-F15 | H15: =IF(C15=0,"",F15/C15)
F16: =D16+E16 | G16: =C16-F16 | H16: =IF(C16=0,"",F16/C16)
F17: =D17+E17 | G17: =C17-F17 | H17: =IF(C17=0,"",F17/C17)
F18: =D18+E18 | G18: =C18-F18 | H18: =IF(C18=0,"",F18/C18)
F19: =D19+E19 | G19: =C19-F19 | H19: =IF(C19=0,"",F19/C19)
F20: =D20+E20 | G20: =C20-F20 | H20: =IF(C20=0,"",F20/C20)
B21: TOTAL | C21: =SUM(C9:C20) | D21: =SUM(D9:D20) | E21: =SUM(E9:E20) | F21: =SUM(F9:F20) | G21: =SUM(G9:G20) | H21: =IF(C21=0,"",F21/C21)
A23: Remplir code et libellé suivant la nomenclature budgétaire de l'entité ; expliquer les écarts significatifs entre budget et réalisation.

Sheet TABLE COMMENTAIRE
A1: TABLE DES COMMENTAIRES | G1: COMMENTAIRES PAGE 1/7
A2: Dénomination sociale : PROJET EAU POTABLE RURALE
A3: Adresse : | F3: Sigle usuel : PEPR
A4: N° de compte contribuable (NCC) : PD-2023-017 | E4: Exercice clos le 31-12-2025 | G4: Durée (en mois) : 12
A5: N° de télédéclarant (NTD) :
A6: Partie 1 : Informations générales
A7: Note 1 | B7: INFORMATIONS OBLIGATOIRES
A9: Partie 2 : Notes sur le tableau emplois-ressources, le tableau d'exécution budgétaire et la réconciliation de trésorerie
A10: Note 2 | B10: INFORMATIONS SPÉCIFIQUES
A12: Partie 3 : Notes sur le bilan
A13: Note 3A | B13: IMMOBILISATIONS BRUTES
A15: Note 3B | B15: BIENS PRIS EN LOCATION-ACQUISITION
A17: TABLE DES COMMENTAIRES | G17: COMMENTAIRES PAGE 2/7
A18: Dénomination sociale : PROJET EAU POTABLE RURALE
A19: Adresse : | F19: Sigle usuel : PEPR
A20: N° de compte contribuable (NCC) : PD-2023-017 | E20: Exercice clos le 31-12-2025 | G20: Durée (en mois) : 12
A21: N° de télédéclarant (NTD) :
A22: Note 4 | B22: ACTIF CIRCULANT ET DETTES CIRCULANTES HAO
A24: Note 5 | B24: STOCKS ET ENCOURS
A26: Note 6 | B26: CLIENTS-USAGERS ET AUTRES CRÉANCES
A28: Note 7 | B28: DISPONIBILITÉS
A30: TABLE DES COMMENTAIRES | G30: COMMENTAIRES PAGE 3/7
A31: Dénomination sociale : PROJET EAU POTABLE RURALE
