Workbook

Sheet GARDE
B2: ÉTATS FINANCIERS ANNUELS — SYSCOHADA
B4: SYSTÈME MINIMAL DE TRÉSORERIE (AUDCIF, Titre X)
B6: Désignation de l'entité | D6: ETS KAPINGA
B7: Numéro d'identification | D7: IDNAT 01-234-N56789K
B8: Exercice clos le | D8: 31/12/2025
B9: Durée de l'exercice (mois) | D9: 12
B10: Balance N-1 fournie | D10: Non
B12: Composition du jeu d'états (AUDCIF Titre X)
B13: • Bilan (actif et passif, une feuille chacun)
B14: • Compte de résultat (recettes/dépenses corrigées)
B15: • Notes annexes 1 à 4 + journaux de suivi
B16: • Feuilles d'audit : BALANCE, BALANCE_N1, CONTROLES, ANOMALIES
B18: Chaque montant porte une formule Excel pointant vers la feuille BALANCE : tout chiffre est retraçable jusqu'au compte qui l'alimente.

Sheet BILAN ACTIF
A1: BILAN SMT — ACTIF
A2: Système minimal de trésorerie (AUDCIF, Titre X)
A4: Désignation entité : ETS KAPINGA | D4: Exercice clos le : 31/12/2025
A5: Numéro d'identification : IDNAT 01-234-N56789K | D5: Durée (en mois) : 12
A7: REF | B7: ACTIF | C7: Note | D7: Exercice N | E7: Exercice N-1
A8: SA1 | B8: Immobilisations (1) | C8: 1 | D8: =SUMIF(BALANCE!$A$2:$A$50,"2*",BALANCE!$F$2:$F$50)-SUMIF(BALANCE!$A$2:$A$50,"2*",BALANCE!$G$2:$G$50)
A9: SA2 | B9: Stocks | C9: 2 | D9: =SUMIF(BALANCE!$A$2:$A$50,"3*",BALANCE!$F$2:$F$50)-SUMIF(BALANCE!$A$2:$A$50,"3*",BALANCE!$G$2:$G$50)
A10: SA3 | B10: Clients et débiteurs divers | C10: 3 | D10: =SUMIF(BALANCE!$A$2:$A$50,"4*",BALANCE!$F$2:$F$50)-(SUMIF(BALANCE!$A$2:$A$50,"49*",BALANCE!$G$2:$G$50)+SUMIF(BALANCE!$A$2:$A$50,"591*",BALANCE!$G$2:$G$50)+SUMIF(BALANCE!$A$2:$A$50,"590*",BALANCE!$G$2:$G$50))+(SUMIF(BALANCE!$A$2:$A$50,"50*",BALANCE!$F$2:$F$50)-SUMIF(BALANCE!$A$2:$A$50,"50*",BALANCE!$G$2:$G$50)+SUMIF(BALANCE!$A$2:$A$50,"51*",BALANCE!$F$2:$F$50)-SUMIF(BALANCE!$A$2:$A$50,"51*",BALANCE!$G$2:$G$50))
A11: SA4 | B11: Caisse | C11: 4 | D11: =SUMIF(BALANCE!$A$2:$A$50,"57*",BALANCE!$F$2:$F$50)-SUMIF(BALANCE!$A$2:$A$50,"57*",BALANCE!$G$2:$G$50)
A12: SA5 | B12: Banque (en + ou en -) | C12: 4 | D12: =SUMIF(BALANCE!$A$2:$A$50,"52*",BALANCE!$F$2:$F$50)-SUMIF(BALANCE!$A$2:$A$50,"52*",BALANCE!$G$2:$G$50)+SUMIF(BALANCE!$A$2:$A$50,"54*",BALANCE!$F$2:$F$50)-SUMIF(BALANCE!$A$2:$A$50,"54*",BALANCE!$G$2:$G$50)+SUMIF(BALANCE!$A$2:$A$50,"56*",BALANCE!$F$2:$F$50)-SUMIF(BALANCE!$A$2:$A$50,"56*",BALANCE!$G$2:$G$50)+SUMIF(BALANCE!$A$2:$A$50,"55*",BALANCE!$F$2:$F$50)-SUMIF(BALANCE!$A$2:$A$50,"55*",BALANCE!$G$2:$G$50)+SUMIF(BALANCE!$A$2:$A$50,"58*",BALANCE!$F$2:$F$50)-SUMIF(BALANCE!$A$2:$A$50,"58*",BALANCE!$G$2:$G$50)+SUMIF(BALANCE!$A$2:$A$50,"53*",BALANCE!$F$2:$F$50)-SUMIF(BALANCE!$A$2:$A$50,"53*",BALANCE!$G$2:$G$50)-(SUMIF(BALANCE!$A$2:$A$50,"592*",BALANCE!$G$2:$G$50)+SUMIF(BALANCE!$A$2:$A$50,"594*",BALANCE!$G$2:$G$50)+SUMIF(BALANCE!$A$2:$A$50,"593*",BALANCE!$G$2:$G$50))
A13: SAZ | B13: TOTAL ACTIF | D13: =SUM(D8:D12)
A15: (1) À faire figurer à l'actif si montants significatifs (AUDCIF Titre X). Registre des immobilisations : NOTE 1.

Sheet BILAN PASSIF
A1: BILAN SMT — PASSIF
A2: Système minimal de trésorerie (AUDCIF, Titre X)
A4: Désignation entité : ETS KAPINGA | D4: Exercice clos le : 31/12/2025
A5: Numéro d'identification : IDNAT 01-234-N56789K | D5: Durée (en mois) : 12
A7: REF | B7: PASSIF | C7: Note | D7: Exercice N | E7: Exercice N-1
A8: SP1 | B8: Compte exploitant | C8: 1 | D8: =SUMIF(BALANCE!$A$2:$A$50,"10*",BALANCE!$G$2:$G$50)-SUMIF(BALANCE!$A$2:$A$50,"10*",BALANCE!$F$2:$F$50)+SUMIF(BALANCE!$A$2:$A$50,"14*",BALANCE!$G$2:$G$50)-SUMIF(BALANCE!$A$2:$A$50,"14*",BALANCE!$F$2:$F$50)+SUMIF(BALANCE!$A$2:$A$50,"11*",BALANCE!$G$2:$G$50)-SUMIF(BALANCE!$A$2:$A$50,"11*",BALANCE!$F$2:$F$50)+SUMIF(BALANCE!$A$2:$A$50,"12*",BALANCE!$G$2:$G$50)-SUMIF(BALANCE!$A$2:$A$50,"12*",BALANCE!$F$2:$F$50)+SUMIF(BALANCE!$A$2:$A$50,"15*",BALANCE!$G$2:$G$50)-SUMIF(BALANCE!$A$2:$A$50,"15*",BALANCE!$F$2:$F$50)
A9: SP2 | B9: Résultat de l'exercice (en + ou en -) | D9: ='COMPTE DE RESULTAT'!D23+(SUMIF(BALANCE!$A$2:$A$50,"13*",BALANCE!$G$2:$G$50)-SUMIF(BALANCE!$A$2:$A$50,"13*",BALANCE!$F$2:$F$50))
A10: SP3 | B10: Emprunt | D10: =SUMIF(BALANCE!$A$2:$A$50,"16*",BALANCE!$G$2:$G$50)-SUMIF(BALANCE!$A$2:$A$50,"16*",BALANCE!$F$2:$F$50)+SUMIF(BALANCE!$A$2:$A$50,"19*",BALANCE!$G$2:$G$50)-SUMIF(BALANCE!$A$2:$A$50,"19*",BALANCE!$F$2:$F$50)+SUMIF(BALANCE!$A$2:$A$50,"17*",BALANCE!$G$2:$G$50)-SUMIF(BALANCE!$A$2:$A$50,"17*",BALANCE!$F$2:$F$50)+SUMIF(BALANCE!$A$2:$A$50,"18*",BALANCE!$G$2:$G$50)-SUMIF(BALANCE!$A$2:$A$50,"18*",BALANCE!$F$2:$F$50)
A11: SP4 | B11: Fournisseurs et créditeurs divers | C11: 3 | D11: =SUMIF(BALANCE!$A$2:$A$50,"4*",BALANCE!$G$2:$G$50)-SUMIF(BALANCE!$A$2:$A$50,"49*",BALANCE!$G$2:$G$50)+(SUMIF(BALANCE!$A$2:$A$50,"599*",BALANCE!$G$2:$G$50)-SUMIF(BALANCE!$A$2:$A$50,"599*",BALANCE!$F$2:$F$50))
A12: SPZ | B12: TOTAL PASSIF | D12: =SUM(D8:D11)
A14: Le compte exploitant regroupe apports, prélèvements et réserves de l'exploitant (comptes 10, 11, 12, 14, 15).

Sheet COMPTE DE RESULTAT
A1: COMPTE DE RÉSULTAT SMT
A2: Recettes et dépenses corrigées des variations d'inventaire et des amortissements
A4: Désignation entité : ETS KAPINGA | D4: Exercice clos le : 31/12/2025
A5: Numéro d'identification : IDNAT 01-234-N56789K | D5: Durée (en mois) : 12
A7: REF | B7: RUBRIQUES | C7: Note | D7: Exercice N | E7: Exercice N-1
A8: KA | B8: Recettes sur ventes ou prestations de services | C8: 4 | D8: =SUMIF(BALANCE!$A$2:$A$50,"70*",BALANCE!$G$2:$G$50)-SUMIF(BALANCE!$A$2:$A$50,"70*",BALANCE!$F$2:$F$50)
A9: KB | B9: Autres recettes sur activités | C9: 4 | D9: =SUMIF(BALANCE!$A$2:$A$50,"84*",BALANCE!$G$2:$G$50)-SUMIF(BALANCE!$A$2:$A$50,"84*",BALANCE!$F$2:$F$50)+SUMIF(BALANCE!$A$2:$A$50,"86*",BALANCE!$G$2:$G$50)-SUMIF(BALANCE!$A$2:$A$50,"86*",BALANCE!$F$2:$F$50)+SUMIF(BALANCE!$A$2:$A$50,"82*",BALANCE!$G$2:$G$50)-SUMIF(BALANCE!$A$2:$A$50,"82*",BALANCE!$F$2:$F$50)+SUMIF(BALANCE!$A$2:$A$50,"71*",BALANCE!$G$2:$G$50)-SUMIF(BALANCE!$A$2:$A$50,"71*",BALANCE!$F$2:$F$50)+SUMIF(BALANCE!$A$2:$A$50,"79*",BALANCE!$G$2:$G$50)-SUMIF(BALANCE!$A$2:$A$50,"79*",BALANCE!$F$2:$F$50)+SUMIF(BALANCE!$A$2:$A$50,"88*",BALANCE!$G$2:$G$50)-SUMIF(BALANCE!$A$2:$A$50,"88*",BALANCE!$F$2:$F$50)+SUMIF(BALANCE!$A$2:$A$50,"72*",BALANCE!$G$2:$G$50)-SUMIF(BALANCE!$A$2:$A$50,"72*",BALANCE!$F$2:$F$50)+SUMIF(BALANCE!$A$2:$A$50,"75*",BALANCE!$G$2:$G$50)-SUMIF(BALANCE!$A$2:$A$50,"75*",BALANCE!$F$2:$F$50)+SUMIF(BALANCE!$A$2:$A$50,"78*",BALANCE!$G$2:$G$50)-SUMIF(BALANCE!$A$2:$A$50,"78*",BALANCE!$F$2:$F$50)+SUMIF(BALANCE!$A$2:$A$50,"77*",BALANCE!$G$2:$G$50)-SUMIF(BALANCE!$A$2:$A$50,"77*",BALANCE!$F$2:$F$50)
A10: KX | B10: TOTAL DES RECETTES SUR PRODUITS (A) | D10: =D8+D9
A11: JA | B11: Dépenses sur achats | C11: 4 | D11: =SUMIF(BALANCE!$A$2:$A$50,"60*",BALANCE!$F$2:$F$50)-SUMIF(BALANCE!$A$2:$A$50,"60*",BALANCE!$G$2:$G$50)-SUMIF(BALANCE!$A$2:$A$50,"603*",BALANCE!$F$2:$F$50)+SUMIF(BALANCE!$A$2:$A$50,"603*",BALANCE!$G$2:$G$50)
A12: JB | B12: Dépenses sur loyers | C12: 4 | D12: =SUMIF(BALANCE!$A$2:$A$50,"622*",BALANCE!$F$2:$F$50)-SUMIF(BALANCE!$A$2:$A$50,"622*",BALANCE!$G$2:$G$50)
A13: JC | B13: Dépenses sur salaires | C13: 4 | D13: =SUMIF(BALANCE!$A$2:$A$50,"66*",BALANCE!$F$2:$F$50)-SUMIF(BALANCE!$A$2:$A$50,"66*",BALANCE!$G$2:$G$50)
A14: JD | B14: Dépenses sur impôts et taxes | C14: 4 | D14: =SUMIF(BALANCE!$A$2:$A$50,"89*",BALANCE!$F$2:$F$50)-SUMIF(BALANCE!$A$2:$A$50,"89*",BALANCE!$G$2:$G$50)+SUMIF(BALANCE!$A$2:$A$50,"64*",BALANCE!$F$2:$F$50)-SUMIF(BALANCE!$A$2:$A$50,"64*",BALANCE!$G$2:$G$50)
A15: JE | B15: Charges d'intérêts | D15: =SUMIF(BALANCE!$A$2:$A$50,"67*",BALANCE!$F$2:$F$50)-SUMIF(BALANCE!$A$2:$A$50,"67*",BALANCE!$G$2:$G$50)
A16: JF | B16: Autres dépenses sur activités | C16: 4 | D16: =SUMIF(BALANCE!$A$2:$A$50,"62*",BALANCE!$F$2:$F$50)-SUMIF(BALANCE!$A$2:$A$50,"62*",BALANCE!$G$2:$G$50)+SUMIF(BALANCE!$A$2:$A$50,"61*",BALANCE!$F$2:$F$50)-SUMIF(BALANCE!$A$2:$A$50,"61*",BALANCE!$G$2:$G$50)-SUMIF(BALANCE!$A$2:$A$50,"87*",BALANCE!$F$2:$F$50)+SUMIF(BALANCE!$A$2:$A$50,"87*",BALANCE!$G$2:$G$50)-SUMIF(BALANCE!$A$2:$A$50,"83*",BALANCE!$F$2:$F$50)+SUMIF(BALANCE!$A$2:$A$50,"83*",BALANCE!$G$2:$G$50)-SUMIF(BALANCE!$A$2:$A$50,"63*",BALANCE!$F$2:$F$50)+SUMIF(BALANCE!$A$2:$A$50,"63*",BALANCE!$G$2:$G$50)-SUMIF(BALANCE!$A$2:$A$50,"65*",BALANCE!$F$2:$F$50)+SUMIF(BALANCE!$A$2:$A$50,"65*",BALANCE!$G$2:$G$50)-SUMIF(BALANCE!$A$2:$A$50,"81*",BALANCE!$F$2:$F$50)+SUMIF(BALANCE!$A$2:$A$50,"81*",BALANCE!$G$2:$G$50)-SUMIF(BALANCE!$A$2:$A$50,"622*",BALANCE!$F$2:$F$50)+SUMIF(BALANCE!$A$2:$A$50,"622*",BALANCE!$G$2:$G$50)
A17: JX | B17: TOTAL DÉPENSES SUR CHARGES (B) | D17: =D11+D12+D13+D14+D15+D16
A18: KZ | B18: SOLDE : Excédent (+) ou insuffisance (-) de recettes (C = A - B) | D18: =D10-D17
A19: VA | B19: Variation des stocks [N - (N-1)] (D) | C19: 2 | D19: =(SUMIF(BALANCE!$A$2:$A$50,"603*",BALANCE!$G$2:$G$50)-SUMIF(BALANCE!$A$2:$A$50,"603*",BALANCE!$F$2:$F$50))+(SUMIF(BALANCE!$A$2:$A$50,"73*",BALANCE!$G$2:$G$50)-SUMIF(BALANCE!$A$2:$A$50,"73*",BALANCE!$F$2:$F$50))
A20: VB | B20: Variation des créances [N - (N-1)] (D) — à saisir depuis la NOTE 3 | C20: 3 | D20: 0
A21: VC | B21: Variation des dettes d'exploitation [N - (N-1)] (E) — à saisir depuis la NOTE 3 | C21: 3 | D21: 0
A22: JG | B22: DOTATIONS AUX AMORTISSEMENTS (F) | D22: =SUMIF(BALANCE!$A$2:$A$50,"69*",BALANCE!$F$2:$F$50)-SUMIF(BALANCE!$A$2:$A$50,"69*",BALANCE!$G$2:$G$50)+SUMIF(BALANCE!$A$2:$A$50,"85*",BALANCE!$F$2:$F$50)-SUMIF(BALANCE!$A$2:$A$50,"85*",BALANCE!$G$2:$G$50)+SUMIF(BALANCE!$A$2:$A$50,"68*",BALANCE!$F$2:$F$50)-SUMIF(BALANCE!$A$2:$A$50,"68*",BALANCE!$G$2:$G$50)
A23: KZC | B23: RÉSULTAT DE L'EXERCICE (G = C + D stocks + D créances - E dettes - F) | D23: =D18+D19+D20-D21-D22
A25: Lecture (AUDCIF Titre X) : G = C - D + E - F. Les variations sont ici affichées en N - (N-1) : une hausse des stocks ou des créances augmente le résultat, une hausse des dettes le diminue. VB et VC se saisissent depuis la NOTE 3 (inventaire extra-comptable).

Sheet NOTE 1 IMMOBILISATIONS
A1: NOTE 1 — TABLEAU SMT DE SUIVI DU MATÉRIEL, DU MOBILIER ET DES CAUTIONS
A2: Registre des immobilisations — amortissement linéaire sans prorata temporis
A4: Désignation entité : ETS KAPINGA | F4: Exercice clos le : 31/12/2025
A5: Numéro d'identification : IDNAT 01-234-N56789K | F5: Durée (en mois) : 12
A7: Compte | B7: Désignation | C7: Montant | D7: Date d'acquisition | E7: Durée d'utilité | F7: Date de sortie | G7: Prix de cession
A8: 2441 | B8: Matériel et mobilier | C8: =SUMIF(BALANCE!$A$2:$A$50,"2441*",BALANCE!$F$2:$F$50)-SUMIF(BALANCE!$A$2:$A$50,"2441*",BALANCE!$G$2:$G$50)
B9: TOTAL IMMOBILISATIONS BRUTES | C9: =SUM(C8:C8)
B10: Amortissements et dépréciations cumulés (28/29) | C10: =SUMIF(BALANCE!$A$2:$A$50,"29*",BALANCE!$G$2:$G$50)-SUMIF(BALANCE!$A$2:$A$50,"29*",BALANCE!$F$2:$F$50)+SUMIF(BALANCE!$A$2:$A$50,"28*",BALANCE!$G$2:$G$50)-SUMIF(BALANCE!$A$2:$A$50,"28*",BALANCE!$F$2:$F$50)
B11: VALEUR NETTE (= poste Immobilisations du bilan) | C11: =C9-C10
A13: Compléter dates, durées et sorties depuis le registre : la balance ne porte que les montants.

Sheet NOTE 2 STOCKS
A1: NOTE 2 — ÉTAT DES STOCKS
A2: Inventaire extra-comptable au 31 décembre
A4: Désignation entité : ETS KAPINGA | D4: Exercice clos le : 31/12/2025
A5: Numéro d'identification : IDNAT 01-234-N56789K | D5: Durée (en mois) : 12
A7: Référence | B7: Désignation | C7: Quantité | D7: Prix unitaire | E7: Montant
A8: 33 | B8: Stocks d'autres approvisionnements | E8: =SUMIF(BALANCE!$A$2:$A$50,"33*",BALANCE!$F$2:$F$50)-SUMIF(BALANCE!$A$2:$A$50,"33*",BALANCE!$G$2:$G$50)
B12: VALEUR DU STOCK FINAL | E12: =SUMIF(BALANCE!$A$2:$A$50,"3*",BALANCE!$F$2:$F$50)-SUMIF(BALANCE!$A$2:$A$50,"3*",BALANCE!$G$2:$G$50)
B13: VALEUR DU STOCK INITIAL | E13: 0
B14: VARIATION DES STOCKS [final - initial] | E14: =E12-E13

Sheet NOTE 3 CREANCES-DETTES
A1: NOTE 3 — ÉTAT DES CRÉANCES ET DES DETTES NON ÉCHUES
A2: Inventaire extra-comptable au 31 décembre
A4: Désignation entité : ETS KAPINGA | E4: Exercice clos le : 31/12/2025
A5: Numéro d'identification : IDNAT 01-234-N56789K | E5: Durée (en mois) : 12
A7: CRÉANCES — clients-usagers et autres débiteurs
A8: Date | B8: Nom | C8: Montant au 31/12/N | D8: Montant au 01/01/N | E8: Variation en valeur | F8: Variation en %
E9: =C9-D9 | F9: =IF(D9=0,"",(C9-D9)/D9)
E10: =C10-D10 | F10: =IF(D10=0,"",(C10-D10)/D10)
E11: =C11-D11 | F11: =IF(D11=0,"",(C11-D11)/D11)
E12: =C12-D12 | F12: =IF(D12=0,"",(C12-D12)/D12)
E13: =C13-D13 | F13: =IF(D13=0,"",(C13-D13)/D13)
E14: =C14-D14 | F14: =IF(D14=0,"",(C14-D14)/D14)
B15: TOTAL DES CRÉANCES | C15: =SUM(C9:C14) | D15: =SUM(D9:D14) | E15: =SUM(E9:E14)
B16: Rappel balance (classe 4, soldes débiteurs) — contrôle | C16: =SUMIF(BALANCE!$A$2:$A$50,"4*",BALANCE!$F$2:$F$50) | D16: =0
A19: DETTES — fournisseurs et autres créditeurs
A20: Date | B20: Nom | C20: Montant au 31/12/N | D20: Montant au 01/01/N | E20: Variation en valeur | F20: Variation en %
E21: =C21-D21 | F21: =IF(D21=0,"",(C21-D21)/D21)
E22: =C22-D22 | F22: =IF(D22=0,"",(C22-D22)/D22)
E23: =C23-D23 | F23: =IF(D23=0,"",(C23-D23)/D23)
E24: =C24-D24 | F24: =IF(D24=0,"",(C24-D24)/D24)
E25: =C25-D25 | F25: =IF(D25=0,"",(C25-D25)/D25)
E26: =C26-D26 | F26: =IF(D26=0,"",(C26-D26)/D26)
B27: TOTAL DES DETTES | C27: =SUM(C21:C26) | D27: =SUM(D21:D26) | E27: =SUM(E21:E26)
B28: Rappel balance (classe 4, soldes créditeurs) — contrôle | C28: =SUMIF(BALANCE!$A$2:$A$50,"4*",BALANCE!$G$2:$G$50) | D28: =0
A31: Reporter la variation des créances en VB et celle des dettes en VC du compte de résultat.

Sheet NOTE 4 JOURNAL TRESORERIE
A1: NOTE 4 — JOURNAL DE TRÉSORERIE SMT
A2: Un journal par banque et un journal pour la caisse (AUDCIF Titre X, ch. 3)
A4: Désignation entité : ETS KAPINGA | J4: Exercice clos le : 31/12/2025
A5: Numéro d'identification : IDNAT 01-234-N56789K | J5: Durée (en mois) : 12
A7: Date | B7: Libellés | C7: Recettes | D7: Dépenses | E7: Solde | F7: Vent. recettes : Ventes | G7: Autres | H7: Matériel et mobilier | I7: Vent. dépenses : Achats | J7: Loyers / Salaires / Impôts | K7: Autres
B8: Report à nouveau
E9: =E8+C9-D9
E10: =E9+C10-D10
E11: =E10+C11-D11
E12: =E11+C12-D12
E13: =E12+C13-D13
E14: =E13+C14-D14
E15: =E14+C15-D15
E16: =E15+C16-D16
E17: =E16+C17-D17
E18: =E17+C18-D18
E19: =E18+C19-D19
E20: =E19+C20-D20
... E22: =E21+C22-D22
B23: Solde à reporter | E23: =E22

Sheet JOURNAUX DE SUIVI
A1: JOURNAUX DE SUIVI SMT
A2: Créances impayées et dettes à payer — pièces de base de la fiabilité du SMT (Titre X, ch. 1)
A4: Désignation entité : ETS KAPINGA | D4: Exercice clos le : 31/12/2025
A5: Numéro d'identification : IDNAT 01-234-N56789K | D5: Durée (en mois) : 12
A7: JOURNAL DE SUIVI DES CRÉANCES IMPAYÉES
A8: Date | B8: N° facture | C8: Nom du client | D8: Montant | E8: Date de paiement
C16: TOTAL | D16: =SUM(D9:D15)
A19: JOURNAL DE SUIVI DES DETTES À PAYER
A20: Date | B20: N° facture | C20: Nom du fournisseur | D20: Montant | E20: Date de paiement
C28: TOTAL | D28: =SUM(D21:D27)

Sheet BALANCE
A1: Compte | B1: Intitulé | C1: Préfixe 2 | D1: Préfixe 3 | E1: Préfixe 4 | F1: Solde final débit | G1: Solde final crédit | H1: Mouvement débit | I1: Mouvement crédit
A2: 2441 | B2: Matériel et mobilier | C2: 24 | D2: 244 | E2: 2441 | F2: 3000000 | G2: 0 | H2: 0 | I2: 0
A3: 2844 | B3: Amortissements du matériel et mobilier | C3: 28 | D3: 284 | E3: 2844 | F3: 0 | G3: 1200000 | H3: 0 | I3: 0
A4: 33 | B4: Stocks d'autres approvisionnements | C4: 33 | D4: 33 | E4: 33 | F4: 800000 | G4: 0 | H4: 0 | I4: 0
A5: 521 | B5: Banque locale | C5: 52 | D5: 521 | E5: 521 | F5: 2500000 | G5: 0 | H5: 0 | I5: 0
A6: 571 | B6: Caisse | C6: 57 | D6: 571 | E6: 571 | F6: 500000 | G6: 0 | H6: 0 | I6: 0
A7: 103 | B7: Capital personnel | C7: 10 | D7: 103 | E7: 103 | F7: 0 | G7: 2000000 | H7: 0 | I7: 0
A8: 162 | B8: Emprunt établissement de crédit | C8: 16 | D8: 162 | E8: 162 | F8: 0 | G8: 1500000 | H8: 0 | I8: 0
A9: 401 | B9: Fournisseurs | C9: 40 | D9: 401 | E9: 401 | F9: 0 | G9: 400000 | H9: 0 | I9: 0
A10: 601 | B10: Achats de marchandises | C10: 60 | D10: 601 | E10: 601 | F10: 5200000 | G10: 0 | H10: 0 | I10: 0
A11: 622 | B11: Locations et charges locatives | C11: 62 | D11: 622 | E11: 622 | F11: 1200000 | G11: 0 | H11: 0 | I11: 0
A12: 661 | B12: Salaires | C12: 66 | D12: 661 | E12: 661 | F12: 1800000 | G12: 0 | H12: 0 | I12: 0
A13: 641 | B13: Impôts et taxes directs | C13: 64 | D13: 641 | E13: 641 | F13: 300000 | G13: 0 | H13: 0 | I13: 0
... A18: 707 | B18: Produits accessoires | C18: 70 | D18: 707 | E18: 707 | F18: 0 | G18: 1000000 | H18: 0 | I18: 0

Sheet CONTROLES
A1: Contrôle | B1: Valeur | C1: Attendu
A2: Total solde débit balance | B2: =SUM(BALANCE!F2:F18)
A3: Total solde crédit balance | B3: =SUM(BALANCE!G2:G18)
A4: Écart balance (doit être 0) | B4: =B2-B3 | C4: 0
A5: Total actif | B5: ='BILAN ACTIF'!D13
A6: Total passif | B6: ='BILAN PASSIF'!D12
A7: Écart actif - passif (doit être 0) | B7: =B5-B6 | C7: 0
A8: Résultat (compte de résultat, G) | B8: ='COMPTE DE RESULTAT'!D23

Sheet ANOMALIES
A1: Gravité | B1: Compte | C1: Intitulé | D1: Problème | E1: Solution proposée
A2: INFO | C2: Classe 4 | D2: La balance porte des comptes de tiers : recettes et dépenses incluent alors des montants non encaissés/décaissés (base engagement). | E2: Dans ce cas, laisser VB et VC à zéro : le résultat est déjà en base engagement. Ne les servir que pour une balance de trésorerie pure, depuis l'inventaire extra-comptable (NOTE 3).
A3: INFO | C3: SMT — seuils | D3: Vérifier l'assujettissement au SMT : CA HT ≤ 60 M FCFA (négoce), 40 M (artisanat), 30 M (services) — AUDCIF art. 13. | E3: Au-delà des seuils, monter la liasse du Système normal (monter_liasse.py).
