Workbook

Sheet BALANCE N
A1: Compte | B1: Intitulé | C1: Solde d'ouverture débit | D1: Solde d'ouverture crédit | E1: Mouvement débit | F1: Mouvement crédit | G1: Solde de clôture débit | H1: Solde de clôture crédit
B2: TOTAL GENERAL | C2: 0 | D2: 0 | E2: 0 | F2: 0 | G2: 0 | H2: 0
B3: Contrôle d'équilibre par solde (débit - crédit, doit être 0) | C3: =C2-D2 | E3: =E2-F2 | G3: =G2-H2

Sheet BALANCE N-1
A1: Compte | B1: Intitulé | C1: Solde d'ouverture débit | D1: Solde d'ouverture crédit | E1: Mouvement débit | F1: Mouvement crédit | G1: Solde de clôture débit | H1: Solde de clôture crédit
B2: TOTAL GENERAL | C2: 0 | D2: 0 | E2: 0 | F2: 0 | G2: 0 | H2: 0
B3: Contrôle d'équilibre par solde (débit - crédit, doit être 0) | C3: =C2-D2 | E3: =E2-F2 | G3: =G2-H2

Sheet CONTROLE BALANCE
A1: EQUILIBRE DE LA BALANCE
A2: BALANCE N | B2: Solde d'ouverture Débit | C2: Solde d'ouverture Crédit | D2: Mouvements Débit | E2: Mouvements Crédit | F2: Solde de clôture Débit | G2: Solde de clôture Crédit
B3: =SUM('BALANCE N'!C2:C2) | C3: =SUM('BALANCE N'!D2:D2) | D3: =SUM('BALANCE N'!E2:E2) | E3: =SUM('BALANCE N'!F2:F2) | F3: =SUM('BALANCE N'!G2:G2) | G3: =SUM('BALANCE N'!H2:H2)
B4: =IF(ROUND(B3-C3,0)=0,"Equilibre","Déséquilibre : écart de "&TEXT(B3-C3,"#,##0")) | D4: =IF(ROUND(D3-E3,0)=0,"Equilibre","Déséquilibre : écart de "&TEXT(D3-E3,"#,##0")) | F4: =IF(ROUND(F3-G3,0)=0,"Equilibre","Déséquilibre : écart de "&TEXT(F3-G3,"#,##0"))
A5: BALANCE N-1 | B5: Solde d'ouverture Débit | C5: Solde d'ouverture Crédit | D5: Mouvements Débit | E5: Mouvements Crédit | F5: Solde de clôture Débit | G5: Solde de clôture Crédit
B6: =SUM('BALANCE N-1'!C2:C2) | C6: =SUM('BALANCE N-1'!D2:D2) | D6: =SUM('BALANCE N-1'!E2:E2) | E6: =SUM('BALANCE N-1'!F2:F2) | F6: =SUM('BALANCE N-1'!G2:G2) | G6: =SUM('BALANCE N-1'!H2:H2)
B7: =IF(ROUND(B6-C6,0)=0,"Equilibre","Déséquilibre : écart de "&TEXT(B6-C6,"#,##0")) | D7: =IF(ROUND(D6-E6,0)=0,"Equilibre","Déséquilibre : écart de "&TEXT(D6-E6,"#,##0")) | F7: =IF(ROUND(F6-G6,0)=0,"Equilibre","Déséquilibre : écart de "&TEXT(F6-G6,"#,##0"))

Sheet Couverture
E31: LIASSE SYSTEME NORMAL
E34: Exercice clos le

Sheet Garde
B12: ETATS FINANCIERS NORMALISES DU SYSTEME COMPTABLE DES ENTITES A BUT NON LUCRATIF (SYCEBNL)
B13: Associations, Ordres Professionnels, Fondations et Assimilées
C16: Exercice clos le - Durée (en mois) : 12
B20: DESIGNATION DE L'ENTITE
B22: DENOMINATION SOCIALE :
B24: SIGLE USUEL :
B26: ADRESSE COMPLETE :
B28: N° de compte contribuable (NCC) :
B30: N° de télédéclarant (NTD) :
B32: SYSTEME NORMAL
B34: Documents déposés | H34: Réservé à l'administration
B35: Fiche d'identification et renseignements divers | F35: X | H35: Date de dépôt
B36: Bilan (actif et passif) | F36: X
B37: Compte de résultat | F37: X
B38: Tableau des flux de trésorerie | F38: X
B39: Notes annexes | F39: X | H39: Nom de l'agent ayant réceptionné le dépôt
H43: Signature de l'agent et cachet du service
B48: Nombre de pages déposées par exemplaire :
B49: Nombre d'exemplaires déposés :

Sheet Fiche 1
A1: - 1 -
I2: FICHE 1
A3: Dénomination sociale :
A4: Adresse : | I4: Sigle usuel :
A5: N° de compte contribuable (NCC) : | G5: Exercice clos le | I5: Durée (en mois) : 12
A6: N° de télédéclarant (NTD) :
A7: FICHE D'IDENTIFICATION ET RENSEIGNEMENTS DIVERS
A8: SYCEBNL - Associations et ordres professionnels - Système normal
A10: ZA | B10: EXERCICE COMPTABLE | G10: DU : AU :
A11: ZB | B11: DATE D'ARRETE EFFECTIF DES COMPTES
A12: ZC | B12: EXERCICE PRECEDENT CLOS LE
A13: ZD | B13: DUREE DE L'EXERCICE PRECEDENT (EN MOIS)
A14: ZE | B14: N° REGISTRE (RCCM, F92, CONVENTION...) ET GREFFE
A15: ZF | B15: N° REPERTOIRE DES ENTITES
A16: ZG | B16: N° DE CAISSE SOCIALE
A17: ZH | B17: N° CODE IMPORTATEUR
A18: ZI | B18: CODE ACTIVITE PRINCIPALE
A19: ZJ | B19: DESIGNATION DE L'ENTITE ET SIGLE
A20: ZK | B20: N° DE TELEPHONE, ADRESSE E-MAIL, BOITE POSTALE, VILLE
A21: ZL | B21: ADRESSE GEOGRAPHIQUE COMPLETE (IMMEUBLE, RUE, QUARTIER, VILLE, PAYS)
A22: ZM | B22: DESIGNATION PRECISE DE L'ACTIVITE PRINCIPALE EXERCEE
... A32: ZW | B32: DOMICILIATIONS BANCAIRES (BANQUE ET NUMERO DE COMPTE)
B34: Signature

Sheet Fiche 2
A1: - 2 -
I2: FICHE 2
A3: Dénomination sociale :
A4: Adresse : | I4: Sigle usuel :
A5: N° de compte contribuable (NCC) : | G5: Exercice clos le | I5: Durée (en mois) : 12
A6: N° de télédéclarant (NTD) :
A7: FICHE D'IDENTIFICATION ET RENSEIGNEMENTS DIVERS
A8: EQUIPE DE L'ENTITE A BUT NON LUCRATIF
A10: Nom et Prénoms | C10: Nationalité | D10: Autres nationalités (à préciser) (2) | E10: Qualité | F10: N° d'identification fiscale | H10: Adresse (BP, ville, pays, adresse géographique et adresse e-mail)
A32: (2) Mentionner les autres nationalités le cas échéant.

Sheet Bilan paysage
A1: - 3 -
K2: BILAN SYSTEME NORMAL PAGE 1/1
A3: Dénomination sociale :
A4: Adresse : | K4: Sigle usuel :
A5: N° de compte contribuable (NCC) : | I5: Exercice clos le | K5: Durée (en mois) : 12
A6: N° de télédéclarant (NTD) :
C7: BILAN
A8: REF | B8: ACTIF | C8: NOTE | D8: BRUT | E8: AMORT et DEPREC. | F8: NET | G8: NET N-1 | H8: REF | I8: PASSIF | J8: NOTE | K8: NET | L8: NET N-1
A10: AA | B10: IMMOBILISATIONS DESTINEES A LA VENTE PROVENANT DE DONS ET LEGS NON ENCORE RECUES ET USUFRUIT TEMPORAIRE | C10: note 5 | D10: ='Bilan-Actif'!D10 | E10: ='Bilan-Actif'!E10 | F10: ='Bilan-Actif'!F10 | G10: ='Bilan-Actif'!G10 | H10: CA | I10: Donation non consomptible sans droit reprise | J10: note 15 | K10: ='Bilan-Passif'!D10 | L10: ='Bilan-Passif'!E10
A11: AB | B11: Immobilisations incorporelles | D11: ='Bilan-Actif'!D11 | E11: ='Bilan-Actif'!E11 | F11: ='Bilan-Actif'!F11 | G11: ='Bilan-Actif'!G11 | H11: CB | I11: Donation non consomptible avec droit reprise | J11: note 15 | K11: ='Bilan-Passif'!D11 | L11: ='Bilan-Passif'!E11
A12: AC | B12: Immobilisations corporelles et financieres | D12: ='Bilan-Actif'!D12 | E12: ='Bilan-Actif'!E12 | F12: ='Bilan-Actif'!F12 | G12: ='Bilan-Actif'!G12 | H12: CC | I12: Droit d'entree | J12: note 15 | K12: ='Bilan-Passif'!D12 | L12: ='Bilan-Passif'!E12
A13: AD | B13: IMMOBILISATIONS INCORPORELLES | C13: note 5 | D13: ='Bilan-Actif'!D13 | E13: ='Bilan-Actif'!E13 | F13: ='Bilan-Actif'!F13 | G13: ='Bilan-Actif'!G13 | H13: CD | I13: Donation consomptible | J13: note 15 | K13: ='Bilan-Passif'!D13 | L13: ='Bilan-Passif'!E13
A14: AE | B14: Brevets, licences, logiciels et droits similaires | C14: note 5F | D14: ='Bilan-Actif'!D14 | E14: ='Bilan-Actif'!E14 | F14: ='Bilan-Actif'!F14 | G14: ='Bilan-Actif'!G14 | H14: CE | I14: Ecarts de reevaluation | J14: note 5F | K14: ='Bilan-Passif'!D14 | L14: ='Bilan-Passif'!E14
A15: AF | B15: Autres immobilisations incorporelles | D15: ='Bilan-Actif'!D15 | E15: ='Bilan-Actif'!E15 | F15: ='Bilan-Actif'!F15 | G15: ='Bilan-Actif'!G15 | H15: CF | I15: Reserves | J15: note 16 | K15: ='Bilan-Passif'!D15 | L15: ='Bilan-Passif'!E15
A16: AG | B16: Avances et acomptes verses sur immobilisations incorporelles | D16: ='Bilan-Actif'!D16 | E16: ='Bilan-Actif'!E16 | F16: ='Bilan-Actif'!F16 | G16: ='Bilan-Actif'!G16 | H16: CG | I16: Report a nouveau (+ ou -) | J16: note 16 | K16: ='Bilan-Passif'!D16 | L16: ='Bilan-Passif'!E16
A17: AH | B17: IMMOBILISATIONS CORPORELLES | C17: note 5 | D17: ='Bilan-Actif'!D17 | E17: ='Bilan-Actif'!E17 | F17: ='Bilan-Actif'!F17 | G17: ='Bilan-Actif'!G17 | H17: CH | I17: Resultat net de l'exercice (excedent + ou deficit -) | K17: ='Bilan-Passif'!D17 | L17: ='Bilan-Passif'!E17
A18: AI | B18: Terrains | D18: ='Bilan-Actif'!D18 | E18: ='Bilan-Actif'!E18 | F18: ='Bilan-Actif'!F18 | G18: ='Bilan-Actif'!G18 | H18: CI | I18: Subventions d'investissement | J18: note 17A | K18: ='Bilan-Passif'!D18 | L18: ='Bilan-Passif'!E18
A19: AJ | B19: Batiments | D19: ='Bilan-Actif'!D19 | E19: ='Bilan-Actif'!E19 | F19: ='Bilan-Actif'!F19 | G19: ='Bilan-Actif'!G19 | H19: CJ | I19: Provisions reglementees | J19: note 17A | K19: ='Bilan-Passif'!D19 | L19: ='Bilan-Passif'!E19
A20: AK | B20: Amenagements, agencements et installations | D20: ='Bilan-Actif'!D20 | E20: ='Bilan-Actif'!E20 | F20: ='Bilan-Actif'!F20 | G20: ='Bilan-Actif'!G20 | H20: CK | I20: TOTAL FONDS PROPRES ET ASSIMILES | K20: ='Bilan-Passif'!D20 | L20: ='Bilan-Passif'!E20
A21: AL | B21: Materiel, mobilier et actifs biologiques | D21: ='Bilan-Actif'!D21 | E21: ='Bilan-Actif'!E21 | F21: ='Bilan-Actif'!F21 | G21: ='Bilan-Actif'!G21 | H21: CW | I21: Fonds affectes et provenant de dons et legs d'immobilisations | J21: note 17B | K21: ='Bilan-Passif'!D21 | L21: ='Bilan-Passif'!E21
A22: AM | B22: Materiel de transport | D22: ='Bilan-Actif'!D22 | E22: ='Bilan-Actif'!E22 | F22: ='Bilan-Actif'!F22 | G22: ='Bilan-Actif'!G22 | H22: CX | I22: Fonds reportes | J22: note 17B | K22: ='Bilan-Passif'!D22 | L22: ='Bilan-Passif'!E22
A23: AN | B23: Avances et acomptes verses sur immobilisations corporelles | D23: ='Bilan-Actif'!D23 | E23: ='Bilan-Actif'!E23 | F23: ='Bilan-Actif'!F23 | G23: ='Bilan-Actif'!G23 | H23: CY | I23: TOTAL FONDS AFFECTES ET REPORTES | K23: ='Bilan-Passif'!D23 | L23: ='Bilan-Passif'!E23
A24: AO | B24: IMMOBILISATIONS FINANCIERES | C24: note 6 | D24: ='Bilan-Actif'!D24 | E24: ='Bilan-Actif'!E24 | F24: ='Bilan-Actif'!F24 | G24: ='Bilan-Actif'!G24 | H24: CZ | I24: TOTAL RESSOURCES PROPRES ET ASSIMILEES | K24: ='Bilan-Passif'!D24 | L24: ='Bilan-Passif'!E24
A25: AX | B25: Titres de participation | D25: ='Bilan-Actif'!D25 | E25: ='Bilan-Actif'!E25 | F25: ='Bilan-Actif'!F25 | G25: ='Bilan-Actif'!G25 | H25: DA | I25: Emprunts et dettes financieres | J25: note 18A | K25: ='Bilan-Passif'!D25 | L25: ='Bilan-Passif'!E25
A26: AY | B26: Autres immobilisations financieres | D26: ='Bilan-Actif'!D26 | E26: ='Bilan-Actif'!E26 | F26: ='Bilan-Actif'!F26 | G26: ='Bilan-Actif'!G26 | H26: DB | I26: Dettes de location-acquisition | J26: note 18A | K26: ='Bilan-Passif'!D26 | L26: ='Bilan-Passif'!E26
A27: AZ | B27: TOTAL ACTIF IMMOBILISE | D27: ='Bilan-Actif'!D27 | E27: ='Bilan-Actif'!E27 | F27: ='Bilan-Actif'!F27 | G27: ='Bilan-Actif'!G27 | H27: DC | I27: Provisions pour risques et charges | J27: note 18A | K27: ='Bilan-Passif'!D27 | L27: ='Bilan-Passif'!E27
A28: BA | B28: Actif circulant HAO | C28: note 7 | D28: ='Bilan-Actif'!D28 | E28: ='Bilan-Actif'!E28 | F28: ='Bilan-Actif'!F28 | G28: ='Bilan-Actif'!G28 | H28: DD | I28: TOTAL DETTES FINANCIERES ET RESSOURCES ASSIMILEES | K28: ='Bilan-Passif'!D28 | L28: ='Bilan-Passif'!E28
A29: BB | B29: Stocks et encours | C29: note 8 | D29: ='Bilan-Actif'!D29 | E29: ='Bilan-Actif'!E29 | F29: ='Bilan-Actif'!F29 | G29: ='Bilan-Actif'!G29 | H29: DE | I29: TOTAL RESSOURCES STABLES | K29: ='Bilan-Passif'!D29 | L29: ='Bilan-Passif'!E29
A30: BC | B30: Fournisseurs debiteurs | C30: note 19 | D30: ='Bilan-Actif'!D30 | E30: ='Bilan-Actif'!E30 | F30: ='Bilan-Actif'!F30 | G30: ='Bilan-Actif'!G30 | H30: DF | I30: Dettes circulantes HAO | J30: note 7 | K30: ='Bilan-Passif'!D30 | L30: ='Bilan-Passif'!E30
A31: BD | B31: Adherents, Clients-usagers | C31: note 9 | D31: ='Bilan-Actif'!D31 | E31: ='Bilan-Actif'!E31 | F31: ='Bilan-Actif'!F31 | G31: ='Bilan-Actif'!G31 | H31: DG | I31: Adherents, clients-usagers crediteurs | J31: note 9 | K31: ='Bilan-Passif'!D31 | L31: ='Bilan-Passif'!E31
A32: BE | B32: Autres creances | C32: note 10 | D32: ='Bilan-Actif'!D32 | E32: ='Bilan-Actif'!E32 | F32: ='Bilan-Actif'!F32 | G32: ='Bilan-Actif'!G32 | H32: DH | I32: Fournisseurs | J32: note 19 | K32: ='Bilan-Passif'!D32 | L32: ='Bilan-Passif'!E32
A33: BT | B33: TOTAL ACTIF CIRCULANT | D33: ='Bilan-Actif'!D33 | E33: ='Bilan-Actif'!E33 | F33: ='Bilan-Actif'!F33 | G33: ='Bilan-Actif'!G33 | H33: DI | I33: Autres dettes | J33: note 20 et 21 | K33: ='Bilan-Passif'!D33 | L33: ='Bilan-Passif'!E33
A34: BU | B34: Titres de placement | C34: note 11 | D34: ='Bilan-Actif'!D34 | E34: ='Bilan-Actif'!E34 | F34: ='Bilan-Actif'!F34 | G34: ='Bilan-Actif'!G34 | H34: DV | I34: TOTAL PASSIF CIRCULANT | K34: ='Bilan-Passif'!D34 | L34: ='Bilan-Passif'!E34
A35: BV | B35: Valeurs a encaisser | C35: note 12 | D35: ='Bilan-Actif'!D35 | E35: ='Bilan-Actif'!E35 | F35: ='Bilan-Actif'!F35 | G35: ='Bilan-Actif'!G35 | H35: DW | I35: Banques, etablissements financiers et credits de tresorerie | J35: note 22 | K35: ='Bilan-Passif'!D35 | L35: ='Bilan-Passif'!E35
A36: BW | B36: Banques, etablissements financiers, caisses et assimiles | C36: note 13 | D36: ='Bilan-Actif'!D36 | E36: ='Bilan-Actif'!E36 | F36: ='Bilan-Actif'!F36 | G36: ='Bilan-Actif'!G36 | H36: DX | I36: TOTAL TRESORERIE PASSIF | K36: ='Bilan-Passif'!D36 | L36: ='Bilan-Passif'!E36
A37: BX | B37: TOTAL TRESORERIE ACTIF | D37: ='Bilan-Actif'!D37 | E37: ='Bilan-Actif'!E37 | F37: ='Bilan-Actif'!F37 | G37: ='Bilan-Actif'!G37 | H37: DY | I37: Ecart de conversion-Passif | J37: note 14 | K37: ='Bilan-Passif'!D37 | L37: ='Bilan-Passif'!E37
A38: BY | B38: Ecart de conversion-Actif | C38: note 14 | D38: ='Bilan-Actif'!D38 | E38: ='Bilan-Actif'!E38 | F38: ='Bilan-Actif'!F38 | G38: ='Bilan-Actif'!G38 | H38: DZ | I38: TOTAL GENERAL | K38: ='Bilan-Passif'!D38 | L38: ='Bilan-Passif'!E38
A39: BZ | B39: TOTAL GENERAL | D39: ='Bilan-Actif'!D39 | E39: ='Bilan-Actif'!E39 | F39: ='Bilan-Actif'!F39 | G39: ='Bilan-Actif'!G39

Sheet Bilan-Actif
A1: - 4 -
F2: BILAN SYSTEME NORMAL PAGE 1/2
A3: Dénomination sociale :
A4: Adresse : | F4: Sigle usuel :
A5: N° de compte contribuable (NCC) : | D5: Exercice clos le | F5: Durée (en mois) : 12
A6: N° de télédéclarant (NTD) :
B7: BILAN
A8: REF | B8: ACTIF | C8: NOTE | D8: EXERCICE AU 31/12/N | G8: EXERCICE AU 31/12/N-1
D9: BRUT | E9: AMORT et DEPREC. | F9: NET | G9: NET
A10: AA | B10: IMMOBILISATIONS DESTINEES A LA VENTE PROVENANT DE DONS ET LEGS NON ENCORE RECUES ET USUFRUIT TEMPORAIRE | C10: note 5 | D10: =D11+D12 | E10: =E11+E12 | F10: =F11+F12 | G10: =G11+G12
A11: AB | B11: Immobilisations incorporelles | D11: =(SUMIF('BALANCE N'!$A$2:$A$2000,"201*",'BALANCE N'!$G$2:$G$2000)-SUMIF('BALANCE N'!$A$2:$A$2000,"201*",'BALANCE N'!$H$2:$H$2000)) | E11: =(SUMIF('BALANCE N'!$A$2:$A$2000,"280*",'BALANCE N'!$H$2:$H$2000)-SUMIF('BALANCE N'!$A$2:$A$2000,"280*",'BALANCE N'!$G$2:$G$2000)+SUMIF('BALANCE N'!$A$2:$A$2000,"2901*",'BALANCE N'!$H$2:$H$2000)-SUMIF('BALANCE N'!$A$2:$A$2000,"2901*",'BALANCE N'!$G$2:$G$2000)) | F11: =D11-E11 | G11: =((SUMIF('BALANCE N-1'!$A$2:$A$2000,"201*",'BALANCE N-1'!$G$2:$G$2000)-SUMIF('BALANCE N-1'!$A$2:$A$2000,"201*",'BALANCE N-1'!$H$2:$H$2000)))-((SUMIF('BALANCE N-1'!$A$2:$A$2000,"280*",'BALANCE N-1'!$H$2:$H$2000)-SUMIF('BALANCE N-1'!$A$2:$A$2000,"280*",'BALANCE N-1'!$G$2:$G$2000)+SUMIF('BALANCE N-1'!$A$2:$A$2000,"2901*",'BALANCE N-1'!$H$2:$H$2000)-SUMIF('BALANCE N-1'!$A$2:$A$2000,"2901*",'BALANCE N-1'!$G$2:$G$2000)))
A12: AC | B12: Immobilisations corporelles et financieres | D12: =(SUMIF('BALANCE N'!$A$2:$A$2000,"202*",'BALANCE N'!$G$2:$G$2000)-SUMIF('BALANCE N'!$A$2:$A$2000,"202*",'BALANCE N'!$H$2:$H$2000)+SUMIF('BALANCE N'!$A$2:$A$2000,"203*",'BALANCE N'!$G$2:$G$2000)-SUMIF('BALANCE N'!$A$2:$A$2000,"203*",'BALANCE N'!$H$2:$H$2000)+SUMIF('BALANCE N'!$A$2:$A$2000,"204*",'BALANCE N'!$G$2:$G$2000)-SUMIF('BALANCE N'!$A$2:$A$2000,"204*",'BALANCE N'!$H$2:$H$2000)+SUMIF('BALANCE N'!$A$2:$A$2000,"205*",'BALANCE N'!$G$2:$G$2000)-SUMIF('BALANCE N'!$A$2:$A$2000,"205*",'BALANCE N'!$H$2:$H$2000)) | E12: =(SUMIF('BALANCE N'!$A$2:$A$2000,"2902*",'BALANCE N'!$H$2:$H$2000)-SUMIF('BALANCE N'!$A$2:$A$2000,"2902*",'BALANCE N'!$G$2:$G$2000)) | F12: =D12-E12 | G12: =((SUMIF('BALANCE N-1'!$A$2:$A$2000,"202*",'BALANCE N-1'!$G$2:$G$2000)-SUMIF('BALANCE N-1'!$A$2:$A$2000,"202*",'BALANCE N-1'!$H$2:$H$2000)+SUMIF('BALANCE N-1'!$A$2:$A$2000,"203*",'BALANCE N-1'!$G$2:$G$2000)-SUMIF('BALANCE N-1'!$A$2:$A$2000,"203*",'BALANCE N-1'!$H$2:$H$2000)+SUMIF('BALANCE N-1'!$A$2:$A$2000,"204*",'BALANCE N-1'!$G$2:$G$2000)-SUMIF('BALANCE N-1'!$A$2:$A$2000,"204*",'BALANCE N-1'!$H$2:$H$2000)+SUMIF('BALANCE N-1'!$A$2:$A$2000,"205*",'BALANCE N-1'!$G$2:$G$2000)-SUMIF('BALANCE N-1'!$A$2:$A$2000,"205*",'BALANCE N-1'!$H$2:$H$2000)))-((SUMIF('BALANCE N-1'!$A$2:$A$2000,"2902*",'BALANCE N-1'!$H$2:$H$2000)-SUMIF('BALANCE N-1'!$A$2:$A$2000,"2902*",'BALANCE N-1'!$G$2:$G$2000)))
A13: AD | B13: IMMOBILISATIONS INCORPORELLES | C13: note 5 | D13: =D14+D15+D16 | E13: =E14+E15+E16 | F13: =F14+F15+F16 | G13: =G14+G15+G16
A14: AE | B14: Brevets, licences, logiciels et droits similaires | C14: note 5F | D14: =(SUMIF('BALANCE N'!$A$2:$A$2000,"212*",'BALANCE N'!$G$2:$G$2000)-SUMIF('BALANCE N'!$A$2:$A$2000,"212*",'BALANCE N'!$H$2:$H$2000)+SUMIF('BALANCE N'!$A$2:$A$2000,"213*",'BALANCE N'!$G$2:$G$2000)-SUMIF('BALANCE N'!$A$2:$A$2000,"213*",'BALANCE N'!$H$2:$H$2000)+SUMIF('BALANCE N'!$A$2:$A$2000,"214*",'BALANCE N'!$G$2:$G$2000)-SUMIF('BALANCE N'!$A$2:$A$2000,"214*",'BALANCE N'!$H$2:$H$2000)+SUMIF('BALANCE N'!$A$2:$A$2000,"2193*",'BALANCE N'!$G$2:$G$2000)-SUMIF('BALANCE N'!$A$2:$A$2000,"2193*",'BALANCE N'!$H$2:$H$2000)) | E14: =(SUMIF('BALANCE N'!$A$2:$A$2000,"2812*",'BALANCE N'!$H$2:$H$2000)-SUMIF('BALANCE N'!$A$2:$A$2000,"2812*",'BALANCE N'!$G$2:$G$2000)+SUMIF('BALANCE N'!$A$2:$A$2000,"2813*",'BALANCE N'!$H$2:$H$2000)-SUMIF('BALANCE N'!$A$2:$A$2000,"2813*",'BALANCE N'!$G$2:$G$2000)+SUMIF('BALANCE N'!$A$2:$A$2000,"2814*",'BALANCE N'!$H$2:$H$2000)-SUMIF('BALANCE N'!$A$2:$A$2000,"2814*",'BALANCE N'!$G$2:$G$2000)+SUMIF('BALANCE N'!$A$2:$A$2000,"2912*",'BALANCE N'!$H$2:$H$2000)-SUMIF('BALANCE N'!$A$2:$A$2000,"2912*",'BALANCE N'!$G$2:$G$2000)+SUMIF('BALANCE N'!$A$2:$A$2000,"2913*",'BALANCE N'!$H$2:$H$2000)-SUMIF('BALANCE N'!$A$2:$A$2000,"2913*",'BALANCE N'!$G$2:$G$2000)+SUMIF('BALANCE N'!$A$2:$A$2000,"2919*",'BALANCE N'!$H$2:$H$2000)-SUMIF('BALANCE N'!$A$2:$A$2000,"2919*",'BALANCE N'!$G$2:$G$2000)) | F14: =D14-E14 | G14: =((SUMIF('BALANCE N-1'!$A$2:$A$2000,"212*",'BALANCE N-1'!$G$2:$G$2000)-SUMIF('BALANCE N-1'!$A$2:$A$2000,"212*",'BALANCE N-1'!$H$2:$H$2000)+SUMIF('BALANCE N-1'!$A$2:$A$2000,"213*",'BALANCE N-1'!$G$2:$G$2000)-SUMIF('BALANCE N-1'!$A$2:$A$2000,"213*",'BALANCE N-1'!$H$2:$H$2000)+SUMIF('BALANCE N-1'!$A$2:$A$2000,"214*",'BALANCE N-1'!$G$2:$G$2000)-SUMIF('BALANCE N-1'!$A$2:$A$2000,"214*",'BALANCE N-1'!$H$2:$H$2000)+SUMIF('BALANCE N-1'!$A$2:$A$2000,"2193*",'BALANCE N-1'!$G$2:$G$2000)-SUMIF('BALANCE N-1'!$A$2:$A$2000,"2193*",'BALANCE N-1'!$H$2:$H$2000)))-((SUMIF('BALANCE N-1'!$A$2:$A$2000,"2812*",'BALANCE N-1'!$H$2:$H$2000)-SUMIF('BALANCE N-1'!$A$2:$A$2000,"2812*",'BALANCE N-1'!$G$2:$G$2000)+SUMIF('BALANCE N-1'!$A$2:$A$2000,"2813*",'BALANCE N-1'!$H$2:$H$2000)-SUMIF('BALANCE N-1'!$A$2:$A$2000,"2813*",'BALANCE N-1'!$G$2:$G$2000)+SUMIF('BALANCE N-1'!$A$2:$A$2000,"2814*",'BALANCE N-1'!$H$2:$H$2000)-SUMIF('BALANCE N-1'!$A$2:$A$2000,"2814*",'BALANCE N-1'!$G$2:$G$2000)+SUMIF('BALANCE N-1'!$A$2:$A$2000,"2912*",'BALANCE N-1'!$H$2:$H$2000)-SUMIF('BALANCE N-1'!$A$2:$A$2000,"2912*",'BALANCE N-1'!$G$2:$G$2000)+SUMIF('BALANCE N-1'!$A$2:$A$2000,"2913*",'BALANCE N-1'!$H$2:$H$2000)-SUMIF('BALANCE N-1'!$A$2:$A$2000,"2913*",'BALANCE N-1'!$G$2:$G$2000)+SUMIF('BALANCE N-1'!$A$2:$A$2000,"2919*",'BALANCE N-1'!$H$2:$H$2000)-SUMIF('BALANCE N-1'!$A$2:$A$2000,"2919*",'BALANCE N-1'!$G$2:$G$2000)))
A15: AF | B15: Autres immobilisations incorporelles | D15: =(SUMIF('BALANCE N'!$A$2:$A$2000,"218*",'BALANCE N'!$G$2:$G$2000)-SUMIF('BALANCE N'!$A$2:$A$2000,"218*",'BALANCE N'!$H$2:$H$2000)+SUMIF('BALANCE N'!$A$2:$A$2000,"2198*",'BALANCE N'!$G$2:$G$2000)-SUMIF('BALANCE N'!$A$2:$A$2000,"2198*",'BALANCE N'!$H$2:$H$2000)) | E15: =(SUMIF('BALANCE N'!$A$2:$A$2000,"2818*",'BALANCE N'!$H$2:$H$2000)-SUMIF('BALANCE N'!$A$2:$A$2000,"2818*",'BALANCE N'!$G$2:$G$2000)+SUMIF('BALANCE N'!$A$2:$A$2000,"2918*",'BALANCE N'!$H$2:$H$2000)-SUMIF('BALANCE N'!$A$2:$A$2000,"2918*",'BALANCE N'!$G$2:$G$2000)+SUMIF('BALANCE N'!$A$2:$A$2000,"2919*",'BALANCE N'!$H$2:$H$2000)-SUMIF('BALANCE N'!$A$2:$A$2000,"2919*",'BALANCE N'!$G$2:$G$2000)) | F15: =D15-E15 | G15: =((SUMIF('BALANCE N-1'!$A$2:$A$2000,"218*",'BALANCE N-1'!$G$2:$G$2000)-SUMIF('BALANCE N-1'!$A$2:$A$2000,"218*",'BALANCE N-1'!$H$2:$H$2000)+SUMIF('BALANCE N-1'!$A$2:$A$2000,"2198*",'BALANCE N-1'!$G$2:$G$2000)-SUMIF('BALANCE N-1'!$A$2:$A$2000,"2198*",'BALANCE N-1'!$H$2:$H$2000)))-((SUMIF('BALANCE N-1'!$A$2:$A$2000,"2818*",'BALANCE N-1'!$H$2:$H$2000)-SUMIF('BALANCE N-1'!$A$2:$A$2000,"2818*",'BALANCE N-1'!$G$2:$G$2000)+SUMIF('BALANCE N-1'!$A$2:$A$2000,"2918*",'BALANCE N-1'!$H$2:$H$2000)-SUMIF('BALANCE N-1'!$A$2:$A$2000,"2918*",'BALANCE N-1'!$G$2:$G$2000)+SUMIF('BALANCE N-1'!$A$2:$A$2000,"2919*",'BALANCE N-1'!$H$2:$H$2000)-SUMIF('BALANCE N-1'!$A$2:$A$2000,"2919*",'BALANCE N-1'!$G$2:$G$2000)))
A16: AG | B16: Avances et acomptes verses sur immobilisations incorporelles | D16: =(SUMIF('BALANCE N'!$A$2:$A$2000,"251*",'BALANCE N'!$G$2:$G$2000)-SUMIF('BALANCE N'!$A$2:$A$2000,"251*",'BALANCE N'!$H$2:$H$2000)) | E16: 0 | F16: =D16-E16 | G16: =((SUMIF('BALANCE N-1'!$A$2:$A$2000,"251*",'BALANCE N-1'!$G$2:$G$2000)-SUMIF('BALANCE N-1'!$A$2:$A$2000,"251*",'BALANCE N-1'!$H$2:$H$2000)))-(0)
A17: AH | B17: IMMOBILISATIONS CORPORELLES | C17: note 5 | D17: =D18+D19+D20+D21+D22+D23 | E17: =E18+E19+E20+E21+E22+E23 | F17: =F18+F19+F20+F21+F22+F23 | G17: =G18+G19+G20+G21+G22+G23
A18: AI | B18: Terrains | D18: =(SUMIF('BALANCE N'!$A$2:$A$2000,"22*",'BALANCE N'!$G$2:$G$2000)-SUMIF('BALANCE N'!$A$2:$A$2000,"22*",'BALANCE N'!$H$2:$H$2000)) | E18: =(SUMIF('BALANCE N'!$A$2:$A$2000,"282*",'BALANCE N'!$H$2:$H$2000)-SUMIF('BALANCE N'!$A$2:$A$2000,"282*",'BALANCE N'!$G$2:$G$2000)+SUMIF('BALANCE N'!$A$2:$A$2000,"292*",'BALANCE N'!$H$2:$H$2000)-SUMIF('BALANCE N'!$A$2:$A$2000,"292*",'BALANCE N'!$G$2:$G$2000)) | F18: =D18-E18 | G18: =((SUMIF('BALANCE N-1'!$A$2:$A$2000,"22*",'BALANCE N-1'!$G$2:$G$2000)-SUMIF('BALANCE N-1'!$A$2:$A$2000,"22*",'BALANCE N-1'!$H$2:$H$2000)))-((SUMIF('BALANCE N-1'!$A$2:$A$2000,"282*",'BALANCE N-1'!$H$2:$H$2000)-SUMIF('BALANCE N-1'!$A$2:$A$2000,"282*",'BALANCE N-1'!$G$2:$G$2000)+SUMIF('BALANCE N-1'!$A$2:$A$2000,"292*",'BALANCE N-1'!$H$2:$H$2000)-SUMIF('BALANCE N-1'!$A$2:$A$2000,"292*",'BALANCE N-1'!$G$2:$G$2000)))
A19: AJ | B19: Batiments | D19: =(SUMIF('BALANCE N'!$A$2:$A$2000,"231*",'BALANCE N'!$G$2:$G$2000)-SUMIF('BALANCE N'!$A$2:$A$2000,"231*",'BALANCE N'!$H$2:$H$2000)+SUMIF('BALANCE N'!$A$2:$A$2000,"232*",'BALANCE N'!$G$2:$G$2000)-SUMIF('BALANCE N'!$A$2:$A$2000,"232*",'BALANCE N'!$H$2:$H$2000)+SUMIF('BALANCE N'!$A$2:$A$2000,"233*",'BALANCE N'!$G$2:$G$2000)-SUMIF('BALANCE N'!$A$2:$A$2000,"233*",'BALANCE N'!$H$2:$H$2000)+SUMIF('BALANCE N'!$A$2:$A$2000,"2391*",'BALANCE N'!$G$2:$G$2000)-SUMIF('BALANCE N'!$A$2:$A$2000,"2391*",'BALANCE N'!$H$2:$H$2000)+SUMIF('BALANCE N'!$A$2:$A$2000,"2392*",'BALANCE N'!$G$2:$G$2000)-SUMIF('BALANCE N'!$A$2:$A$2000,"2392*",'BALANCE N'!$H$2:$H$2000)+SUMIF('BALANCE N'!$A$2:$A$2000,"2393*",'BALANCE N'!$G$2:$G$2000)-SUMIF('BALANCE N'!$A$2:$A$2000,"2393*",'BALANCE N'!$H$2:$H$2000)+SUMIF('BALANCE N'!$A$2:$A$2000,"2396*",'BALANCE N'!$G$2:$G$2000)-SUMIF('BALANCE N'!$A$2:$A$2000,"2396*",'BALANCE N'!$H$2:$H$2000)) | E19: =(SUMIF('BALANCE N'!$A$2:$A$2000,"2831*",'BALANCE N'!$H$2:$H$2000)-SUMIF('BALANCE N'!$A$2:$A$2000,"2831*",'BALANCE N'!$G$2:$G$2000)+SUMIF('BALANCE N'!$A$2:$A$2000,"2832*",'BALANCE N'!$H$2:$H$2000)-SUMIF('BALANCE N'!$A$2:$A$2000,"2832*",'BALANCE N'!$G$2:$G$2000)+SUMIF('BALANCE N'!$A$2:$A$2000,"2833*",'BALANCE N'!$H$2:$H$2000)-SUMIF('BALANCE N'!$A$2:$A$2000,"2833*",'BALANCE N'!$G$2:$G$2000)+SUMIF('BALANCE N'!$A$2:$A$2000,"2931*",'BALANCE N'!$H$2:$H$2000)-SUMIF('BALANCE N'!$A$2:$A$2000,"2931*",'BALANCE N'!$G$2:$G$2000)+SUMIF('BALANCE N'!$A$2:$A$2000,"2932*",'BALANCE N'!$H$2:$H$2000)-SUMIF('BALANCE N'!$A$2:$A$2000,"2932*",'BALANCE N'!$G$2:$G$2000)+SUMIF('BALANCE N'!$A$2:$A$2000,"2933*",'BALANCE N'!$H$2:$H$2000)-SUMIF('BALANCE N'!$A$2:$A$2000,"2933*",'BALANCE N'!$G$2:$G$2000)+SUMIF('BALANCE N'!$A$2:$A$2000,"2939*",'BALANCE N'!$H$2:$H$2000)-SUMIF('BALANCE N'!$A$2:$A$2000,"2939*",'BALANCE N'!$G$2:$G$2000)) | F19: =D19-E19 | G19: =((SUMIF('BALANCE N-1'!$A$2:$A$2000,"231*",'BALANCE N-1'!$G$2:$G$2000)-SUMIF('BALANCE N-1'!$A$2:$A$2000,"231*",'BALANCE N-1'!$H$2:$H$2000)+SUMIF('BALANCE N-1'!$A$2:$A$2000,"232*",'BALANCE N-1'!$G$2:$G$2000)-SUMIF('BALANCE N-1'!$A$2:$A$2000,"232*",'BALANCE N-1'!$H$2:$H$2000)+SUMIF('BALANCE N-1'!$A$2:$A$2000,"233*",'BALANCE N-1'!$G$2:$G$2000)-SUMIF('BALANCE N-1'!$A$2:$A$2000,"233*",'BALANCE N-1'!$H$2:$H$2000)+SUMIF('BALANCE N-1'!$A$2:$A$2000,"2391*",'BALANCE N-1'!$G$2:$G$2000)-SUMIF('BALANCE N-1'!$A$2:$A$2000,"2391*",'BALANCE N-1'!$H$2:$H$2000)+SUMIF('BALANCE N-1'!$A$2:$A$2000,"2392*",'BALANCE N-1'!$G$2:$G$2000)-SUMIF('BALANCE N-1'!$A$2:$A$2000,"2392*",'BALANCE N-1'!$H$2:$H$2000)+SUMIF('BALANCE N-1'!$A$2:$A$2000,"2393*",'BALANCE N-1'!$G$2:$G$2000)-SUMIF('BALANCE N-1'!$A$2:$A$2000,"2393*",'BALANCE N-1'!$H$2:$H$2000)+SUMIF('BALANCE N-1'!$A$2:$A$2000,"2396*",'BALANCE N-1'!$G$2:$G$2000)-SUMIF('BALANCE N-1'!$A$2:$A$2000,"2396*",'BALANCE N-1'!$H$2:$H$2000)))-((SUMIF('BALANCE N-1'!$A$2:$A$2000,"2831*",'BALANCE N-1'!$H$2:$H$2000)-SUMIF('BALANCE N-1'!$A$2:$A$2000,"2831*",'BALANCE N-1'!$G$2:$G$2000)+SUMIF('BALANCE N-1'!$A$2:$A$2000,"2832*",'BALANCE N-1'!$H$2:$H$2000)-SUMIF('BALANCE N-1'!$A$2:$A$2000,"2832*",'BALANCE N-1'!$G$2:$G$2000)+SUMIF('BALANCE N-1'!$A$2:$A$2000,"2833*",'BALANCE N-1'!$H$2:$H$2000)-SUMIF('BALANCE N-1'!$A$2:$A$2000,"2833*",'BALANCE N-1'!$G$2:$G$2000)+SUMIF('BALANCE N-1'!$A$2:$A$2000,"2931*",'BALANCE N-1'!$H$2:$H$2000)-SUMIF('BALANCE N-1'!$A$2:$A$2000,"2931*",'BALANCE N-1'!$G$2:$G$2000)+SUMIF('BALANCE N-1'!$A$2:$A$2000,"2932*",'BALANCE N-1'!$H$2:$H$2000)-SUMIF('BALANCE N-1'!$A$2:$A$2000,"2932*",'BALANCE N-1'!$G$2:$G$2000)+SUMIF('BALANCE N-1'!$A$2:$A$2000,"2933*",'BALANCE N-1'!$H$2:$H$2000)-SUMIF('BALANCE N-1'!$A$2:$A$2000,"2933*",'BALANCE N-1'!$G$2:$G$2000)+SUMIF('BALANCE N-1'!$A$2:$A$2000,"2939*",'BALANCE N-1'!$H$2:$H$2000)-SUMIF('BALANCE N-1'!$A$2:$A$2000,"2939*",'BALANCE N-1'!$G$2:$G$2000)))
A20: AK | B20: Amenagements, agencements et installations | D20: =(SUMIF('BALANCE N'!$A$2:$A$2000,"234*",'BALANCE N'!$G$2:$G$2000)-SUMIF('BALANCE N'!$A$2:$A$2000,"234*",'BALANCE N'!$H$2:$H$2000)+SUMIF('BALANCE N'!$A$2:$A$2000,"235*",'BALANCE N'!$G$2:$G$2000)-SUMIF('BALANCE N'!$A$2:$A$2000,"235*",'BALANCE N'!$H$2:$H$2000)+SUMIF('BALANCE N'!$A$2:$A$2000,"238*",'BALANCE N'!$G$2:$G$2000)-SUMIF('BALANCE N'!$A$2:$A$2000,"238*",'BALANCE N'!$H$2:$H$2000)+SUMIF('BALANCE N'!$A$2:$A$2000,"2394*",'BALANCE N'!$G$2:$G$2000)-SUMIF('BALANCE N'!$A$2:$A$2000,"2394*",'BALANCE N'!$H$2:$H$2000)+SUMIF('BALANCE N'!$A$2:$A$2000,"2395*",'BALANCE N'!$G$2:$G$2000)-SUMIF('BALANCE N'!$A$2:$A$2000,"2395*",'BALANCE N'!$H$2:$H$2000)+SUMIF('BALANCE N'!$A$2:$A$2000,"2398*",'BALANCE N'!$G$2:$G$2000)-SUMIF('BALANCE N'!$A$2:$A$2000,"2398*",'BALANCE N'!$H$2:$H$2000)) | E20: =(SUMIF('BALANCE N'!$A$2:$A$2000,"2834*",'BALANCE N'!$H$2:$H$2000)-SUMIF('BALANCE N'!$A$2:$A$2000,"2834*",'BALANCE N'!$G$2:$G$2000)+SUMIF('BALANCE N'!$A$2:$A$2000,"2835*",'BALANCE N'!$H$2:$H$2000)-SUMIF('BALANCE N'!$A$2:$A$2000,"2835*",'BALANCE N'!$G$2:$G$2000)+SUMIF('BALANCE N'!$A$2:$A$2000,"2838*",'BALANCE N'!$H$2:$H$2000)-SUMIF('BALANCE N'!$A$2:$A$2000,"2838*",'BALANCE N'!$G$2:$G$2000)+SUMIF('BALANCE N'!$A$2:$A$2000,"2934*",'BALANCE N'!$H$2:$H$2000)-SUMIF('BALANCE N'!$A$2:$A$2000,"2934*",'BALANCE N'!$G$2:$G$2000)+SUMIF('BALANCE N'!$A$2:$A$2000,"2935*",'BALANCE N'!$H$2:$H$2000)-SUMIF('BALANCE N'!$A$2:$A$2000,"2935*",'BALANCE N'!$G$2:$G$2000)+SUMIF('BALANCE N'!$A$2:$A$2000,"2938*",'BALANCE N'!$H$2:$H$2000)-SUMIF('BALANCE N'!$A$2:$A$2000,"2938*",'BALANCE N'!$G$2:$G$2000)+SUMIF('BALANCE N'!$A$2:$A$2000,"2939*",'BALANCE N'!$H$2:$H$2000)-SUMIF('BALANCE N'!$A$2:$A$2000,"2939*",'BALANCE N'!$G$2:$G$2000)) | F20: =D20-E20 | G20: =((SUMIF('BALANCE N-1'!$A$2:$A$2000,"234*",'BALANCE N-1'!$G$2:$G$2000)-SUMIF('BALANCE N-1'!$A$2:$A$2000,"234*",'BALANCE N-1'!$H$2:$H$2000)+SUMIF('BALANCE N-1'!$A$2:$A$2000,"235*",'BALANCE N-1'!$G$2:$G$2000)-SUMIF('BALANCE N-1'!$A$2:$A$2000,"235*",'BALANCE N-1'!$H$2:$H$2000)+SUMIF('BALANCE N-1'!$A$2:$A$2000,"238*",'BALANCE N-1'!$G$2:$G$2000)-SUMIF('BALANCE N-1'!$A$2:$A$2000,"238*",'BALANCE N-1'!$H$2:$H$2000)+SUMIF('BALANCE N-1'!$A$2:$A$2000,"2394*",'BALANCE N-1'!$G$2:$G$2000)-SUMIF('BALANCE N-1'!$A$2:$A$2000,"2394*",'BALANCE N-1'!$H$2:$H$2000)+SUMIF('BALANCE N-1'!$A$2:$A$2000,"2395*",'BALANCE N-1'!$G$2:$G$2000)-SUMIF('BALANCE N-1'!$A$2:$A$2000,"2395*",'BALANCE N-1'!$H$2:$H$2000)+SUMIF('BALANCE N-1'!$A$2:$A$2000,"2398*",'BALANCE N-1'!$G$2:$G$2000)-SUMIF('BALANCE N-1'!$A$2:$A$2000,"2398*",'BALANCE N-1'!$H$2:$H$2000)))-((SUMIF('BALANCE N-1'!$A$2:$A$2000,"2834*",'BALANCE N-1'!$H$2:$H$2000)-SUMIF('BALANCE N-1'!$A$2:$A$2000,"2834*",'BALANCE N-1'!$G$2:$G$2000)+SUMIF('BALANCE N-1'!$A$2:$A$2000,"2835*",'BALANCE N-1'!$H$2:$H$2000)-SUMIF('BALANCE N-1'!$A$2:$A$2000,"2835*",'BALANCE N-1'!$G$2:$G$2000)+SUMIF('BALANCE N-1'!$A$2:$A$2000,"2838*",'BALANCE N-1'!$H$2:$H$2000)-SUMIF('BALANCE N-1'!$A$2:$A$2000,"2838*",'BALANCE N-1'!$G$2:$G$2000)+SUMIF('BALANCE N-1'!$A$2:$A$2000,"2934*",'BALANCE N-1'!$H$2:$H$2000)-SUMIF('BALANCE N-1'!$A$2:$A$2000,"2934*",'BALANCE N-1'!$G$2:$G$2000)+SUMIF('BALANCE N-1'!$A$2:$A$2000,"2935*",'BALANCE N-1'!$H$2:$H$2000)-SUMIF('BALANCE N-1'!$A$2:$A$2000,"2935*",'BALANCE N-1'!$G$2:$G$2000)+SUMIF('BALANCE N-1'!$A$2:$A$2000,"2938*",'BALANCE N-1'!$H$2:$H$2000)-SUMIF('BALANCE N-1'!$A$2:$A$2000,"2938*",'BALANCE N-1'!$G$2:$G$2000)+SUMIF('BALANCE N-1'!$A$2:$A$2000,"2939*",'BALANCE N-1'!$H$2:$H$2000)-SUMIF('BALANCE N-1'!$A$2:$A$2000,"2939*",'BALANCE N-1'!$G$2:$G$2000)))
A21: AL | B21: Materiel, mobilier et actifs biologiques | D21: =(SUMIF('BALANCE N'!$A$2:$A$2000,"24*",'BALANCE N'!$G$2:$G$2000)-SUMIF('BALANCE N'!$A$2:$A$2000,"24*",'BALANCE N'!$H$2:$H$2000)-SUMIF('BALANCE N'!$A$2:$A$2000,"245*",'BALANCE N'!$G$2:$G$2000)+SUMIF('BALANCE N'!$A$2:$A$2000,"245*",'BALANCE N'!$H$2:$H$2000)-SUMIF('BALANCE N'!$A$2:$A$2000,"2495*",'BALANCE N'!$G$2:$G$2000)+SUMIF('BALANCE N'!$A$2:$A$2000,"2495*",'BALANCE N'!$H$2:$H$2000)) | E21: =(SUMIF('BALANCE N'!$A$2:$A$2000,"284*",'BALANCE N'!$H$2:$H$2000)-SUMIF('BALANCE N'!$A$2:$A$2000,"284*",'BALANCE N'!$G$2:$G$2000)+SUMIF('BALANCE N'!$A$2:$A$2000,"294*",'BALANCE N'!$H$2:$H$2000)-SUMIF('BALANCE N'!$A$2:$A$2000,"294*",'BALANCE N'!$G$2:$G$2000)-SUMIF('BALANCE N'!$A$2:$A$2000,"2845*",'BALANCE N'!$H$2:$H$2000)+SUMIF('BALANCE N'!$A$2:$A$2000,"2845*",'BALANCE N'!$G$2:$G$2000)-SUMIF('BALANCE N'!$A$2:$A$2000,"2945*",'BALANCE N'!$H$2:$H$2000)+SUMIF('BALANCE N'!$A$2:$A$2000,"2945*",'BALANCE N'!$G$2:$G$2000)-SUMIF('BALANCE N'!$A$2:$A$2000,"2949*",'BALANCE N'!$H$2:$H$2000)+SUMIF('BALANCE N'!$A$2:$A$2000,"2949*",'BALANCE N'!$G$2:$G$2000)) | F21: =D21-E21 | G21: =((SUMIF('BALANCE N-1'!$A$2:$A$2000,"24*",'BALANCE N-1'!$G$2:$G$2000)-SUMIF('BALANCE N-1'!$A$2:$A$2000,"24*",'BALANCE N-1'!$H$2:$H$2000)-SUMIF('BALANCE N-1'!$A$2:$A$2000,"245*",'BALANCE N-1'!$G$2:$G$2000)+SUMIF('BALANCE N-1'!$A$2:$A$2000,"245*",'BALANCE N-1'!$H$2:$H$2000)-SUMIF('BALANCE N-1'!$A$2:$A$2000,"2495*",'BALANCE N-1'!$G$2:$G$2000)+SUMIF('BALANCE N-1'!$A$2:$A$2000,"2495*",'BALANCE N-1'!$H$2:$H$2000)))-((SUMIF('BALANCE N-1'!$A$2:$A$2000,"284*",'BALANCE N-1'!$H$2:$H$2000)-SUMIF('BALANCE N-1'!$A$2:$A$2000,"284*",'BALANCE N-1'!$G$2:$G$2000)+SUMIF('BALANCE N-1'!$A$2:$A$2000,"294*",'BALANCE N-1'!$H$2:$H$2000)-SUMIF('BALANCE N-1'!$A$2:$A$2000,"294*",'BALANCE N-1'!$G$2:$G$2000)-SUMIF('BALANCE N-1'!$A$2:$A$2000,"2845*",'BALANCE N-1'!$H$2:$H$2000)+SUMIF('BALANCE N-1'!$A$2:$A$2000,"2845*",'BALANCE N-1'!$G$2:$G$2000)-SUMIF('BALANCE N-1'!$A$2:$A$2000,"2945*",'BALANCE N-1'!$H$2:$H$2000)+SUMIF('BALANCE N-1'!$A$2:$A$2000,"2945*",'BALANCE N-1'!$G$2:$G$2000)-SUMIF('BALANCE N-1'!$A$2:$A$2000,"2949*",'BALANCE N-1'!$H$2:$H$2000)+SUMIF('BALANCE N-1'!$A$2:$A$2000,"2949*",'BALANCE N-1'!$G$2:$G$2000)))
A22: AM | B22: Materiel de transport | D22: =(SUMIF('BALANCE N'!$A$2:$A$2000,"245*",'BALANCE N'!$G$2:$G$2000)-SUMIF('BALANCE N'!$A$2:$A$2000,"245*",'BALANCE N'!$H$2:$H$2000)+SUMIF('BALANCE N'!$A$2:$A$2000,"2495*",'BALANCE N'!$G$2:$G$2000)-SUMIF('BALANCE N'!$A$2:$A$2000,"2495*",'BALANCE N'!$H$2:$H$2000)) | E22: =(SUMIF('BALANCE N'!$A$2:$A$2000,"2845*",'BALANCE N'!$H$2:$H$2000)-SUMIF('BALANCE N'!$A$2:$A$2000,"2845*",'BALANCE N'!$G$2:$G$2000)+SUMIF('BALANCE N'!$A$2:$A$2000,"2945*",'BALANCE N'!$H$2:$H$2000)-SUMIF('BALANCE N'!$A$2:$A$2000,"2945*",'BALANCE N'!$G$2:$G$2000)+SUMIF('BALANCE N'!$A$2:$A$2000,"2949*",'BALANCE N'!$H$2:$H$2000)-SUMIF('BALANCE N'!$A$2:$A$2000,"2949*",'BALANCE N'!$G$2:$G$2000)) | F22: =D22-E22 | G22: =((SUMIF('BALANCE N-1'!$A$2:$A$2000,"245*",'BALANCE N-1'!$G$2:$G$2000)-SUMIF('BALANCE N-1'!$A$2:$A$2000,"245*",'BALANCE N-1'!$H$2:$H$2000)+SUMIF('BALANCE N-1'!$A$2:$A$2000,"2495*",'BALANCE N-1'!$G$2:$G$2000)-SUMIF('BALANCE N-1'!$A$2:$A$2000,"2495*",'BALANCE N-1'!$H$2:$H$2000)))-((SUMIF('BALANCE N-1'!$A$2:$A$2000,"2845*",'BALANCE N-1'!$H$2:$H$2000)-SUMIF('BALANCE N-1'!$A$2:$A$2000,"2845*",'BALANCE N-1'!$G$2:$G$2000)+SUMIF('BALANCE N-1'!$A$2:$A$2000,"2945*",'BALANCE N-1'!$H$2:$H$2000)-SUMIF('BALANCE N-1'!$A$2:$A$2000,"2945*",'BALANCE N-1'!$G$2:$G$2000)+SUMIF('BALANCE N-1'!$A$2:$A$2000,"2949*",'BALANCE N-1'!$H$2:$H$2000)-SUMIF('BALANCE N-1'!$A$2:$A$2000,"2949*",'BALANCE N-1'!$G$2:$G$2000)))
A23: AN | B23: Avances et acomptes verses sur immobilisations corporelles | D23: =(SUMIF('BALANCE N'!$A$2:$A$2000,"252*",'BALANCE N'!$G$2:$G$2000)-SUMIF('BALANCE N'!$A$2:$A$2000,"252*",'BALANCE N'!$H$2:$H$2000)) | E23: =(SUMIF('BALANCE N'!$A$2:$A$2000,"2952*",'BALANCE N'!$H$2:$H$2000)-SUMIF('BALANCE N'!$A$2:$A$2000,"2952*",'BALANCE N'!$G$2:$G$2000)) | F23: =D23-E23 | G23: =((SUMIF('BALANCE N-1'!$A$2:$A$2000,"252*",'BALANCE N-1'!$G$2:$G$2000)-SUMIF('BALANCE N-1'!$A$2:$A$2000,"252*",'BALANCE N-1'!$H$2:$H$2000)))-((SUMIF('BALANCE N-1'!$A$2:$A$2000,"2952*",'BALANCE N-1'!$H$2:$H$2000)-SUMIF('BALANCE N-1'!$A$2:$A$2000,"2952*",'BALANCE N-1'!$G$2:$G$2000)))
A24: AO | B24: IMMOBILISATIONS FINANCIERES | C24: note 6 | D24: =D25+D26 | E24: =E25+E26 | F24: =F25+F26 | G24: =G25+G26
A25: AX | B25: Titres de participation | D25: =(SUMIF('BALANCE N'!$A$2:$A$2000,"26*",'BALANCE N'!$G$2:$G$2000)-SUMIF('BALANCE N'!$A$2:$A$2000,"26*",'BALANCE N'!$H$2:$H$2000)) | E25: =(SUMIF('BALANCE N'!$A$2:$A$2000,"296*",'BALANCE N'!$H$2:$H$2000)-SUMIF('BALANCE N'!$A$2:$A$2000,"296*",'BALANCE N'!$G$2:$G$2000)) | F25: =D25-E25 | G25: =((SUMIF('BALANCE N-1'!$A$2:$A$2000,"26*",'BALANCE N-1'!$G$2:$G$2000)-SUMIF('BALANCE N-1'!$A$2:$A$2000,"26*",'BALANCE N-1'!$H$2:$H$2000)))-((SUMIF('BALANCE N-1'!$A$2:$A$2000,"296*",'BALANCE N-1'!$H$2:$H$2000)-SUMIF('BALANCE N-1'!$A$2:$A$2000,"296*",'BALANCE N-1'!$G$2:$G$2000)))
A26: AY | B26: Autres immobilisations financieres | D26: =(SUMIF('BALANCE N'!$A$2:$A$2000,"27*",'BALANCE N'!$G$2:$G$2000)-SUMIF('BALANCE N'!$A$2:$A$2000,"27*",'BALANCE N'!$H$2:$H$2000)) | E26: =(SUMIF('BALANCE N'!$A$2:$A$2000,"297*",'BALANCE N'!$H$2:$H$2000)-SUMIF('BALANCE N'!$A$2:$A$2000,"297*",'BALANCE N'!$G$2:$G$2000)) | F26: =D26-E26 | G26: =((SUMIF('BALANCE N-1'!$A$2:$A$2000,"27*",'BALANCE N-1'!$G$2:$G$2000)-SUMIF('BALANCE N-1'!$A$2:$A$2000,"27*",'BALANCE N-1'!$H$2:$H$2000)))-((SUMIF('BALANCE N-1'!$A$2:$A$2000,"297*",'BALANCE N-1'!$H$2:$H$2000)-SUMIF('BALANCE N-1'!$A$2:$A$2000,"297*",'BALANCE N-1'!$G$2:$G$2000)))
A27: AZ | B27: TOTAL ACTIF IMMOBILISE | D27: =D10+D13+D17+D24 | E27: =E10+E13+E17+E24 | F27: =F10+F13+F17+F24 | G27: =G10+G13+G17+G24
A28: BA | B28: Actif circulant HAO | C28: note 7 | D28: =(SUMIF('BALANCE N'!$A$2:$A$2000,"485*",'BALANCE N'!$G$2:$G$2000)-SUMIF('BALANCE N'!$A$2:$A$2000,"485*",'BALANCE N'!$H$2:$H$2000)+SUMIF('BALANCE N'!$A$2:$A$2000,"4865*",'BALANCE N'!$G$2:$G$2000)-SUMIF('BALANCE N'!$A$2:$A$2000,"4865*",'BALANCE N'!$H$2:$H$2000)) | E28: =(SUMIF('BALANCE N'!$A$2:$A$2000,"498*",'BALANCE N'!$H$2:$H$2000)-SUMIF('BALANCE N'!$A$2:$A$2000,"498*",'BALANCE N'!$G$2:$G$2000)) | F28: =D28-E28 | G28: =((SUMIF('BALANCE N-1'!$A$2:$A$2000,"485*",'BALANCE N-1'!$G$2:$G$2000)-SUMIF('BALANCE N-1'!$A$2:$A$2000,"485*",'BALANCE N-1'!$H$2:$H$2000)+SUMIF('BALANCE N-1'!$A$2:$A$2000,"4865*",'BALANCE N-1'!$G$2:$G$2000)-SUMIF('BALANCE N-1'!$A$2:$A$2000,"4865*",'BALANCE N-1'!$H$2:$H$2000)))-((SUMIF('BALANCE N-1'!$A$2:$A$2000,"498*",'BALANCE N-1'!$H$2:$H$2000)-SUMIF('BALANCE N-1'!$A$2:$A$2000,"498*",'BALANCE N-1'!$G$2:$G$2000)))
A29: BB | B29: Stocks et encours | C29: note 8 | D29: =(SUMIF('BALANCE N'!$A$2:$A$2000,"31*",'BALANCE N'!$G$2:$G$2000)-SUMIF('BALANCE N'!$A$2:$A$2000,"31*",'BALANCE N'!$H$2:$H$2000)+SUMIF('BALANCE N'!$A$2:$A$2000,"32*",'BALANCE N'!$G$2:$G$2000)-SUMIF('BALANCE N'!$A$2:$A$2000,"32*",'BALANCE N'!$H$2:$H$2000)+SUMIF('BALANCE N'!$A$2:$A$2000,"33*",'BALANCE N'!$G$2:$G$2000)-SUMIF('BALANCE N'!$A$2:$A$2000,"33*",'BALANCE N'!$H$2:$H$2000)+SUMIF('BALANCE N'!$A$2:$A$2000,"34*",'BALANCE N'!$G$2:$G$2000)-SUMIF('BALANCE N'!$A$2:$A$2000,"34*",'BALANCE N'!$H$2:$H$2000)+SUMIF('BALANCE N'!$A$2:$A$2000,"36*",'BALANCE N'!$G$2:$G$2000)-SUMIF('BALANCE N'!$A$2:$A$2000,"36*",'BALANCE N'!$H$2:$H$2000)+SUMIF('BALANCE N'!$A$2:$A$2000,"37*",'BALANCE N'!$G$2:$G$2000)-SUMIF('BALANCE N'!$A$2:$A$2000,"37*",'BALANCE N'!$H$2:$H$2000)+SUMIF('BALANCE N'!$A$2:$A$2000,"38*",'BALANCE N'!$G$2:$G$2000)-SUMIF('BALANCE N'!$A$2:$A$2000,"38*",'BALANCE N'!$H$2:$H$2000)) | E29: =(SUMIF('BALANCE N'!$A$2:$A$2000,"39*",'BALANCE N'!$H$2:$H$2000)-SUMIF('BALANCE N'!$A$2:$A$2000,"39*",'BALANCE N'!$G$2:$G$2000)) | F29: =D29-E29 | G29: =((SUMIF('BALANCE N-1'!$A$2:$A$2000,"31*",'BALANCE N-1'!$G$2:$G$2000)-SUMIF('BALANCE N-1'!$A$2:$A$2000,"31*",'BALANCE N-1'!$H$2:$H$2000)+SUMIF('BALANCE N-1'!$A$2:$A$2000,"32*",'BALANCE N-1'!$G$2:$G$2000)-SUMIF('BALANCE N-1'!$A$2:$A$2000,"32*",'BALANCE N-1'!$H$2:$H$2000)+SUMIF('BALANCE N-1'!$A$2:$A$2000,"33*",'BALANCE N-1'!$G$2:$G$2000)-SUMIF('BALANCE N-1'!$A$2:$A$2000,"33*",'BALANCE N-1'!$H$2:$H$2000)+SUMIF('BALANCE N-1'!$A$2:$A$2000,"34*",'BALANCE N-1'!$G$2:$G$2000)-SUMIF('BALANCE N-1'!$A$2:$A$2000,"34*",'BALANCE N-1'!$H$2:$H$2000)+SUMIF('BALANCE N-1'!$A$2:$A$2000,"36*",'BALANCE N-1'!$G$2:$G$2000)-SUMIF('BALANCE N-1'!$A$2:$A$2000,"36*",'BALANCE N-1'!$H$2:$H$2000)+SUMIF('BALANCE N-1'!$A$2:$A$2000,"37*",'BALANCE N-1'!$G$2:$G$2000)-SUMIF('BALANCE N-1'!$A$2:$A$2000,"37*",'BALANCE N-1'!$H$2:$H$2000)+SUMIF('BALANCE N-1'!$A$2:$A$2000,"38*",'BALANCE N-1'!$G$2:$G$2000)-SUMIF('BALANCE N-1'!$A$2:$A$2000,"38*",'BALANCE N-1'!$H$2:$H$2000)))-((SUMIF('BALANCE N-1'!$A$2:$A$2000,"39*",'BALANCE N-1'!$H$2:$H$2000)-SUMIF('BALANCE N-1'!$A$2:$A$2000,"39*",'BALANCE N-1'!$G$2:$G$2000)))
A30: BC | B30: Fournisseurs debiteurs | C30: note 19 | D30: =(SUMIF('BALANCE N'!$A$2:$A$2000,"409*",'BALANCE N'!$G$2:$G$2000)-SUMIF('BALANCE N'!$A$2:$A$2000,"409*",'BALANCE N'!$H$2:$H$2000)) | E30: =(SUMIF('BALANCE N'!$A$2:$A$2000,"490*",'BALANCE N'!$H$2:$H$2000)-SUMIF('BALANCE N'!$A$2:$A$2000,"490*",'BALANCE N'!$G$2:$G$2000)) | F30: =D30-E30 | G30: =((SUMIF('BALANCE N-1'!$A$2:$A$2000,"409*",'BALANCE N-1'!$G$2:$G$2000)-SUMIF('BALANCE N-1'!$A$2:$A$2000,"409*",'BALANCE N-1'!$H$2:$H$2000)))-((SUMIF('BALANCE N-1'!$A$2:$A$2000,"490*",'BALANCE N-1'!$H$2:$H$2000)-SUMIF('BALANCE N-1'!$A$2:$A$2000,"490*",'BALANCE N-1'!$G$2:$G$2000)))
A31: BD | B31: Adherents, Clients-usagers | C31: note 9 | D31: =(SUMIF('BALANCE N'!$A$2:$A$2000,"41*",'BALANCE N'!$G$2:$G$2000)-SUMIF('BALANCE N'!$A$2:$A$2000,"41*",'BALANCE N'!$H$2:$H$2000)-SUMIF('BALANCE N'!$A$2:$A$2000,"419*",'BALANCE N'!$G$2:$G$2000)+SUMIF('BALANCE N'!$A$2:$A$2000,"419*",'BALANCE N'!$H$2:$H$2000)) | E31: =(SUMIF('BALANCE N'!$A$2:$A$2000,"491*",'BALANCE N'!$H$2:$H$2000)-SUMIF('BALANCE N'!$A$2:$A$2000,"491*",'BALANCE N'!$G$2:$G$2000)) | F31: =D31-E31 | G31: =((SUMIF('BALANCE N-1'!$A$2:$A$2000,"41*",'BALANCE N-1'!$G$2:$G$2000)-SUMIF('BALANCE N-1'!$A$2:$A$2000,"41*",'BALANCE N-1'!$H$2:$H$2000)-SUMIF('BALANCE N-1'!$A$2:$A$2000,"419*",'BALANCE N-1'!$G$2:$G$2000)+SUMIF('BALANCE N-1'!$A$2:$A$2000,"419*",'BALANCE N-1'!$H$2:$H$2000)))-((SUMIF('BALANCE N-1'!$A$2:$A$2000,"491*",'BALANCE N-1'!$H$2:$H$2000)-SUMIF('BALANCE N-1'!$A$2:$A$2000,"491*",'BALANCE N-1'!$G$2:$G$2000)))
A32: BE | B32: Autres creances | C32: note 10 | D32: =(SUMIF('BALANCE N'!$A$2:$A$2000,"42*",'BALANCE N'!$G$2:$G$2000)+SUMIF('BALANCE N'!$A$2:$A$2000,"43*",'BALANCE N'!$G$2:$G$2000)+SUMIF('BALANCE N'!$A$2:$A$2000,"44*",'BALANCE N'!$G$2:$G$2000)+SUMIF('BALANCE N'!$A$2:$A$2000,"45*",'BALANCE N'!$G$2:$G$2000)+SUMIF('BALANCE N'!$A$2:$A$2000,"46*",'BALANCE N'!$G$2:$G$2000)+SUMIF('BALANCE N'!$A$2:$A$2000,"47*",'BALANCE N'!$G$2:$G$2000)-SUMIF('BALANCE N'!$A$2:$A$2000,"478*",'BALANCE N'!$G$2:$G$2000)) | E32: =(SUMIF('BALANCE N'!$A$2:$A$2000,"492*",'BALANCE N'!$H$2:$H$2000)-SUMIF('BALANCE N'!$A$2:$A$2000,"492*",'BALANCE N'!$G$2:$G$2000)+SUMIF('BALANCE N'!$A$2:$A$2000,"493*",'BALANCE N'!$H$2:$H$2000)-SUMIF('BALANCE N'!$A$2:$A$2000,"493*",'BALANCE N'!$G$2:$G$2000)+SUMIF('BALANCE N'!$A$2:$A$2000,"494*",'BALANCE N'!$H$2:$H$2000)-SUMIF('BALANCE N'!$A$2:$A$2000,"494*",'BALANCE N'!$G$2:$G$2000)+SUMIF('BALANCE N'!$A$2:$A$2000,"497*",'BALANCE N'!$H$2:$H$2000)-SUMIF('BALANCE N'!$A$2:$A$2000,"497*",'BALANCE N'!$G$2:$G$2000)) | F32: =D32-E32 | G32: =((SUMIF('BALANCE N-1'!$A$2:$A$2000,"42*",'BALANCE N-1'!$G$2:$G$2000)+SUMIF('BALANCE N-1'!$A$2:$A$2000,"43*",'BALANCE N-1'!$G$2:$G$2000)+SUMIF('BALANCE N-1'!$A$2:$A$2000,"44*",'BALANCE N-1'!$G$2:$G$2000)+SUMIF('BALANCE N-1'!$A$2:$A$2000,"45*",'BALANCE N-1'!$G$2:$G$2000)+SUMIF('BALANCE N-1'!$A$2:$A$2000,"46*",'BALANCE N-1'!$G$2:$G$2000)+SUMIF('BALANCE N-1'!$A$2:$A$2000,"47*",'BALANCE N-1'!$G$2:$G$2000)-SUMIF('BALANCE N-1'!$A$2:$A$2000,"478*",'BALANCE N-1'!$G$2:$G$2000)))-((SUMIF('BALANCE N-1'!$A$2:$A$2000,"492*",'BALANCE N-1'!$H$2:$H$2000)-SUMIF('BALANCE N-1'!$A$2:$A$2000,"492*",'BALANCE N-1'!$G$2:$G$2000)+SUMIF('BALANCE N-1'!$A$2:$A$2000,"493*",'BALANCE N-1'!$H$2:$H$2000)-SUMIF('BALANCE N-1'!$A$2:$A$2000,"493*",'BALANCE N-1'!$G$2:$G$2000)+SUMIF('BALANCE N-1'!$A$2:$A$2000,"494*",'BALANCE N-1'!$H$2:$H$2000)-SUMIF('BALANCE N-1'!$A$2:$A$2000,"494*",'BALANCE N-1'!$G$2:$G$2000)+SUMIF('BALANCE N-1'!$A$2:$A$2000,"497*",'BALANCE N-1'!$H$2:$H$2000)-SUMIF('BALANCE N-1'!$A$2:$A$2000,"497*",'BALANCE N-1'!$G$2:$G$2000)))
A33: BT | B33: TOTAL ACTIF CIRCULANT | D33: =D28+D29+D30+D31+D32 | E33: =E28+E29+E30+E31+E32 | F33: =F28+F29+F30+F31+F32 | G33: =G28+G29+G30+G31+G32
A34: BU | B34: Titres de placement | C34: note 11 | D34: =(SUMIF('BALANCE N'!$A$2:$A$2000,"50*",'BALANCE N'!$G$2:$G$2000)-SUMIF('BALANCE N'!$A$2:$A$2000,"50*",'BALANCE N'!$H$2:$H$2000)) | E34: =(SUMIF('BALANCE N'!$A$2:$A$2000,"590*",'BALANCE N'!$H$2:$H$2000)-SUMIF('BALANCE N'!$A$2:$A$2000,"590*",'BALANCE N'!$G$2:$G$2000)) | F34: =D34-E34 | G34: =((SUMIF('BALANCE N-1'!$A$2:$A$2000,"50*",'BALANCE N-1'!$G$2:$G$2000)-SUMIF('BALANCE N-1'!$A$2:$A$2000,"50*",'BALANCE N-1'!$H$2:$H$2000)))-((SUMIF('BALANCE N-1'!$A$2:$A$2000,"590*",'BALANCE N-1'!$H$2:$H$2000)-SUMIF('BALANCE N-1'!$A$2:$A$2000,"590*",'BALANCE N-1'!$G$2:$G$2000)))
A35: BV | B35: Valeurs a encaisser | C35: note 12 | D35: =(SUMIF('BALANCE N'!$A$2:$A$2000,"51*",'BALANCE N'!$G$2:$G$2000)-SUMIF('BALANCE N'!$A$2:$A$2000,"51*",'BALANCE N'!$H$2:$H$2000)) | E35: =(SUMIF('BALANCE N'!$A$2:$A$2000,"591*",'BALANCE N'!$H$2:$H$2000)-SUMIF('BALANCE N'!$A$2:$A$2000,"591*",'BALANCE N'!$G$2:$G$2000)) | F35: =D35-E35 | G35: =((SUMIF('BALANCE N-1'!$A$2:$A$2000,"51*",'BALANCE N-1'!$G$2:$G$2000)-SUMIF('BALANCE N-1'!$A$2:$A$2000,"51*",'BALANCE N-1'!$H$2:$H$2000)))-((SUMIF('BALANCE N-1'!$A$2:$A$2000,"591*",'BALANCE N-1'!$H$2:$H$2000)-SUMIF('BALANCE N-1'!$A$2:$A$2000,"591*",'BALANCE N-1'!$G$2:$G$2000)))
A36: BW | B36: Banques, etablissements financiers, caisses et assimiles | C36: note 13 | D36: =(SUMIF('BALANCE N'!$A$2:$A$2000,"52*",'BALANCE N'!$G$2:$G$2000)-SUMIF('BALANCE N'!$A$2:$A$2000,"52*",'BALANCE N'!$H$2:$H$2000)+SUMIF('BALANCE N'!$A$2:$A$2000,"53*",'BALANCE N'!$G$2:$G$2000)-SUMIF('BALANCE N'!$A$2:$A$2000,"53*",'BALANCE N'!$H$2:$H$2000)+SUMIF('BALANCE N'!$A$2:$A$2000,"55*",'BALANCE N'!$G$2:$G$2000)-SUMIF('BALANCE N'!$A$2:$A$2000,"55*",'BALANCE N'!$H$2:$H$2000)+SUMIF('BALANCE N'!$A$2:$A$2000,"57*",'BALANCE N'!$G$2:$G$2000)-SUMIF('BALANCE N'!$A$2:$A$2000,"57*",'BALANCE N'!$H$2:$H$2000)) | E36: =(SUMIF('BALANCE N'!$A$2:$A$2000,"592*",'BALANCE N'!$H$2:$H$2000)-SUMIF('BALANCE N'!$A$2:$A$2000,"592*",'BALANCE N'!$G$2:$G$2000)+SUMIF('BALANCE N'!$A$2:$A$2000,"593*",'BALANCE N'!$H$2:$H$2000)-SUMIF('BALANCE N'!$A$2:$A$2000,"593*",'BALANCE N'!$G$2:$G$2000)+SUMIF('BALANCE N'!$A$2:$A$2000,"595*",'BALANCE N'!$H$2:$H$2000)-SUMIF('BALANCE N'!$A$2:$A$2000,"595*",'BALANCE N'!$G$2:$G$2000)) | F36: =D36-E36 | G36: =((SUMIF('BALANCE N-1'!$A$2:$A$2000,"52*",'BALANCE N-1'!$G$2:$G$2000)-SUMIF('BALANCE N-1'!$A$2:$A$2000,"52*",'BALANCE N-1'!$H$2:$H$2000)+SUMIF('BALANCE N-1'!$A$2:$A$2000,"53*",'BALANCE N-1'!$G$2:$G$2000)-SUMIF('BALANCE N-1'!$A$2:$A$2000,"53*",'BALANCE N-1'!$H$2:$H$2000)+SUMIF('BALANCE N-1'!$A$2:$A$2000,"55*",'BALANCE N-1'!$G$2:$G$2000)-SUMIF('BALANCE N-1'!$A$2:$A$2000,"55*",'BALANCE N-1'!$H$2:$H$2000)+SUMIF('BALANCE N-1'!$A$2:$A$2000,"57*",'BALANCE N-1'!$G$2:$G$2000)-SUMIF('BALANCE N-1'!$A$2:$A$2000,"57*",'BALANCE N-1'!$H$2:$H$2000)))-((SUMIF('BALANCE N-1'!$A$2:$A$2000,"592*",'BALANCE N-1'!$H$2:$H$2000)-SUMIF('BALANCE N-1'!$A$2:$A$2000,"592*",'BALANCE N-1'!$G$2:$G$2000)+SUMIF('BALANCE N-1'!$A$2:$A$2000,"593*",'BALANCE N-1'!$H$2:$H$2000)-SUMIF('BALANCE N-1'!$A$2:$A$2000,"593*",'BALANCE N-1'!$G$2:$G$2000)+SUMIF('BALANCE N-1'!$A$2:$A$2000,"595*",'BALANCE N-1'!$H$2:$H$2000)-SUMIF('BALANCE N-1'!$A$2:$A$2000,"595*",'BALANCE N-1'!$G$2:$G$2000)))
A37: BX | B37: TOTAL TRESORERIE ACTIF | D37: =D34+D35+D36 | E37: =E34+E35+E36 | F37: =F34+F35+F36 | G37: =G34+G35+G36
A38: BY | B38: Ecart de conversion-Actif | C38: note 14 | D38: =(SUMIF('BALANCE N'!$A$2:$A$2000,"478*",'BALANCE N'!$G$2:$G$2000)-SUMIF('BALANCE N'!$A$2:$A$2000,"478*",'BALANCE N'!$H$2:$H$2000)) | E38: 0 | F38: =D38-E38 | G38: =((SUMIF('BALANCE N-1'!$A$2:$A$2000,"478*",'BALANCE N-1'!$G$2:$G$2000)-SUMIF('BALANCE N-1'!$A$2:$A$2000,"478*",'BALANCE N-1'!$H$2:$H$2000)))-(0)
A39: BZ | B39: TOTAL GENERAL | D39: =D27+D33+D37+D38 | E39: =E27+E33+E37+E38 | F39: =F27+F33+F37+F38 | G39: =G27+G33+G37+G38

Sheet Bilan-Passif
A1: - 5 -
D2: BILAN SYSTEME NORMAL PAGE 2/2
A3: Dénomination sociale :
A4: Adresse : | D4: Sigle usuel :
A5: N° de compte contribuable (NCC) : | C5: Exercice clos le | D5: Durée (en mois) : 12
A6: N° de télédéclarant (NTD) :
B7: BILAN
A8: REF | B8: PASSIF | C8: NOTE | D8: EXERCICE AU 31/12/N | E8: EXERCICE AU 31/12/N-1
D9: NET | E9: NET
A10: CA | B10: Donation non consomptible sans droit reprise | C10: note 15 | D10: =(SUMIF('BALANCE N'!$A$2:$A$2000,"101*",'BALANCE N'!$H$2:$H$2000)-SUMIF('BALANCE N'!$A$2:$A$2000,"101*",'BALANCE N'!$G$2:$G$2000)) | E10: =(SUMIF('BALANCE N-1'!$A$2:$A$2000,"101*",'BALANCE N-1'!$H$2:$H$2000)-SUMIF('BALANCE N-1'!$A$2:$A$2000,"101*",'BALANCE N-1'!$G$2:$G$2000))
A11: CB | B11: Donation non consomptible avec droit reprise | C11: note 15 | D11: =(SUMIF('BALANCE N'!$A$2:$A$2000,"102*",'BALANCE N'!$H$2:$H$2000)-SUMIF('BALANCE N'!$A$2:$A$2000,"102*",'BALANCE N'!$G$2:$G$2000)) | E11: =(SUMIF('BALANCE N-1'!$A$2:$A$2000,"102*",'BALANCE N-1'!$H$2:$H$2000)-SUMIF('BALANCE N-1'!$A$2:$A$2000,"102*",'BALANCE N-1'!$G$2:$G$2000))
A12: CC | B12: Droit d'entree | C12: note 15 | D12: =(SUMIF('BALANCE N'!$A$2:$A$2000,"103*",'BALANCE N'!$H$2:$H$2000)-SUMIF('BALANCE N'!$A$2:$A$2000,"103*",'BALANCE N'!$G$2:$G$2000)) | E12: =(SUMIF('BALANCE N-1'!$A$2:$A$2000,"103*",'BALANCE N-1'!$H$2:$H$2000)-SUMIF('BALANCE N-1'!$A$2:$A$2000,"103*",'BALANCE N-1'!$G$2:$G$2000))
A13: CD | B13: Donation consomptible | C13: note 15 | D13: =(SUMIF('BALANCE N'!$A$2:$A$2000,"104*",'BALANCE N'!$H$2:$H$2000)-SUMIF('BALANCE N'!$A$2:$A$2000,"104*",'BALANCE N'!$G$2:$G$2000)) | E13: =(SUMIF('BALANCE N-1'!$A$2:$A$2000,"104*",'BALANCE N-1'!$H$2:$H$2000)-SUMIF('BALANCE N-1'!$A$2:$A$2000,"104*",'BALANCE N-1'!$G$2:$G$2000))
A14: CE | B14: Ecarts de reevaluation | C14: note 5F | D14: =(SUMIF('BALANCE N'!$A$2:$A$2000,"106*",'BALANCE N'!$H$2:$H$2000)-SUMIF('BALANCE N'!$A$2:$A$2000,"106*",'BALANCE N'!$G$2:$G$2000)) | E14: =(SUMIF('BALANCE N-1'!$A$2:$A$2000,"106*",'BALANCE N-1'!$H$2:$H$2000)-SUMIF('BALANCE N-1'!$A$2:$A$2000,"106*",'BALANCE N-1'!$G$2:$G$2000))
A15: CF | B15: Reserves | C15: note 16 | D15: =(SUMIF('BALANCE N'!$A$2:$A$2000,"11*",'BALANCE N'!$H$2:$H$2000)-SUMIF('BALANCE N'!$A$2:$A$2000,"11*",'BALANCE N'!$G$2:$G$2000)) | E15: =(SUMIF('BALANCE N-1'!$A$2:$A$2000,"11*",'BALANCE N-1'!$H$2:$H$2000)-SUMIF('BALANCE N-1'!$A$2:$A$2000,"11*",'BALANCE N-1'!$G$2:$G$2000))
A16: CG | B16: Report a nouveau (+ ou -) | C16: note 16 | D16: =(SUMIF('BALANCE N'!$A$2:$A$2000,"12*",'BALANCE N'!$H$2:$H$2000)-SUMIF('BALANCE N'!$A$2:$A$2000,"12*",'BALANCE N'!$G$2:$G$2000)) | E16: =(SUMIF('BALANCE N-1'!$A$2:$A$2000,"12*",'BALANCE N-1'!$H$2:$H$2000)-SUMIF('BALANCE N-1'!$A$2:$A$2000,"12*",'BALANCE N-1'!$G$2:$G$2000))
A17: CH | B17: Resultat net de l'exercice (excedent + ou deficit -) | D17: ='Résultat'!D36+(SUMIF('BALANCE N'!$A$2:$A$2000,"13*",'BALANCE N'!$H$2:$H$2000)-SUMIF('BALANCE N'!$A$2:$A$2000,"13*",'BALANCE N'!$G$2:$G$2000)) | E17: ='Résultat'!E36+(SUMIF('BALANCE N-1'!$A$2:$A$2000,"13*",'BALANCE N-1'!$H$2:$H$2000)-SUMIF('BALANCE N-1'!$A$2:$A$2000,"13*",'BALANCE N-1'!$G$2:$G$2000))
A18: CI | B18: Subventions d'investissement | C18: note 17A | D18: =(SUMIF('BALANCE N'!$A$2:$A$2000,"14*",'BALANCE N'!$H$2:$H$2000)-SUMIF('BALANCE N'!$A$2:$A$2000,"14*",'BALANCE N'!$G$2:$G$2000)) | E18: =(SUMIF('BALANCE N-1'!$A$2:$A$2000,"14*",'BALANCE N-1'!$H$2:$H$2000)-SUMIF('BALANCE N-1'!$A$2:$A$2000,"14*",'BALANCE N-1'!$G$2:$G$2000))
A19: CJ | B19: Provisions reglementees | C19: note 17A | D19: =(SUMIF('BALANCE N'!$A$2:$A$2000,"15*",'BALANCE N'!$H$2:$H$2000)-SUMIF('BALANCE N'!$A$2:$A$2000,"15*",'BALANCE N'!$G$2:$G$2000)) | E19: =(SUMIF('BALANCE N-1'!$A$2:$A$2000,"15*",'BALANCE N-1'!$H$2:$H$2000)-SUMIF('BALANCE N-1'!$A$2:$A$2000,"15*",'BALANCE N-1'!$G$2:$G$2000))
A20: CK | B20: TOTAL FONDS PROPRES ET ASSIMILES | D20: =D10+D11+D12+D13+D14+D15+D16+D17+D18+D19 | E20: =E10+E11+E12+E13+E14+E15+E16+E17+E18+E19
A21: CW | B21: Fonds affectes et provenant de dons et legs d'immobilisations | C21: note 17B | D21: =(SUMIF('BALANCE N'!$A$2:$A$2000,"16*",'BALANCE N'!$H$2:$H$2000)-SUMIF('BALANCE N'!$A$2:$A$2000,"16*",'BALANCE N'!$G$2:$G$2000)) | E21: =(SUMIF('BALANCE N-1'!$A$2:$A$2000,"16*",'BALANCE N-1'!$H$2:$H$2000)-SUMIF('BALANCE N-1'!$A$2:$A$2000,"16*",'BALANCE N-1'!$G$2:$G$2000))
A22: CX | B22: Fonds reportes | C22: note 17B | D22: =(SUMIF('BALANCE N'!$A$2:$A$2000,"17*",'BALANCE N'!$H$2:$H$2000)-SUMIF('BALANCE N'!$A$2:$A$2000,"17*",'BALANCE N'!$G$2:$G$2000)) | E22: =(SUMIF('BALANCE N-1'!$A$2:$A$2000,"17*",'BALANCE N-1'!$H$2:$H$2000)-SUMIF('BALANCE N-1'!$A$2:$A$2000,"17*",'BALANCE N-1'!$G$2:$G$2000))
A23: CY | B23: TOTAL FONDS AFFECTES ET REPORTES | D23: =D21+D22 | E23: =E21+E22
A24: CZ | B24: TOTAL RESSOURCES PROPRES ET ASSIMILEES | D24: =D20+D23 | E24: =E20+E23
A25: DA | B25: Emprunts et dettes financieres | C25: note 18A | D25: =(SUMIF('BALANCE N'!$A$2:$A$2000,"181*",'BALANCE N'!$H$2:$H$2000)-SUMIF('BALANCE N'!$A$2:$A$2000,"181*",'BALANCE N'!$G$2:$G$2000)+SUMIF('BALANCE N'!$A$2:$A$2000,"182*",'BALANCE N'!$H$2:$H$2000)-SUMIF('BALANCE N'!$A$2:$A$2000,"182*",'BALANCE N'!$G$2:$G$2000)+SUMIF('BALANCE N'!$A$2:$A$2000,"183*",'BALANCE N'!$H$2:$H$2000)-SUMIF('BALANCE N'!$A$2:$A$2000,"183*",'BALANCE N'!$G$2:$G$2000)+SUMIF('BALANCE N'!$A$2:$A$2000,"185*",'BALANCE N'!$H$2:$H$2000)-SUMIF('BALANCE N'!$A$2:$A$2000,"185*",'BALANCE N'!$G$2:$G$2000)+SUMIF('BALANCE N'!$A$2:$A$2000,"186*",'BALANCE N'!$H$2:$H$2000)-SUMIF('BALANCE N'!$A$2:$A$2000,"186*",'BALANCE N'!$G$2:$G$2000)+SUMIF('BALANCE N'!$A$2:$A$2000,"188*",'BALANCE N'!$H$2:$H$2000)-SUMIF('BALANCE N'!$A$2:$A$2000,"188*",'BALANCE N'!$G$2:$G$2000)) | E25: =(SUMIF('BALANCE N-1'!$A$2:$A$2000,"181*",'BALANCE N-1'!$H$2:$H$2000)-SUMIF('BALANCE N-1'!$A$2:$A$2000,"181*",'BALANCE N-1'!$G$2:$G$2000)+SUMIF('BALANCE N-1'!$A$2:$A$2000,"182*",'BALANCE N-1'!$H$2:$H$2000)-SUMIF('BALANCE N-1'!$A$2:$A$2000,"182*",'BALANCE N-1'!$G$2:$G$2000)+SUMIF('BALANCE N-1'!$A$2:$A$2000,"183*",'BALANCE N-1'!$H$2:$H$2000)-SUMIF('BALANCE N-1'!$A$2:$A$2000,"183*",'BALANCE N-1'!$G$2:$G$2000)+SUMIF('BALANCE N-1'!$A$2:$A$2000,"185*",'BALANCE N-1'!$H$2:$H$2000)-SUMIF('BALANCE N-1'!$A$2:$A$2000,"185*",'BALANCE N-1'!$G$2:$G$2000)+SUMIF('BALANCE N-1'!$A$2:$A$2000,"186*",'BALANCE N-1'!$H$2:$H$2000)-SUMIF('BALANCE N-1'!$A$2:$A$2000,"186*",'BALANCE N-1'!$G$2:$G$2000)+SUMIF('BALANCE N-1'!$A$2:$A$2000,"188*",'BALANCE N-1'!$H$2:$H$2000)-SUMIF('BALANCE N-1'!$A$2:$A$2000,"188*",'BALANCE N-1'!$G$2:$G$2000))
A26: DB | B26: Dettes de location-acquisition | C26: note 18A | D26: =(SUMIF('BALANCE N'!$A$2:$A$2000,"187*",'BALANCE N'!$H$2:$H$2000)-SUMIF('BALANCE N'!$A$2:$A$2000,"187*",'BALANCE N'!$G$2:$G$2000)) | E26: =(SUMIF('BALANCE N-1'!$A$2:$A$2000,"187*",'BALANCE N-1'!$H$2:$H$2000)-SUMIF('BALANCE N-1'!$A$2:$A$2000,"187*",'BALANCE N-1'!$G$2:$G$2000))
A27: DC | B27: Provisions pour risques et charges | C27: note 18A | D27: =(SUMIF('BALANCE N'!$A$2:$A$2000,"19*",'BALANCE N'!$H$2:$H$2000)-SUMIF('BALANCE N'!$A$2:$A$2000,"19*",'BALANCE N'!$G$2:$G$2000)) | E27: =(SUMIF('BALANCE N-1'!$A$2:$A$2000,"19*",'BALANCE N-1'!$H$2:$H$2000)-SUMIF('BALANCE N-1'!$A$2:$A$2000,"19*",'BALANCE N-1'!$G$2:$G$2000))
A28: DD | B28: TOTAL DETTES FINANCIERES ET RESSOURCES ASSIMILEES | D28: =D25+D26+D27 | E28: =E25+E26+E27
A29: DE | B29: TOTAL RESSOURCES STABLES | D29: =D24+D28 | E29: =E24+E28
A30: DF | B30: Dettes circulantes HAO | C30: note 7 | D30: =(SUMIF('BALANCE N'!$A$2:$A$2000,"481*",'BALANCE N'!$H$2:$H$2000)-SUMIF('BALANCE N'!$A$2:$A$2000,"481*",'BALANCE N'!$G$2:$G$2000)+SUMIF('BALANCE N'!$A$2:$A$2000,"484*",'BALANCE N'!$H$2:$H$2000)-SUMIF('BALANCE N'!$A$2:$A$2000,"484*",'BALANCE N'!$G$2:$G$2000)+SUMIF('BALANCE N'!$A$2:$A$2000,"488*",'BALANCE N'!$H$2:$H$2000)-SUMIF('BALANCE N'!$A$2:$A$2000,"488*",'BALANCE N'!$G$2:$G$2000)+SUMIF('BALANCE N'!$A$2:$A$2000,"4861*",'BALANCE N'!$H$2:$H$2000)-SUMIF('BALANCE N'!$A$2:$A$2000,"4861*",'BALANCE N'!$G$2:$G$2000)+SUMIF('BALANCE N'!$A$2:$A$2000,"4998*",'BALANCE N'!$H$2:$H$2000)-SUMIF('BALANCE N'!$A$2:$A$2000,"4998*",'BALANCE N'!$G$2:$G$2000)) | E30: =(SUMIF('BALANCE N-1'!$A$2:$A$2000,"481*",'BALANCE N-1'!$H$2:$H$2000)-SUMIF('BALANCE N-1'!$A$2:$A$2000,"481*",'BALANCE N-1'!$G$2:$G$2000)+SUMIF('BALANCE N-1'!$A$2:$A$2000,"484*",'BALANCE N-1'!$H$2:$H$2000)-SUMIF('BALANCE N-1'!$A$2:$A$2000,"484*",'BALANCE N-1'!$G$2:$G$2000)+SUMIF('BALANCE N-1'!$A$2:$A$2000,"488*",'BALANCE N-1'!$H$2:$H$2000)-SUMIF('BALANCE N-1'!$A$2:$A$2000,"488*",'BALANCE N-1'!$G$2:$G$2000)+SUMIF('BALANCE N-1'!$A$2:$A$2000,"4861*",'BALANCE N-1'!$H$2:$H$2000)-SUMIF('BALANCE N-1'!$A$2:$A$2000,"4861*",'BALANCE N-1'!$G$2:$G$2000)+SUMIF('BALANCE N-1'!$A$2:$A$2000,"4998*",'BALANCE N-1'!$H$2:$H$2000)-SUMIF('BALANCE N-1'!$A$2:$A$2000,"4998*",'BALANCE N-1'!$G$2:$G$2000))
A31: DG | B31: Adherents, clients-usagers crediteurs | C31: note 9 | D31: =(SUMIF('BALANCE N'!$A$2:$A$2000,"419*",'BALANCE N'!$H$2:$H$2000)-SUMIF('BALANCE N'!$A$2:$A$2000,"419*",'BALANCE N'!$G$2:$G$2000)) | E31: =(SUMIF('BALANCE N-1'!$A$2:$A$2000,"419*",'BALANCE N-1'!$H$2:$H$2000)-SUMIF('BALANCE N-1'!$A$2:$A$2000,"419*",'BALANCE N-1'!$G$2:$G$2000))
A32: DH | B32: Fournisseurs | C32: note 19 | D32: =(SUMIF('BALANCE N'!$A$2:$A$2000,"40*",'BALANCE N'!$H$2:$H$2000)-SUMIF('BALANCE N'!$A$2:$A$2000,"40*",'BALANCE N'!$G$2:$G$2000)-SUMIF('BALANCE N'!$A$2:$A$2000,"409*",'BALANCE N'!$H$2:$H$2000)+SUMIF('BALANCE N'!$A$2:$A$2000,"409*",'BALANCE N'!$G$2:$G$2000)) | E32: =(SUMIF('BALANCE N-1'!$A$2:$A$2000,"40*",'BALANCE N-1'!$H$2:$H$2000)-SUMIF('BALANCE N-1'!$A$2:$A$2000,"40*",'BALANCE N-1'!$G$2:$G$2000)-SUMIF('BALANCE N-1'!$A$2:$A$2000,"409*",'BALANCE N-1'!$H$2:$H$2000)+SUMIF('BALANCE N-1'!$A$2:$A$2000,"409*",'BALANCE N-1'!$G$2:$G$2000))
A33: DI | B33: Autres dettes | C33: note 20 et 21 | D33: =(SUMIF('BALANCE N'!$A$2:$A$2000,"42*",'BALANCE N'!$H$2:$H$2000)+SUMIF('BALANCE N'!$A$2:$A$2000,"43*",'BALANCE N'!$H$2:$H$2000)+SUMIF('BALANCE N'!$A$2:$A$2000,"44*",'BALANCE N'!$H$2:$H$2000)+SUMIF('BALANCE N'!$A$2:$A$2000,"45*",'BALANCE N'!$H$2:$H$2000)+SUMIF('BALANCE N'!$A$2:$A$2000,"46*",'BALANCE N'!$H$2:$H$2000)+SUMIF('BALANCE N'!$A$2:$A$2000,"47*",'BALANCE N'!$H$2:$H$2000)+SUMIF('BALANCE N'!$A$2:$A$2000,"499*",'BALANCE N'!$H$2:$H$2000)+SUMIF('BALANCE N'!$A$2:$A$2000,"599*",'BALANCE N'!$H$2:$H$2000)-SUMIF('BALANCE N'!$A$2:$A$2000,"479*",'BALANCE N'!$H$2:$H$2000)-SUMIF('BALANCE N'!$A$2:$A$2000,"4998*",'BALANCE N'!$H$2:$H$2000)) | E33: =(SUMIF('BALANCE N-1'!$A$2:$A$2000,"42*",'BALANCE N-1'!$H$2:$H$2000)+SUMIF('BALANCE N-1'!$A$2:$A$2000,"43*",'BALANCE N-1'!$H$2:$H$2000)+SUMIF('BALANCE N-1'!$A$2:$A$2000,"44*",'BALANCE N-1'!$H$2:$H$2000)+SUMIF('BALANCE N-1'!$A$2:$A$2000,"45*",'BALANCE N-1'!$H$2:$H$2000)+SUMIF('BALANCE N-1'!$A$2:$A$2000,"46*",'BALANCE N-1'!$H$2:$H$2000)+SUMIF('BALANCE N-1'!$A$2:$A$2000,"47*",'BALANCE N-1'!$H$2:$H$2000)+SUMIF('BALANCE N-1'!$A$2:$A$2000,"499*",'BALANCE N-1'!$H$2:$H$2000)+SUMIF('BALANCE N-1'!$A$2:$A$2000,"599*",'BALANCE N-1'!$H$2:$H$2000)-SUMIF('BALANCE N-1'!$A$2:$A$2000,"479*",'BALANCE N-1'!$H$2:$H$2000)-SUMIF('BALANCE N-1'!$A$2:$A$2000,"4998*",'BALANCE N-1'!$H$2:$H$2000))
A34: DV | B34: TOTAL PASSIF CIRCULANT | D34: =D30+D31+D32+D33 | E34: =E30+E31+E32+E33
A35: DW | B35: Banques, etablissements financiers et credits de tresorerie | C35: note 22 | D35: =(SUMIF('BALANCE N'!$A$2:$A$2000,"564*",'BALANCE N'!$H$2:$H$2000)-SUMIF('BALANCE N'!$A$2:$A$2000,"564*",'BALANCE N'!$G$2:$G$2000)+SUMIF('BALANCE N'!$A$2:$A$2000,"565*",'BALANCE N'!$H$2:$H$2000)-SUMIF('BALANCE N'!$A$2:$A$2000,"565*",'BALANCE N'!$G$2:$G$2000))+(SUMIF('BALANCE N'!$A$2:$A$2000,"52*",'BALANCE N'!$H$2:$H$2000)+SUMIF('BALANCE N'!$A$2:$A$2000,"53*",'BALANCE N'!$H$2:$H$2000)) | E35: =(SUMIF('BALANCE N-1'!$A$2:$A$2000,"564*",'BALANCE N-1'!$H$2:$H$2000)-SUMIF('BALANCE N-1'!$A$2:$A$2000,"564*",'BALANCE N-1'!$G$2:$G$2000)+SUMIF('BALANCE N-1'!$A$2:$A$2000,"565*",'BALANCE N-1'!$H$2:$H$2000)-SUMIF('BALANCE N-1'!$A$2:$A$2000,"565*",'BALANCE N-1'!$G$2:$G$2000))+(SUMIF('BALANCE N-1'!$A$2:$A$2000,"52*",'BALANCE N-1'!$H$2:$H$2000)+SUMIF('BALANCE N-1'!$A$2:$A$2000,"53*",'BALANCE N-1'!$H$2:$H$2000))
A36: DX | B36: TOTAL TRESORERIE PASSIF | D36: =D35 | E36: =E35
A37: DY | B37: Ecart de conversion-Passif | C37: note 14 | D37: =(SUMIF('BALANCE N'!$A$2:$A$2000,"479*",'BALANCE N'!$H$2:$H$2000)-SUMIF('BALANCE N'!$A$2:$A$2000,"479*",'BALANCE N'!$G$2:$G$2000)) | E37: =(SUMIF('BALANCE N-1'!$A$2:$A$2000,"479*",'BALANCE N-1'!$H$2:$H$2000)-SUMIF('BALANCE N-1'!$A$2:$A$2000,"479*",'BALANCE N-1'!$G$2:$G$2000))
A38: DZ | B38: TOTAL GENERAL | D38: =D29+D34+D36+D37 | E38: =E29+E34+E36+E37

Sheet Résultat
A1: - 6 -
D2: COMPTE DE RESULTAT SYSTEME NORMAL
A3: Dénomination sociale :
A4: Adresse : | D4: Sigle usuel :
A5: N° de compte contribuable (NCC) : | C5: Exercice clos le | D5: Durée (en mois) : 12
A6: N° de télédéclarant (NTD) :
B7: COMPTE DE RESULTAT
A8: REF | B8: LIBELLES | C8: NOTE | D8: EXERCICE AU 31/12/N | E8: EXERCICE AU 31/12/N-1
D9: NET | E9: NET
A10: RA | B10: Cotisations | C10: note 23 | D10: =(SUMIF('BALANCE N'!$A$2:$A$2000,"701*",'BALANCE N'!$H$2:$H$2000)-SUMIF('BALANCE N'!$A$2:$A$2000,"701*",'BALANCE N'!$G$2:$G$2000)) | E10: =(SUMIF('BALANCE N-1'!$A$2:$A$2000,"701*",'BALANCE N-1'!$H$2:$H$2000)-SUMIF('BALANCE N-1'!$A$2:$A$2000,"701*",'BALANCE N-1'!$G$2:$G$2000))
A11: RB | B11: Dotations consomptibles transferees au compte de resultat | C11: note 23 | D11: =(SUMIF('BALANCE N'!$A$2:$A$2000,"703*",'BALANCE N'!$H$2:$H$2000)-SUMIF('BALANCE N'!$A$2:$A$2000,"703*",'BALANCE N'!$G$2:$G$2000)) | E11: =(SUMIF('BALANCE N-1'!$A$2:$A$2000,"703*",'BALANCE N-1'!$H$2:$H$2000)-SUMIF('BALANCE N-1'!$A$2:$A$2000,"703*",'BALANCE N-1'!$G$2:$G$2000))
A12: RC | B12: Revenus lies a la generosite | C12: note 23 | D12: =(SUMIF('BALANCE N'!$A$2:$A$2000,"704*",'BALANCE N'!$H$2:$H$2000)-SUMIF('BALANCE N'!$A$2:$A$2000,"704*",'BALANCE N'!$G$2:$G$2000)) | E12: =(SUMIF('BALANCE N-1'!$A$2:$A$2000,"704*",'BALANCE N-1'!$H$2:$H$2000)-SUMIF('BALANCE N-1'!$A$2:$A$2000,"704*",'BALANCE N-1'!$G$2:$G$2000))
A13: RD | B13: Ventes de marchandises | C13: note 23 | D13: =(SUMIF('BALANCE N'!$A$2:$A$2000,"7051*",'BALANCE N'!$H$2:$H$2000)-SUMIF('BALANCE N'!$A$2:$A$2000,"7051*",'BALANCE N'!$G$2:$G$2000)) | E13: =(SUMIF('BALANCE N-1'!$A$2:$A$2000,"7051*",'BALANCE N-1'!$H$2:$H$2000)-SUMIF('BALANCE N-1'!$A$2:$A$2000,"7051*",'BALANCE N-1'!$G$2:$G$2000))
A14: RE | B14: Ventes de services et produits finis | C14: note 23 | D14: =(SUMIF('BALANCE N'!$A$2:$A$2000,"7052*",'BALANCE N'!$H$2:$H$2000)-SUMIF('BALANCE N'!$A$2:$A$2000,"7052*",'BALANCE N'!$G$2:$G$2000)+SUMIF('BALANCE N'!$A$2:$A$2000,"7053*",'BALANCE N'!$H$2:$H$2000)-SUMIF('BALANCE N'!$A$2:$A$2000,"7053*",'BALANCE N'!$G$2:$G$2000)) | E14: =(SUMIF('BALANCE N-1'!$A$2:$A$2000,"7052*",'BALANCE N-1'!$H$2:$H$2000)-SUMIF('BALANCE N-1'!$A$2:$A$2000,"7052*",'BALANCE N-1'!$G$2:$G$2000)+SUMIF('BALANCE N-1'!$A$2:$A$2000,"7053*",'BALANCE N-1'!$H$2:$H$2000)-SUMIF('BALANCE N-1'!$A$2:$A$2000,"7053*",'BALANCE N-1'!$G$2:$G$2000))
A15: RF | B15: Subventions d'exploitation | C15: note 23 | D15: =(SUMIF('BALANCE N'!$A$2:$A$2000,"71*",'BALANCE N'!$H$2:$H$2000)-SUMIF('BALANCE N'!$A$2:$A$2000,"71*",'BALANCE N'!$G$2:$G$2000)) | E15: =(SUMIF('BALANCE N-1'!$A$2:$A$2000,"71*",'BALANCE N-1'!$H$2:$H$2000)-SUMIF('BALANCE N-1'!$A$2:$A$2000,"71*",'BALANCE N-1'!$G$2:$G$2000))
A16: RG | B16: Autres produits et transferts de charges | C16: note 23 | D16: =(SUMIF('BALANCE N'!$A$2:$A$2000,"72*",'BALANCE N'!$H$2:$H$2000)-SUMIF('BALANCE N'!$A$2:$A$2000,"72*",'BALANCE N'!$G$2:$G$2000)+SUMIF('BALANCE N'!$A$2:$A$2000,"73*",'BALANCE N'!$H$2:$H$2000)-SUMIF('BALANCE N'!$A$2:$A$2000,"73*",'BALANCE N'!$G$2:$G$2000)+SUMIF('BALANCE N'!$A$2:$A$2000,"75*",'BALANCE N'!$H$2:$H$2000)-SUMIF('BALANCE N'!$A$2:$A$2000,"75*",'BALANCE N'!$G$2:$G$2000)+SUMIF('BALANCE N'!$A$2:$A$2000,"77*",'BALANCE N'!$H$2:$H$2000)-SUMIF('BALANCE N'!$A$2:$A$2000,"77*",'BALANCE N'!$G$2:$G$2000)+SUMIF('BALANCE N'!$A$2:$A$2000,"78*",'BALANCE N'!$H$2:$H$2000)-SUMIF('BALANCE N'!$A$2:$A$2000,"78*",'BALANCE N'!$G$2:$G$2000)+SUMIF('BALANCE N'!$A$2:$A$2000,"706*",'BALANCE N'!$H$2:$H$2000)-SUMIF('BALANCE N'!$A$2:$A$2000,"706*",'BALANCE N'!$G$2:$G$2000)+SUMIF('BALANCE N'!$A$2:$A$2000,"707*",'BALANCE N'!$H$2:$H$2000)-SUMIF('BALANCE N'!$A$2:$A$2000,"707*",'BALANCE N'!$G$2:$G$2000)+SUMIF('BALANCE N'!$A$2:$A$2000,"708*",'BALANCE N'!$H$2:$H$2000)-SUMIF('BALANCE N'!$A$2:$A$2000,"708*",'BALANCE N'!$G$2:$G$2000)) | E16: =(SUMIF('BALANCE N-1'!$A$2:$A$2000,"72*",'BALANCE N-1'!$H$2:$H$2000)-SUMIF('BALANCE N-1'!$A$2:$A$2000,"72*",'BALANCE N-1'!$G$2:$G$2000)+SUMIF('BALANCE N-1'!$A$2:$A$2000,"73*",'BALANCE N-1'!$H$2:$H$2000)-SUMIF('BALANCE N-1'!$A$2:$A$2000,"73*",'BALANCE N-1'!$G$2:$G$2000)+SUMIF('BALANCE N-1'!$A$2:$A$2000,"75*",'BALANCE N-1'!$H$2:$H$2000)-SUMIF('BALANCE N-1'!$A$2:$A$2000,"75*",'BALANCE N-1'!$G$2:$G$2000)+SUMIF('BALANCE N-1'!$A$2:$A$2000,"77*",'BALANCE N-1'!$H$2:$H$2000)-SUMIF('BALANCE N-1'!$A$2:$A$2000,"77*",'BALANCE N-1'!$G$2:$G$2000)+SUMIF('BALANCE N-1'!$A$2:$A$2000,"78*",'BALANCE N-1'!$H$2:$H$2000)-SUMIF('BALANCE N-1'!$A$2:$A$2000,"78*",'BALANCE N-1'!$G$2:$G$2000)+SUMIF('BALANCE N-1'!$A$2:$A$2000,"706*",'BALANCE N-1'!$H$2:$H$2000)-SUMIF('BALANCE N-1'!$A$2:$A$2000,"706*",'BALANCE N-1'!$G$2:$G$2000)+SUMIF('BALANCE N-1'!$A$2:$A$2000,"707*",'BALANCE N-1'!$H$2:$H$2000)-SUMIF('BALANCE N-1'!$A$2:$A$2000,"707*",'BALANCE N-1'!$G$2:$G$2000)+SUMIF('BALANCE N-1'!$A$2:$A$2000,"708*",'BALANCE N-1'!$H$2:$H$2000)-SUMIF('BALANCE N-1'!$A$2:$A$2000,"708*",'BALANCE N-1'!$G$2:$G$2000))
A17: RH | B17: Reprises de provisions, depreciations, subventions et autres reprises | C17: note 5D et 30 | D17: =(SUMIF('BALANCE N'!$A$2:$A$2000,"79*",'BALANCE N'!$H$2:$H$2000)-SUMIF('BALANCE N'!$A$2:$A$2000,"79*",'BALANCE N'!$G$2:$G$2000)) | E17: =(SUMIF('BALANCE N-1'!$A$2:$A$2000,"79*",'BALANCE N-1'!$H$2:$H$2000)-SUMIF('BALANCE N-1'!$A$2:$A$2000,"79*",'BALANCE N-1'!$G$2:$G$2000))
A18: XA | B18: REVENUS DES ACTIVITES ORDINAIRES | D18: =D10+D11+D12+D13+D14+D15+D16+D17 | E18: =E10+E11+E12+E13+E14+E15+E16+E17
A19: TA | B19: Achats de biens et services lies a l'activite | C19: note 24 | D19: =(SUMIF('BALANCE N'!$A$2:$A$2000,"601*",'BALANCE N'!$H$2:$H$2000)-SUMIF('BALANCE N'!$A$2:$A$2000,"601*",'BALANCE N'!$G$2:$G$2000)) | E19: =(SUMIF('BALANCE N-1'!$A$2:$A$2000,"601*",'BALANCE N-1'!$H$2:$H$2000)-SUMIF('BALANCE N-1'!$A$2:$A$2000,"601*",'BALANCE N-1'!$G$2:$G$2000))
A20: TB | B20: Variation de stocks des achats de biens et services lies a l'activite | C20: note 8 | D20: =(SUMIF('BALANCE N'!$A$2:$A$2000,"6031*",'BALANCE N'!$H$2:$H$2000)-SUMIF('BALANCE N'!$A$2:$A$2000,"6031*",'BALANCE N'!$G$2:$G$2000)) | E20: =(SUMIF('BALANCE N-1'!$A$2:$A$2000,"6031*",'BALANCE N-1'!$H$2:$H$2000)-SUMIF('BALANCE N-1'!$A$2:$A$2000,"6031*",'BALANCE N-1'!$G$2:$G$2000))
A21: TC | B21: Achats de marchandises et matieres premieres | C21: note 24 | D21: =(SUMIF('BALANCE N'!$A$2:$A$2000,"602*",'BALANCE N'!$H$2:$H$2000)-SUMIF('BALANCE N'!$A$2:$A$2000,"602*",'BALANCE N'!$G$2:$G$2000)) | E21: =(SUMIF('BALANCE N-1'!$A$2:$A$2000,"602*",'BALANCE N-1'!$H$2:$H$2000)-SUMIF('BALANCE N-1'!$A$2:$A$2000,"602*",'BALANCE N-1'!$G$2:$G$2000))
A22: TD | B22: Autres achats | C22: note 24 | D22: =(SUMIF('BALANCE N'!$A$2:$A$2000,"604*",'BALANCE N'!$H$2:$H$2000)-SUMIF('BALANCE N'!$A$2:$A$2000,"604*",'BALANCE N'!$G$2:$G$2000)+SUMIF('BALANCE N'!$A$2:$A$2000,"605*",'BALANCE N'!$H$2:$H$2000)-SUMIF('BALANCE N'!$A$2:$A$2000,"605*",'BALANCE N'!$G$2:$G$2000)+SUMIF('BALANCE N'!$A$2:$A$2000,"606*",'BALANCE N'!$H$2:$H$2000)-SUMIF('BALANCE N'!$A$2:$A$2000,"606*",'BALANCE N'!$G$2:$G$2000)+SUMIF('BALANCE N'!$A$2:$A$2000,"608*",'BALANCE N'!$H$2:$H$2000)-SUMIF('BALANCE N'!$A$2:$A$2000,"608*",'BALANCE N'!$G$2:$G$2000)) | E22: =(SUMIF('BALANCE N-1'!$A$2:$A$2000,"604*",'BALANCE N-1'!$H$2:$H$2000)-SUMIF('BALANCE N-1'!$A$2:$A$2000,"604*",'BALANCE N-1'!$G$2:$G$2000)+SUMIF('BALANCE N-1'!$A$2:$A$2000,"605*",'BALANCE N-1'!$H$2:$H$2000)-SUMIF('BALANCE N-1'!$A$2:$A$2000,"605*",'BALANCE N-1'!$G$2:$G$2000)+SUMIF('BALANCE N-1'!$A$2:$A$2000,"606*",'BALANCE N-1'!$H$2:$H$2000)-SUMIF('BALANCE N-1'!$A$2:$A$2000,"606*",'BALANCE N-1'!$G$2:$G$2000)+SUMIF('BALANCE N-1'!$A$2:$A$2000,"608*",'BALANCE N-1'!$H$2:$H$2000)-SUMIF('BALANCE N-1'!$A$2:$A$2000,"608*",'BALANCE N-1'!$G$2:$G$2000))
A23: TE | B23: Variation de stocks de marchandises, de matieres premieres et autres | C23: note 8 | D23: =(SUMIF('BALANCE N'!$A$2:$A$2000,"6032*",'BALANCE N'!$H$2:$H$2000)-SUMIF('BALANCE N'!$A$2:$A$2000,"6032*",'BALANCE N'!$G$2:$G$2000)+SUMIF('BALANCE N'!$A$2:$A$2000,"6033*",'BALANCE N'!$H$2:$H$2000)-SUMIF('BALANCE N'!$A$2:$A$2000,"6033*",'BALANCE N'!$G$2:$G$2000)+SUMIF('BALANCE N'!$A$2:$A$2000,"6034*",'BALANCE N'!$H$2:$H$2000)-SUMIF('BALANCE N'!$A$2:$A$2000,"6034*",'BALANCE N'!$G$2:$G$2000)+SUMIF('BALANCE N'!$A$2:$A$2000,"6035*",'BALANCE N'!$H$2:$H$2000)-SUMIF('BALANCE N'!$A$2:$A$2000,"6035*",'BALANCE N'!$G$2:$G$2000)) | E23: =(SUMIF('BALANCE N-1'!$A$2:$A$2000,"6032*",'BALANCE N-1'!$H$2:$H$2000)-SUMIF('BALANCE N-1'!$A$2:$A$2000,"6032*",'BALANCE N-1'!$G$2:$G$2000)+SUMIF('BALANCE N-1'!$A$2:$A$2000,"6033*",'BALANCE N-1'!$H$2:$H$2000)-SUMIF('BALANCE N-1'!$A$2:$A$2000,"6033*",'BALANCE N-1'!$G$2:$G$2000)+SUMIF('BALANCE N-1'!$A$2:$A$2000,"6034*",'BALANCE N-1'!$H$2:$H$2000)-SUMIF('BALANCE N-1'!$A$2:$A$2000,"6034*",'BALANCE N-1'!$G$2:$G$2000)+SUMIF('BALANCE N-1'!$A$2:$A$2000,"6035*",'BALANCE N-1'!$H$2:$H$2000)-SUMIF('BALANCE N-1'!$A$2:$A$2000,"6035*",'BALANCE N-1'!$G$2:$G$2000))
A24: TF | B24: Transports | C24: note 25 | D24: =(SUMIF('BALANCE N'!$A$2:$A$2000,"61*",'BALANCE N'!$H$2:$H$2000)-SUMIF('BALANCE N'!$A$2:$A$2000,"61*",'BALANCE N'!$G$2:$G$2000)) | E24: =(SUMIF('BALANCE N-1'!$A$2:$A$2000,"61*",'BALANCE N-1'!$H$2:$H$2000)-SUMIF('BALANCE N-1'!$A$2:$A$2000,"61*",'BALANCE N-1'!$G$2:$G$2000))
A25: TG | B25: Services exterieurs | C25: note 26 | D25: =(SUMIF('BALANCE N'!$A$2:$A$2000,"62*",'BALANCE N'!$H$2:$H$2000)-SUMIF('BALANCE N'!$A$2:$A$2000,"62*",'BALANCE N'!$G$2:$G$2000)+SUMIF('BALANCE N'!$A$2:$A$2000,"63*",'BALANCE N'!$H$2:$H$2000)-SUMIF('BALANCE N'!$A$2:$A$2000,"63*",'BALANCE N'!$G$2:$G$2000)) | E25: =(SUMIF('BALANCE N-1'!$A$2:$A$2000,"62*",'BALANCE N-1'!$H$2:$H$2000)-SUMIF('BALANCE N-1'!$A$2:$A$2000,"62*",'BALANCE N-1'!$G$2:$G$2000)+SUMIF('BALANCE N-1'!$A$2:$A$2000,"63*",'BALANCE N-1'!$H$2:$H$2000)-SUMIF('BALANCE N-1'!$A$2:$A$2000,"63*",'BALANCE N-1'!$G$2:$G$2000))
A26: TH | B26: Impots et taxes | C26: note 27 | D26: =(SUMIF('BALANCE N'!$A$2:$A$2000,"64*",'BALANCE N'!$H$2:$H$2000)-SUMIF('BALANCE N'!$A$2:$A$2000,"64*",'BALANCE N'!$G$2:$G$2000)) | E26: =(SUMIF('BALANCE N-1'!$A$2:$A$2000,"64*",'BALANCE N-1'!$H$2:$H$2000)-SUMIF('BALANCE N-1'!$A$2:$A$2000,"64*",'BALANCE N-1'!$G$2:$G$2000))
A27: TI | B27: Autres charges | C27: note 28 | D27: =(SUMIF('BALANCE N'!$A$2:$A$2000,"65*",'BALANCE N'!$H$2:$H$2000)-SUMIF('BALANCE N'!$A$2:$A$2000,"65*",'BALANCE N'!$G$2:$G$2000)) | E27: =(SUMIF('BALANCE N-1'!$A$2:$A$2000,"65*",'BALANCE N-1'!$H$2:$H$2000)-SUMIF('BALANCE N-1'!$A$2:$A$2000,"65*",'BALANCE N-1'!$G$2:$G$2000))
A28: TJ | B28: Charges de personnel | C28: note 29 | D28: =(SUMIF('BALANCE N'!$A$2:$A$2000,"66*",'BALANCE N'!$H$2:$H$2000)-SUMIF('BALANCE N'!$A$2:$A$2000,"66*",'BALANCE N'!$G$2:$G$2000)) | E28: =(SUMIF('BALANCE N-1'!$A$2:$A$2000,"66*",'BALANCE N-1'!$H$2:$H$2000)-SUMIF('BALANCE N-1'!$A$2:$A$2000,"66*",'BALANCE N-1'!$G$2:$G$2000))
A29: TK | B29: Frais financiers et charges assimilees | C29: note 31 | D29: =(SUMIF('BALANCE N'!$A$2:$A$2000,"67*",'BALANCE N'!$H$2:$H$2000)-SUMIF('BALANCE N'!$A$2:$A$2000,"67*",'BALANCE N'!$G$2:$G$2000)) | E29: =(SUMIF('BALANCE N-1'!$A$2:$A$2000,"67*",'BALANCE N-1'!$H$2:$H$2000)-SUMIF('BALANCE N-1'!$A$2:$A$2000,"67*",'BALANCE N-1'!$G$2:$G$2000))
A30: TL | B30: Dotations aux amortissements, aux provisions, aux depreciations et autres | C30: note 5D et 30 | D30: =(SUMIF('BALANCE N'!$A$2:$A$2000,"68*",'BALANCE N'!$H$2:$H$2000)-SUMIF('BALANCE N'!$A$2:$A$2000,"68*",'BALANCE N'!$G$2:$G$2000)+SUMIF('BALANCE N'!$A$2:$A$2000,"69*",'BALANCE N'!$H$2:$H$2000)-SUMIF('BALANCE N'!$A$2:$A$2000,"69*",'BALANCE N'!$G$2:$G$2000)) | E30: =(SUMIF('BALANCE N-1'!$A$2:$A$2000,"68*",'BALANCE N-1'!$H$2:$H$2000)-SUMIF('BALANCE N-1'!$A$2:$A$2000,"68*",'BALANCE N-1'!$G$2:$G$2000)+SUMIF('BALANCE N-1'!$A$2:$A$2000,"69*",'BALANCE N-1'!$H$2:$H$2000)-SUMIF('BALANCE N-1'!$A$2:$A$2000,"69*",'BALANCE N-1'!$G$2:$G$2000))
A31: XB | B31: CHARGES DES ACTIVITES ORDINAIRES | D31: =D19+D20+D21+D22+D23+D24+D25+D26+D27+D28+D29+D30 | E31: =E19+E20+E21+E22+E23+E24+E25+E26+E27+E28+E29+E30
A32: XC | B32: RESULTAT DES ACTIVITES ORDINAIRES | D32: =D18+D31 | E32: =E18+E31
A33: TM | B33: Produits H.A.O. | C33: note 32 | D33: =(SUMIF('BALANCE N'!$A$2:$A$2000,"82*",'BALANCE N'!$H$2:$H$2000)-SUMIF('BALANCE N'!$A$2:$A$2000,"82*",'BALANCE N'!$G$2:$G$2000)+SUMIF('BALANCE N'!$A$2:$A$2000,"84*",'BALANCE N'!$H$2:$H$2000)-SUMIF('BALANCE N'!$A$2:$A$2000,"84*",'BALANCE N'!$G$2:$G$2000)+SUMIF('BALANCE N'!$A$2:$A$2000,"86*",'BALANCE N'!$H$2:$H$2000)-SUMIF('BALANCE N'!$A$2:$A$2000,"86*",'BALANCE N'!$G$2:$G$2000)+SUMIF('BALANCE N'!$A$2:$A$2000,"88*",'BALANCE N'!$H$2:$H$2000)-SUMIF('BALANCE N'!$A$2:$A$2000,"88*",'BALANCE N'!$G$2:$G$2000)) | E33: =(SUMIF('BALANCE N-1'!$A$2:$A$2000,"82*",'BALANCE N-1'!$H$2:$H$2000)-SUMIF('BALANCE N-1'!$A$2:$A$2000,"82*",'BALANCE N-1'!$G$2:$G$2000)+SUMIF('BALANCE N-1'!$A$2:$A$2000,"84*",'BALANCE N-1'!$H$2:$H$2000)-SUMIF('BALANCE N-1'!$A$2:$A$2000,"84*",'BALANCE N-1'!$G$2:$G$2000)+SUMIF('BALANCE N-1'!$A$2:$A$2000,"86*",'BALANCE N-1'!$H$2:$H$2000)-SUMIF('BALANCE N-1'!$A$2:$A$2000,"86*",'BALANCE N-1'!$G$2:$G$2000)+SUMIF('BALANCE N-1'!$A$2:$A$2000,"88*",'BALANCE N-1'!$H$2:$H$2000)-SUMIF('BALANCE N-1'!$A$2:$A$2000,"88*",'BALANCE N-1'!$G$2:$G$2000))
A34: TN | B34: Charges H.A.O. | C34: note 32 | D34: =(SUMIF('BALANCE N'!$A$2:$A$2000,"81*",'BALANCE N'!$H$2:$H$2000)-SUMIF('BALANCE N'!$A$2:$A$2000,"81*",'BALANCE N'!$G$2:$G$2000)+SUMIF('BALANCE N'!$A$2:$A$2000,"83*",'BALANCE N'!$H$2:$H$2000)-SUMIF('BALANCE N'!$A$2:$A$2000,"83*",'BALANCE N'!$G$2:$G$2000)+SUMIF('BALANCE N'!$A$2:$A$2000,"85*",'BALANCE N'!$H$2:$H$2000)-SUMIF('BALANCE N'!$A$2:$A$2000,"85*",'BALANCE N'!$G$2:$G$2000)+SUMIF('BALANCE N'!$A$2:$A$2000,"87*",'BALANCE N'!$H$2:$H$2000)-SUMIF('BALANCE N'!$A$2:$A$2000,"87*",'BALANCE N'!$G$2:$G$2000)) | E34: =(SUMIF('BALANCE N-1'!$A$2:$A$2000,"81*",'BALANCE N-1'!$H$2:$H$2000)-SUMIF('BALANCE N-1'!$A$2:$A$2000,"81*",'BALANCE N-1'!$G$2:$G$2000)+SUMIF('BALANCE N-1'!$A$2:$A$2000,"83*",'BALANCE N-1'!$H$2:$H$2000)-SUMIF('BALANCE N-1'!$A$2:$A$2000,"83*",'BALANCE N-1'!$G$2:$G$2000)+SUMIF('BALANCE N-1'!$A$2:$A$2000,"85*",'BALANCE N-1'!$H$2:$H$2000)-SUMIF('BALANCE N-1'!$A$2:$A$2000,"85*",'BALANCE N-1'!$G$2:$G$2000)+SUMIF('BALANCE N-1'!$A$2:$A$2000,"87*",'BALANCE N-1'!$H$2:$H$2000)-SUMIF('BALANCE N-1'!$A$2:$A$2000,"87*",'BALANCE N-1'!$G$2:$G$2000))
A35: XD | B35: RESULTAT H.A.O. | D35: =D33+D34 | E35: =E33+E34
A36: XE | B36: RESULTAT NET DE L'EXERCICE (+excedent, -deficit) | D36: =D32+D35 | E36: =E32+E35

Sheet TFT
A1: - 7 -
D2: TABLEAU DES FLUX DE TRESORERIE
A3: Dénomination sociale :
A4: Adresse : | D4: Sigle usuel :
A5: N° de compte contribuable (NCC) : | C5: Exercice clos le | D5: Durée (en mois) : 12
A6: N° de télédéclarant (NTD) :
A7: TABLEAU DES FLUX DE TRESORERIE
A8: REF | B8: LIBELLES | C8: Rep. | D8: EXERCICE N | E8: EXERCICE N-1
A9: ZA | B9: Trésorerie nette au 1er janvier (Trésorerie actif N-1 - Trésorerie passif N-1) | C9: A | D9: =((((SUMIF('BALANCE N-1'!$A$2:$A$2000,"50*",'BALANCE N-1'!$G$2:$G$2000)-SUMIF('BALANCE N-1'!$A$2:$A$2000,"50*",'BALANCE N-1'!$H$2:$H$2000)))-((SUMIF('BALANCE N-1'!$A$2:$A$2000,"590*",'BALANCE N-1'!$H$2:$H$2000)-SUMIF('BALANCE N-1'!$A$2:$A$2000,"590*",'BALANCE N-1'!$G$2:$G$2000))))+(((SUMIF('BALANCE N-1'!$A$2:$A$2000,"51*",'BALANCE N-1'!$G$2:$G$2000)-SUMIF('BALANCE N-1'!$A$2:$A$2000,"51*",'BALANCE N-1'!$H$2:$H$2000)))-((SUMIF('BALANCE N-1'!$A$2:$A$2000,"591*",'BALANCE N-1'!$H$2:$H$2000)-SUMIF('BALANCE N-1'!$A$2:$A$2000,"591*",'BALANCE N-1'!$G$2:$G$2000))))+(((SUMIF('BALANCE N-1'!$A$2:$A$2000,"52*",'BALANCE N-1'!$G$2:$G$2000)-SUMIF('BALANCE N-1'!$A$2:$A$2000,"52*",'BALANCE N-1'!$H$2:$H$2000)+SUMIF('BALANCE N-1'!$A$2:$A$2000,"53*",'BALANCE N-1'!$G$2:$G$2000)-SUMIF('BALANCE N-1'!$A$2:$A$2000,"53*",'BALANCE N-1'!$H$2:$H$2000)+SUMIF('BALANCE N-1'!$A$2:$A$2000,"55*",'BALANCE N-1'!$G$2:$G$2000)-SUMIF('BALANCE N-1'!$A$2:$A$2000,"55*",'BALANCE N-1'!$H$2:$H$2000)+SUMIF('BALANCE N-1'!$A$2:$A$2000,"57*",'BALANCE N-1'!$G$2:$G$2000)-SUMIF('BALANCE N-1'!$A$2:$A$2000,"57*",'BALANCE N-1'!$H$2:$H$2000)))-((SUMIF('BALANCE N-1'!$A$2:$A$2000,"592*",'BALANCE N-1'!$H$2:$H$2000)-SUMIF('BALANCE N-1'!$A$2:$A$2000,"592*",'BALANCE N-1'!$G$2:$G$2000)+SUMIF('BALANCE N-1'!$A$2:$A$2000,"593*",'BALANCE N-1'!$H$2:$H$2000)-SUMIF('BALANCE N-1'!$A$2:$A$2000,"593*",'BALANCE N-1'!$G$2:$G$2000)+SUMIF('BALANCE N-1'!$A$2:$A$2000,"595*",'BALANCE N-1'!$H$2:$H$2000)-SUMIF('BALANCE N-1'!$A$2:$A$2000,"595*",'BALANCE N-1'!$G$2:$G$2000)))))-((SUMIF('BALANCE N-1'!$A$2:$A$2000,"564*",'BALANCE N-1'!$H$2:$H$2000)-SUMIF('BALANCE N-1'!$A$2:$A$2000,"564*",'BALANCE N-1'!$G$2:$G$2000)+SUMIF('BALANCE N-1'!$A$2:$A$2000,"565*",'BALANCE N-1'!$H$2:$H$2000)-SUMIF('BALANCE N-1'!$A$2:$A$2000,"565*",'BALANCE N-1'!$G$2:$G$2000))+(SUMIF('BALANCE N-1'!$A$2:$A$2000,"52*",'BALANCE N-1'!$H$2:$H$2000)+SUMIF('BALANCE N-1'!$A$2:$A$2000,"53*",'BALANCE N-1'!$H$2:$H$2000)))
B10: Flux de trésorerie provenant des activités opérationnelles
A11: FA | B11: + Encaissement des cotisations
A12: FB | B12: + Encaissement des subventions d'exploitation et d'équilibre
A13: FC | B13: + Encaissement des revenus liés à la générosité
A14: FD | B14: + Encaissement des revenus des manifestations
A15: FE | B15: + Encaissement des autres revenus
A16: FF | B16: - Décaissement des sommes versées aux fournisseurs (1)
A17: FG | B17: - Décaissement des sommes versées au personnel
A18: FH | B18: - Autres décaissements
A19: ZB | B19: FLUX DE TRÉSORERIE PROVENANT DES ACTIVITÉS OPÉRATIONNELLES - calculé en résidu (voir README) | C19: B | D19: =D35-D25-D30-D34
B20: Flux de trésorerie provenant des activités d'investissement
A21: FI | B21: - Décaissements liés aux acquisitions d'immobilisations incorporelles et corporelles
A22: FJ | B22: - Décaissements liés aux acquisitions d'immobilisations financières
A23: FK | B23: + Encaissements liés aux cessions d'immobilisations incorporelles et corporelles
A24: FL | B24: + Encaissements liés aux cessions d'immobilisations financières
A25: ZC | B25: FLUX DE TRÉSORERIE PROVENANT DES ACTIVITÉS D'INVESTISSEMENT | C25: C | D25: =-((((SUMIF('BALANCE N'!$A$2:$A$2000,"201*",'BALANCE N'!$G$2:$G$2000)-SUMIF('BALANCE N'!$A$2:$A$2000,"201*",'BALANCE N'!$H$2:$H$2000)))+((SUMIF('BALANCE N'!$A$2:$A$2000,"202*",'BALANCE N'!$G$2:$G$2000)-SUMIF('BALANCE N'!$A$2:$A$2000,"202*",'BALANCE N'!$H$2:$H$2000)+SUMIF('BALANCE N'!$A$2:$A$2000,"203*",'BALANCE N'!$G$2:$G$2000)-SUMIF('BALANCE N'!$A$2:$A$2000,"203*",'BALANCE N'!$H$2:$H$2000)+SUMIF('BALANCE N'!$A$2:$A$2000,"204*",'BALANCE N'!$G$2:$G$2000)-SUMIF('BALANCE N'!$A$2:$A$2000,"204*",'BALANCE N'!$H$2:$H$2000)+SUMIF('BALANCE N'!$A$2:$A$2000,"205*",'BALANCE N'!$G$2:$G$2000)-SUMIF('BALANCE N'!$A$2:$A$2000,"205*",'BALANCE N'!$H$2:$H$2000)))+((SUMIF('BALANCE N'!$A$2:$A$2000,"212*",'BALANCE N'!$G$2:$G$2000)-SUMIF('BALANCE N'!$A$2:$A$2000,"212*",'BALANCE N'!$H$2:$H$2000)+SUMIF('BALANCE N'!$A$2:$A$2000,"213*",'BALANCE N'!$G$2:$G$2000)-SUMIF('BALANCE N'!$A$2:$A$2000,"213*",'BALANCE N'!$H$2:$H$2000)+SUMIF('BALANCE N'!$A$2:$A$2000,"214*",'BALANCE N'!$G$2:$G$2000)-SUMIF('BALANCE N'!$A$2:$A$2000,"214*",'BALANCE N'!$H$2:$H$2000)+SUMIF('BALANCE N'!$A$2:$A$2000,"2193*",'BALANCE N'!$G$2:$G$2000)-SUMIF('BALANCE N'!$A$2:$A$2000,"2193*",'BALANCE N'!$H$2:$H$2000)))+((SUMIF('BALANCE N'!$A$2:$A$2000,"218*",'BALANCE N'!$G$2:$G$2000)-SUMIF('BALANCE N'!$A$2:$A$2000,"218*",'BALANCE N'!$H$2:$H$2000)+SUMIF('BALANCE N'!$A$2:$A$2000,"2198*",'BALANCE N'!$G$2:$G$2000)-SUMIF('BALANCE N'!$A$2:$A$2000,"2198*",'BALANCE N'!$H$2:$H$2000)))+((SUMIF('BALANCE N'!$A$2:$A$2000,"251*",'BALANCE N'!$G$2:$G$2000)-SUMIF('BALANCE N'!$A$2:$A$2000,"251*",'BALANCE N'!$H$2:$H$2000)))+((SUMIF('BALANCE N'!$A$2:$A$2000,"22*",'BALANCE N'!$G$2:$G$2000)-SUMIF('BALANCE N'!$A$2:$A$2000,"22*",'BALANCE N'!$H$2:$H$2000)))+((SUMIF('BALANCE N'!$A$2:$A$2000,"231*",'BALANCE N'!$G$2:$G$2000)-SUMIF('BALANCE N'!$A$2:$A$2000,"231*",'BALANCE N'!$H$2:$H$2000)+SUMIF('BALANCE N'!$A$2:$A$2000,"232*",'BALANCE N'!$G$2:$G$2000)-SUMIF('BALANCE N'!$A$2:$A$2000,"232*",'BALANCE N'!$H$2:$H$2000)+SUMIF('BALANCE N'!$A$2:$A$2000,"233*",'BALANCE N'!$G$2:$G$2000)-SUMIF('BALANCE N'!$A$2:$A$2000,"233*",'BALANCE N'!$H$2:$H$2000)+SUMIF('BALANCE N'!$A$2:$A$2000,"2391*",'BALANCE N'!$G$2:$G$2000)-SUMIF('BALANCE N'!$A$2:$A$2000,"2391*",'BALANCE N'!$H$2:$H$2000)+SUMIF('BALANCE N'!$A$2:$A$2000,"2392*",'BALANCE N'!$G$2:$G$2000)-SUMIF('BALANCE N'!$A$2:$A$2000,"2392*",'BALANCE N'!$H$2:$H$2000)+SUMIF('BALANCE N'!$A$2:$A$2000,"2393*",'BALANCE N'!$G$2:$G$2000)-SUMIF('BALANCE N'!$A$2:$A$2000,"2393*",'BALANCE N'!$H$2:$H$2000)+SUMIF('BALANCE N'!$A$2:$A$2000,"2396*",'BALANCE N'!$G$2:$G$2000)-SUMIF('BALANCE N'!$A$2:$A$2000,"2396*",'BALANCE N'!$H$2:$H$2000)))+((SUMIF('BALANCE N'!$A$2:$A$2000,"234*",'BALANCE N'!$G$2:$G$2000)-SUMIF('BALANCE N'!$A$2:$A$2000,"234*",'BALANCE N'!$H$2:$H$2000)+SUMIF('BALANCE N'!$A$2:$A$2000,"235*",'BALANCE N'!$G$2:$G$2000)-SUMIF('BALANCE N'!$A$2:$A$2000,"235*",'BALANCE N'!$H$2:$H$2000)+SUMIF('BALANCE N'!$A$2:$A$2000,"238*",'BALANCE N'!$G$2:$G$2000)-SUMIF('BALANCE N'!$A$2:$A$2000,"238*",'BALANCE N'!$H$2:$H$2000)+SUMIF('BALANCE N'!$A$2:$A$2000,"2394*",'BALANCE N'!$G$2:$G$2000)-SUMIF('BALANCE N'!$A$2:$A$2000,"2394*",'BALANCE N'!$H$2:$H$2000)+SUMIF('BALANCE N'!$A$2:$A$2000,"2395*",'BALANCE N'!$G$2:$G$2000)-SUMIF('BALANCE N'!$A$2:$A$2000,"2395*",'BALANCE N'!$H$2:$H$2000)+SUMIF('BALANCE N'!$A$2:$A$2000,"2398*",'BALANCE N'!$G$2:$G$2000)-SUMIF('BALANCE N'!$A$2:$A$2000,"2398*",'BALANCE N'!$H$2:$H$2000)))+((SUMIF('BALANCE N'!$A$2:$A$2000,"24*",'BALANCE N'!$G$2:$G$2000)-SUMIF('BALANCE N'!$A$2:$A$2000,"24*",'BALANCE N'!$H$2:$H$2000)-SUMIF('BALANCE N'!$A$2:$A$2000,"245*",'BALANCE N'!$G$2:$G$2000)+SUMIF('BALANCE N'!$A$2:$A$2000,"245*",'BALANCE N'!$H$2:$H$2000)-SUMIF('BALANCE N'!$A$2:$A$2000,"2495*",'BALANCE N'!$G$2:$G$2000)+SUMIF('BALANCE N'!$A$2:$A$2000,"2495*",'BALANCE N'!$H$2:$H$2000)))+((SUMIF('BALANCE N'!$A$2:$A$2000,"245*",'BALANCE N'!$G$2:$G$2000)-SUMIF('BALANCE N'!$A$2:$A$2000,"245*",'BALANCE N'!$H$2:$H$2000)+SUMIF('BALANCE N'!$A$2:$A$2000,"2495*",'BALANCE N'!$G$2:$G$2000)-SUMIF('BALANCE N'!$A$2:$A$2000,"2495*",'BALANCE N'!$H$2:$H$2000)))+((SUMIF('BALANCE N'!$A$2:$A$2000,"252*",'BALANCE N'!$G$2:$G$2000)-SUMIF('BALANCE N'!$A$2:$A$2000,"252*",'BALANCE N'!$H$2:$H$2000)))+((SUMIF('BALANCE N'!$A$2:$A$2000,"26*",'BALANCE N'!$G$2:$G$2000)-SUMIF('BALANCE N'!$A$2:$A$2000,"26*",'BALANCE N'!$H$2:$H$2000)))+((SUMIF('BALANCE N'!$A$2:$A$2000,"27*",'BALANCE N'!$G$2:$G$2000)-SUMIF('BALANCE N'!$A$2:$A$2000,"27*",'BALANCE N'!$H$2:$H$2000))))-(((SUMIF('BALANCE N-1'!$A$2:$A$2000,"201*",'BALANCE N-1'!$G$2:$G$2000)-SUMIF('BALANCE N-1'!$A$2:$A$2000,"201*",'BALANCE N-1'!$H$2:$H$2000)))+((SUMIF('BALANCE N-1'!$A$2:$A$2000,"202*",'BALANCE N-1'!$G$2:$G$2000)-SUMIF('BALANCE N-1'!$A$2:$A$2000,"202*",'BALANCE N-1'!$H$2:$H$2000)+SUMIF('BALANCE N-1'!$A$2:$A$2000,"203*",'BALANCE N-1'!$G$2:$G$2000)-SUMIF('BALANCE N-1'!$A$2:$A$2000,"203*",'BALANCE N-1'!$H$2:$H$2000)+SUMIF('BALANCE N-1'!$A$2:$A$2000,"204*",'BALANCE N-1'!$G$2:$G$2000)-SUMIF('BALANCE N-1'!$A$2:$A$2000,"204*",'BALANCE N-1'!$H$2:$H$2000)+SUMIF('BALANCE N-1'!$A$2:$A$2000,"205*",'BALANCE N-1'!$G$2:$G$2000)-SUMIF('BALANCE N-1'!$A$2:$A$2000,"205*",'BALANCE N-1'!$H$2:$H$2000)))+((SUMIF('BALANCE N-1'!$A$2:$A$2000,"212*",'BALANCE N-1'!$G$2:$G$2000)-SUMIF('BALANCE N-1'!$A$2:$A$2000,"212*",'BALANCE N-1'!$H$2:$H$2000)+SUMIF('BALANCE N-1'!$A$2:$A$2000,"213*",'BALANCE N-1'!$G$2:$G$2000)-SUMIF('BALANCE N-1'!$A$2:$A$2000,"213*",'BALANCE N-1'!$H$2:$H$2000)+SUMIF('BALANCE N-1'!$A$2:$A$2000,"214*",'BALANCE N-1'!$G$2:$G$2000)-SUMIF('BALANCE N-1'!$A$2:$A$2000,"214*",'BALANCE N-1'!$H$2:$H$2000)+SUMIF('BALANCE N-1'!$A$2:$A$2000,"2193*",'BALANCE N-1'!$G$2:$G$2000)-SUMIF('BALANCE N-1'!$A$2:$A$2000,"2193*",'BALANCE N-1'!$H$2:$H$2000)))+((SUMIF('BALANCE N-1'!$A$2:$A$2000,"218*",'BALANCE N-1'!$G$2:$G$2000)-SUMIF('BALANCE N-1'!$A$2:$A$2000,"218*",'BALANCE N-1'!$H$2:$H$2000)+SUMIF('BALANCE N-1'!$A$2:$A$2000,"2198*",'BALANCE N-1'!$G$2:$G$2000)-SUMIF('BALANCE N-1'!$A$2:$A$2000,"2198*",'BALANCE N-1'!$H$2:$H$2000)))+((SUMIF('BALANCE N-1'!$A$2:$A$2000,"251*",'BALANCE N-1'!$G$2:$G$2000)-SUMIF('BALANCE N-1'!$A$2:$A$2000,"251*",'BALANCE N-1'!$H$2:$H$2000)))+((SUMIF('BALANCE N-1'!$A$2:$A$2000,"22*",'BALANCE N-1'!$G$2:$G$2000)-SUMIF('BALANCE N-1'!$A$2:$A$2000,"22*",'BALANCE N-1'!$H$2:$H$2000)))+((SUMIF('BALANCE N-1'!$A$2:$A$2000,"231*",'BALANCE N-1'!$G$2:$G$2000)-SUMIF('BALANCE N-1'!$A$2:$A$2000,"231*",'BALANCE N-1'!$H$2:$H$2000)+SUMIF('BALANCE N-1'!$A$2:$A$2000,"232*",'BALANCE N-1'!$G$2:$G$2000)-SUMIF('BALANCE N-1'!$A$2:$A$2000,"232*",'BALANCE N-1'!$H$2:$H$2000)+SUMIF('BALANCE N-1'!$A$2:$A$2000,"233*",'BALANCE N-1'!$G$2:$G$2000)-SUMIF('BALANCE N-1'!$A$2:$A$2000,"233*",'BALANCE N-1'!$H$2:$H$2000)+SUMIF('BALANCE N-1'!$A$2:$A$2000,"2391*",'BALANCE N-1'!$G$2:$G$2000)-SUMIF('BALANCE N-1'!$A$2:$A$2000,"2391*",'BALANCE N-1'!$H$2:$H$2000)+SUMIF('BALANCE N-1'!$A$2:$A$2000,"2392*",'BALANCE N-1'!$G$2:$G$2000)-SUMIF('BALANCE N-1'!$A$2:$A$2000,"2392*",'BALANCE N-1'!$H$2:$H$2000)+SUMIF('BALANCE N-1'!$A$2:$A$2000,"2393*",'BALANCE N-1'!$G$2:$G$2000)-SUMIF('BALANCE N-1'!$A$2:$A$2000,"2393*",'BALANCE N-1'!$H$2:$H$2000)+SUMIF('BALANCE N-1'!$A$2:$A$2000,"2396*",'BALANCE N-1'!$G$2:$G$2000)-SUMIF('BALANCE N-1'!$A$2:$A$2000,"2396*",'BALANCE N-1'!$H$2:$H$2000)))+((SUMIF('BALANCE N-1'!$A$2:$A$2000,"234*",'BALANCE N-1'!$G$2:$G$2000)-SUMIF('BALANCE N-1'!$A$2:$A$2000,"234*",'BALANCE N-1'!$H$2:$H$2000)+SUMIF('BALANCE N-1'!$A$2:$A$2000,"235*",'BALANCE N-1'!$G$2:$G$2000)-SUMIF('BALANCE N-1'!$A$2:$A$2000,"235*",'BALANCE N-1'!$H$2:$H$2000)+SUMIF('BALANCE N-1'!$A$2:$A$2000,"238*",'BALANCE N-1'!$G$2:$G$2000)-SUMIF('BALANCE N-1'!$A$2:$A$2000,"238*",'BALANCE N-1'!$H$2:$H$2000)+SUMIF('BALANCE N-1'!$A$2:$A$2000,"2394*",'BALANCE N-1'!$G$2:$G$2000)-SUMIF('BALANCE N-1'!$A$2:$A$2000,"2394*",'BALANCE N-1'!$H$2:$H$2000)+SUMIF('BALANCE N-1'!$A$2:$A$2000,"2395*",'BALANCE N-1'!$G$2:$G$2000)-SUMIF('BALANCE N-1'!$A$2:$A$2000,"2395*",'BALANCE N-1'!$H$2:$H$2000)+SUMIF('BALANCE N-1'!$A$2:$A$2000,"2398*",'BALANCE N-1'!$G$2:$G$2000)-SUMIF('BALANCE N-1'!$A$2:$A$2000,"2398*",'BALANCE N-1'!$H$2:$H$2000)))+((SUMIF('BALANCE N-1'!$A$2:$A$2000,"24*",'BALANCE N-1'!$G$2:$G$2000)-SUMIF('BALANCE N-1'!$A$2:$A$2000,"24*",'BALANCE N-1'!$H$2:$H$2000)-SUMIF('BALANCE N-1'!$A$2:$A$2000,"245*",'BALANCE N-1'!$G$2:$G$2000)+SUMIF('BALANCE N-1'!$A$2:$A$2000,"245*",'BALANCE N-1'!$H$2:$H$2000)-SUMIF('BALANCE N-1'!$A$2:$A$2000,"2495*",'BALANCE N-1'!$G$2:$G$2000)+SUMIF('BALANCE N-1'!$A$2:$A$2000,"2495*",'BALANCE N-1'!$H$2:$H$2000)))+((SUMIF('BALANCE N-1'!$A$2:$A$2000,"245*",'BALANCE N-1'!$G$2:$G$2000)-SUMIF('BALANCE N-1'!$A$2:$A$2000,"245*",'BALANCE N-1'!$H$2:$H$2000)+SUMIF('BALANCE N-1'!$A$2:$A$2000,"2495*",'BALANCE N-1'!$G$2:$G$2000)-SUMIF('BALANCE N-1'!$A$2:$A$2000,"2495*",'BALANCE N-1'!$H$2:$H$2000)))+((SUMIF('BALANCE N-1'!$A$2:$A$2000,"252*",'BALANCE N-1'!$G$2:$G$2000)-SUMIF('BALANCE N-1'!$A$2:$A$2000,"252*",'BALANCE N-1'!$H$2:$H$2000)))+((SUMIF('BALANCE N-1'!$A$2:$A$2000,"26*",'BALANCE N-1'!$G$2:$G$2000)-SUMIF('BALANCE N-1'!$A$2:$A$2000,"26*",'BALANCE N-1'!$H$2:$H$2000)))+((SUMIF('BALANCE N-1'!$A$2:$A$2000,"27*",'BALANCE N-1'!$G$2:$G$2000)-SUMIF('BALANCE N-1'!$A$2:$A$2000,"27*",'BALANCE N-1'!$H$2:$H$2000)))))
B26: Flux de trésorerie provenant du financement par les fonds propres
A27: FM | B27: + Encaissement des dotations et autres fonds propres
A28: FN | B28: + Subventions d'investissement reçues
A29: FO | B29: - Décaissement des dotations et autres fonds propres
A30: ZD | B30: FLUX DE TRÉSORERIE PROVENANT DES FONDS PROPRES | C30: D | D30: =(((SUMIF('BALANCE N'!$A$2:$A$2000,"101*",'BALANCE N'!$H$2:$H$2000)-SUMIF('BALANCE N'!$A$2:$A$2000,"101*",'BALANCE N'!$G$2:$G$2000)))+((SUMIF('BALANCE N'!$A$2:$A$2000,"102*",'BALANCE N'!$H$2:$H$2000)-SUMIF('BALANCE N'!$A$2:$A$2000,"102*",'BALANCE N'!$G$2:$G$2000)))+((SUMIF('BALANCE N'!$A$2:$A$2000,"103*",'BALANCE N'!$H$2:$H$2000)-SUMIF('BALANCE N'!$A$2:$A$2000,"103*",'BALANCE N'!$G$2:$G$2000)))+((SUMIF('BALANCE N'!$A$2:$A$2000,"104*",'BALANCE N'!$H$2:$H$2000)-SUMIF('BALANCE N'!$A$2:$A$2000,"104*",'BALANCE N'!$G$2:$G$2000)))+((SUMIF('BALANCE N'!$A$2:$A$2000,"14*",'BALANCE N'!$H$2:$H$2000)-SUMIF('BALANCE N'!$A$2:$A$2000,"14*",'BALANCE N'!$G$2:$G$2000)))+((SUMIF('BALANCE N'!$A$2:$A$2000,"16*",'BALANCE N'!$H$2:$H$2000)-SUMIF('BALANCE N'!$A$2:$A$2000,"16*",'BALANCE N'!$G$2:$G$2000)))+((SUMIF('BALANCE N'!$A$2:$A$2000,"17*",'BALANCE N'!$H$2:$H$2000)-SUMIF('BALANCE N'!$A$2:$A$2000,"17*",'BALANCE N'!$G$2:$G$2000))))-(((SUMIF('BALANCE N-1'!$A$2:$A$2000,"101*",'BALANCE N-1'!$H$2:$H$2000)-SUMIF('BALANCE N-1'!$A$2:$A$2000,"101*",'BALANCE N-1'!$G$2:$G$2000)))+((SUMIF('BALANCE N-1'!$A$2:$A$2000,"102*",'BALANCE N-1'!$H$2:$H$2000)-SUMIF('BALANCE N-1'!$A$2:$A$2000,"102*",'BALANCE N-1'!$G$2:$G$2000)))+((SUMIF('BALANCE N-1'!$A$2:$A$2000,"103*",'BALANCE N-1'!$H$2:$H$2000)-SUMIF('BALANCE N-1'!$A$2:$A$2000,"103*",'BALANCE N-1'!$G$2:$G$2000)))+((SUMIF('BALANCE N-1'!$A$2:$A$2000,"104*",'BALANCE N-1'!$H$2:$H$2000)-SUMIF('BALANCE N-1'!$A$2:$A$2000,"104*",'BALANCE N-1'!$G$2:$G$2000)))+((SUMIF('BALANCE N-1'!$A$2:$A$2000,"14*",'BALANCE N-1'!$H$2:$H$2000)-SUMIF('BALANCE N-1'!$A$2:$A$2000,"14*",'BALANCE N-1'!$G$2:$G$2000)))+((SUMIF('BALANCE N-1'!$A$2:$A$2000,"16*",'BALANCE N-1'!$H$2:$H$2000)-SUMIF('BALANCE N-1'!$A$2:$A$2000,"16*",'BALANCE N-1'!$G$2:$G$2000)))+((SUMIF('BALANCE N-1'!$A$2:$A$2000,"17*",'BALANCE N-1'!$H$2:$H$2000)-SUMIF('BALANCE N-1'!$A$2:$A$2000,"17*",'BALANCE N-1'!$G$2:$G$2000))))
B31: Trésorerie provenant du financement par les fonds étrangers
A32: FP | B32: + Encaissement provenant des emprunts et des autres dettes financières
A33: FQ | B33: - Remboursements des emprunts et autres dettes financières
A34: ZE | B34: TRÉSORERIE PROVENANT DES FONDS ÉTRANGERS | C34: E | D34: =(((SUMIF('BALANCE N'!$A$2:$A$2000,"181*",'BALANCE N'!$H$2:$H$2000)-SUMIF('BALANCE N'!$A$2:$A$2000,"181*",'BALANCE N'!$G$2:$G$2000)+SUMIF('BALANCE N'!$A$2:$A$2000,"182*",'BALANCE N'!$H$2:$H$2000)-SUMIF('BALANCE N'!$A$2:$A$2000,"182*",'BALANCE N'!$G$2:$G$2000)+SUMIF('BALANCE N'!$A$2:$A$2000,"183*",'BALANCE N'!$H$2:$H$2000)-SUMIF('BALANCE N'!$A$2:$A$2000,"183*",'BALANCE N'!$G$2:$G$2000)+SUMIF('BALANCE N'!$A$2:$A$2000,"185*",'BALANCE N'!$H$2:$H$2000)-SUMIF('BALANCE N'!$A$2:$A$2000,"185*",'BALANCE N'!$G$2:$G$2000)+SUMIF('BALANCE N'!$A$2:$A$2000,"186*",'BALANCE N'!$H$2:$H$2000)-SUMIF('BALANCE N'!$A$2:$A$2000,"186*",'BALANCE N'!$G$2:$G$2000)+SUMIF('BALANCE N'!$A$2:$A$2000,"188*",'BALANCE N'!$H$2:$H$2000)-SUMIF('BALANCE N'!$A$2:$A$2000,"188*",'BALANCE N'!$G$2:$G$2000)))+((SUMIF('BALANCE N'!$A$2:$A$2000,"187*",'BALANCE N'!$H$2:$H$2000)-SUMIF('BALANCE N'!$A$2:$A$2000,"187*",'BALANCE N'!$G$2:$G$2000)))+((SUMIF('BALANCE N'!$A$2:$A$2000,"19*",'BALANCE N'!$H$2:$H$2000)-SUMIF('BALANCE N'!$A$2:$A$2000,"19*",'BALANCE N'!$G$2:$G$2000))))-(((SUMIF('BALANCE N-1'!$A$2:$A$2000,"181*",'BALANCE N-1'!$H$2:$H$2000)-SUMIF('BALANCE N-1'!$A$2:$A$2000,"181*",'BALANCE N-1'!$G$2:$G$2000)+SUMIF('BALANCE N-1'!$A$2:$A$2000,"182*",'BALANCE N-1'!$H$2:$H$2000)-SUMIF('BALANCE N-1'!$A$2:$A$2000,"182*",'BALANCE N-1'!$G$2:$G$2000)+SUMIF('BALANCE N-1'!$A$2:$A$2000,"183*",'BALANCE N-1'!$H$2:$H$2000)-SUMIF('BALANCE N-1'!$A$2:$A$2000,"183*",'BALANCE N-1'!$G$2:$G$2000)+SUMIF('BALANCE N-1'!$A$2:$A$2000,"185*",'BALANCE N-1'!$H$2:$H$2000)-SUMIF('BALANCE N-1'!$A$2:$A$2000,"185*",'BALANCE N-1'!$G$2:$G$2000)+SUMIF('BALANCE N-1'!$A$2:$A$2000,"186*",'BALANCE N-1'!$H$2:$H$2000)-SUMIF('BALANCE N-1'!$A$2:$A$2000,"186*",'BALANCE N-1'!$G$2:$G$2000)+SUMIF('BALANCE N-1'!$A$2:$A$2000,"188*",'BALANCE N-1'!$H$2:$H$2000)-SUMIF('BALANCE N-1'!$A$2:$A$2000,"188*",'BALANCE N-1'!$G$2:$G$2000)))+((SUMIF('BALANCE N-1'!$A$2:$A$2000,"187*",'BALANCE N-1'!$H$2:$H$2000)-SUMIF('BALANCE N-1'!$A$2:$A$2000,"187*",'BALANCE N-1'!$G$2:$G$2000)))+((SUMIF('BALANCE N-1'!$A$2:$A$2000,"19*",'BALANCE N-1'!$H$2:$H$2000)-SUMIF('BALANCE N-1'!$A$2:$A$2000,"19*",'BALANCE N-1'!$G$2:$G$2000))))
A35: ZF | B35: VARIATION DE LA TRÉSORERIE NETTE DE LA PÉRIODE (B+C+D+E) | C35: G | D35: =(((((SUMIF('BALANCE N'!$A$2:$A$2000,"50*",'BALANCE N'!$G$2:$G$2000)-SUMIF('BALANCE N'!$A$2:$A$2000,"50*",'BALANCE N'!$H$2:$H$2000)))-((SUMIF('BALANCE N'!$A$2:$A$2000,"590*",'BALANCE N'!$H$2:$H$2000)-SUMIF('BALANCE N'!$A$2:$A$2000,"590*",'BALANCE N'!$G$2:$G$2000))))+(((SUMIF('BALANCE N'!$A$2:$A$2000,"51*",'BALANCE N'!$G$2:$G$2000)-SUMIF('BALANCE N'!$A$2:$A$2000,"51*",'BALANCE N'!$H$2:$H$2000)))-((SUMIF('BALANCE N'!$A$2:$A$2000,"591*",'BALANCE N'!$H$2:$H$2000)-SUMIF('BALANCE N'!$A$2:$A$2000,"591*",'BALANCE N'!$G$2:$G$2000))))+(((SUMIF('BALANCE N'!$A$2:$A$2000,"52*",'BALANCE N'!$G$2:$G$2000)-SUMIF('BALANCE N'!$A$2:$A$2000,"52*",'BALANCE N'!$H$2:$H$2000)+SUMIF('BALANCE N'!$A$2:$A$2000,"53*",'BALANCE N'!$G$2:$G$2000)-SUMIF('BALANCE N'!$A$2:$A$2000,"53*",'BALANCE N'!$H$2:$H$2000)+SUMIF('BALANCE N'!$A$2:$A$2000,"55*",'BALANCE N'!$G$2:$G$2000)-SUMIF('BALANCE N'!$A$2:$A$2000,"55*",'BALANCE N'!$H$2:$H$2000)+SUMIF('BALANCE N'!$A$2:$A$2000,"57*",'BALANCE N'!$G$2:$G$2000)-SUMIF('BALANCE N'!$A$2:$A$2000,"57*",'BALANCE N'!$H$2:$H$2000)))-((SUMIF('BALANCE N'!$A$2:$A$2000,"592*",'BALANCE N'!$H$2:$H$2000)-SUMIF('BALANCE N'!$A$2:$A$2000,"592*",'BALANCE N'!$G$2:$G$2000)+SUMIF('BALANCE N'!$A$2:$A$2000,"593*",'BALANCE N'!$H$2:$H$2000)-SUMIF('BALANCE N'!$A$2:$A$2000,"593*",'BALANCE N'!$G$2:$G$2000)+SUMIF('BALANCE N'!$A$2:$A$2000,"595*",'BALANCE N'!$H$2:$H$2000)-SUMIF('BALANCE N'!$A$2:$A$2000,"595*",'BALANCE N'!$G$2:$G$2000)))))-((SUMIF('BALANCE N'!$A$2:$A$2000,"564*",'BALANCE N'!$H$2:$H$2000)-SUMIF('BALANCE N'!$A$2:$A$2000,"564*",'BALANCE N'!$G$2:$G$2000)+SUMIF('BALANCE N'!$A$2:$A$2000,"565*",'BALANCE N'!$H$2:$H$2000)-SUMIF('BALANCE N'!$A$2:$A$2000,"565*",'BALANCE N'!$G$2:$G$2000))+(SUMIF('BALANCE N'!$A$2:$A$2000,"52*",'BALANCE N'!$H$2:$H$2000)+SUMIF('BALANCE N'!$A$2:$A$2000,"53*",'BALANCE N'!$H$2:$H$2000))))-D9
A36: ZG | B36: TRÉSORERIE NETTE AU 31 DÉCEMBRE (G+A) - contrôle : trésorerie actif N - trésorerie passif N | C36: H | D36: =D35+D9
A38: (1) à l'exclusion des fournisseurs d'investissements. Les lignes FA à FH (ventilation par nature des encaissements/décaissements) se saisissent depuis le journal de trésorerie : une balance de clôture ne porte pas cette information.

Sheet NOTES ANNEXES
A1: - 8 -
I2: NOTES ANNEXES
A3: Dénomination sociale :
A4: Adresse : | I4: Sigle usuel :
A5: N° de compte contribuable (NCC) : | G5: Exercice clos le | I5: Durée (en mois) : 12
A6: N° de télédéclarant (NTD) :
A7: FICHE RECAPITULATIVE NOTES ANNEXES PRESENTEES (1)
A8: NOTES | B8: INTITULES | I8: A (2) | J8: N/A (2)
A9: Partie 1 : Informations générales
A10: Note 1 | B10: DETTES GARANTIES PAR DES SÛRETÉS RÉELLES, ENGAGEMENTS FINANCIERS ET CONTRIBUTIONS VOLONTAIRES EN NATURE
A11: Note 2 | B11: INFORMATIONS OBLIGATOIRES
A12: Note 3 | B12: ÉVÈNEMENTS POSTÉRIEURS À LA CLÔTURE DE L'EXERCICE
A13: Note 4 | B13: CHANGEMENTS DE MÉTHODES COMPTABLES, D'ESTIMATIONS ET CORRECTIONS D'ERREURS
A14: Partie 2 : Notes sur le bilan
A15: Note 5A | B15: DONS ET LEGS D'IMMOBILISATIONS NON REÇUS DESTINÉS À LA VENTE ET USUFRUIT TEMPORAIRE
A16: Note 5B | B16: IMMOBILISATIONS BRUTES
A17: Note 5C | B17: BIENS PRIS EN LOCATION-ACQUISITION
A18: Note 5D | B18: DONS ET LEGS D'IMMOBILISATIONS NON REÇUS DESTINÉS À LA VENTE ET USUFRUIT TEMPORAIRE (AMORTISSEMENTS ET DÉPRÉCIATIONS)
A19: Note 5E | B19: IMMOBILISATIONS : AMORTISSEMENTS
A20: Note 5F | B20: IMMOBILISATIONS : DÉPRÉCIATIONS
A21: Note 5G | B21: IMMOBILISATIONS : PLUS-VALUES ET MOINS-VALUES DE CESSION
A22: Note 5H | B22: INFORMATIONS SUR LES RÉÉVALUATIONS EFFECTUÉES PAR L'ENTITÉ
A23: Note 6 | B23: IMMOBILISATIONS FINANCIÈRES
A24: Note 7 | B24: ACTIF CIRCULANT ET DETTES CIRCULANTES HAO
A25: Note 8 | B25: STOCKS ET ENCOURS
A26: Note 9 | B26: ADHÉRENTS, CLIENTS-USAGERS
... A41: Note 22 | B41: BANQUES, CRÉDIT D'ESCOMPTE ET DE TRÉSORERIE
A42: Partie 3 : Notes sur le compte de résultat
A43: Note 23 | B43: REVENUS ET AUTRES PRODUITS
A44: Note 24 | B44: ACHATS
A45: Note 25 | B45: TRANSPORTS
A46: Note 26 | B46: SERVICES EXTÉRIEURS
A47: Note 27 | B47: IMPÔTS ET TAXES
A48: Note 28 | B48: AUTRES CHARGES
A49: Note 29A | B49: CHARGES DE PERSONNEL
A50: Note 29B | B50: EFFECTIFS, MASSE SALARIALE ET PERSONNEL EXTÉRIEUR
A51: Note 30 | B51: DOTATIONS ET CHARGES POUR PROVISIONS ET DÉPRÉCIATIONS
A52: Note 31 | B52: CHARGES ET REVENUS FINANCIERS
A53: Note 32 | B53: AUTRES CHARGES ET PRODUITS HAO
A54: Partie 4 : Autres informations
A55: Note 33 | B55: FICHE DE SYNTHÈSE DES PRINCIPAUX INDICATEURS FINANCIERS
A56: Note 34 | B56: LISTE DES INFORMATIONS SOCIALES, ENVIRONNEMENTALES ET SOCIÉTALES
A57: Note 35 | B57: TABLEAU D'EXÉCUTION BUDGÉTAIRE
A59: (1) Les notes non documentées ne doivent pas être jointes aux états financiers ; dans une note, les lignes non chiffrées doivent être supprimées.
A60: (2) A : applicable ; N/A : non applicable. Cocher la colonne correspondante pour chaque note.
A62: NOTE À COMPLÉTER

Sheet NOTE 1
A1: - 9 -
E2: NOTE 1 SYSTEME NORMAL
A3: Dénomination sociale :
A4: Adresse : | E4: Sigle usuel :
A5: N° de compte contribuable (NCC) : | C5: Exercice clos le | E5: Durée (en mois) : 12
A6: N° de télédéclarant (NTD) :
A7: NOTE 1 : DETTES GARANTIES PAR DES SÛRETÉS RÉELLES, ENGAGEMENTS FINANCIERS ET CONTRIBUTIONS VOLONTAIRES EN NATURE
A8: DETTES GARANTIES PAR DES SÛRETÉS RÉELLES
A9: Libellés | B9: Note | C9: Montant brut | D9: Hypothèques | E9: Nantissements | F9: Gages / autres
A10: Emprunts et dettes financières diverses : | B10: 18A
A11: Emprunts obligataires | C11: =SUMIF('BALANCE N'!$A$2:$A$2000,"181*",'BALANCE N'!$H$2:$H$2000)-SUMIF('BALANCE N'!$A$2:$A$2000,"181*",'BALANCE N'!$G$2:$G$2000)
A12: Emprunts et dettes des établissements de crédit | C12: =SUMIF('BALANCE N'!$A$2:$A$2000,"182*",'BALANCE N'!$H$2:$H$2000)-SUMIF('BALANCE N'!$A$2:$A$2000,"182*",'BALANCE N'!$G$2:$G$2000)
A13: Autres dettes financières | C13: =SUMIF('BALANCE N'!$A$2:$A$2000,"183*",'BALANCE N'!$H$2:$H$2000)-SUMIF('BALANCE N'!$A$2:$A$2000,"183*",'BALANCE N'!$G$2:$G$2000)+SUMIF('BALANCE N'!$A$2:$A$2000,"185*",'BALANCE N'!$H$2:$H$2000)-SUMIF('BALANCE N'!$A$2:$A$2000,"185*",'BALANCE N'!$G$2:$G$2000)+SUMIF('BALANCE N'!$A$2:$A$2000,"186*",'BALANCE N'!$H$2:$H$2000)-SUMIF('BALANCE N'!$A$2:$A$2000,"186*",'BALANCE N'!$G$2:$G$2000)+SUMIF('BALANCE N'!$A$2:$A$2000,"188*",'BALANCE N'!$H$2:$H$2000)-SUMIF('BALANCE N'!$A$2:$A$2000,"188*",'BALANCE N'!$G$2:$G$2000)
A14: Dettes de location-acquisition : | B14: 18A
A15: Dettes de crédit-bail immobilier | C15: =SUMIF('BALANCE N'!$A$2:$A$2000,"1871*",'BALANCE N'!$H$2:$H$2000)-SUMIF('BALANCE N'!$A$2:$A$2000,"1871*",'BALANCE N'!$G$2:$G$2000)
A16: Dettes de crédit-bail mobilier | C16: =SUMIF('BALANCE N'!$A$2:$A$2000,"1872*",'BALANCE N'!$H$2:$H$2000)-SUMIF('BALANCE N'!$A$2:$A$2000,"1872*",'BALANCE N'!$G$2:$G$2000)
A17: Dettes sur contrats de location-vente et autres | C17: =SUMIF('BALANCE N'!$A$2:$A$2000,"187*",'BALANCE N'!$H$2:$H$2000)-SUMIF('BALANCE N'!$A$2:$A$2000,"187*",'BALANCE N'!$G$2:$G$2000)-SUMIF('BALANCE N'!$A$2:$A$2000,"1871*",'BALANCE N'!$H$2:$H$2000)+SUMIF('BALANCE N'!$A$2:$A$2000,"1871*",'BALANCE N'!$G$2:$G$2000)-SUMIF('BALANCE N'!$A$2:$A$2000,"1872*",'BALANCE N'!$H$2:$H$2000)+SUMIF('BALANCE N'!$A$2:$A$2000,"1872*",'BALANCE N'!$G$2:$G$2000)-SUMIF('BALANCE N'!$A$2:$A$2000,"1873*",'BALANCE N'!$H$2:$H$2000)+SUMIF('BALANCE N'!$A$2:$A$2000,"1873*",'BALANCE N'!$G$2:$G$2000)-SUMIF('BALANCE N'!$A$2:$A$2000,"1876*",'BALANCE N'!$H$2:$H$2000)+SUMIF('BALANCE N'!$A$2:$A$2000,"1876*",'BALANCE N'!$G$2:$G$2000)
A18: Dettes du passif circulant :
A19: Fournisseurs et comptes rattachés | B19: 19 | C19: =SUMIF('BALANCE N'!$A$2:$A$2000,"40*",'BALANCE N'!$H$2:$H$2000)-SUMIF('BALANCE N'!$A$2:$A$2000,"409*",'BALANCE N'!$H$2:$H$2000)
A20: Adhérents, clients-usagers créditeurs | B20: 9 | C20: =SUMIF('BALANCE N'!$A$2:$A$2000,"419*",'BALANCE N'!$H$2:$H$2000)
A21: Personnel | B21: 20 | C21: =SUMIF('BALANCE N'!$A$2:$A$2000,"42*",'BALANCE N'!$H$2:$H$2000)
A22: Organismes sociaux | B22: 20 | C22: =SUMIF('BALANCE N'!$A$2:$A$2000,"43*",'BALANCE N'!$H$2:$H$2000)
A23: État et collectivités | B23: 20 | C23: =SUMIF('BALANCE N'!$A$2:$A$2000,"44*",'BALANCE N'!$H$2:$H$2000)
A24: Fondateurs, apporteurs et comptes rattachés | B24: 21 | C24: =SUMIF('BALANCE N'!$A$2:$A$2000,"45*",'BALANCE N'!$H$2:$H$2000)
A25: Bailleurs, État et autres organismes, fonds d'administration | B25: 21 | C25: =SUMIF('BALANCE N'!$A$2:$A$2000,"46*",'BALANCE N'!$H$2:$H$2000)
A26: Créditeurs divers | B26: 21 | C26: =SUMIF('BALANCE N'!$A$2:$A$2000,"47*",'BALANCE N'!$H$2:$H$2000)-SUMIF('BALANCE N'!$A$2:$A$2000,"478*",'BALANCE N'!$H$2:$H$2000)-SUMIF('BALANCE N'!$A$2:$A$2000,"479*",'BALANCE N'!$H$2:$H$2000)
A27: TOTAL | C27: =C11+C12+C13+C15+C16+C17+C19+C20+C21+C22+C23+C24+C25+C26
A29: Colonnes hypothèques / nantissements / gages : à servir depuis les actes de sûretés - la balance ne les porte pas. Indiquer la raison d'être des sûretés.
A31: ENGAGEMENTS FINANCIERS
A32: Libellés | B32: Engagements réciproques | C32: Engagements donnés | D32: Engagements reçus
A33: Avals, cautions, garanties
A34: Hypothèques, nantissements, gages, autres
A35: Effets escomptés non échus
A36: TOTAL | B36: =SUM(B33:B35) | C36: =SUM(C33:C35) | D36: =SUM(D33:D35)
A38: CONTRIBUTIONS VOLONTAIRES EN NATURE (classe 9)
A39: Libellés | B39: Ressources (91) | C39: Emplois (90)
A40: Dons en nature | B40: =SUMIF('BALANCE N'!$A$2:$A$2000,"910*",'BALANCE N'!$H$2:$H$2000)-SUMIF('BALANCE N'!$A$2:$A$2000,"910*",'BALANCE N'!$G$2:$G$2000) | C40: =SUMIF('BALANCE N'!$A$2:$A$2000,"900*",'BALANCE N'!$G$2:$G$2000)-SUMIF('BALANCE N'!$A$2:$A$2000,"900*",'BALANCE N'!$H$2:$H$2000)
A41: Mises à disposition gratuite des biens | C41: =SUMIF('BALANCE N'!$A$2:$A$2000,"901*",'BALANCE N'!$G$2:$G$2000)-SUMIF('BALANCE N'!$A$2:$A$2000,"901*",'BALANCE N'!$H$2:$H$2000)
A42: Prestations en nature | B42: =SUMIF('BALANCE N'!$A$2:$A$2000,"911*",'BALANCE N'!$H$2:$H$2000)-SUMIF('BALANCE N'!$A$2:$A$2000,"911*",'BALANCE N'!$G$2:$G$2000) | C42: =SUMIF('BALANCE N'!$A$2:$A$2000,"902*",'BALANCE N'!$G$2:$G$2000)-SUMIF('BALANCE N'!$A$2:$A$2000,"902*",'BALANCE N'!$H$2:$H$2000)
A43: Personnel bénévole | B43: =SUMIF('BALANCE N'!$A$2:$A$2000,"914*",'BALANCE N'!$H$2:$H$2000)-SUMIF('BALANCE N'!$A$2:$A$2000,"914*",'BALANCE N'!$G$2:$G$2000) | C43: =SUMIF('BALANCE N'!$A$2:$A$2000,"904*",'BALANCE N'!$G$2:$G$2000)-SUMIF('BALANCE N'!$A$2:$A$2000,"904*",'BALANCE N'!$H$2:$H$2000)
A44: TOTAL | B44: =SUM(B40:B43) | C44: =SUM(C40:C43)
A46: Évaluer les contributions volontaires à la valeur actuelle (cadre conceptuel SYCEBNL).
A48: =IF(SUM(B33:B44,C10:C44,D10:D36,E10:E26,F10:F26)=0,"NÉANT","")

Sheet NOTE 2
A1: - 10 -
E2: NOTE 2 SYSTEME NORMAL
A3: Dénomination sociale :
A4: Adresse : | E4: Sigle usuel :
A5: N° de compte contribuable (NCC) : | C5: Exercice clos le | E5: Durée (en mois) : 12
A6: N° de télédéclarant (NTD) :
A7: NOTE 2 : INFORMATIONS OBLIGATOIRES
A9: A - IDENTITÉ, ORGANISATION : décrire brièvement l'identité de l'entité (date de création, nature du projet associatif, mission) et l'organisation avec des données chiffrées (effectifs, nombre de bénévoles, total des revenus, moyens utilisés).
A12: B - DÉCLARATION DE CONFORMITÉ AU SYSTÈME COMPTABLE DES ENTITÉS À BUT NON LUCRATIF ET FAITS MARQUANTS DE L'EXERCICE.
A15: C - RÈGLES, MÉTHODES COMPTABLES ET DÉROGATION AUX PRINCIPES COMPTABLES.
A18: D - INFORMATIONS COMPLÉMENTAIRES RELATIVES AU BILAN, AU COMPTE DE RÉSULTAT ET AU TABLEAU DES FLUX DE TRÉSORERIE.
A21: NOTE À COMPLÉTER

Sheet NOTE 3
A1: - 11 -
E2: NOTE 3 SYSTEME NORMAL
A3: Dénomination sociale :
A4: Adresse : | E4: Sigle usuel :
A5: N° de compte contribuable (NCC) : | C5: Exercice clos le | E5: Durée (en mois) : 12
A6: N° de télédéclarant (NTD) :
A7: NOTE 3 : ÉVÈNEMENTS POSTÉRIEURS À LA CLÔTURE DE L'EXERCICE
A9: Date d'arrêté des états financiers :
A12: Organe ayant autorisé la publication des comptes :
A15: A - ÉVÈNEMENTS POSTÉRIEURS DONNANT LIEU À AJUSTEMENTS : nature des évènements et précisions sur les comptes ajustés.
A18: B - ÉVÈNEMENTS POSTÉRIEURS NE DONNANT PAS LIEU À AJUSTEMENTS : estimation de l'impact financier ou indication que l'estimation ne peut être fournie.
A21: C - ÉVÈNEMENTS REMETTANT EN CAUSE LA CONTINUITÉ DE L'EXPLOITATION : nature de l'évènement, valeurs liquidatives retenues.
A24: NOTE À COMPLÉTER

Sheet NOTE 4
A1: - 12 -
E2: NOTE 4 SYSTEME NORMAL
A3: Dénomination sociale :
A4: Adresse : | E4: Sigle usuel :
A5: N° de compte contribuable (NCC) : | C5: Exercice clos le | E5: Durée (en mois) : 12
A6: N° de télédéclarant (NTD) :
A7: NOTE 4 : CHANGEMENTS DE MÉTHODES COMPTABLES, D'ESTIMATIONS ET CORRECTIONS D'ERREURS
A9: A - CHANGEMENTS DE MÉTHODES COMPTABLES : 1. changement de réglementation comptable ; 2. changement à l'initiative de l'entité (impact à l'ouverture, retraitement rétrospectif ou application prospective).
A12: B - CHANGEMENTS D'ESTIMATIONS : indiquer et justifier le changement d'estimation.
A15: C - CORRECTIONS D'ERREURS : nature des erreurs corrigées et principaux postes retraités.
A18: NOTE À COMPLÉTER

Sheet NOTE 5A
A1: - 13 -
D2: NOTE 5A SYSTEME NORMAL
A3: Dénomination sociale :
A4: Adresse : | D4: Sigle usuel :
A5: N° de compte contribuable (NCC) : | C5: Exercice clos le | D5: Durée (en mois) : 12
A6: N° de télédéclarant (NTD) :
A7: NOTE 5A : DONS ET LEGS D'IMMOBILISATIONS NON REÇUS DESTINÉS À LA VENTE ET USUFRUIT TEMPORAIRE
A8: RUBRIQUES | B8: Montant brut à l'ouverture (A) | C8: Augmentations (B) | D8: Diminutions (C) | E8: Montant brut à la clôture (D = A + B - C)
A9: IMMOBILISATIONS INCORPORELLES
A10: Usufruit | B10: =SUMIF('BALANCE N-1'!$A$2:$A$2000,"2011*",'BALANCE N-1'!$G$2:$G$2000)-SUMIF('BALANCE N-1'!$A$2:$A$2000,"2011*",'BALANCE N-1'!$H$2:$H$2000) | C10: =MAX(0,(SUMIF('BALANCE N'!$A$2:$A$2000,"2011*",'BALANCE N'!$G$2:$G$2000)-SUMIF('BALANCE N'!$A$2:$A$2000,"2011*",'BALANCE N'!$H$2:$H$2000))-(SUMIF('BALANCE N-1'!$A$2:$A$2000,"2011*",'BALANCE N-1'!$G$2:$G$2000)-SUMIF('BALANCE N-1'!$A$2:$A$2000,"2011*",'BALANCE N-1'!$H$2:$H$2000))) | D10: =MAX(0,(SUMIF('BALANCE N-1'!$A$2:$A$2000,"2011*",'BALANCE N-1'!$G$2:$G$2000)-SUMIF('BALANCE N-1'!$A$2:$A$2000,"2011*",'BALANCE N-1'!$H$2:$H$2000))-(SUMIF('BALANCE N'!$A$2:$A$2000,"2011*",'BALANCE N'!$G$2:$G$2000)-SUMIF('BALANCE N'!$A$2:$A$2000,"2011*",'BALANCE N'!$H$2:$H$2000))) | E10: =B10+C10-D10
A11: Brevets, licences, logiciels et droits similaires | B11: =SUMIF('BALANCE N-1'!$A$2:$A$2000,"2012*",'BALANCE N-1'!$G$2:$G$2000)-SUMIF('BALANCE N-1'!$A$2:$A$2000,"2012*",'BALANCE N-1'!$H$2:$H$2000)+SUMIF('BALANCE N-1'!$A$2:$A$2000,"2013*",'BALANCE N-1'!$G$2:$G$2000)-SUMIF('BALANCE N-1'!$A$2:$A$2000,"2013*",'BALANCE N-1'!$H$2:$H$2000) | C11: =MAX(0,(SUMIF('BALANCE N'!$A$2:$A$2000,"2012*",'BALANCE N'!$G$2:$G$2000)-SUMIF('BALANCE N'!$A$2:$A$2000,"2012*",'BALANCE N'!$H$2:$H$2000)+SUMIF('BALANCE N'!$A$2:$A$2000,"2013*",'BALANCE N'!$G$2:$G$2000)-SUMIF('BALANCE N'!$A$2:$A$2000,"2013*",'BALANCE N'!$H$2:$H$2000))-(SUMIF('BALANCE N-1'!$A$2:$A$2000,"2012*",'BALANCE N-1'!$G$2:$G$2000)-SUMIF('BALANCE N-1'!$A$2:$A$2000,"2012*",'BALANCE N-1'!$H$2:$H$2000)+SUMIF('BALANCE N-1'!$A$2:$A$2000,"2013*",'BALANCE N-1'!$G$2:$G$2000)-SUMIF('BALANCE N-1'!$A$2:$A$2000,"2013*",'BALANCE N-1'!$H$2:$H$2000))) | D11: =MAX(0,(SUMIF('BALANCE N-1'!$A$2:$A$2000,"2012*",'BALANCE N-1'!$G$2:$G$2000)-SUMIF('BALANCE N-1'!$A$2:$A$2000,"2012*",'BALANCE N-1'!$H$2:$H$2000)+SUMIF('BALANCE N-1'!$A$2:$A$2000,"2013*",'BALANCE N-1'!$G$2:$G$2000)-SUMIF('BALANCE N-1'!$A$2:$A$2000,"2013*",'BALANCE N-1'!$H$2:$H$2000))-(SUMIF('BALANCE N'!$A$2:$A$2000,"2012*",'BALANCE N'!$G$2:$G$2000)-SUMIF('BALANCE N'!$A$2:$A$2000,"2012*",'BALANCE N'!$H$2:$H$2000)+SUMIF('BALANCE N'!$A$2:$A$2000,"2013*",'BALANCE N'!$G$2:$G$2000)-SUMIF('BALANCE N'!$A$2:$A$2000,"2013*",'BALANCE N'!$H$2:$H$2000))) | E11: =B11+C11-D11
A12: Autres immobilisations incorporelles | B12: =SUMIF('BALANCE N-1'!$A$2:$A$2000,"2014*",'BALANCE N-1'!$G$2:$G$2000)-SUMIF('BALANCE N-1'!$A$2:$A$2000,"2014*",'BALANCE N-1'!$H$2:$H$2000)+SUMIF('BALANCE N-1'!$A$2:$A$2000,"2017*",'BALANCE N-1'!$G$2:$G$2000)-SUMIF('BALANCE N-1'!$A$2:$A$2000,"2017*",'BALANCE N-1'!$H$2:$H$2000) | C12: =MAX(0,(SUMIF('BALANCE N'!$A$2:$A$2000,"2014*",'BALANCE N'!$G$2:$G$2000)-SUMIF('BALANCE N'!$A$2:$A$2000,"2014*",'BALANCE N'!$H$2:$H$2000)+SUMIF('BALANCE N'!$A$2:$A$2000,"2017*",'BALANCE N'!$G$2:$G$2000)-SUMIF('BALANCE N'!$A$2:$A$2000,"2017*",'BALANCE N'!$H$2:$H$2000))-(SUMIF('BALANCE N-1'!$A$2:$A$2000,"2014*",'BALANCE N-1'!$G$2:$G$2000)-SUMIF('BALANCE N-1'!$A$2:$A$2000,"2014*",'BALANCE N-1'!$H$2:$H$2000)+SUMIF('BALANCE N-1'!$A$2:$A$2000,"2017*",'BALANCE N-1'!$G$2:$G$2000)-SUMIF('BALANCE N-1'!$A$2:$A$2000,"2017*",'BALANCE N-1'!$H$2:$H$2000))) | D12: =MAX(0,(SUMIF('BALANCE N-1'!$A$2:$A$2000,"2014*",'BALANCE N-1'!$G$2:$G$2000)-SUMIF('BALANCE N-1'!$A$2:$A$2000,"2014*",'BALANCE N-1'!$H$2:$H$2000)+SUMIF('BALANCE N-1'!$A$2:$A$2000,"2017*",'BALANCE N-1'!$G$2:$G$2000)-SUMIF('BALANCE N-1'!$A$2:$A$2000,"2017*",'BALANCE N-1'!$H$2:$H$2000))-(SUMIF('BALANCE N'!$A$2:$A$2000,"2014*",'BALANCE N'!$G$2:$G$2000)-SUMIF('BALANCE N'!$A$2:$A$2000,"2014*",'BALANCE N'!$H$2:$H$2000)+SUMIF('BALANCE N'!$A$2:$A$2000,"2017*",'BALANCE N'!$G$2:$G$2000)-SUMIF('BALANCE N'!$A$2:$A$2000,"2017*",'BALANCE N'!$H$2:$H$2000))) | E12: =B12+C12-D12
A13: IMMOBILISATIONS CORPORELLES
A14: Terrains | B14: =SUMIF('BALANCE N-1'!$A$2:$A$2000,"202*",'BALANCE N-1'!$G$2:$G$2000)-SUMIF('BALANCE N-1'!$A$2:$A$2000,"202*",'BALANCE N-1'!$H$2:$H$2000) | C14: =MAX(0,(SUMIF('BALANCE N'!$A$2:$A$2000,"202*",'BALANCE N'!$G$2:$G$2000)-SUMIF('BALANCE N'!$A$2:$A$2000,"202*",'BALANCE N'!$H$2:$H$2000))-(SUMIF('BALANCE N-1'!$A$2:$A$2000,"202*",'BALANCE N-1'!$G$2:$G$2000)-SUMIF('BALANCE N-1'!$A$2:$A$2000,"202*",'BALANCE N-1'!$H$2:$H$2000))) | D14: =MAX(0,(SUMIF('BALANCE N-1'!$A$2:$A$2000,"202*",'BALANCE N-1'!$G$2:$G$2000)-SUMIF('BALANCE N-1'!$A$2:$A$2000,"202*",'BALANCE N-1'!$H$2:$H$2000))-(SUMIF('BALANCE N'!$A$2:$A$2000,"202*",'BALANCE N'!$G$2:$G$2000)-SUMIF('BALANCE N'!$A$2:$A$2000,"202*",'BALANCE N'!$H$2:$H$2000))) | E14: =B14+C14-D14
A15: Bâtiments | B15: =SUMIF('BALANCE N-1'!$A$2:$A$2000,"203*",'BALANCE N-1'!$G$2:$G$2000)-SUMIF('BALANCE N-1'!$A$2:$A$2000,"203*",'BALANCE N-1'!$H$2:$H$2000) | C15: =MAX(0,(SUMIF('BALANCE N'!$A$2:$A$2000,"203*",'BALANCE N'!$G$2:$G$2000)-SUMIF('BALANCE N'!$A$2:$A$2000,"203*",'BALANCE N'!$H$2:$H$2000))-(SUMIF('BALANCE N-1'!$A$2:$A$2000,"203*",'BALANCE N-1'!$G$2:$G$2000)-SUMIF('BALANCE N-1'!$A$2:$A$2000,"203*",'BALANCE N-1'!$H$2:$H$2000))) | D15: =MAX(0,(SUMIF('BALANCE N-1'!$A$2:$A$2000,"203*",'BALANCE N-1'!$G$2:$G$2000)-SUMIF('BALANCE N-1'!$A$2:$A$2000,"203*",'BALANCE N-1'!$H$2:$H$2000))-(SUMIF('BALANCE N'!$A$2:$A$2000,"203*",'BALANCE N'!$G$2:$G$2000)-SUMIF('BALANCE N'!$A$2:$A$2000,"203*",'BALANCE N'!$H$2:$H$2000))) | E15: =B15+C15-D15
A16: Matériels et mobiliers | B16: =SUMIF('BALANCE N-1'!$A$2:$A$2000,"204*",'BALANCE N-1'!$G$2:$G$2000)-SUMIF('BALANCE N-1'!$A$2:$A$2000,"204*",'BALANCE N-1'!$H$2:$H$2000) | C16: =MAX(0,(SUMIF('BALANCE N'!$A$2:$A$2000,"204*",'BALANCE N'!$G$2:$G$2000)-SUMIF('BALANCE N'!$A$2:$A$2000,"204*",'BALANCE N'!$H$2:$H$2000))-(SUMIF('BALANCE N-1'!$A$2:$A$2000,"204*",'BALANCE N-1'!$G$2:$G$2000)-SUMIF('BALANCE N-1'!$A$2:$A$2000,"204*",'BALANCE N-1'!$H$2:$H$2000))) | D16: =MAX(0,(SUMIF('BALANCE N-1'!$A$2:$A$2000,"204*",'BALANCE N-1'!$G$2:$G$2000)-SUMIF('BALANCE N-1'!$A$2:$A$2000,"204*",'BALANCE N-1'!$H$2:$H$2000))-(SUMIF('BALANCE N'!$A$2:$A$2000,"204*",'BALANCE N'!$G$2:$G$2000)-SUMIF('BALANCE N'!$A$2:$A$2000,"204*",'BALANCE N'!$H$2:$H$2000))) | E16: =B16+C16-D16
A17: IMMOBILISATIONS FINANCIÈRES
A18: Titres de participation | B18: =SUMIF('BALANCE N-1'!$A$2:$A$2000,"205*",'BALANCE N-1'!$G$2:$G$2000)-SUMIF('BALANCE N-1'!$A$2:$A$2000,"205*",'BALANCE N-1'!$H$2:$H$2000) | C18: =MAX(0,(SUMIF('BALANCE N'!$A$2:$A$2000,"205*",'BALANCE N'!$G$2:$G$2000)-SUMIF('BALANCE N'!$A$2:$A$2000,"205*",'BALANCE N'!$H$2:$H$2000))-(SUMIF('BALANCE N-1'!$A$2:$A$2000,"205*",'BALANCE N-1'!$G$2:$G$2000)-SUMIF('BALANCE N-1'!$A$2:$A$2000,"205*",'BALANCE N-1'!$H$2:$H$2000))) | D18: =MAX(0,(SUMIF('BALANCE N-1'!$A$2:$A$2000,"205*",'BALANCE N-1'!$G$2:$G$2000)-SUMIF('BALANCE N-1'!$A$2:$A$2000,"205*",'BALANCE N-1'!$H$2:$H$2000))-(SUMIF('BALANCE N'!$A$2:$A$2000,"205*",'BALANCE N'!$G$2:$G$2000)-SUMIF('BALANCE N'!$A$2:$A$2000,"205*",'BALANCE N'!$H$2:$H$2000))) | E18: =B18+C18-D18
A19: TOTAL GÉNÉRAL | B19: =B10+B11+B12+B14+B15+B16+B18 | C19: =C10+C11+C12+C14+C15+C16+C18 | D19: =D10+D11+D12+D14+D15+D16+D18 | E19: =E10+E11+E12+E14+E15+E16+E18
A21: Sans balance N-1, seule la colonne de clôture est servie ; avec N-1, les mouvements sont posés en variation nette (augmentation ou diminution) faute d'état des mouvements - à ajuster depuis l'inventaire des immobilisations.
A23: =IF(SUM(B9:B19,C9:C19,D9:D19,E9:E19)=0,"NÉANT","")

Sheet NOTE 5B
A1: - 14 -
D2: NOTE 5B SYSTEME NORMAL
A3: Dénomination sociale :
A4: Adresse : | D4: Sigle usuel :
A5: N° de compte contribuable (NCC) : | C5: Exercice clos le | D5: Durée (en mois) : 12
A6: N° de télédéclarant (NTD) :
A7: NOTE 5B : IMMOBILISATIONS BRUTES
A8: RUBRIQUES | B8: Montant brut à l'ouverture (A) | C8: Augmentations (B) | D8: Diminutions (C) | E8: Montant brut à la clôture (D = A + B - C)
A9: IMMOBILISATIONS INCORPORELLES
A10: Brevets, licences et droits similaires | B10: =SUMIF('BALANCE N-1'!$A$2:$A$2000,"212*",'BALANCE N-1'!$G$2:$G$2000)-SUMIF('BALANCE N-1'!$A$2:$A$2000,"212*",'BALANCE N-1'!$H$2:$H$2000)+SUMIF('BALANCE N-1'!$A$2:$A$2000,"214*",'BALANCE N-1'!$G$2:$G$2000)-SUMIF('BALANCE N-1'!$A$2:$A$2000,"214*",'BALANCE N-1'!$H$2:$H$2000)+SUMIF('BALANCE N-1'!$A$2:$A$2000,"218*",'BALANCE N-1'!$G$2:$G$2000)-SUMIF('BALANCE N-1'!$A$2:$A$2000,"218*",'BALANCE N-1'!$H$2:$H$2000) | C10: =MAX(0,(SUMIF('BALANCE N'!$A$2:$A$2000,"212*",'BALANCE N'!$G$2:$G$2000)-SUMIF('BALANCE N'!$A$2:$A$2000,"212*",'BALANCE N'!$H$2:$H$2000)+SUMIF('BALANCE N'!$A$2:$A$2000,"214*",'BALANCE N'!$G$2:$G$2000)-SUMIF('BALANCE N'!$A$2:$A$2000,"214*",'BALANCE N'!$H$2:$H$2000)+SUMIF('BALANCE N'!$A$2:$A$2000,"218*",'BALANCE N'!$G$2:$G$2000)-SUMIF('BALANCE N'!$A$2:$A$2000,"218*",'BALANCE N'!$H$2:$H$2000))-(SUMIF('BALANCE N-1'!$A$2:$A$2000,"212*",'BALANCE N-1'!$G$2:$G$2000)-SUMIF('BALANCE N-1'!$A$2:$A$2000,"212*",'BALANCE N-1'!$H$2:$H$2000)+SUMIF('BALANCE N-1'!$A$2:$A$2000,"214*",'BALANCE N-1'!$G$2:$G$2000)-SUMIF('BALANCE N-1'!$A$2:$A$2000,"214*",'BALANCE N-1'!$H$2:$H$2000)+SUMIF('BALANCE N-1'!$A$2:$A$2000,"218*",'BALANCE N-1'!$G$2:$G$2000)-SUMIF('BALANCE N-1'!$A$2:$A$2000,"218*",'BALANCE N-1'!$H$2:$H$2000))) | D10: =MAX(0,(SUMIF('BALANCE N-1'!$A$2:$A$2000,"212*",'BALANCE N-1'!$G$2:$G$2000)-SUMIF('BALANCE N-1'!$A$2:$A$2000,"212*",'BALANCE N-1'!$H$2:$H$2000)+SUMIF('BALANCE N-1'!$A$2:$A$2000,"214*",'BALANCE N-1'!$G$2:$G$2000)-SUMIF('BALANCE N-1'!$A$2:$A$2000,"214*",'BALANCE N-1'!$H$2:$H$2000)+SUMIF('BALANCE N-1'!$A$2:$A$2000,"218*",'BALANCE N-1'!$G$2:$G$2000)-SUMIF('BALANCE N-1'!$A$2:$A$2000,"218*",'BALANCE N-1'!$H$2:$H$2000))-(SUMIF('BALANCE N'!$A$2:$A$2000,"212*",'BALANCE N'!$G$2:$G$2000)-SUMIF('BALANCE N'!$A$2:$A$2000,"212*",'BALANCE N'!$H$2:$H$2000)+SUMIF('BALANCE N'!$A$2:$A$2000,"214*",'BALANCE N'!$G$2:$G$2000)-SUMIF('BALANCE N'!$A$2:$A$2000,"214*",'BALANCE N'!$H$2:$H$2000)+SUMIF('BALANCE N'!$A$2:$A$2000,"218*",'BALANCE N'!$G$2:$G$2000)-SUMIF('BALANCE N'!$A$2:$A$2000,"218*",'BALANCE N'!$H$2:$H$2000))) | E10: =B10+C10-D10
A11: Logiciels et sites internet | B11: =SUMIF('BALANCE N-1'!$A$2:$A$2000,"213*",'BALANCE N-1'!$G$2:$G$2000)-SUMIF('BALANCE N-1'!$A$2:$A$2000,"213*",'BALANCE N-1'!$H$2:$H$2000)+SUMIF('BALANCE N-1'!$A$2:$A$2000,"2193*",'BALANCE N-1'!$G$2:$G$2000)-SUMIF('BALANCE N-1'!$A$2:$A$2000,"2193*",'BALANCE N-1'!$H$2:$H$2000) | C11: =MAX(0,(SUMIF('BALANCE N'!$A$2:$A$2000,"213*",'BALANCE N'!$G$2:$G$2000)-SUMIF('BALANCE N'!$A$2:$A$2000,"213*",'BALANCE N'!$H$2:$H$2000)+SUMIF('BALANCE N'!$A$2:$A$2000,"2193*",'BALANCE N'!$G$2:$G$2000)-SUMIF('BALANCE N'!$A$2:$A$2000,"2193*",'BALANCE N'!$H$2:$H$2000))-(SUMIF('BALANCE N-1'!$A$2:$A$2000,"213*",'BALANCE N-1'!$G$2:$G$2000)-SUMIF('BALANCE N-1'!$A$2:$A$2000,"213*",'BALANCE N-1'!$H$2:$H$2000)+SUMIF('BALANCE N-1'!$A$2:$A$2000,"2193*",'BALANCE N-1'!$G$2:$G$2000)-SUMIF('BALANCE N-1'!$A$2:$A$2000,"2193*",'BALANCE N-1'!$H$2:$H$2000))) | D11: =MAX(0,(SUMIF('BALANCE N-1'!$A$2:$A$2000,"213*",'BALANCE N-1'!$G$2:$G$2000)-SUMIF('BALANCE N-1'!$A$2:$A$2000,"213*",'BALANCE N-1'!$H$2:$H$2000)+SUMIF('BALANCE N-1'!$A$2:$A$2000,"2193*",'BALANCE N-1'!$G$2:$G$2000)-SUMIF('BALANCE N-1'!$A$2:$A$2000,"2193*",'BALANCE N-1'!$H$2:$H$2000))-(SUMIF('BALANCE N'!$A$2:$A$2000,"213*",'BALANCE N'!$G$2:$G$2000)-SUMIF('BALANCE N'!$A$2:$A$2000,"213*",'BALANCE N'!$H$2:$H$2000)+SUMIF('BALANCE N'!$A$2:$A$2000,"2193*",'BALANCE N'!$G$2:$G$2000)-SUMIF('BALANCE N'!$A$2:$A$2000,"2193*",'BALANCE N'!$H$2:$H$2000))) | E11: =B11+C11-D11
A12: Avances et acomptes sur immobilisations incorporelles | B12: =SUMIF('BALANCE N-1'!$A$2:$A$2000,"251*",'BALANCE N-1'!$G$2:$G$2000)-SUMIF('BALANCE N-1'!$A$2:$A$2000,"251*",'BALANCE N-1'!$H$2:$H$2000) | C12: =MAX(0,(SUMIF('BALANCE N'!$A$2:$A$2000,"251*",'BALANCE N'!$G$2:$G$2000)-SUMIF('BALANCE N'!$A$2:$A$2000,"251*",'BALANCE N'!$H$2:$H$2000))-(SUMIF('BALANCE N-1'!$A$2:$A$2000,"251*",'BALANCE N-1'!$G$2:$G$2000)-SUMIF('BALANCE N-1'!$A$2:$A$2000,"251*",'BALANCE N-1'!$H$2:$H$2000))) | D12: =MAX(0,(SUMIF('BALANCE N-1'!$A$2:$A$2000,"251*",'BALANCE N-1'!$G$2:$G$2000)-SUMIF('BALANCE N-1'!$A$2:$A$2000,"251*",'BALANCE N-1'!$H$2:$H$2000))-(SUMIF('BALANCE N'!$A$2:$A$2000,"251*",'BALANCE N'!$G$2:$G$2000)-SUMIF('BALANCE N'!$A$2:$A$2000,"251*",'BALANCE N'!$H$2:$H$2000))) | E12: =B12+C12-D12
A13: Autres immobilisations incorporelles | B13: =SUMIF('BALANCE N-1'!$A$2:$A$2000,"2198*",'BALANCE N-1'!$G$2:$G$2000)-SUMIF('BALANCE N-1'!$A$2:$A$2000,"2198*",'BALANCE N-1'!$H$2:$H$2000) | C13: =MAX(0,(SUMIF('BALANCE N'!$A$2:$A$2000,"2198*",'BALANCE N'!$G$2:$G$2000)-SUMIF('BALANCE N'!$A$2:$A$2000,"2198*",'BALANCE N'!$H$2:$H$2000))-(SUMIF('BALANCE N-1'!$A$2:$A$2000,"2198*",'BALANCE N-1'!$G$2:$G$2000)-SUMIF('BALANCE N-1'!$A$2:$A$2000,"2198*",'BALANCE N-1'!$H$2:$H$2000))) | D13: =MAX(0,(SUMIF('BALANCE N-1'!$A$2:$A$2000,"2198*",'BALANCE N-1'!$G$2:$G$2000)-SUMIF('BALANCE N-1'!$A$2:$A$2000,"2198*",'BALANCE N-1'!$H$2:$H$2000))-(SUMIF('BALANCE N'!$A$2:$A$2000,"2198*",'BALANCE N'!$G$2:$G$2000)-SUMIF('BALANCE N'!$A$2:$A$2000,"2198*",'BALANCE N'!$H$2:$H$2000))) | E13: =B13+C13-D13
A14: IMMOBILISATIONS CORPORELLES
A15: Terrains hors immeuble de placement | B15: =SUMIF('BALANCE N-1'!$A$2:$A$2000,"22*",'BALANCE N-1'!$G$2:$G$2000)-SUMIF('BALANCE N-1'!$A$2:$A$2000,"22*",'BALANCE N-1'!$H$2:$H$2000)-SUMIF('BALANCE N-1'!$A$2:$A$2000,"2281*",'BALANCE N-1'!$G$2:$G$2000)+SUMIF('BALANCE N-1'!$A$2:$A$2000,"2281*",'BALANCE N-1'!$H$2:$H$2000) | C15: =MAX(0,(SUMIF('BALANCE N'!$A$2:$A$2000,"22*",'BALANCE N'!$G$2:$G$2000)-SUMIF('BALANCE N'!$A$2:$A$2000,"22*",'BALANCE N'!$H$2:$H$2000)-SUMIF('BALANCE N'!$A$2:$A$2000,"2281*",'BALANCE N'!$G$2:$G$2000)+SUMIF('BALANCE N'!$A$2:$A$2000,"2281*",'BALANCE N'!$H$2:$H$2000))-(SUMIF('BALANCE N-1'!$A$2:$A$2000,"22*",'BALANCE N-1'!$G$2:$G$2000)-SUMIF('BALANCE N-1'!$A$2:$A$2000,"22*",'BALANCE N-1'!$H$2:$H$2000)-SUMIF('BALANCE N-1'!$A$2:$A$2000,"2281*",'BALANCE N-1'!$G$2:$G$2000)+SUMIF('BALANCE N-1'!$A$2:$A$2000,"2281*",'BALANCE N-1'!$H$2:$H$2000))) | D15: =MAX(0,(SUMIF('BALANCE N-1'!$A$2:$A$2000,"22*",'BALANCE N-1'!$G$2:$G$2000)-SUMIF('BALANCE N-1'!$A$2:$A$2000,"22*",'BALANCE N-1'!$H$2:$H$2000)-SUMIF('BALANCE N-1'!$A$2:$A$2000,"2281*",'BALANCE N-1'!$G$2:$G$2000)+SUMIF('BALANCE N-1'!$A$2:$A$2000,"2281*",'BALANCE N-1'!$H$2:$H$2000))-(SUMIF('BALANCE N'!$A$2:$A$2000,"22*",'BALANCE N'!$G$2:$G$2000)-SUMIF('BALANCE N'!$A$2:$A$2000,"22*",'BALANCE N'!$H$2:$H$2000)-SUMIF('BALANCE N'!$A$2:$A$2000,"2281*",'BALANCE N'!$G$2:$G$2000)+SUMIF('BALANCE N'!$A$2:$A$2000,"2281*",'BALANCE N'!$H$2:$H$2000))) | E15: =B15+C15-D15
A16: Terrains - immeuble de placement | B16: =SUMIF('BALANCE N-1'!$A$2:$A$2000,"2281*",'BALANCE N-1'!$G$2:$G$2000)-SUMIF('BALANCE N-1'!$A$2:$A$2000,"2281*",'BALANCE N-1'!$H$2:$H$2000) | C16: =MAX(0,(SUMIF('BALANCE N'!$A$2:$A$2000,"2281*",'BALANCE N'!$G$2:$G$2000)-SUMIF('BALANCE N'!$A$2:$A$2000,"2281*",'BALANCE N'!$H$2:$H$2000))-(SUMIF('BALANCE N-1'!$A$2:$A$2000,"2281*",'BALANCE N-1'!$G$2:$G$2000)-SUMIF('BALANCE N-1'!$A$2:$A$2000,"2281*",'BALANCE N-1'!$H$2:$H$2000))) | D16: =MAX(0,(SUMIF('BALANCE N-1'!$A$2:$A$2000,"2281*",'BALANCE N-1'!$G$2:$G$2000)-SUMIF('BALANCE N-1'!$A$2:$A$2000,"2281*",'BALANCE N-1'!$H$2:$H$2000))-(SUMIF('BALANCE N'!$A$2:$A$2000,"2281*",'BALANCE N'!$G$2:$G$2000)-SUMIF('BALANCE N'!$A$2:$A$2000,"2281*",'BALANCE N'!$H$2:$H$2000))) | E16: =B16+C16-D16
A17: Bâtiments hors immeuble de placement | B17: =SUMIF('BALANCE N-1'!$A$2:$A$2000,"231*",'BALANCE N-1'!$G$2:$G$2000)-SUMIF('BALANCE N-1'!$A$2:$A$2000,"231*",'BALANCE N-1'!$H$2:$H$2000)+SUMIF('BALANCE N-1'!$A$2:$A$2000,"232*",'BALANCE N-1'!$G$2:$G$2000)-SUMIF('BALANCE N-1'!$A$2:$A$2000,"232*",'BALANCE N-1'!$H$2:$H$2000)+SUMIF('BALANCE N-1'!$A$2:$A$2000,"233*",'BALANCE N-1'!$G$2:$G$2000)-SUMIF('BALANCE N-1'!$A$2:$A$2000,"233*",'BALANCE N-1'!$H$2:$H$2000)+SUMIF('BALANCE N-1'!$A$2:$A$2000,"2391*",'BALANCE N-1'!$G$2:$G$2000)-SUMIF('BALANCE N-1'!$A$2:$A$2000,"2391*",'BALANCE N-1'!$H$2:$H$2000)+SUMIF('BALANCE N-1'!$A$2:$A$2000,"2392*",'BALANCE N-1'!$G$2:$G$2000)-SUMIF('BALANCE N-1'!$A$2:$A$2000,"2392*",'BALANCE N-1'!$H$2:$H$2000)+SUMIF('BALANCE N-1'!$A$2:$A$2000,"2393*",'BALANCE N-1'!$G$2:$G$2000)-SUMIF('BALANCE N-1'!$A$2:$A$2000,"2393*",'BALANCE N-1'!$H$2:$H$2000)-SUMIF('BALANCE N-1'!$A$2:$A$2000,"2315*",'BALANCE N-1'!$G$2:$G$2000)+SUMIF('BALANCE N-1'!$A$2:$A$2000,"2315*",'BALANCE N-1'!$H$2:$H$2000)-SUMIF('BALANCE N-1'!$A$2:$A$2000,"2325*",'BALANCE N-1'!$G$2:$G$2000)+SUMIF('BALANCE N-1'!$A$2:$A$2000,"2325*",'BALANCE N-1'!$H$2:$H$2000) | C17: =MAX(0,(SUMIF('BALANCE N'!$A$2:$A$2000,"231*",'BALANCE N'!$G$2:$G$2000)-SUMIF('BALANCE N'!$A$2:$A$2000,"231*",'BALANCE N'!$H$2:$H$2000)+SUMIF('BALANCE N'!$A$2:$A$2000,"232*",'BALANCE N'!$G$2:$G$2000)-SUMIF('BALANCE N'!$A$2:$A$2000,"232*",'BALANCE N'!$H$2:$H$2000)+SUMIF('BALANCE N'!$A$2:$A$2000,"233*",'BALANCE N'!$G$2:$G$2000)-SUMIF('BALANCE N'!$A$2:$A$2000,"233*",'BALANCE N'!$H$2:$H$2000)+SUMIF('BALANCE N'!$A$2:$A$2000,"2391*",'BALANCE N'!$G$2:$G$2000)-SUMIF('BALANCE N'!$A$2:$A$2000,"2391*",'BALANCE N'!$H$2:$H$2000)+SUMIF('BALANCE N'!$A$2:$A$2000,"2392*",'BALANCE N'!$G$2:$G$2000)-SUMIF('BALANCE N'!$A$2:$A$2000,"2392*",'BALANCE N'!$H$2:$H$2000)+SUMIF('BALANCE N'!$A$2:$A$2000,"2393*",'BALANCE N'!$G$2:$G$2000)-SUMIF('BALANCE N'!$A$2:$A$2000,"2393*",'BALANCE N'!$H$2:$H$2000)-SUMIF('BALANCE N'!$A$2:$A$2000,"2315*",'BALANCE N'!$G$2:$G$2000)+SUMIF('BALANCE N'!$A$2:$A$2000,"2315*",'BALANCE N'!$H$2:$H$2000)-SUMIF('BALANCE N'!$A$2:$A$2000,"2325*",'BALANCE N'!$G$2:$G$2000)+SUMIF('BALANCE N'!$A$2:$A$2000,"2325*",'BALANCE N'!$H$2:$H$2000))-(SUMIF('BALANCE N-1'!$A$2:$A$2000,"231*",'BALANCE N-1'!$G$2:$G$2000)-SUMIF('BALANCE N-1'!$A$2:$A$2000,"231*",'BALANCE N-1'!$H$2:$H$2000)+SUMIF('BALANCE N-1'!$A$2:$A$2000,"232*",'BALANCE N-1'!$G$2:$G$2000)-SUMIF('BALANCE N-1'!$A$2:$A$2000,"232*",'BALANCE N-1'!$H$2:$H$2000)+SUMIF('BALANCE N-1'!$A$2:$A$2000,"233*",'BALANCE N-1'!$G$2:$G$2000)-SUMIF('BALANCE N-1'!$A$2:$A$2000,"233*",'BALANCE N-1'!$H$2:$H$2000)+SUMIF('BALANCE N-1'!$A$2:$A$2000,"2391*",'BALANCE N-1'!$G$2:$G$2000)-SUMIF('BALANCE N-1'!$A$2:$A$2000,"2391*",'BALANCE N-1'!$H$2:$H$2000)+SUMIF('BALANCE N-1'!$A$2:$A$2000,"2392*",'BALANCE N-1'!$G$2:$G$2000)-SUMIF('BALANCE N-1'!$A$2:$A$2000,"2392*",'BALANCE N-1'!$H$2:$H$2000)+SUMIF('BALANCE N-1'!$A$2:$A$2000,"2393*",'BALANCE N-1'!$G$2:$G$2000)-SUMIF('BALANCE N-1'!$A$2:$A$2000,"2393*",'BALANCE N-1'!$H$2:$H$2000)-SUMIF('BALANCE N-1'!$A$2:$A$2000,"2315*",'BALANCE N-1'!$G$2:$G$2000)+SUMIF('BALANCE N-1'!$A$2:$A$2000,"2315*",'BALANCE N-1'!$H$2:$H$2000)-SUMIF('BALANCE N-1'!$A$2:$A$2000,"2325*",'BALANCE N-1'!$G$2:$G$2000)+SUMIF('BALANCE N-1'!$A$2:$A$2000,"2325*",'BALANCE N-1'!$H$2:$H$2000))) | D17: =MAX(0,(SUMIF('BALANCE N-1'!$A$2:$A$2000,"231*",'BALANCE N-1'!$G$2:$G$2000)-SUMIF('BALANCE N-1'!$A$2:$A$2000,"231*",'BALANCE N-1'!$H$2:$H$2000)+SUMIF('BALANCE N-1'!$A$2:$A$2000,"232*",'BALANCE N-1'!$G$2:$G$2000)-SUMIF('BALANCE N-1'!$A$2:$A$2000,"232*",'BALANCE N-1'!$H$2:$H$2000)+SUMIF('BALANCE N-1'!$A$2:$A$2000,"233*",'BALANCE N-1'!$G$2:$G$2000)-SUMIF('BALANCE N-1'!$A$2:$A$2000,"233*",'BALANCE N-1'!$H$2:$H$2000)+SUMIF('BALANCE N-1'!$A$2:$A$2000,"2391*",'BALANCE N-1'!$G$2:$G$2000)-SUMIF('BALANCE N-1'!$A$2:$A$2000,"2391*",'BALANCE N-1'!$H$2:$H$2000)+SUMIF('BALANCE N-1'!$A$2:$A$2000,"2392*",'BALANCE N-1'!$G$2:$G$2000)-SUMIF('BALANCE N-1'!$A$2:$A$2000,"2392*",'BALANCE N-1'!$H$2:$H$2000)+SUMIF('BALANCE N-1'!$A$2:$A$2000,"2393*",'BALANCE N-1'!$G$2:$G$2000)-SUMIF('BALANCE N-1'!$A$2:$A$2000,"2393*",'BALANCE N-1'!$H$2:$H$2000)-SUMIF('BALANCE N-1'!$A$2:$A$2000,"2315*",'BALANCE N-1'!$G$2:$G$2000)+SUMIF('BALANCE N-1'!$A$2:$A$2000,"2315*",'BALANCE N-1'!$H$2:$H$2000)-SUMIF('BALANCE N-1'!$A$2:$A$2000,"2325*",'BALANCE N-1'!$G$2:$G$2000)+SUMIF('BALANCE N-1'!$A$2:$A$2000,"2325*",'BALANCE N-1'!$H$2:$H$2000))-(SUMIF('BALANCE N'!$A$2:$A$2000,"231*",'BALANCE N'!$G$2:$G$2000)-SUMIF('BALANCE N'!$A$2:$A$2000,"231*",'BALANCE N'!$H$2:$H$2000)+SUMIF('BALANCE N'!$A$2:$A$2000,"232*",'BALANCE N'!$G$2:$G$2000)-SUMIF('BALANCE N'!$A$2:$A$2000,"232*",'BALANCE N'!$H$2:$H$2000)+SUMIF('BALANCE N'!$A$2:$A$2000,"233*",'BALANCE N'!$G$2:$G$2000)-SUMIF('BALANCE N'!$A$2:$A$2000,"233*",'BALANCE N'!$H$2:$H$2000)+SUMIF('BALANCE N'!$A$2:$A$2000,"2391*",'BALANCE N'!$G$2:$G$2000)-SUMIF('BALANCE N'!$A$2:$A$2000,"2391*",'BALANCE N'!$H$2:$H$2000)+SUMIF('BALANCE N'!$A$2:$A$2000,"2392*",'BALANCE N'!$G$2:$G$2000)-SUMIF('BALANCE N'!$A$2:$A$2000,"2392*",'BALANCE N'!$H$2:$H$2000)+SUMIF('BALANCE N'!$A$2:$A$2000,"2393*",'BALANCE N'!$G$2:$G$2000)-SUMIF('BALANCE N'!$A$2:$A$2000,"2393*",'BALANCE N'!$H$2:$H$2000)-SUMIF('BALANCE N'!$A$2:$A$2000,"2315*",'BALANCE N'!$G$2:$G$2000)+SUMIF('BALANCE N'!$A$2:$A$2000,"2315*",'BALANCE N'!$H$2:$H$2000)-SUMIF('BALANCE N'!$A$2:$A$2000,"2325*",'BALANCE N'!$G$2:$G$2000)+SUMIF('BALANCE N'!$A$2:$A$2000,"2325*",'BALANCE N'!$H$2:$H$2000))) | E17: =B17+C17-D17
A18: Bâtiments - immeuble de placement | B18: =SUMIF('BALANCE N-1'!$A$2:$A$2000,"2315*",'BALANCE N-1'!$G$2:$G$2000)-SUMIF('BALANCE N-1'!$A$2:$A$2000,"2315*",'BALANCE N-1'!$H$2:$H$2000)+SUMIF('BALANCE N-1'!$A$2:$A$2000,"2325*",'BALANCE N-1'!$G$2:$G$2000)-SUMIF('BALANCE N-1'!$A$2:$A$2000,"2325*",'BALANCE N-1'!$H$2:$H$2000)+SUMIF('BALANCE N-1'!$A$2:$A$2000,"2396*",'BALANCE N-1'!$G$2:$G$2000)-SUMIF('BALANCE N-1'!$A$2:$A$2000,"2396*",'BALANCE N-1'!$H$2:$H$2000) | C18: =MAX(0,(SUMIF('BALANCE N'!$A$2:$A$2000,"2315*",'BALANCE N'!$G$2:$G$2000)-SUMIF('BALANCE N'!$A$2:$A$2000,"2315*",'BALANCE N'!$H$2:$H$2000)+SUMIF('BALANCE N'!$A$2:$A$2000,"2325*",'BALANCE N'!$G$2:$G$2000)-SUMIF('BALANCE N'!$A$2:$A$2000,"2325*",'BALANCE N'!$H$2:$H$2000)+SUMIF('BALANCE N'!$A$2:$A$2000,"2396*",'BALANCE N'!$G$2:$G$2000)-SUMIF('BALANCE N'!$A$2:$A$2000,"2396*",'BALANCE N'!$H$2:$H$2000))-(SUMIF('BALANCE N-1'!$A$2:$A$2000,"2315*",'BALANCE N-1'!$G$2:$G$2000)-SUMIF('BALANCE N-1'!$A$2:$A$2000,"2315*",'BALANCE N-1'!$H$2:$H$2000)+SUMIF('BALANCE N-1'!$A$2:$A$2000,"2325*",'BALANCE N-1'!$G$2:$G$2000)-SUMIF('BALANCE N-1'!$A$2:$A$2000,"2325*",'BALANCE N-1'!$H$2:$H$2000)+SUMIF('BALANCE N-1'!$A$2:$A$2000,"2396*",'BALANCE N-1'!$G$2:$G$2000)-SUMIF('BALANCE N-1'!$A$2:$A$2000,"2396*",'BALANCE N-1'!$H$2:$H$2000))) | D18: =MAX(0,(SUMIF('BALANCE N-1'!$A$2:$A$2000,"2315*",'BALANCE N-1'!$G$2:$G$2000)-SUMIF('BALANCE N-1'!$A$2:$A$2000,"2315*",'BALANCE N-1'!$H$2:$H$2000)+SUMIF('BALANCE N-1'!$A$2:$A$2000,"2325*",'BALANCE N-1'!$G$2:$G$2000)-SUMIF('BALANCE N-1'!$A$2:$A$2000,"2325*",'BALANCE N-1'!$H$2:$H$2000)+SUMIF('BALANCE N-1'!$A$2:$A$2000,"2396*",'BALANCE N-1'!$G$2:$G$2000)-SUMIF('BALANCE N-1'!$A$2:$A$2000,"2396*",'BALANCE N-1'!$H$2:$H$2000))-(SUMIF('BALANCE N'!$A$2:$A$2000,"2315*",'BALANCE N'!$G$2:$G$2000)-SUMIF('BALANCE N'!$A$2:$A$2000,"2315*",'BALANCE N'!$H$2:$H$2000)+SUMIF('BALANCE N'!$A$2:$A$2000,"2325*",'BALANCE N'!$G$2:$G$2000)-SUMIF('BALANCE N'!$A$2:$A$2000,"2325*",'BALANCE N'!$H$2:$H$2000)+SUMIF('BALANCE N'!$A$2:$A$2000,"2396*",'BALANCE N'!$G$2:$G$2000)-SUMIF('BALANCE N'!$A$2:$A$2000,"2396*",'BALANCE N'!$H$2:$H$2000))) | E18: =B18+C18-D18
A19: Aménagements, agencements et installations | B19: =SUMIF('BALANCE N-1'!$A$2:$A$2000,"234*",'BALANCE N-1'!$G$2:$G$2000)-SUMIF('BALANCE N-1'!$A$2:$A$2000,"234*",'BALANCE N-1'!$H$2:$H$2000)+SUMIF('BALANCE N-1'!$A$2:$A$2000,"235*",'BALANCE N-1'!$G$2:$G$2000)-SUMIF('BALANCE N-1'!$A$2:$A$2000,"235*",'BALANCE N-1'!$H$2:$H$2000)+SUMIF('BALANCE N-1'!$A$2:$A$2000,"238*",'BALANCE N-1'!$G$2:$G$2000)-SUMIF('BALANCE N-1'!$A$2:$A$2000,"238*",'BALANCE N-1'!$H$2:$H$2000)+SUMIF('BALANCE N-1'!$A$2:$A$2000,"2394*",'BALANCE N-1'!$G$2:$G$2000)-SUMIF('BALANCE N-1'!$A$2:$A$2000,"2394*",'BALANCE N-1'!$H$2:$H$2000)+SUMIF('BALANCE N-1'!$A$2:$A$2000,"2395*",'BALANCE N-1'!$G$2:$G$2000)-SUMIF('BALANCE N-1'!$A$2:$A$2000,"2395*",'BALANCE N-1'!$H$2:$H$2000)+SUMIF('BALANCE N-1'!$A$2:$A$2000,"2398*",'BALANCE N-1'!$G$2:$G$2000)-SUMIF('BALANCE N-1'!$A$2:$A$2000,"2398*",'BALANCE N-1'!$H$2:$H$2000) | C19: =MAX(0,(SUMIF('BALANCE N'!$A$2:$A$2000,"234*",'BALANCE N'!$G$2:$G$2000)-SUMIF('BALANCE N'!$A$2:$A$2000,"234*",'BALANCE N'!$H$2:$H$2000)+SUMIF('BALANCE N'!$A$2:$A$2000,"235*",'BALANCE N'!$G$2:$G$2000)-SUMIF('BALANCE N'!$A$2:$A$2000,"235*",'BALANCE N'!$H$2:$H$2000)+SUMIF('BALANCE N'!$A$2:$A$2000,"238*",'BALANCE N'!$G$2:$G$2000)-SUMIF('BALANCE N'!$A$2:$A$2000,"238*",'BALANCE N'!$H$2:$H$2000)+SUMIF('BALANCE N'!$A$2:$A$2000,"2394*",'BALANCE N'!$G$2:$G$2000)-SUMIF('BALANCE N'!$A$2:$A$2000,"2394*",'BALANCE N'!$H$2:$H$2000)+SUMIF('BALANCE N'!$A$2:$A$2000,"2395*",'BALANCE N'!$G$2:$G$2000)-SUMIF('BALANCE N'!$A$2:$A$2000,"2395*",'BALANCE N'!$H$2:$H$2000)+SUMIF('BALANCE N'!$A$2:$A$2000,"2398*",'BALANCE N'!$G$2:$G$2000)-SUMIF('BALANCE N'!$A$2:$A$2000,"2398*",'BALANCE N'!$H$2:$H$2000))-(SUMIF('BALANCE N-1'!$A$2:$A$2000,"234*",'BALANCE N-1'!$G$2:$G$2000)-SUMIF('BALANCE N-1'!$A$2:$A$2000,"234*",'BALANCE N-1'!$H$2:$H$2000)+SUMIF('BALANCE N-1'!$A$2:$A$2000,"235*",'BALANCE N-1'!$G$2:$G$2000)-SUMIF('BALANCE N-1'!$A$2:$A$2000,"235*",'BALANCE N-1'!$H$2:$H$2000)+SUMIF('BALANCE N-1'!$A$2:$A$2000,"238*",'BALANCE N-1'!$G$2:$G$2000)-SUMIF('BALANCE N-1'!$A$2:$A$2000,"238*",'BALANCE N-1'!$H$2:$H$2000)+SUMIF('BALANCE N-1'!$A$2:$A$2000,"2394*",'BALANCE N-1'!$G$2:$G$2000)-SUMIF('BALANCE N-1'!$A$2:$A$2000,"2394*",'BALANCE N-1'!$H$2:$H$2000)+SUMIF('BALANCE N-1'!$A$2:$A$2000,"2395*",'BALANCE N-1'!$G$2:$G$2000)-SUMIF('BALANCE N-1'!$A$2:$A$2000,"2395*",'BALANCE N-1'!$H$2:$H$2000)+SUMIF('BALANCE N-1'!$A$2:$A$2000,"2398*",'BALANCE N-1'!$G$2:$G$2000)-SUMIF('BALANCE N-1'!$A$2:$A$2000,"2398*",'BALANCE N-1'!$H$2:$H$2000))) | D19: =MAX(0,(SUMIF('BALANCE N-1'!$A$2:$A$2000,"234*",'BALANCE N-1'!$G$2:$G$2000)-SUMIF('BALANCE N-1'!$A$2:$A$2000,"234*",'BALANCE N-1'!$H$2:$H$2000)+SUMIF('BALANCE N-1'!$A$2:$A$2000,"235*",'BALANCE N-1'!$G$2:$G$2000)-SUMIF('BALANCE N-1'!$A$2:$A$2000,"235*",'BALANCE N-1'!$H$2:$H$2000)+SUMIF('BALANCE N-1'!$A$2:$A$2000,"238*",'BALANCE N-1'!$G$2:$G$2000)-SUMIF('BALANCE N-1'!$A$2:$A$2000,"238*",'BALANCE N-1'!$H$2:$H$2000)+SUMIF('BALANCE N-1'!$A$2:$A$2000,"2394*",'BALANCE N-1'!$G$2:$G$2000)-SUMIF('BALANCE N-1'!$A$2:$A$2000,"2394*",'BALANCE N-1'!$H$2:$H$2000)+SUMIF('BALANCE N-1'!$A$2:$A$2000,"2395*",'BALANCE N-1'!$G$2:$G$2000)-SUMIF('BALANCE N-1'!$A$2:$A$2000,"2395*",'BALANCE N-1'!$H$2:$H$2000)+SUMIF('BALANCE N-1'!$A$2:$A$2000,"2398*",'BALANCE N-1'!$G$2:$G$2000)-SUMIF('BALANCE N-1'!$A$2:$A$2000,"2398*",'BALANCE N-1'!$H$2:$H$2000))-(SUMIF('BALANCE N'!$A$2:$A$2000,"234*",'BALANCE N'!$G$2:$G$2000)-SUMIF('BALANCE N'!$A$2:$A$2000,"234*",'BALANCE N'!$H$2:$H$2000)+SUMIF('BALANCE N'!$A$2:$A$2000,"235*",'BALANCE N'!$G$2:$G$2000)-SUMIF('BALANCE N'!$A$2:$A$2000,"235*",'BALANCE N'!$H$2:$H$2000)+SUMIF('BALANCE N'!$A$2:$A$2000,"238*",'BALANCE N'!$G$2:$G$2000)-SUMIF('BALANCE N'!$A$2:$A$2000,"238*",'BALANCE N'!$H$2:$H$2000)+SUMIF('BALANCE N'!$A$2:$A$2000,"2394*",'BALANCE N'!$G$2:$G$2000)-SUMIF('BALANCE N'!$A$2:$A$2000,"2394*",'BALANCE N'!$H$2:$H$2000)+SUMIF('BALANCE N'!$A$2:$A$2000,"2395*",'BALANCE N'!$G$2:$G$2000)-SUMIF('BALANCE N'!$A$2:$A$2000,"2395*",'BALANCE N'!$H$2:$H$2000)+SUMIF('BALANCE N'!$A$2:$A$2000,"2398*",'BALANCE N'!$G$2:$G$2000)-SUMIF('BALANCE N'!$A$2:$A$2000,"2398*",'BALANCE N'!$H$2:$H$2000))) | E19: =B19+C19-D19
A20: Matériel, mobilier et actifs biologiques | B20: =SUMIF('BALANCE N-1'!$A$2:$A$2000,"24*",'BALANCE N-1'!$G$2:$G$2000)-SUMIF('BALANCE N-1'!$A$2:$A$2000,"24*",'BALANCE N-1'!$H$2:$H$2000)-SUMIF('BALANCE N-1'!$A$2:$A$2000,"245*",'BALANCE N-1'!$G$2:$G$2000)+SUMIF('BALANCE N-1'!$A$2:$A$2000,"245*",'BALANCE N-1'!$H$2:$H$2000)-SUMIF('BALANCE N-1'!$A$2:$A$2000,"2495*",'BALANCE N-1'!$G$2:$G$2000)+SUMIF('BALANCE N-1'!$A$2:$A$2000,"2495*",'BALANCE N-1'!$H$2:$H$2000) | C20: =MAX(0,(SUMIF('BALANCE N'!$A$2:$A$2000,"24*",'BALANCE N'!$G$2:$G$2000)-SUMIF('BALANCE N'!$A$2:$A$2000,"24*",'BALANCE N'!$H$2:$H$2000)-SUMIF('BALANCE N'!$A$2:$A$2000,"245*",'BALANCE N'!$G$2:$G$2000)+SUMIF('BALANCE N'!$A$2:$A$2000,"245*",'BALANCE N'!$H$2:$H$2000)-SUMIF('BALANCE N'!$A$2:$A$2000,"2495*",'BALANCE N'!$G$2:$G$2000)+SUMIF('BALANCE N'!$A$2:$A$2000,"2495*",'BALANCE N'!$H$2:$H$2000))-(SUMIF('BALANCE N-1'!$A$2:$A$2000,"24*",'BALANCE N-1'!$G$2:$G$2000)-SUMIF('BALANCE N-1'!$A$2:$A$2000,"24*",'BALANCE N-1'!$H$2:$H$2000)-SUMIF('BALANCE N-1'!$A$2:$A$2000,"245*",'BALANCE N-1'!$G$2:$G$2000)+SUMIF('BALANCE N-1'!$A$2:$A$2000,"245*",'BALANCE N-1'!$H$2:$H$2000)-SUMIF('BALANCE N-1'!$A$2:$A$2000,"2495*",'BALANCE N-1'!$G$2:$G$2000)+SUMIF('BALANCE N-1'!$A$2:$A$2000,"2495*",'BALANCE N-1'!$H$2:$H$2000))) | D20: =MAX(0,(SUMIF('BALANCE N-1'!$A$2:$A$2000,"24*",'BALANCE N-1'!$G$2:$G$2000)-SUMIF('BALANCE N-1'!$A$2:$A$2000,"24*",'BALANCE N-1'!$H$2:$H$2000)-SUMIF('BALANCE N-1'!$A$2:$A$2000,"245*",'BALANCE N-1'!$G$2:$G$2000)+SUMIF('BALANCE N-1'!$A$2:$A$2000,"245*",'BALANCE N-1'!$H$2:$H$2000)-SUMIF('BALANCE N-1'!$A$2:$A$2000,"2495*",'BALANCE N-1'!$G$2:$G$2000)+SUMIF('BALANCE N-1'!$A$2:$A$2000,"2495*",'BALANCE N-1'!$H$2:$H$2000))-(SUMIF('BALANCE N'!$A$2:$A$2000,"24*",'BALANCE N'!$G$2:$G$2000)-SUMIF('BALANCE N'!$A$2:$A$2000,"24*",'BALANCE N'!$H$2:$H$2000)-SUMIF('BALANCE N'!$A$2:$A$2000,"245*",'BALANCE N'!$G$2:$G$2000)+SUMIF('BALANCE N'!$A$2:$A$2000,"245*",'BALANCE N'!$H$2:$H$2000)-SUMIF('BALANCE N'!$A$2:$A$2000,"2495*",'BALANCE N'!$G$2:$G$2000)+SUMIF('BALANCE N'!$A$2:$A$2000,"2495*",'BALANCE N'!$H$2:$H$2000))) | E20: =B20+C20-D20
A21: Matériel de transport | B21: =SUMIF('BALANCE N-1'!$A$2:$A$2000,"245*",'BALANCE N-1'!$G$2:$G$2000)-SUMIF('BALANCE N-1'!$A$2:$A$2000,"245*",'BALANCE N-1'!$H$2:$H$2000)+SUMIF('BALANCE N-1'!$A$2:$A$2000,"2495*",'BALANCE N-1'!$G$2:$G$2000)-SUMIF('BALANCE N-1'!$A$2:$A$2000,"2495*",'BALANCE N-1'!$H$2:$H$2000) | C21: =MAX(0,(SUMIF('BALANCE N'!$A$2:$A$2000,"245*",'BALANCE N'!$G$2:$G$2000)-SUMIF('BALANCE N'!$A$2:$A$2000,"245*",'BALANCE N'!$H$2:$H$2000)+SUMIF('BALANCE N'!$A$2:$A$2000,"2495*",'BALANCE N'!$G$2:$G$2000)-SUMIF('BALANCE N'!$A$2:$A$2000,"2495*",'BALANCE N'!$H$2:$H$2000))-(SUMIF('BALANCE N-1'!$A$2:$A$2000,"245*",'BALANCE N-1'!$G$2:$G$2000)-SUMIF('BALANCE N-1'!$A$2:$A$2000,"245*",'BALANCE N-1'!$H$2:$H$2000)+SUMIF('BALANCE N-1'!$A$2:$A$2000,"2495*",'BALANCE N-1'!$G$2:$G$2000)-SUMIF('BALANCE N-1'!$A$2:$A$2000,"2495*",'BALANCE N-1'!$H$2:$H$2000))) | D21: =MAX(0,(SUMIF('BALANCE N-1'!$A$2:$A$2000,"245*",'BALANCE N-1'!$G$2:$G$2000)-SUMIF('BALANCE N-1'!$A$2:$A$2000,"245*",'BALANCE N-1'!$H$2:$H$2000)+SUMIF('BALANCE N-1'!$A$2:$A$2000,"2495*",'BALANCE N-1'!$G$2:$G$2000)-SUMIF('BALANCE N-1'!$A$2:$A$2000,"2495*",'BALANCE N-1'!$H$2:$H$2000))-(SUMIF('BALANCE N'!$A$2:$A$2000,"245*",'BALANCE N'!$G$2:$G$2000)-SUMIF('BALANCE N'!$A$2:$A$2000,"245*",'BALANCE N'!$H$2:$H$2000)+SUMIF('BALANCE N'!$A$2:$A$2000,"2495*",'BALANCE N'!$G$2:$G$2000)-SUMIF('BALANCE N'!$A$2:$A$2000,"2495*",'BALANCE N'!$H$2:$H$2000))) | E21: =B21+C21-D21
A22: Avances et acomptes sur immobilisations corporelles | B22: =SUMIF('BALANCE N-1'!$A$2:$A$2000,"252*",'BALANCE N-1'!$G$2:$G$2000)-SUMIF('BALANCE N-1'!$A$2:$A$2000,"252*",'BALANCE N-1'!$H$2:$H$2000) | C22: =MAX(0,(SUMIF('BALANCE N'!$A$2:$A$2000,"252*",'BALANCE N'!$G$2:$G$2000)-SUMIF('BALANCE N'!$A$2:$A$2000,"252*",'BALANCE N'!$H$2:$H$2000))-(SUMIF('BALANCE N-1'!$A$2:$A$2000,"252*",'BALANCE N-1'!$G$2:$G$2000)-SUMIF('BALANCE N-1'!$A$2:$A$2000,"252*",'BALANCE N-1'!$H$2:$H$2000))) | D22: =MAX(0,(SUMIF('BALANCE N-1'!$A$2:$A$2000,"252*",'BALANCE N-1'!$G$2:$G$2000)-SUMIF('BALANCE N-1'!$A$2:$A$2000,"252*",'BALANCE N-1'!$H$2:$H$2000))-(SUMIF('BALANCE N'!$A$2:$A$2000,"252*",'BALANCE N'!$G$2:$G$2000)-SUMIF('BALANCE N'!$A$2:$A$2000,"252*",'BALANCE N'!$H$2:$H$2000))) | E22: =B22+C22-D22
A23: IMMOBILISATIONS FINANCIÈRES
A24: Titres de participation | B24: =SUMIF('BALANCE N-1'!$A$2:$A$2000,"26*",'BALANCE N-1'!$G$2:$G$2000)-SUMIF('BALANCE N-1'!$A$2:$A$2000,"26*",'BALANCE N-1'!$H$2:$H$2000) | C24: =MAX(0,(SUMIF('BALANCE N'!$A$2:$A$2000,"26*",'BALANCE N'!$G$2:$G$2000)-SUMIF('BALANCE N'!$A$2:$A$2000,"26*",'BALANCE N'!$H$2:$H$2000))-(SUMIF('BALANCE N-1'!$A$2:$A$2000,"26*",'BALANCE N-1'!$G$2:$G$2000)-SUMIF('BALANCE N-1'!$A$2:$A$2000,"26*",'BALANCE N-1'!$H$2:$H$2000))) | D24: =MAX(0,(SUMIF('BALANCE N-1'!$A$2:$A$2000,"26*",'BALANCE N-1'!$G$2:$G$2000)-SUMIF('BALANCE N-1'!$A$2:$A$2000,"26*",'BALANCE N-1'!$H$2:$H$2000))-(SUMIF('BALANCE N'!$A$2:$A$2000,"26*",'BALANCE N'!$G$2:$G$2000)-SUMIF('BALANCE N'!$A$2:$A$2000,"26*",'BALANCE N'!$H$2:$H$2000))) | E24: =B24+C24-D24
A25: Autres immobilisations financières | B25: =SUMIF('BALANCE N-1'!$A$2:$A$2000,"27*",'BALANCE N-1'!$G$2:$G$2000)-SUMIF('BALANCE N-1'!$A$2:$A$2000,"27*",'BALANCE N-1'!$H$2:$H$2000) | C25: =MAX(0,(SUMIF('BALANCE N'!$A$2:$A$2000,"27*",'BALANCE N'!$G$2:$G$2000)-SUMIF('BALANCE N'!$A$2:$A$2000,"27*",'BALANCE N'!$H$2:$H$2000))-(SUMIF('BALANCE N-1'!$A$2:$A$2000,"27*",'BALANCE N-1'!$G$2:$G$2000)-SUMIF('BALANCE N-1'!$A$2:$A$2000,"27*",'BALANCE N-1'!$H$2:$H$2000))) | D25: =MAX(0,(SUMIF('BALANCE N-1'!$A$2:$A$2000,"27*",'BALANCE N-1'!$G$2:$G$2000)-SUMIF('BALANCE N-1'!$A$2:$A$2000,"27*",'BALANCE N-1'!$H$2:$H$2000))-(SUMIF('BALANCE N'!$A$2:$A$2000,"27*",'BALANCE N'!$G$2:$G$2000)-SUMIF('BALANCE N'!$A$2:$A$2000,"27*",'BALANCE N'!$H$2:$H$2000))) | E25: =B25+C25-D25
A26: TOTAL GÉNÉRAL | B26: =B10+B11+B12+B13+B15+B16+B17+B18+B19+B20+B21+B22+B24+B25 | C26: =C10+C11+C12+C13+C15+C16+C17+C18+C19+C20+C21+C22+C24+C25 | D26: =D10+D11+D12+D13+D15+D16+D17+D18+D19+D20+D21+D22+D24+D25 | E26: =E10+E11+E12+E13+E15+E16+E17+E18+E19+E20+E21+E22+E24+E25
A28: Sans balance N-1, seule la colonne de clôture est servie ; avec N-1, les mouvements sont posés en variation nette (augmentation ou diminution) faute d'état des mouvements - à ajuster depuis l'inventaire des immobilisations.
A30: =IF(SUM(B9:B26,C9:C26,D9:D26,E9:E26)=0,"NÉANT","")

Sheet NOTE 5C
A1: - 15 -
D2: NOTE 5C SYSTEME NORMAL
A3: Dénomination sociale :
A4: Adresse : | D4: Sigle usuel :
A5: N° de compte contribuable (NCC) : | C5: Exercice clos le | D5: Durée (en mois) : 12
A6: N° de télédéclarant (NTD) :
A7: NOTE 5C : BIENS PRIS EN LOCATION-ACQUISITION
A8: I : crédit-bail immobilier ; M : crédit-bail mobilier ; A : autres contrats
A9: RUBRIQUES | B9: Montant brut à l'ouverture (A) | C9: Augmentations (B) | D9: Diminutions (C) | E9: Montant brut à la clôture (D = A + B - C)
A10: Terrains | B10: =SUMIF('BALANCE N-1'!$A$2:$A$2000,"2286*",'BALANCE N-1'!$G$2:$G$2000)-SUMIF('BALANCE N-1'!$A$2:$A$2000,"2286*",'BALANCE N-1'!$H$2:$H$2000) | C10: =MAX(0,(SUMIF('BALANCE N'!$A$2:$A$2000,"2286*",'BALANCE N'!$G$2:$G$2000)-SUMIF('BALANCE N'!$A$2:$A$2000,"2286*",'BALANCE N'!$H$2:$H$2000))-(SUMIF('BALANCE N-1'!$A$2:$A$2000,"2286*",'BALANCE N-1'!$G$2:$G$2000)-SUMIF('BALANCE N-1'!$A$2:$A$2000,"2286*",'BALANCE N-1'!$H$2:$H$2000))) | D10: =MAX(0,(SUMIF('BALANCE N-1'!$A$2:$A$2000,"2286*",'BALANCE N-1'!$G$2:$G$2000)-SUMIF('BALANCE N-1'!$A$2:$A$2000,"2286*",'BALANCE N-1'!$H$2:$H$2000))-(SUMIF('BALANCE N'!$A$2:$A$2000,"2286*",'BALANCE N'!$G$2:$G$2000)-SUMIF('BALANCE N'!$A$2:$A$2000,"2286*",'BALANCE N'!$H$2:$H$2000))) | E10: =B10+C10-D10
A11: Bâtiments | B11: =SUMIF('BALANCE N-1'!$A$2:$A$2000,"2316*",'BALANCE N-1'!$G$2:$G$2000)-SUMIF('BALANCE N-1'!$A$2:$A$2000,"2316*",'BALANCE N-1'!$H$2:$H$2000) | C11: =MAX(0,(SUMIF('BALANCE N'!$A$2:$A$2000,"2316*",'BALANCE N'!$G$2:$G$2000)-SUMIF('BALANCE N'!$A$2:$A$2000,"2316*",'BALANCE N'!$H$2:$H$2000))-(SUMIF('BALANCE N-1'!$A$2:$A$2000,"2316*",'BALANCE N-1'!$G$2:$G$2000)-SUMIF('BALANCE N-1'!$A$2:$A$2000,"2316*",'BALANCE N-1'!$H$2:$H$2000))) | D11: =MAX(0,(SUMIF('BALANCE N-1'!$A$2:$A$2000,"2316*",'BALANCE N-1'!$G$2:$G$2000)-SUMIF('BALANCE N-1'!$A$2:$A$2000,"2316*",'BALANCE N-1'!$H$2:$H$2000))-(SUMIF('BALANCE N'!$A$2:$A$2000,"2316*",'BALANCE N'!$G$2:$G$2000)-SUMIF('BALANCE N'!$A$2:$A$2000,"2316*",'BALANCE N'!$H$2:$H$2000))) | E11: =B11+C11-D11
A12: Matériel, mobilier | B12: =SUMIF('BALANCE N-1'!$A$2:$A$2000,"2416*",'BALANCE N-1'!$G$2:$G$2000)-SUMIF('BALANCE N-1'!$A$2:$A$2000,"2416*",'BALANCE N-1'!$H$2:$H$2000)+SUMIF('BALANCE N-1'!$A$2:$A$2000,"2426*",'BALANCE N-1'!$G$2:$G$2000)-SUMIF('BALANCE N-1'!$A$2:$A$2000,"2426*",'BALANCE N-1'!$H$2:$H$2000)+SUMIF('BALANCE N-1'!$A$2:$A$2000,"2446*",'BALANCE N-1'!$G$2:$G$2000)-SUMIF('BALANCE N-1'!$A$2:$A$2000,"2446*",'BALANCE N-1'!$H$2:$H$2000) | C12: =MAX(0,(SUMIF('BALANCE N'!$A$2:$A$2000,"2416*",'BALANCE N'!$G$2:$G$2000)-SUMIF('BALANCE N'!$A$2:$A$2000,"2416*",'BALANCE N'!$H$2:$H$2000)+SUMIF('BALANCE N'!$A$2:$A$2000,"2426*",'BALANCE N'!$G$2:$G$2000)-SUMIF('BALANCE N'!$A$2:$A$2000,"2426*",'BALANCE N'!$H$2:$H$2000)+SUMIF('BALANCE N'!$A$2:$A$2000,"2446*",'BALANCE N'!$G$2:$G$2000)-SUMIF('BALANCE N'!$A$2:$A$2000,"2446*",'BALANCE N'!$H$2:$H$2000))-(SUMIF('BALANCE N-1'!$A$2:$A$2000,"2416*",'BALANCE N-1'!$G$2:$G$2000)-SUMIF('BALANCE N-1'!$A$2:$A$2000,"2416*",'BALANCE N-1'!$H$2:$H$2000)+SUMIF('BALANCE N-1'!$A$2:$A$2000,"2426*",'BALANCE N-1'!$G$2:$G$2000)-SUMIF('BALANCE N-1'!$A$2:$A$2000,"2426*",'BALANCE N-1'!$H$2:$H$2000)+SUMIF('BALANCE N-1'!$A$2:$A$2000,"2446*",'BALANCE N-1'!$G$2:$G$2000)-SUMIF('BALANCE N-1'!$A$2:$A$2000,"2446*",'BALANCE N-1'!$H$2:$H$2000))) | D12: =MAX(0,(SUMIF('BALANCE N-1'!$A$2:$A$2000,"2416*",'BALANCE N-1'!$G$2:$G$2000)-SUMIF('BALANCE N-1'!$A$2:$A$2000,"2416*",'BALANCE N-1'!$H$2:$H$2000)+SUMIF('BALANCE N-1'!$A$2:$A$2000,"2426*",'BALANCE N-1'!$G$2:$G$2000)-SUMIF('BALANCE N-1'!$A$2:$A$2000,"2426*",'BALANCE N-1'!$H$2:$H$2000)+SUMIF('BALANCE N-1'!$A$2:$A$2000,"2446*",'BALANCE N-1'!$G$2:$G$2000)-SUMIF('BALANCE N-1'!$A$2:$A$2000,"2446*",'BALANCE N-1'!$H$2:$H$2000))-(SUMIF('BALANCE N'!$A$2:$A$2000,"2416*",'BALANCE N'!$G$2:$G$2000)-SUMIF('BALANCE N'!$A$2:$A$2000,"2416*",'BALANCE N'!$H$2:$H$2000)+SUMIF('BALANCE N'!$A$2:$A$2000,"2426*",'BALANCE N'!$G$2:$G$2000)-SUMIF('BALANCE N'!$A$2:$A$2000,"2426*",'BALANCE N'!$H$2:$H$2000)+SUMIF('BALANCE N'!$A$2:$A$2000,"2446*",'BALANCE N'!$G$2:$G$2000)-SUMIF('BALANCE N'!$A$2:$A$2000,"2446*",'BALANCE N'!$H$2:$H$2000))) | E12: =B12+C12-D12
A13: Matériel de transport | B13: =SUMIF('BALANCE N-1'!$A$2:$A$2000,"2456*",'BALANCE N-1'!$G$2:$G$2000)-SUMIF('BALANCE N-1'!$A$2:$A$2000,"2456*",'BALANCE N-1'!$H$2:$H$2000) | C13: =MAX(0,(SUMIF('BALANCE N'!$A$2:$A$2000,"2456*",'BALANCE N'!$G$2:$G$2000)-SUMIF('BALANCE N'!$A$2:$A$2000,"2456*",'BALANCE N'!$H$2:$H$2000))-(SUMIF('BALANCE N-1'!$A$2:$A$2000,"2456*",'BALANCE N-1'!$G$2:$G$2000)-SUMIF('BALANCE N-1'!$A$2:$A$2000,"2456*",'BALANCE N-1'!$H$2:$H$2000))) | D13: =MAX(0,(SUMIF('BALANCE N-1'!$A$2:$A$2000,"2456*",'BALANCE N-1'!$G$2:$G$2000)-SUMIF('BALANCE N-1'!$A$2:$A$2000,"2456*",'BALANCE N-1'!$H$2:$H$2000))-(SUMIF('BALANCE N'!$A$2:$A$2000,"2456*",'BALANCE N'!$G$2:$G$2000)-SUMIF('BALANCE N'!$A$2:$A$2000,"2456*",'BALANCE N'!$H$2:$H$2000))) | E13: =B13+C13-D13
A14: TOTAL GÉNÉRAL | B14: =B10+B11+B12+B13 | C14: =C10+C11+C12+C13 | D14: =D10+D11+D12+D13 | E14: =E10+E11+E12+E13
A16: Sans balance N-1, seule la colonne de clôture est servie ; avec N-1, les mouvements sont posés en variation nette (augmentation ou diminution) faute d'état des mouvements - à ajuster depuis l'inventaire des immobilisations.
A18: =IF(SUM(B10:B14,C10:C14,D10:D14,E10:E14)=0,"NÉANT","")

Sheet NOTE 5D
A1: - 16 -
D2: NOTE 5D SYSTEME NORMAL
A3: Dénomination sociale :
A4: Adresse : | D4: Sigle usuel :
A5: N° de compte contribuable (NCC) : | C5: Exercice clos le | D5: Durée (en mois) : 12
A6: N° de télédéclarant (NTD) :
A7: NOTE 5D : DONS ET LEGS D'IMMOBILISATIONS NON REÇUS DESTINÉS À LA VENTE ET USUFRUIT TEMPORAIRE (AMORTISSEMENTS ET DÉPRÉCIATIONS)
A8: RUBRIQUES | B8: Cumul à l'ouverture (A) | C8: Augmentations : dotations (B) | D8: Diminutions : reprises et sorties (C) | E8: Cumul à la clôture (D = A + B - C)
A9: Usufruit | B9: =SUMIF('BALANCE N-1'!$A$2:$A$2000,"280*",'BALANCE N-1'!$H$2:$H$2000)-SUMIF('BALANCE N-1'!$A$2:$A$2000,"280*",'BALANCE N-1'!$G$2:$G$2000)+SUMIF('BALANCE N-1'!$A$2:$A$2000,"2901*",'BALANCE N-1'!$H$2:$H$2000)-SUMIF('BALANCE N-1'!$A$2:$A$2000,"2901*",'BALANCE N-1'!$G$2:$G$2000) | C9: =MAX(0,(SUMIF('BALANCE N'!$A$2:$A$2000,"280*",'BALANCE N'!$H$2:$H$2000)-SUMIF('BALANCE N'!$A$2:$A$2000,"280*",'BALANCE N'!$G$2:$G$2000)+SUMIF('BALANCE N'!$A$2:$A$2000,"2901*",'BALANCE N'!$H$2:$H$2000)-SUMIF('BALANCE N'!$A$2:$A$2000,"2901*",'BALANCE N'!$G$2:$G$2000))-(SUMIF('BALANCE N-1'!$A$2:$A$2000,"280*",'BALANCE N-1'!$H$2:$H$2000)-SUMIF('BALANCE N-1'!$A$2:$A$2000,"280*",'BALANCE N-1'!$G$2:$G$2000)+SUMIF('BALANCE N-1'!$A$2:$A$2000,"2901*",'BALANCE N-1'!$H$2:$H$2000)-SUMIF('BALANCE N-1'!$A$2:$A$2000,"2901*",'BALANCE N-1'!$G$2:$G$2000))) | D9: =MAX(0,(SUMIF('BALANCE N-1'!$A$2:$A$2000,"280*",'BALANCE N-1'!$H$2:$H$2000)-SUMIF('BALANCE N-1'!$A$2:$A$2000,"280*",'BALANCE N-1'!$G$2:$G$2000)+SUMIF('BALANCE N-1'!$A$2:$A$2000,"2901*",'BALANCE N-1'!$H$2:$H$2000)-SUMIF('BALANCE N-1'!$A$2:$A$2000,"2901*",'BALANCE N-1'!$G$2:$G$2000))-(SUMIF('BALANCE N'!$A$2:$A$2000,"280*",'BALANCE N'!$H$2:$H$2000)-SUMIF('BALANCE N'!$A$2:$A$2000,"280*",'BALANCE N'!$G$2:$G$2000)+SUMIF('BALANCE N'!$A$2:$A$2000,"2901*",'BALANCE N'!$H$2:$H$2000)-SUMIF('BALANCE N'!$A$2:$A$2000,"2901*",'BALANCE N'!$G$2:$G$2000))) | E9: =B9+C9-D9
A10: Immobilisations destinées à la vente (dons et legs) | B10: =SUMIF('BALANCE N-1'!$A$2:$A$2000,"2902*",'BALANCE N-1'!$H$2:$H$2000)-SUMIF('BALANCE N-1'!$A$2:$A$2000,"2902*",'BALANCE N-1'!$G$2:$G$2000) | C10: =MAX(0,(SUMIF('BALANCE N'!$A$2:$A$2000,"2902*",'BALANCE N'!$H$2:$H$2000)-SUMIF('BALANCE N'!$A$2:$A$2000,"2902*",'BALANCE N'!$G$2:$G$2000))-(SUMIF('BALANCE N-1'!$A$2:$A$2000,"2902*",'BALANCE N-1'!$H$2:$H$2000)-SUMIF('BALANCE N-1'!$A$2:$A$2000,"2902*",'BALANCE N-1'!$G$2:$G$2000))) | D10: =MAX(0,(SUMIF('BALANCE N-1'!$A$2:$A$2000,"2902*",'BALANCE N-1'!$H$2:$H$2000)-SUMIF('BALANCE N-1'!$A$2:$A$2000,"2902*",'BALANCE N-1'!$G$2:$G$2000))-(SUMIF('BALANCE N'!$A$2:$A$2000,"2902*",'BALANCE N'!$H$2:$H$2000)-SUMIF('BALANCE N'!$A$2:$A$2000,"2902*",'BALANCE N'!$G$2:$G$2000))) | E10: =B10+C10-D10
A11: TOTAL GÉNÉRAL | B11: =B9+B10 | C11: =C9+C10 | D11: =D9+D10 | E11: =E9+E10
A13: Sans balance N-1, seule la colonne de clôture est servie ; avec N-1, les mouvements sont posés en variation nette (augmentation ou diminution) faute d'état des mouvements - à ajuster depuis l'inventaire des immobilisations.
A15: =IF(SUM(B9:B11,C9:C11,D9:D11,E9:E11)=0,"NÉANT","")

Sheet NOTE 5E
A1: - 17 -
D2: NOTE 5E SYSTEME NORMAL
A3: Dénomination sociale :
A4: Adresse : | D4: Sigle usuel :
A5: N° de compte contribuable (NCC) : | C5: Exercice clos le | D5: Durée (en mois) : 12
A6: N° de télédéclarant (NTD) :
A7: NOTE 5E : IMMOBILISATIONS : AMORTISSEMENTS
A8: RUBRIQUES | B8: Cumul à l'ouverture (A) | C8: Augmentations : dotations (B) | D8: Diminutions : reprises et sorties (C) | E8: Cumul à la clôture (D = A + B - C)
A9: IMMOBILISATIONS INCORPORELLES
A10: Brevets, licences et droits similaires | B10: =SUMIF('BALANCE N-1'!$A$2:$A$2000,"2812*",'BALANCE N-1'!$H$2:$H$2000)-SUMIF('BALANCE N-1'!$A$2:$A$2000,"2812*",'BALANCE N-1'!$G$2:$G$2000)+SUMIF('BALANCE N-1'!$A$2:$A$2000,"2814*",'BALANCE N-1'!$H$2:$H$2000)-SUMIF('BALANCE N-1'!$A$2:$A$2000,"2814*",'BALANCE N-1'!$G$2:$G$2000)+SUMIF('BALANCE N-1'!$A$2:$A$2000,"2817*",'BALANCE N-1'!$H$2:$H$2000)-SUMIF('BALANCE N-1'!$A$2:$A$2000,"2817*",'BALANCE N-1'!$G$2:$G$2000) | C10: =MAX(0,(SUMIF('BALANCE N'!$A$2:$A$2000,"2812*",'BALANCE N'!$H$2:$H$2000)-SUMIF('BALANCE N'!$A$2:$A$2000,"2812*",'BALANCE N'!$G$2:$G$2000)+SUMIF('BALANCE N'!$A$2:$A$2000,"2814*",'BALANCE N'!$H$2:$H$2000)-SUMIF('BALANCE N'!$A$2:$A$2000,"2814*",'BALANCE N'!$G$2:$G$2000)+SUMIF('BALANCE N'!$A$2:$A$2000,"2817*",'BALANCE N'!$H$2:$H$2000)-SUMIF('BALANCE N'!$A$2:$A$2000,"2817*",'BALANCE N'!$G$2:$G$2000))-(SUMIF('BALANCE N-1'!$A$2:$A$2000,"2812*",'BALANCE N-1'!$H$2:$H$2000)-SUMIF('BALANCE N-1'!$A$2:$A$2000,"2812*",'BALANCE N-1'!$G$2:$G$2000)+SUMIF('BALANCE N-1'!$A$2:$A$2000,"2814*",'BALANCE N-1'!$H$2:$H$2000)-SUMIF('BALANCE N-1'!$A$2:$A$2000,"2814*",'BALANCE N-1'!$G$2:$G$2000)+SUMIF('BALANCE N-1'!$A$2:$A$2000,"2817*",'BALANCE N-1'!$H$2:$H$2000)-SUMIF('BALANCE N-1'!$A$2:$A$2000,"2817*",'BALANCE N-1'!$G$2:$G$2000))) | D10: =MAX(0,(SUMIF('BALANCE N-1'!$A$2:$A$2000,"2812*",'BALANCE N-1'!$H$2:$H$2000)-SUMIF('BALANCE N-1'!$A$2:$A$2000,"2812*",'BALANCE N-1'!$G$2:$G$2000)+SUMIF('BALANCE N-1'!$A$2:$A$2000,"2814*",'BALANCE N-1'!$H$2:$H$2000)-SUMIF('BALANCE N-1'!$A$2:$A$2000,"2814*",'BALANCE N-1'!$G$2:$G$2000)+SUMIF('BALANCE N-1'!$A$2:$A$2000,"2817*",'BALANCE N-1'!$H$2:$H$2000)-SUMIF('BALANCE N-1'!$A$2:$A$2000,"2817*",'BALANCE N-1'!$G$2:$G$2000))-(SUMIF('BALANCE N'!$A$2:$A$2000,"2812*",'BALANCE N'!$H$2:$H$2000)-SUMIF('BALANCE N'!$A$2:$A$2000,"2812*",'BALANCE N'!$G$2:$G$2000)+SUMIF('BALANCE N'!$A$2:$A$2000,"2814*",'BALANCE N'!$H$2:$H$2000)-SUMIF('BALANCE N'!$A$2:$A$2000,"2814*",'BALANCE N'!$G$2:$G$2000)+SUMIF('BALANCE N'!$A$2:$A$2000,"2817*",'BALANCE N'!$H$2:$H$2000)-SUMIF('BALANCE N'!$A$2:$A$2000,"2817*",'BALANCE N'!$G$2:$G$2000))) | E10: =B10+C10-D10
A11: Logiciels et sites internet | B11: =SUMIF('BALANCE N-1'!$A$2:$A$2000,"2813*",'BALANCE N-1'!$H$2:$H$2000)-SUMIF('BALANCE N-1'!$A$2:$A$2000,"2813*",'BALANCE N-1'!$G$2:$G$2000) | C11: =MAX(0,(SUMIF('BALANCE N'!$A$2:$A$2000,"2813*",'BALANCE N'!$H$2:$H$2000)-SUMIF('BALANCE N'!$A$2:$A$2000,"2813*",'BALANCE N'!$G$2:$G$2000))-(SUMIF('BALANCE N-1'!$A$2:$A$2000,"2813*",'BALANCE N-1'!$H$2:$H$2000)-SUMIF('BALANCE N-1'!$A$2:$A$2000,"2813*",'BALANCE N-1'!$G$2:$G$2000))) | D11: =MAX(0,(SUMIF('BALANCE N-1'!$A$2:$A$2000,"2813*",'BALANCE N-1'!$H$2:$H$2000)-SUMIF('BALANCE N-1'!$A$2:$A$2000,"2813*",'BALANCE N-1'!$G$2:$G$2000))-(SUMIF('BALANCE N'!$A$2:$A$2000,"2813*",'BALANCE N'!$H$2:$H$2000)-SUMIF('BALANCE N'!$A$2:$A$2000,"2813*",'BALANCE N'!$G$2:$G$2000))) | E11: =B11+C11-D11
A12: Autres immobilisations incorporelles | B12: =SUMIF('BALANCE N-1'!$A$2:$A$2000,"2818*",'BALANCE N-1'!$H$2:$H$2000)-SUMIF('BALANCE N-1'!$A$2:$A$2000,"2818*",'BALANCE N-1'!$G$2:$G$2000) | C12: =MAX(0,(SUMIF('BALANCE N'!$A$2:$A$2000,"2818*",'BALANCE N'!$H$2:$H$2000)-SUMIF('BALANCE N'!$A$2:$A$2000,"2818*",'BALANCE N'!$G$2:$G$2000))-(SUMIF('BALANCE N-1'!$A$2:$A$2000,"2818*",'BALANCE N-1'!$H$2:$H$2000)-SUMIF('BALANCE N-1'!$A$2:$A$2000,"2818*",'BALANCE N-1'!$G$2:$G$2000))) | D12: =MAX(0,(SUMIF('BALANCE N-1'!$A$2:$A$2000,"2818*",'BALANCE N-1'!$H$2:$H$2000)-SUMIF('BALANCE N-1'!$A$2:$A$2000,"2818*",'BALANCE N-1'!$G$2:$G$2000))-(SUMIF('BALANCE N'!$A$2:$A$2000,"2818*",'BALANCE N'!$H$2:$H$2000)-SUMIF('BALANCE N'!$A$2:$A$2000,"2818*",'BALANCE N'!$G$2:$G$2000))) | E12: =B12+C12-D12
A13: IMMOBILISATIONS CORPORELLES
A14: Terrains | B14: =SUMIF('BALANCE N-1'!$A$2:$A$2000,"282*",'BALANCE N-1'!$H$2:$H$2000)-SUMIF('BALANCE N-1'!$A$2:$A$2000,"282*",'BALANCE N-1'!$G$2:$G$2000) | C14: =MAX(0,(SUMIF('BALANCE N'!$A$2:$A$2000,"282*",'BALANCE N'!$H$2:$H$2000)-SUMIF('BALANCE N'!$A$2:$A$2000,"282*",'BALANCE N'!$G$2:$G$2000))-(SUMIF('BALANCE N-1'!$A$2:$A$2000,"282*",'BALANCE N-1'!$H$2:$H$2000)-SUMIF('BALANCE N-1'!$A$2:$A$2000,"282*",'BALANCE N-1'!$G$2:$G$2000))) | D14: =MAX(0,(SUMIF('BALANCE N-1'!$A$2:$A$2000,"282*",'BALANCE N-1'!$H$2:$H$2000)-SUMIF('BALANCE N-1'!$A$2:$A$2000,"282*",'BALANCE N-1'!$G$2:$G$2000))-(SUMIF('BALANCE N'!$A$2:$A$2000,"282*",'BALANCE N'!$H$2:$H$2000)-SUMIF('BALANCE N'!$A$2:$A$2000,"282*",'BALANCE N'!$G$2:$G$2000))) | E14: =B14+C14-D14
A15: Bâtiments et ouvrages d'infrastructure | B15: =SUMIF('BALANCE N-1'!$A$2:$A$2000,"2831*",'BALANCE N-1'!$H$2:$H$2000)-SUMIF('BALANCE N-1'!$A$2:$A$2000,"2831*",'BALANCE N-1'!$G$2:$G$2000)+SUMIF('BALANCE N-1'!$A$2:$A$2000,"2832*",'BALANCE N-1'!$H$2:$H$2000)-SUMIF('BALANCE N-1'!$A$2:$A$2000,"2832*",'BALANCE N-1'!$G$2:$G$2000)+SUMIF('BALANCE N-1'!$A$2:$A$2000,"2833*",'BALANCE N-1'!$H$2:$H$2000)-SUMIF('BALANCE N-1'!$A$2:$A$2000,"2833*",'BALANCE N-1'!$G$2:$G$2000) | C15: =MAX(0,(SUMIF('BALANCE N'!$A$2:$A$2000,"2831*",'BALANCE N'!$H$2:$H$2000)-SUMIF('BALANCE N'!$A$2:$A$2000,"2831*",'BALANCE N'!$G$2:$G$2000)+SUMIF('BALANCE N'!$A$2:$A$2000,"2832*",'BALANCE N'!$H$2:$H$2000)-SUMIF('BALANCE N'!$A$2:$A$2000,"2832*",'BALANCE N'!$G$2:$G$2000)+SUMIF('BALANCE N'!$A$2:$A$2000,"2833*",'BALANCE N'!$H$2:$H$2000)-SUMIF('BALANCE N'!$A$2:$A$2000,"2833*",'BALANCE N'!$G$2:$G$2000))-(SUMIF('BALANCE N-1'!$A$2:$A$2000,"2831*",'BALANCE N-1'!$H$2:$H$2000)-SUMIF('BALANCE N-1'!$A$2:$A$2000,"2831*",'BALANCE N-1'!$G$2:$G$2000)+SUMIF('BALANCE N-1'!$A$2:$A$2000,"2832*",'BALANCE N-1'!$H$2:$H$2000)-SUMIF('BALANCE N-1'!$A$2:$A$2000,"2832*",'BALANCE N-1'!$G$2:$G$2000)+SUMIF('BALANCE N-1'!$A$2:$A$2000,"2833*",'BALANCE N-1'!$H$2:$H$2000)-SUMIF('BALANCE N-1'!$A$2:$A$2000,"2833*",'BALANCE N-1'!$G$2:$G$2000))) | D15: =MAX(0,(SUMIF('BALANCE N-1'!$A$2:$A$2000,"2831*",'BALANCE N-1'!$H$2:$H$2000)-SUMIF('BALANCE N-1'!$A$2:$A$2000,"2831*",'BALANCE N-1'!$G$2:$G$2000)+SUMIF('BALANCE N-1'!$A$2:$A$2000,"2832*",'BALANCE N-1'!$H$2:$H$2000)-SUMIF('BALANCE N-1'!$A$2:$A$2000,"2832*",'BALANCE N-1'!$G$2:$G$2000)+SUMIF('BALANCE N-1'!$A$2:$A$2000,"2833*",'BALANCE N-1'!$H$2:$H$2000)-SUMIF('BALANCE N-1'!$A$2:$A$2000,"2833*",'BALANCE N-1'!$G$2:$G$2000))-(SUMIF('BALANCE N'!$A$2:$A$2000,"2831*",'BALANCE N'!$H$2:$H$2000)-SUMIF('BALANCE N'!$A$2:$A$2000,"2831*",'BALANCE N'!$G$2:$G$2000)+SUMIF('BALANCE N'!$A$2:$A$2000,"2832*",'BALANCE N'!$H$2:$H$2000)-SUMIF('BALANCE N'!$A$2:$A$2000,"2832*",'BALANCE N'!$G$2:$G$2000)+SUMIF('BALANCE N'!$A$2:$A$2000,"2833*",'BALANCE N'!$H$2:$H$2000)-SUMIF('BALANCE N'!$A$2:$A$2000,"2833*",'BALANCE N'!$G$2:$G$2000))) | E15: =B15+C15-D15
A16: Aménagements, agencements et installations | B16: =SUMIF('BALANCE N-1'!$A$2:$A$2000,"2834*",'BALANCE N-1'!$H$2:$H$2000)-SUMIF('BALANCE N-1'!$A$2:$A$2000,"2834*",'BALANCE N-1'!$G$2:$G$2000)+SUMIF('BALANCE N-1'!$A$2:$A$2000,"2835*",'BALANCE N-1'!$H$2:$H$2000)-SUMIF('BALANCE N-1'!$A$2:$A$2000,"2835*",'BALANCE N-1'!$G$2:$G$2000)+SUMIF('BALANCE N-1'!$A$2:$A$2000,"2838*",'BALANCE N-1'!$H$2:$H$2000)-SUMIF('BALANCE N-1'!$A$2:$A$2000,"2838*",'BALANCE N-1'!$G$2:$G$2000) | C16: =MAX(0,(SUMIF('BALANCE N'!$A$2:$A$2000,"2834*",'BALANCE N'!$H$2:$H$2000)-SUMIF('BALANCE N'!$A$2:$A$2000,"2834*",'BALANCE N'!$G$2:$G$2000)+SUMIF('BALANCE N'!$A$2:$A$2000,"2835*",'BALANCE N'!$H$2:$H$2000)-SUMIF('BALANCE N'!$A$2:$A$2000,"2835*",'BALANCE N'!$G$2:$G$2000)+SUMIF('BALANCE N'!$A$2:$A$2000,"2838*",'BALANCE N'!$H$2:$H$2000)-SUMIF('BALANCE N'!$A$2:$A$2000,"2838*",'BALANCE N'!$G$2:$G$2000))-(SUMIF('BALANCE N-1'!$A$2:$A$2000,"2834*",'BALANCE N-1'!$H$2:$H$2000)-SUMIF('BALANCE N-1'!$A$2:$A$2000,"2834*",'BALANCE N-1'!$G$2:$G$2000)+SUMIF('BALANCE N-1'!$A$2:$A$2000,"2835*",'BALANCE N-1'!$H$2:$H$2000)-SUMIF('BALANCE N-1'!$A$2:$A$2000,"2835*",'BALANCE N-1'!$G$2:$G$2000)+SUMIF('BALANCE N-1'!$A$2:$A$2000,"2838*",'BALANCE N-1'!$H$2:$H$2000)-SUMIF('BALANCE N-1'!$A$2:$A$2000,"2838*",'BALANCE N-1'!$G$2:$G$2000))) | D16: =MAX(0,(SUMIF('BALANCE N-1'!$A$2:$A$2000,"2834*",'BALANCE N-1'!$H$2:$H$2000)-SUMIF('BALANCE N-1'!$A$2:$A$2000,"2834*",'BALANCE N-1'!$G$2:$G$2000)+SUMIF('BALANCE N-1'!$A$2:$A$2000,"2835*",'BALANCE N-1'!$H$2:$H$2000)-SUMIF('BALANCE N-1'!$A$2:$A$2000,"2835*",'BALANCE N-1'!$G$2:$G$2000)+SUMIF('BALANCE N-1'!$A$2:$A$2000,"2838*",'BALANCE N-1'!$H$2:$H$2000)-SUMIF('BALANCE N-1'!$A$2:$A$2000,"2838*",'BALANCE N-1'!$G$2:$G$2000))-(SUMIF('BALANCE N'!$A$2:$A$2000,"2834*",'BALANCE N'!$H$2:$H$2000)-SUMIF('BALANCE N'!$A$2:$A$2000,"2834*",'BALANCE N'!$G$2:$G$2000)+SUMIF('BALANCE N'!$A$2:$A$2000,"2835*",'BALANCE N'!$H$2:$H$2000)-SUMIF('BALANCE N'!$A$2:$A$2000,"2835*",'BALANCE N'!$G$2:$G$2000)+SUMIF('BALANCE N'!$A$2:$A$2000,"2838*",'BALANCE N'!$H$2:$H$2000)-SUMIF('BALANCE N'!$A$2:$A$2000,"2838*",'BALANCE N'!$G$2:$G$2000))) | E16: =B16+C16-D16
A17: Matériel, mobilier et actifs biologiques | B17: =SUMIF('BALANCE N-1'!$A$2:$A$2000,"284*",'BALANCE N-1'!$H$2:$H$2000)-SUMIF('BALANCE N-1'!$A$2:$A$2000,"284*",'BALANCE N-1'!$G$2:$G$2000)-SUMIF('BALANCE N-1'!$A$2:$A$2000,"2845*",'BALANCE N-1'!$H$2:$H$2000)+SUMIF('BALANCE N-1'!$A$2:$A$2000,"2845*",'BALANCE N-1'!$G$2:$G$2000) | C17: =MAX(0,(SUMIF('BALANCE N'!$A$2:$A$2000,"284*",'BALANCE N'!$H$2:$H$2000)-SUMIF('BALANCE N'!$A$2:$A$2000,"284*",'BALANCE N'!$G$2:$G$2000)-SUMIF('BALANCE N'!$A$2:$A$2000,"2845*",'BALANCE N'!$H$2:$H$2000)+SUMIF('BALANCE N'!$A$2:$A$2000,"2845*",'BALANCE N'!$G$2:$G$2000))-(SUMIF('BALANCE N-1'!$A$2:$A$2000,"284*",'BALANCE N-1'!$H$2:$H$2000)-SUMIF('BALANCE N-1'!$A$2:$A$2000,"284*",'BALANCE N-1'!$G$2:$G$2000)-SUMIF('BALANCE N-1'!$A$2:$A$2000,"2845*",'BALANCE N-1'!$H$2:$H$2000)+SUMIF('BALANCE N-1'!$A$2:$A$2000,"2845*",'BALANCE N-1'!$G$2:$G$2000))) | D17: =MAX(0,(SUMIF('BALANCE N-1'!$A$2:$A$2000,"284*",'BALANCE N-1'!$H$2:$H$2000)-SUMIF('BALANCE N-1'!$A$2:$A$2000,"284*",'BALANCE N-1'!$G$2:$G$2000)-SUMIF('BALANCE N-1'!$A$2:$A$2000,"2845*",'BALANCE N-1'!$H$2:$H$2000)+SUMIF('BALANCE N-1'!$A$2:$A$2000,"2845*",'BALANCE N-1'!$G$2:$G$2000))-(SUMIF('BALANCE N'!$A$2:$A$2000,"284*",'BALANCE N'!$H$2:$H$2000)-SUMIF('BALANCE N'!$A$2:$A$2000,"284*",'BALANCE N'!$G$2:$G$2000)-SUMIF('BALANCE N'!$A$2:$A$2000,"2845*",'BALANCE N'!$H$2:$H$2000)+SUMIF('BALANCE N'!$A$2:$A$2000,"2845*",'BALANCE N'!$G$2:$G$2000))) | E17: =B17+C17-D17
A18: Matériel de transport | B18: =SUMIF('BALANCE N-1'!$A$2:$A$2000,"2845*",'BALANCE N-1'!$H$2:$H$2000)-SUMIF('BALANCE N-1'!$A$2:$A$2000,"2845*",'BALANCE N-1'!$G$2:$G$2000) | C18: =MAX(0,(SUMIF('BALANCE N'!$A$2:$A$2000,"2845*",'BALANCE N'!$H$2:$H$2000)-SUMIF('BALANCE N'!$A$2:$A$2000,"2845*",'BALANCE N'!$G$2:$G$2000))-(SUMIF('BALANCE N-1'!$A$2:$A$2000,"2845*",'BALANCE N-1'!$H$2:$H$2000)-SUMIF('BALANCE N-1'!$A$2:$A$2000,"2845*",'BALANCE N-1'!$G$2:$G$2000))) | D18: =MAX(0,(SUMIF('BALANCE N-1'!$A$2:$A$2000,"2845*",'BALANCE N-1'!$H$2:$H$2000)-SUMIF('BALANCE N-1'!$A$2:$A$2000,"2845*",'BALANCE N-1'!$G$2:$G$2000))-(SUMIF('BALANCE N'!$A$2:$A$2000,"2845*",'BALANCE N'!$H$2:$H$2000)-SUMIF('BALANCE N'!$A$2:$A$2000,"2845*",'BALANCE N'!$G$2:$G$2000))) | E18: =B18+C18-D18
A19: TOTAL GÉNÉRAL | B19: =B10+B11+B12+B14+B15+B16+B17+B18 | C19: =C10+C11+C12+C14+C15+C16+C17+C18 | D19: =D10+D11+D12+D14+D15+D16+D17+D18 | E19: =E10+E11+E12+E14+E15+E16+E17+E18
A21: Sans balance N-1, seule la colonne de clôture est servie ; avec N-1, les mouvements sont posés en variation nette (augmentation ou diminution) faute d'état des mouvements - à ajuster depuis l'inventaire des immobilisations.
A23: =IF(SUM(B9:B19,C9:C19,D9:D19,E9:E19)=0,"NÉANT","")

Sheet NOTE 5F
A1: - 18 -
D2: NOTE 5F SYSTEME NORMAL
A3: Dénomination sociale :
A4: Adresse : | D4: Sigle usuel :
A5: N° de compte contribuable (NCC) : | C5: Exercice clos le | D5: Durée (en mois) : 12
A6: N° de télédéclarant (NTD) :
A7: NOTE 5F : IMMOBILISATIONS : DÉPRÉCIATIONS
A8: RUBRIQUES | B8: Cumul à l'ouverture (A) | C8: Augmentations : dotations (B) | D8: Diminutions : reprises et sorties (C) | E8: Cumul à la clôture (D = A + B - C)
A9: IMMOBILISATIONS INCORPORELLES
A10: Immobilisations incorporelles | B10: =SUMIF('BALANCE N-1'!$A$2:$A$2000,"291*",'BALANCE N-1'!$H$2:$H$2000)-SUMIF('BALANCE N-1'!$A$2:$A$2000,"291*",'BALANCE N-1'!$G$2:$G$2000) | C10: =MAX(0,(SUMIF('BALANCE N'!$A$2:$A$2000,"291*",'BALANCE N'!$H$2:$H$2000)-SUMIF('BALANCE N'!$A$2:$A$2000,"291*",'BALANCE N'!$G$2:$G$2000))-(SUMIF('BALANCE N-1'!$A$2:$A$2000,"291*",'BALANCE N-1'!$H$2:$H$2000)-SUMIF('BALANCE N-1'!$A$2:$A$2000,"291*",'BALANCE N-1'!$G$2:$G$2000))) | D10: =MAX(0,(SUMIF('BALANCE N-1'!$A$2:$A$2000,"291*",'BALANCE N-1'!$H$2:$H$2000)-SUMIF('BALANCE N-1'!$A$2:$A$2000,"291*",'BALANCE N-1'!$G$2:$G$2000))-(SUMIF('BALANCE N'!$A$2:$A$2000,"291*",'BALANCE N'!$H$2:$H$2000)-SUMIF('BALANCE N'!$A$2:$A$2000,"291*",'BALANCE N'!$G$2:$G$2000))) | E10: =B10+C10-D10
A11: IMMOBILISATIONS CORPORELLES
A12: Terrains | B12: =SUMIF('BALANCE N-1'!$A$2:$A$2000,"292*",'BALANCE N-1'!$H$2:$H$2000)-SUMIF('BALANCE N-1'!$A$2:$A$2000,"292*",'BALANCE N-1'!$G$2:$G$2000) | C12: =MAX(0,(SUMIF('BALANCE N'!$A$2:$A$2000,"292*",'BALANCE N'!$H$2:$H$2000)-SUMIF('BALANCE N'!$A$2:$A$2000,"292*",'BALANCE N'!$G$2:$G$2000))-(SUMIF('BALANCE N-1'!$A$2:$A$2000,"292*",'BALANCE N-1'!$H$2:$H$2000)-SUMIF('BALANCE N-1'!$A$2:$A$2000,"292*",'BALANCE N-1'!$G$2:$G$2000))) | D12: =MAX(0,(SUMIF('BALANCE N-1'!$A$2:$A$2000,"292*",'BALANCE N-1'!$H$2:$H$2000)-SUMIF('BALANCE N-1'!$A$2:$A$2000,"292*",'BALANCE N-1'!$G$2:$G$2000))-(SUMIF('BALANCE N'!$A$2:$A$2000,"292*",'BALANCE N'!$H$2:$H$2000)-SUMIF('BALANCE N'!$A$2:$A$2000,"292*",'BALANCE N'!$G$2:$G$2000))) | E12: =B12+C12-D12
A13: Bâtiments et installations | B13: =SUMIF('BALANCE N-1'!$A$2:$A$2000,"293*",'BALANCE N-1'!$H$2:$H$2000)-SUMIF('BALANCE N-1'!$A$2:$A$2000,"293*",'BALANCE N-1'!$G$2:$G$2000) | C13: =MAX(0,(SUMIF('BALANCE N'!$A$2:$A$2000,"293*",'BALANCE N'!$H$2:$H$2000)-SUMIF('BALANCE N'!$A$2:$A$2000,"293*",'BALANCE N'!$G$2:$G$2000))-(SUMIF('BALANCE N-1'!$A$2:$A$2000,"293*",'BALANCE N-1'!$H$2:$H$2000)-SUMIF('BALANCE N-1'!$A$2:$A$2000,"293*",'BALANCE N-1'!$G$2:$G$2000))) | D13: =MAX(0,(SUMIF('BALANCE N-1'!$A$2:$A$2000,"293*",'BALANCE N-1'!$H$2:$H$2000)-SUMIF('BALANCE N-1'!$A$2:$A$2000,"293*",'BALANCE N-1'!$G$2:$G$2000))-(SUMIF('BALANCE N'!$A$2:$A$2000,"293*",'BALANCE N'!$H$2:$H$2000)-SUMIF('BALANCE N'!$A$2:$A$2000,"293*",'BALANCE N'!$G$2:$G$2000))) | E13: =B13+C13-D13
A14: Matériel, mobilier et actifs biologiques | B14: =SUMIF('BALANCE N-1'!$A$2:$A$2000,"294*",'BALANCE N-1'!$H$2:$H$2000)-SUMIF('BALANCE N-1'!$A$2:$A$2000,"294*",'BALANCE N-1'!$G$2:$G$2000)-SUMIF('BALANCE N-1'!$A$2:$A$2000,"2945*",'BALANCE N-1'!$H$2:$H$2000)+SUMIF('BALANCE N-1'!$A$2:$A$2000,"2945*",'BALANCE N-1'!$G$2:$G$2000) | C14: =MAX(0,(SUMIF('BALANCE N'!$A$2:$A$2000,"294*",'BALANCE N'!$H$2:$H$2000)-SUMIF('BALANCE N'!$A$2:$A$2000,"294*",'BALANCE N'!$G$2:$G$2000)-SUMIF('BALANCE N'!$A$2:$A$2000,"2945*",'BALANCE N'!$H$2:$H$2000)+SUMIF('BALANCE N'!$A$2:$A$2000,"2945*",'BALANCE N'!$G$2:$G$2000))-(SUMIF('BALANCE N-1'!$A$2:$A$2000,"294*",'BALANCE N-1'!$H$2:$H$2000)-SUMIF('BALANCE N-1'!$A$2:$A$2000,"294*",'BALANCE N-1'!$G$2:$G$2000)-SUMIF('BALANCE N-1'!$A$2:$A$2000,"2945*",'BALANCE N-1'!$H$2:$H$2000)+SUMIF('BALANCE N-1'!$A$2:$A$2000,"2945*",'BALANCE N-1'!$G$2:$G$2000))) | D14: =MAX(0,(SUMIF('BALANCE N-1'!$A$2:$A$2000,"294*",'BALANCE N-1'!$H$2:$H$2000)-SUMIF('BALANCE N-1'!$A$2:$A$2000,"294*",'BALANCE N-1'!$G$2:$G$2000)-SUMIF('BALANCE N-1'!$A$2:$A$2000,"2945*",'BALANCE N-1'!$H$2:$H$2000)+SUMIF('BALANCE N-1'!$A$2:$A$2000,"2945*",'BALANCE N-1'!$G$2:$G$2000))-(SUMIF('BALANCE N'!$A$2:$A$2000,"294*",'BALANCE N'!$H$2:$H$2000)-SUMIF('BALANCE N'!$A$2:$A$2000,"294*",'BALANCE N'!$G$2:$G$2000)-SUMIF('BALANCE N'!$A$2:$A$2000,"2945*",'BALANCE N'!$H$2:$H$2000)+SUMIF('BALANCE N'!$A$2:$A$2000,"2945*",'BALANCE N'!$G$2:$G$2000))) | E14: =B14+C14-D14
A15: Matériel de transport | B15: =SUMIF('BALANCE N-1'!$A$2:$A$2000,"2945*",'BALANCE N-1'!$H$2:$H$2000)-SUMIF('BALANCE N-1'!$A$2:$A$2000,"2945*",'BALANCE N-1'!$G$2:$G$2000) | C15: =MAX(0,(SUMIF('BALANCE N'!$A$2:$A$2000,"2945*",'BALANCE N'!$H$2:$H$2000)-SUMIF('BALANCE N'!$A$2:$A$2000,"2945*",'BALANCE N'!$G$2:$G$2000))-(SUMIF('BALANCE N-1'!$A$2:$A$2000,"2945*",'BALANCE N-1'!$H$2:$H$2000)-SUMIF('BALANCE N-1'!$A$2:$A$2000,"2945*",'BALANCE N-1'!$G$2:$G$2000))) | D15: =MAX(0,(SUMIF('BALANCE N-1'!$A$2:$A$2000,"2945*",'BALANCE N-1'!$H$2:$H$2000)-SUMIF('BALANCE N-1'!$A$2:$A$2000,"2945*",'BALANCE N-1'!$G$2:$G$2000))-(SUMIF('BALANCE N'!$A$2:$A$2000,"2945*",'BALANCE N'!$H$2:$H$2000)-SUMIF('BALANCE N'!$A$2:$A$2000,"2945*",'BALANCE N'!$G$2:$G$2000))) | E15: =B15+C15-D15
A16: Avances et acomptes versés sur immobilisations | B16: =SUMIF('BALANCE N-1'!$A$2:$A$2000,"295*",'BALANCE N-1'!$H$2:$H$2000)-SUMIF('BALANCE N-1'!$A$2:$A$2000,"295*",'BALANCE N-1'!$G$2:$G$2000) | C16: =MAX(0,(SUMIF('BALANCE N'!$A$2:$A$2000,"295*",'BALANCE N'!$H$2:$H$2000)-SUMIF('BALANCE N'!$A$2:$A$2000,"295*",'BALANCE N'!$G$2:$G$2000))-(SUMIF('BALANCE N-1'!$A$2:$A$2000,"295*",'BALANCE N-1'!$H$2:$H$2000)-SUMIF('BALANCE N-1'!$A$2:$A$2000,"295*",'BALANCE N-1'!$G$2:$G$2000))) | D16: =MAX(0,(SUMIF('BALANCE N-1'!$A$2:$A$2000,"295*",'BALANCE N-1'!$H$2:$H$2000)-SUMIF('BALANCE N-1'!$A$2:$A$2000,"295*",'BALANCE N-1'!$G$2:$G$2000))-(SUMIF('BALANCE N'!$A$2:$A$2000,"295*",'BALANCE N'!$H$2:$H$2000)-SUMIF('BALANCE N'!$A$2:$A$2000,"295*",'BALANCE N'!$G$2:$G$2000))) | E16: =B16+C16-D16
A17: IMMOBILISATIONS FINANCIÈRES
A18: Titres de participation | B18: =SUMIF('BALANCE N-1'!$A$2:$A$2000,"296*",'BALANCE N-1'!$H$2:$H$2000)-SUMIF('BALANCE N-1'!$A$2:$A$2000,"296*",'BALANCE N-1'!$G$2:$G$2000) | C18: =MAX(0,(SUMIF('BALANCE N'!$A$2:$A$2000,"296*",'BALANCE N'!$H$2:$H$2000)-SUMIF('BALANCE N'!$A$2:$A$2000,"296*",'BALANCE N'!$G$2:$G$2000))-(SUMIF('BALANCE N-1'!$A$2:$A$2000,"296*",'BALANCE N-1'!$H$2:$H$2000)-SUMIF('BALANCE N-1'!$A$2:$A$2000,"296*",'BALANCE N-1'!$G$2:$G$2000))) | D18: =MAX(0,(SUMIF('BALANCE N-1'!$A$2:$A$2000,"296*",'BALANCE N-1'!$H$2:$H$2000)-SUMIF('BALANCE N-1'!$A$2:$A$2000,"296*",'BALANCE N-1'!$G$2:$G$2000))-(SUMIF('BALANCE N'!$A$2:$A$2000,"296*",'BALANCE N'!$H$2:$H$2000)-SUMIF('BALANCE N'!$A$2:$A$2000,"296*",'BALANCE N'!$G$2:$G$2000))) | E18: =B18+C18-D18
A19: Autres immobilisations financières | B19: =SUMIF('BALANCE N-1'!$A$2:$A$2000,"297*",'BALANCE N-1'!$H$2:$H$2000)-SUMIF('BALANCE N-1'!$A$2:$A$2000,"297*",'BALANCE N-1'!$G$2:$G$2000) | C19: =MAX(0,(SUMIF('BALANCE N'!$A$2:$A$2000,"297*",'BALANCE N'!$H$2:$H$2000)-SUMIF('BALANCE N'!$A$2:$A$2000,"297*",'BALANCE N'!$G$2:$G$2000))-(SUMIF('BALANCE N-1'!$A$2:$A$2000,"297*",'BALANCE N-1'!$H$2:$H$2000)-SUMIF('BALANCE N-1'!$A$2:$A$2000,"297*",'BALANCE N-1'!$G$2:$G$2000))) | D19: =MAX(0,(SUMIF('BALANCE N-1'!$A$2:$A$2000,"297*",'BALANCE N-1'!$H$2:$H$2000)-SUMIF('BALANCE N-1'!$A$2:$A$2000,"297*",'BALANCE N-1'!$G$2:$G$2000))-(SUMIF('BALANCE N'!$A$2:$A$2000,"297*",'BALANCE N'!$H$2:$H$2000)-SUMIF('BALANCE N'!$A$2:$A$2000,"297*",'BALANCE N'!$G$2:$G$2000))) | E19: =B19+C19-D19
A20: TOTAL GÉNÉRAL | B20: =B10+B12+B13+B14+B15+B16+B18+B19 | C20: =C10+C12+C13+C14+C15+C16+C18+C19 | D20: =D10+D12+D13+D14+D15+D16+D18+D19 | E20: =E10+E12+E13+E14+E15+E16+E18+E19
A22: Sans balance N-1, seule la colonne de clôture est servie ; avec N-1, les mouvements sont posés en variation nette (augmentation ou diminution) faute d'état des mouvements - à ajuster depuis l'inventaire des immobilisations.
A24: =IF(SUM(B9:B20,C9:C20,D9:D20,E9:E20)=0,"NÉANT","")

Sheet NOTE 5G
A1: - 19 -
E2: NOTE 5G SYSTEME NORMAL
A3: Dénomination sociale :
A4: Adresse : | E4: Sigle usuel :
A5: N° de compte contribuable (NCC) : | C5: Exercice clos le | E5: Durée (en mois) : 12
A6: N° de télédéclarant (NTD) :
A7: NOTE 5G : IMMOBILISATIONS : PLUS-VALUES ET MOINS-VALUES DE CESSION
A8: Libellés | B8: Montant brut (A) | C8: Amortissements pratiqués (B) | D8: Valeur comptable nette (C = A - B) | E8: Prix de cession (D) | F8: Plus ou moins-value (E = D - C)
A9: Immobilisations incorporelles | D9: =SUMIF('BALANCE N'!$A$2:$A$2000,"811*",'BALANCE N'!$G$2:$G$2000)-SUMIF('BALANCE N'!$A$2:$A$2000,"811*",'BALANCE N'!$H$2:$H$2000) | E9: =SUMIF('BALANCE N'!$A$2:$A$2000,"821*",'BALANCE N'!$H$2:$H$2000)-SUMIF('BALANCE N'!$A$2:$A$2000,"821*",'BALANCE N'!$G$2:$G$2000) | F9: =E9-D9
A10: Immobilisations corporelles | D10: =SUMIF('BALANCE N'!$A$2:$A$2000,"812*",'BALANCE N'!$G$2:$G$2000)-SUMIF('BALANCE N'!$A$2:$A$2000,"812*",'BALANCE N'!$H$2:$H$2000) | E10: =SUMIF('BALANCE N'!$A$2:$A$2000,"822*",'BALANCE N'!$H$2:$H$2000)-SUMIF('BALANCE N'!$A$2:$A$2000,"822*",'BALANCE N'!$G$2:$G$2000) | F10: =E10-D10
A11: Immobilisations financières | D11: =SUMIF('BALANCE N'!$A$2:$A$2000,"816*",'BALANCE N'!$G$2:$G$2000)-SUMIF('BALANCE N'!$A$2:$A$2000,"816*",'BALANCE N'!$H$2:$H$2000) | E11: =SUMIF('BALANCE N'!$A$2:$A$2000,"826*",'BALANCE N'!$H$2:$H$2000)-SUMIF('BALANCE N'!$A$2:$A$2000,"826*",'BALANCE N'!$G$2:$G$2000) | F11: =E11-D11
A12: Immobilisations reçues destinées à la vente (dons et legs) | D12: =SUMIF('BALANCE N'!$A$2:$A$2000,"818*",'BALANCE N'!$G$2:$G$2000)-SUMIF('BALANCE N'!$A$2:$A$2000,"818*",'BALANCE N'!$H$2:$H$2000) | E12: =SUMIF('BALANCE N'!$A$2:$A$2000,"828*",'BALANCE N'!$H$2:$H$2000)-SUMIF('BALANCE N'!$A$2:$A$2000,"828*",'BALANCE N'!$G$2:$G$2000) | F12: =E12-D12
A13: TOTAL GÉNÉRAL | B13: =SUM(B9:B12) | C13: =SUM(C9:C12) | D13: =SUM(D9:D12) | E13: =SUM(E9:E12) | F13: =SUM(F9:F12)
A15: Colonnes A et B à compléter depuis l'inventaire ; la valeur comptable (81x) et le prix de cession (82x) sortent de la balance. Mentionner la justification de la cession, la date d'acquisition et la date de sortie.
A17: =IF(SUM(B9:B13,C9:C13,D9:D13,E9:E13,F9:F13)=0,"NÉANT","")

Sheet NOTE 5H
A1: - 20 -
E2: NOTE 5H SYSTEME NORMAL
A3: Dénomination sociale :
A4: Adresse : | E4: Sigle usuel :
A5: N° de compte contribuable (NCC) : | C5: Exercice clos le | E5: Durée (en mois) : 12
A6: N° de télédéclarant (NTD) :
A7: NOTE 5H : INFORMATIONS SUR LES RÉÉVALUATIONS EFFECTUÉES PAR L'ENTITÉ
A9: Nature et date des réévaluations :
A12: Éléments réévalués par postes du bilan | Montants en coûts historiques | Montants réévalués | Écarts et provisions spéciales de réévaluation.
A15: Méthode de réévaluation utilisée :
A18: Traitement fiscal de l'écart de réévaluation et des amortissements supplémentaires :
A21: Montant de l'écart incorporé à la dotation :
A24: NOTE À COMPLÉTER

Sheet NOTE 6
A1: - 21 -
G2: NOTE 6 SYSTEME NORMAL
A3: Dénomination sociale :
A4: Adresse : | G4: Sigle usuel :
A5: N° de compte contribuable (NCC) : | E5: Exercice clos le | G5: Durée (en mois) : 12
A6: N° de télédéclarant (NTD) :
A7: NOTE 6 : IMMOBILISATIONS FINANCIÈRES
A8: Libellés | B8: Année N | C8: Année N-1 | D8: Variation en valeur | E8: Variation en % | F8: À un an au plus | G8: À plus d'un an et deux ans au plus | H8: À plus de deux ans
A9: Titres de participation | B9: =SUMIF('BALANCE N'!$A$2:$A$2000,"26*",'BALANCE N'!$G$2:$G$2000)-SUMIF('BALANCE N'!$A$2:$A$2000,"26*",'BALANCE N'!$H$2:$H$2000) | C9: =SUMIF('BALANCE N-1'!$A$2:$A$2000,"26*",'BALANCE N-1'!$G$2:$G$2000)-SUMIF('BALANCE N-1'!$A$2:$A$2000,"26*",'BALANCE N-1'!$H$2:$H$2000) | D9: =B9-C9 | E9: =IF(C9=0,"",(B9-C9)/C9)
A10: Prêts et créances | B10: =SUMIF('BALANCE N'!$A$2:$A$2000,"271*",'BALANCE N'!$G$2:$G$2000)-SUMIF('BALANCE N'!$A$2:$A$2000,"271*",'BALANCE N'!$H$2:$H$2000)+SUMIF('BALANCE N'!$A$2:$A$2000,"278*",'BALANCE N'!$G$2:$G$2000)-SUMIF('BALANCE N'!$A$2:$A$2000,"278*",'BALANCE N'!$H$2:$H$2000) | C10: =SUMIF('BALANCE N-1'!$A$2:$A$2000,"271*",'BALANCE N-1'!$G$2:$G$2000)-SUMIF('BALANCE N-1'!$A$2:$A$2000,"271*",'BALANCE N-1'!$H$2:$H$2000)+SUMIF('BALANCE N-1'!$A$2:$A$2000,"278*",'BALANCE N-1'!$G$2:$G$2000)-SUMIF('BALANCE N-1'!$A$2:$A$2000,"278*",'BALANCE N-1'!$H$2:$H$2000) | D10: =B10-C10 | E10: =IF(C10=0,"",(B10-C10)/C10)
A11: Prêt au personnel | B11: =SUMIF('BALANCE N'!$A$2:$A$2000,"272*",'BALANCE N'!$G$2:$G$2000)-SUMIF('BALANCE N'!$A$2:$A$2000,"272*",'BALANCE N'!$H$2:$H$2000) | C11: =SUMIF('BALANCE N-1'!$A$2:$A$2000,"272*",'BALANCE N-1'!$G$2:$G$2000)-SUMIF('BALANCE N-1'!$A$2:$A$2000,"272*",'BALANCE N-1'!$H$2:$H$2000) | D11: =B11-C11 | E11: =IF(C11=0,"",(B11-C11)/C11)
A12: Créances sur l'État | B12: =SUMIF('BALANCE N'!$A$2:$A$2000,"273*",'BALANCE N'!$G$2:$G$2000)-SUMIF('BALANCE N'!$A$2:$A$2000,"273*",'BALANCE N'!$H$2:$H$2000) | C12: =SUMIF('BALANCE N-1'!$A$2:$A$2000,"273*",'BALANCE N-1'!$G$2:$G$2000)-SUMIF('BALANCE N-1'!$A$2:$A$2000,"273*",'BALANCE N-1'!$H$2:$H$2000) | D12: =B12-C12 | E12: =IF(C12=0,"",(B12-C12)/C12)
A13: Titres immobilisés | B13: =SUMIF('BALANCE N'!$A$2:$A$2000,"274*",'BALANCE N'!$G$2:$G$2000)-SUMIF('BALANCE N'!$A$2:$A$2000,"274*",'BALANCE N'!$H$2:$H$2000) | C13: =SUMIF('BALANCE N-1'!$A$2:$A$2000,"274*",'BALANCE N-1'!$G$2:$G$2000)-SUMIF('BALANCE N-1'!$A$2:$A$2000,"274*",'BALANCE N-1'!$H$2:$H$2000) | D13: =B13-C13 | E13: =IF(C13=0,"",(B13-C13)/C13)
A14: Dépôts et cautionnements | B14: =SUMIF('BALANCE N'!$A$2:$A$2000,"275*",'BALANCE N'!$G$2:$G$2000)-SUMIF('BALANCE N'!$A$2:$A$2000,"275*",'BALANCE N'!$H$2:$H$2000) | C14: =SUMIF('BALANCE N-1'!$A$2:$A$2000,"275*",'BALANCE N-1'!$G$2:$G$2000)-SUMIF('BALANCE N-1'!$A$2:$A$2000,"275*",'BALANCE N-1'!$H$2:$H$2000) | D14: =B14-C14 | E14: =IF(C14=0,"",(B14-C14)/C14)
A15: Intérêts courus | B15: =SUMIF('BALANCE N'!$A$2:$A$2000,"276*",'BALANCE N'!$G$2:$G$2000)-SUMIF('BALANCE N'!$A$2:$A$2000,"276*",'BALANCE N'!$H$2:$H$2000) | C15: =SUMIF('BALANCE N-1'!$A$2:$A$2000,"276*",'BALANCE N-1'!$G$2:$G$2000)-SUMIF('BALANCE N-1'!$A$2:$A$2000,"276*",'BALANCE N-1'!$H$2:$H$2000) | D15: =B15-C15 | E15: =IF(C15=0,"",(B15-C15)/C15)
A16: TOTAL BRUT | B16: =SUM(B9:B15) | C16: =SUM(C9:C15) | D16: =B16-C16 | E16: =IF(C16=0,"",(B16-C16)/C16)
A17: Dépréciations des titres de participation | B17: =SUMIF('BALANCE N'!$A$2:$A$2000,"296*",'BALANCE N'!$H$2:$H$2000)-SUMIF('BALANCE N'!$A$2:$A$2000,"296*",'BALANCE N'!$G$2:$G$2000) | C17: =SUMIF('BALANCE N-1'!$A$2:$A$2000,"296*",'BALANCE N-1'!$H$2:$H$2000)-SUMIF('BALANCE N-1'!$A$2:$A$2000,"296*",'BALANCE N-1'!$G$2:$G$2000) | D17: =B17-C17 | E17: =IF(C17=0,"",(B17-C17)/C17)
A18: Dépréciations des autres immobilisations financières | B18: =SUMIF('BALANCE N'!$A$2:$A$2000,"297*",'BALANCE N'!$H$2:$H$2000)-SUMIF('BALANCE N'!$A$2:$A$2000,"297*",'BALANCE N'!$G$2:$G$2000) | C18: =SUMIF('BALANCE N-1'!$A$2:$A$2000,"297*",'BALANCE N-1'!$H$2:$H$2000)-SUMIF('BALANCE N-1'!$A$2:$A$2000,"297*",'BALANCE N-1'!$G$2:$G$2000) | D18: =B18-C18 | E18: =IF(C18=0,"",(B18-C18)/C18)
B19: =SUM(B17:B18) | C19: =SUM(C17:C18) | D19: =B19-C19 | E19: =IF(C19=0,"",(B19-C19)/C19)
A20: TOTAL NET DE DÉPRÉCIATIONS | B20: =B16-B19 | C20: =C16-C19 | D20: =B20-C20 | E20: =IF(C20=0,"",(B20-C20)/C20)
A22: Commentaires :
A23: • Justifier toute variation significative ; commenter les créances anciennes ; indiquer le nombre et la date d'acquisition des actions ou parts ; pour les dépréciations, indiquer les évènements et circonstances.
A25: =IF(SUM(B9:B20,C9:C20,D9:D20,F16:F20,G16:G20,H16:H20)=0,"NÉANT","")

Sheet NOTE 7
A1: - 22 -
D2: NOTE 7 SYSTEME NORMAL
A3: Dénomination sociale :
A4: Adresse : | D4: Sigle usuel :
A5: N° de compte contribuable (NCC) : | C5: Exercice clos le | D5: Durée (en mois) : 12
A6: N° de télédéclarant (NTD) :
A7: NOTE 7 : ACTIF CIRCULANT ET DETTES CIRCULANTES HAO
A8: Libellés | B8: Année N | C8: Année N-1 | D8: Variation en valeur | E8: Variation en %
A9: ACTIF CIRCULANT HAO
A10: Créances sur cessions d'immobilisations | B10: =SUMIF('BALANCE N'!$A$2:$A$2000,"485*",'BALANCE N'!$G$2:$G$2000)-SUMIF('BALANCE N'!$A$2:$A$2000,"485*",'BALANCE N'!$H$2:$H$2000) | C10: =SUMIF('BALANCE N-1'!$A$2:$A$2000,"485*",'BALANCE N-1'!$G$2:$G$2000)-SUMIF('BALANCE N-1'!$A$2:$A$2000,"485*",'BALANCE N-1'!$H$2:$H$2000) | D10: =B10-C10 | E10: =IF(C10=0,"",(B10-C10)/C10)
A11: Créances reçues par dons et legs d'immobilisations | B11: =SUMIF('BALANCE N'!$A$2:$A$2000,"4865*",'BALANCE N'!$G$2:$G$2000)-SUMIF('BALANCE N'!$A$2:$A$2000,"4865*",'BALANCE N'!$H$2:$H$2000) | C11: =SUMIF('BALANCE N-1'!$A$2:$A$2000,"4865*",'BALANCE N-1'!$G$2:$G$2000)-SUMIF('BALANCE N-1'!$A$2:$A$2000,"4865*",'BALANCE N-1'!$H$2:$H$2000) | D11: =B11-C11 | E11: =IF(C11=0,"",(B11-C11)/C11)
A12: TOTAL BRUT | B12: =SUM(B10:B11) | C12: =SUM(C10:C11) | D12: =B12-C12 | E12: =IF(C12=0,"",(B12-C12)/C12)
A13: Dépréciations des créances HAO | B13: =SUMIF('BALANCE N'!$A$2:$A$2000,"498*",'BALANCE N'!$H$2:$H$2000)-SUMIF('BALANCE N'!$A$2:$A$2000,"498*",'BALANCE N'!$G$2:$G$2000) | C13: =SUMIF('BALANCE N-1'!$A$2:$A$2000,"498*",'BALANCE N-1'!$H$2:$H$2000)-SUMIF('BALANCE N-1'!$A$2:$A$2000,"498*",'BALANCE N-1'!$G$2:$G$2000) | D13: =B13-C13 | E13: =IF(C13=0,"",(B13-C13)/C13)
B14: =SUM(B13:B13) | C14: =SUM(C13:C13) | D14: =B14-C14 | E14: =IF(C14=0,"",(B14-C14)/C14)
A15: TOTAL NET DE DÉPRÉCIATIONS | B15: =B12-B14 | C15: =C12-C14 | D15: =B15-C15 | E15: =IF(C15=0,"",(B15-C15)/C15)
A17: DETTES CIRCULANTES HAO
A18: Fournisseurs d'investissements | B18: =SUMIF('BALANCE N'!$A$2:$A$2000,"481*",'BALANCE N'!$H$2:$H$2000)-SUMIF('BALANCE N'!$A$2:$A$2000,"481*",'BALANCE N'!$G$2:$G$2000) | C18: =SUMIF('BALANCE N-1'!$A$2:$A$2000,"481*",'BALANCE N-1'!$H$2:$H$2000)-SUMIF('BALANCE N-1'!$A$2:$A$2000,"481*",'BALANCE N-1'!$G$2:$G$2000) | D18: =B18-C18 | E18: =IF(C18=0,"",(B18-C18)/C18)
A19: Dettes des dons et legs d'immobilisations | B19: =SUMIF('BALANCE N'!$A$2:$A$2000,"4861*",'BALANCE N'!$H$2:$H$2000)-SUMIF('BALANCE N'!$A$2:$A$2000,"4861*",'BALANCE N'!$G$2:$G$2000) | C19: =SUMIF('BALANCE N-1'!$A$2:$A$2000,"4861*",'BALANCE N-1'!$H$2:$H$2000)-SUMIF('BALANCE N-1'!$A$2:$A$2000,"4861*",'BALANCE N-1'!$G$2:$G$2000) | D19: =B19-C19 | E19: =IF(C19=0,"",(B19-C19)/C19)
A20: Créditeurs, dons nature HAO non consommés | B20: =SUMIF('BALANCE N'!$A$2:$A$2000,"4881*",'BALANCE N'!$H$2:$H$2000)-SUMIF('BALANCE N'!$A$2:$A$2000,"4881*",'BALANCE N'!$G$2:$G$2000) | C20: =SUMIF('BALANCE N-1'!$A$2:$A$2000,"4881*",'BALANCE N-1'!$H$2:$H$2000)-SUMIF('BALANCE N-1'!$A$2:$A$2000,"4881*",'BALANCE N-1'!$G$2:$G$2000) | D20: =B20-C20 | E20: =IF(C20=0,"",(B20-C20)/C20)
A21: Autres dettes hors activités ordinaires | B21: =SUMIF('BALANCE N'!$A$2:$A$2000,"484*",'BALANCE N'!$H$2:$H$2000)-SUMIF('BALANCE N'!$A$2:$A$2000,"484*",'BALANCE N'!$G$2:$G$2000)+SUMIF('BALANCE N'!$A$2:$A$2000,"488*",'BALANCE N'!$H$2:$H$2000)-SUMIF('BALANCE N'!$A$2:$A$2000,"488*",'BALANCE N'!$G$2:$G$2000)+SUMIF('BALANCE N'!$A$2:$A$2000,"4998*",'BALANCE N'!$H$2:$H$2000)-SUMIF('BALANCE N'!$A$2:$A$2000,"4998*",'BALANCE N'!$G$2:$G$2000)-SUMIF('BALANCE N'!$A$2:$A$2000,"4881*",'BALANCE N'!$H$2:$H$2000)+SUMIF('BALANCE N'!$A$2:$A$2000,"4881*",'BALANCE N'!$G$2:$G$2000) | C21: =SUMIF('BALANCE N-1'!$A$2:$A$2000,"484*",'BALANCE N-1'!$H$2:$H$2000)-SUMIF('BALANCE N-1'!$A$2:$A$2000,"484*",'BALANCE N-1'!$G$2:$G$2000)+SUMIF('BALANCE N-1'!$A$2:$A$2000,"488*",'BALANCE N-1'!$H$2:$H$2000)-SUMIF('BALANCE N-1'!$A$2:$A$2000,"488*",'BALANCE N-1'!$G$2:$G$2000)+SUMIF('BALANCE N-1'!$A$2:$A$2000,"4998*",'BALANCE N-1'!$H$2:$H$2000)-SUMIF('BALANCE N-1'!$A$2:$A$2000,"4998*",'BALANCE N-1'!$G$2:$G$2000)-SUMIF('BALANCE N-1'!$A$2:$A$2000,"4881*",'BALANCE N-1'!$H$2:$H$2000)+SUMIF('BALANCE N-1'!$A$2:$A$2000,"4881*",'BALANCE N-1'!$G$2:$G$2000) | D21: =B21-C21 | E21: =IF(C21=0,"",(B21-C21)/C21)
A22: TOTAL DETTES CIRCULANTES HAO | B22: =SUM(B18:B21) | C22: =SUM(C18:C21) | D22: =B22-C22 | E22: =IF(C22=0,"",(B22-C22)/C22)
A24: Commentaires :
A25: • Commenter toute variation significative ; indiquer la date et la nature de l'immobilisation achetée et/ou cédée.
A27: =IF(SUM(B9:B22,C9:C22,D9:D22)=0,"NÉANT","")

Sheet NOTE 8
A1: - 23 -
D2: NOTE 8 SYSTEME NORMAL
A3: Dénomination sociale :
A4: Adresse : | D4: Sigle usuel :
A5: N° de compte contribuable (NCC) : | C5: Exercice clos le | D5: Durée (en mois) : 12
A6: N° de télédéclarant (NTD) :
A7: NOTE 8 : STOCKS ET ENCOURS
A8: Libellés | B8: Année N | C8: Année N-1 | D8: Variation en valeur | E8: Variation en %
A9: Biens et services liés à l'activité | B9: =SUMIF('BALANCE N'!$A$2:$A$2000,"31*",'BALANCE N'!$G$2:$G$2000)-SUMIF('BALANCE N'!$A$2:$A$2000,"31*",'BALANCE N'!$H$2:$H$2000) | C9: =SUMIF('BALANCE N-1'!$A$2:$A$2000,"31*",'BALANCE N-1'!$G$2:$G$2000)-SUMIF('BALANCE N-1'!$A$2:$A$2000,"31*",'BALANCE N-1'!$H$2:$H$2000) | D9: =B9-C9 | E9: =IF(C9=0,"",(B9-C9)/C9)
A10: Marchandises, matières premières | B10: =SUMIF('BALANCE N'!$A$2:$A$2000,"32*",'BALANCE N'!$G$2:$G$2000)-SUMIF('BALANCE N'!$A$2:$A$2000,"32*",'BALANCE N'!$H$2:$H$2000) | C10: =SUMIF('BALANCE N-1'!$A$2:$A$2000,"32*",'BALANCE N-1'!$G$2:$G$2000)-SUMIF('BALANCE N-1'!$A$2:$A$2000,"32*",'BALANCE N-1'!$H$2:$H$2000) | D10: =B10-C10 | E10: =IF(C10=0,"",(B10-C10)/C10)
A11: Autres approvisionnements | B11: =SUMIF('BALANCE N'!$A$2:$A$2000,"33*",'BALANCE N'!$G$2:$G$2000)-SUMIF('BALANCE N'!$A$2:$A$2000,"33*",'BALANCE N'!$H$2:$H$2000) | C11: =SUMIF('BALANCE N-1'!$A$2:$A$2000,"33*",'BALANCE N-1'!$G$2:$G$2000)-SUMIF('BALANCE N-1'!$A$2:$A$2000,"33*",'BALANCE N-1'!$H$2:$H$2000) | D11: =B11-C11 | E11: =IF(C11=0,"",(B11-C11)/C11)
A12: Dons en nature | B12: =SUMIF('BALANCE N'!$A$2:$A$2000,"34*",'BALANCE N'!$G$2:$G$2000)-SUMIF('BALANCE N'!$A$2:$A$2000,"34*",'BALANCE N'!$H$2:$H$2000) | C12: =SUMIF('BALANCE N-1'!$A$2:$A$2000,"34*",'BALANCE N-1'!$G$2:$G$2000)-SUMIF('BALANCE N-1'!$A$2:$A$2000,"34*",'BALANCE N-1'!$H$2:$H$2000) | D12: =B12-C12 | E12: =IF(C12=0,"",(B12-C12)/C12)
A13: Produits finis et en cours | B13: =SUMIF('BALANCE N'!$A$2:$A$2000,"35*",'BALANCE N'!$G$2:$G$2000)-SUMIF('BALANCE N'!$A$2:$A$2000,"35*",'BALANCE N'!$H$2:$H$2000)+SUMIF('BALANCE N'!$A$2:$A$2000,"36*",'BALANCE N'!$G$2:$G$2000)-SUMIF('BALANCE N'!$A$2:$A$2000,"36*",'BALANCE N'!$H$2:$H$2000) | C13: =SUMIF('BALANCE N-1'!$A$2:$A$2000,"35*",'BALANCE N-1'!$G$2:$G$2000)-SUMIF('BALANCE N-1'!$A$2:$A$2000,"35*",'BALANCE N-1'!$H$2:$H$2000)+SUMIF('BALANCE N-1'!$A$2:$A$2000,"36*",'BALANCE N-1'!$G$2:$G$2000)-SUMIF('BALANCE N-1'!$A$2:$A$2000,"36*",'BALANCE N-1'!$H$2:$H$2000) | D13: =B13-C13 | E13: =IF(C13=0,"",(B13-C13)/C13)
A14: Dons en nature HAO | B14: =SUMIF('BALANCE N'!$A$2:$A$2000,"38*",'BALANCE N'!$G$2:$G$2000)-SUMIF('BALANCE N'!$A$2:$A$2000,"38*",'BALANCE N'!$H$2:$H$2000) | C14: =SUMIF('BALANCE N-1'!$A$2:$A$2000,"38*",'BALANCE N-1'!$G$2:$G$2000)-SUMIF('BALANCE N-1'!$A$2:$A$2000,"38*",'BALANCE N-1'!$H$2:$H$2000) | D14: =B14-C14 | E14: =IF(C14=0,"",(B14-C14)/C14)
A15: Stocks en cours de route, en consignation ou en dépôt | B15: =SUMIF('BALANCE N'!$A$2:$A$2000,"37*",'BALANCE N'!$G$2:$G$2000)-SUMIF('BALANCE N'!$A$2:$A$2000,"37*",'BALANCE N'!$H$2:$H$2000) | C15: =SUMIF('BALANCE N-1'!$A$2:$A$2000,"37*",'BALANCE N-1'!$G$2:$G$2000)-SUMIF('BALANCE N-1'!$A$2:$A$2000,"37*",'BALANCE N-1'!$H$2:$H$2000) | D15: =B15-C15 | E15: =IF(C15=0,"",(B15-C15)/C15)
A16: TOTAL STOCKS ET ENCOURS | B16: =SUM(B9:B15) | C16: =SUM(C9:C15) | D16: =B16-C16 | E16: =IF(C16=0,"",(B16-C16)/C16)
A17: Dépréciations des stocks | B17: =SUMIF('BALANCE N'!$A$2:$A$2000,"39*",'BALANCE N'!$H$2:$H$2000)-SUMIF('BALANCE N'!$A$2:$A$2000,"39*",'BALANCE N'!$G$2:$G$2000) | C17: =SUMIF('BALANCE N-1'!$A$2:$A$2000,"39*",'BALANCE N-1'!$H$2:$H$2000)-SUMIF('BALANCE N-1'!$A$2:$A$2000,"39*",'BALANCE N-1'!$G$2:$G$2000) | D17: =B17-C17 | E17: =IF(C17=0,"",(B17-C17)/C17)
B18: =SUM(B17:B17) | C18: =SUM(C17:C17) | D18: =B18-C18 | E18: =IF(C18=0,"",(B18-C18)/C18)
A19: TOTAL NET DE DÉPRÉCIATIONS | B19: =B16-B18 | C19: =C16-C18 | D19: =B19-C19 | E19: =IF(C19=0,"",(B19-C19)/C19)
A21: Commentaires :
A22: • Indiquer la date de prise d'inventaire, la procédure et les méthodes d'évaluation ; commenter toute variation significative ; détailler les stocks dépréciés.
A24: =IF(SUM(B9:B19,C9:C19,D9:D19)=0,"NÉANT","")

Sheet NOTE 9
A1: - 24 -
G2: NOTE 9 SYSTEME NORMAL
A3: Dénomination sociale :
A4: Adresse : | G4: Sigle usuel :
A5: N° de compte contribuable (NCC) : | E5: Exercice clos le | G5: Durée (en mois) : 12
A6: N° de télédéclarant (NTD) :
A7: NOTE 9 : ADHÉRENTS, CLIENTS-USAGERS
A8: Libellés | B8: Année N | C8: Année N-1 | D8: Variation en valeur | E8: Variation en % | F8: À un an au plus | G8: À plus d'un an et deux ans au plus | H8: À plus de deux ans
A9: Adhérents | B9: =SUMIF('BALANCE N'!$A$2:$A$2000,"411*",'BALANCE N'!$G$2:$G$2000)-SUMIF('BALANCE N'!$A$2:$A$2000,"411*",'BALANCE N'!$H$2:$H$2000) | C9: =SUMIF('BALANCE N-1'!$A$2:$A$2000,"411*",'BALANCE N-1'!$G$2:$G$2000)-SUMIF('BALANCE N-1'!$A$2:$A$2000,"411*",'BALANCE N-1'!$H$2:$H$2000) | D9: =B9-C9 | E9: =IF(C9=0,"",(B9-C9)/C9)
A10: Clients-usagers | B10: =SUMIF('BALANCE N'!$A$2:$A$2000,"412*",'BALANCE N'!$G$2:$G$2000)-SUMIF('BALANCE N'!$A$2:$A$2000,"412*",'BALANCE N'!$H$2:$H$2000) | C10: =SUMIF('BALANCE N-1'!$A$2:$A$2000,"412*",'BALANCE N-1'!$G$2:$G$2000)-SUMIF('BALANCE N-1'!$A$2:$A$2000,"412*",'BALANCE N-1'!$H$2:$H$2000) | D10: =B10-C10 | E10: =IF(C10=0,"",(B10-C10)/C10)
A11: Adhérents, clients-usagers, chèques, effets et autres valeurs impayés | B11: =SUMIF('BALANCE N'!$A$2:$A$2000,"413*",'BALANCE N'!$G$2:$G$2000)-SUMIF('BALANCE N'!$A$2:$A$2000,"413*",'BALANCE N'!$H$2:$H$2000) | C11: =SUMIF('BALANCE N-1'!$A$2:$A$2000,"413*",'BALANCE N-1'!$G$2:$G$2000)-SUMIF('BALANCE N-1'!$A$2:$A$2000,"413*",'BALANCE N-1'!$H$2:$H$2000) | D11: =B11-C11 | E11: =IF(C11=0,"",(B11-C11)/C11)
A12: Adhérents, créances litigieuses ou douteuses | B12: =SUMIF('BALANCE N'!$A$2:$A$2000,"416*",'BALANCE N'!$G$2:$G$2000)-SUMIF('BALANCE N'!$A$2:$A$2000,"416*",'BALANCE N'!$H$2:$H$2000) | C12: =SUMIF('BALANCE N-1'!$A$2:$A$2000,"416*",'BALANCE N-1'!$G$2:$G$2000)-SUMIF('BALANCE N-1'!$A$2:$A$2000,"416*",'BALANCE N-1'!$H$2:$H$2000) | D12: =B12-C12 | E12: =IF(C12=0,"",(B12-C12)/C12)
A13: Adhérents, clients-usagers, produits à recevoir | B13: =SUMIF('BALANCE N'!$A$2:$A$2000,"418*",'BALANCE N'!$G$2:$G$2000)-SUMIF('BALANCE N'!$A$2:$A$2000,"418*",'BALANCE N'!$H$2:$H$2000) | C13: =SUMIF('BALANCE N-1'!$A$2:$A$2000,"418*",'BALANCE N-1'!$G$2:$G$2000)-SUMIF('BALANCE N-1'!$A$2:$A$2000,"418*",'BALANCE N-1'!$H$2:$H$2000) | D13: =B13-C13 | E13: =IF(C13=0,"",(B13-C13)/C13)
A14: TOTAL BRUT ADHÉRENTS, CLIENTS-USAGERS | B14: =SUM(B9:B13) | C14: =SUM(C9:C13) | D14: =B14-C14 | E14: =IF(C14=0,"",(B14-C14)/C14)
A15: Dépréciations des comptes adhérents et clients-usagers | B15: =SUMIF('BALANCE N'!$A$2:$A$2000,"491*",'BALANCE N'!$H$2:$H$2000)-SUMIF('BALANCE N'!$A$2:$A$2000,"491*",'BALANCE N'!$G$2:$G$2000) | C15: =SUMIF('BALANCE N-1'!$A$2:$A$2000,"491*",'BALANCE N-1'!$H$2:$H$2000)-SUMIF('BALANCE N-1'!$A$2:$A$2000,"491*",'BALANCE N-1'!$G$2:$G$2000) | D15: =B15-C15 | E15: =IF(C15=0,"",(B15-C15)/C15)
B16: =SUM(B15:B15) | C16: =SUM(C15:C15) | D16: =B16-C16 | E16: =IF(C16=0,"",(B16-C16)/C16)
A17: TOTAL NET DE DÉPRÉCIATIONS | B17: =B14-B16 | C17: =C14-C16 | D17: =B17-C17 | E17: =IF(C17=0,"",(B17-C17)/C17)
A19: Adhérents, avances reçues | B19: =SUMIF('BALANCE N'!$A$2:$A$2000,"4191*",'BALANCE N'!$H$2:$H$2000) | C19: =SUMIF('BALANCE N-1'!$A$2:$A$2000,"4191*",'BALANCE N-1'!$H$2:$H$2000) | D19: =B19-C19 | E19: =IF(C19=0,"",(B19-C19)/C19)
A20: Clients-usagers, avances et acomptes reçus | B20: =SUMIF('BALANCE N'!$A$2:$A$2000,"4192*",'BALANCE N'!$H$2:$H$2000) | C20: =SUMIF('BALANCE N-1'!$A$2:$A$2000,"4192*",'BALANCE N-1'!$H$2:$H$2000) | D20: =B20-C20 | E20: =IF(C20=0,"",(B20-C20)/C20)
A21: Autres clients créditeurs | B21: =SUMIF('BALANCE N'!$A$2:$A$2000,"419*",'BALANCE N'!$H$2:$H$2000)-SUMIF('BALANCE N'!$A$2:$A$2000,"4191*",'BALANCE N'!$H$2:$H$2000)-SUMIF('BALANCE N'!$A$2:$A$2000,"4192*",'BALANCE N'!$H$2:$H$2000) | C21: =SUMIF('BALANCE N-1'!$A$2:$A$2000,"419*",'BALANCE N-1'!$H$2:$H$2000)-SUMIF('BALANCE N-1'!$A$2:$A$2000,"4191*",'BALANCE N-1'!$H$2:$H$2000)-SUMIF('BALANCE N-1'!$A$2:$A$2000,"4192*",'BALANCE N-1'!$H$2:$H$2000) | D21: =B21-C21 | E21: =IF(C21=0,"",(B21-C21)/C21)
A22: TOTAL CLIENTS CRÉDITEURS | B22: =SUM(B19:B21) | C22: =SUM(C19:C21) | D22: =B22-C22 | E22: =IF(C22=0,"",(B22-C22)/C22)
A24: Commentaires :
A25: • Commenter toute variation significative et les créances anciennes ; indiquer les évènements motivant dépréciation et reprise.
A27: =IF(SUM(B9:B22,C9:C22,D9:D22,F14:F22,G14:G22,H14:H22)=0,"NÉANT","")

Sheet NOTE 10
A1: - 25 -
G2: NOTE 10 SYSTEME NORMAL
A3: Dénomination sociale :
A4: Adresse : | G4: Sigle usuel :
A5: N° de compte contribuable (NCC) : | E5: Exercice clos le | G5: Durée (en mois) : 12
A6: N° de télédéclarant (NTD) :
A7: NOTE 10 : AUTRES CRÉANCES
A8: Libellés | B8: Année N | C8: Année N-1 | D8: Variation en valeur | E8: Variation en % | F8: À un an au plus | G8: À plus d'un an et deux ans au plus | H8: À plus de deux ans
A9: Personnel | B9: =SUMIF('BALANCE N'!$A$2:$A$2000,"42*",'BALANCE N'!$G$2:$G$2000) | C9: =SUMIF('BALANCE N-1'!$A$2:$A$2000,"42*",'BALANCE N-1'!$G$2:$G$2000) | D9: =B9-C9 | E9: =IF(C9=0,"",(B9-C9)/C9)
A10: Organismes sociaux | B10: =SUMIF('BALANCE N'!$A$2:$A$2000,"43*",'BALANCE N'!$G$2:$G$2000) | C10: =SUMIF('BALANCE N-1'!$A$2:$A$2000,"43*",'BALANCE N-1'!$G$2:$G$2000) | D10: =B10-C10 | E10: =IF(C10=0,"",(B10-C10)/C10)
A11: État et collectivités publiques | B11: =SUMIF('BALANCE N'!$A$2:$A$2000,"44*",'BALANCE N'!$G$2:$G$2000) | C11: =SUMIF('BALANCE N-1'!$A$2:$A$2000,"44*",'BALANCE N-1'!$G$2:$G$2000) | D11: =B11-C11 | E11: =IF(C11=0,"",(B11-C11)/C11)
A12: Fondateurs, apporteurs et comptes courants | B12: =SUMIF('BALANCE N'!$A$2:$A$2000,"45*",'BALANCE N'!$G$2:$G$2000) | C12: =SUMIF('BALANCE N-1'!$A$2:$A$2000,"45*",'BALANCE N-1'!$G$2:$G$2000) | D12: =B12-C12 | E12: =IF(C12=0,"",(B12-C12)/C12)
A13: Bailleurs, État et autres organismes, fonds d'administration | B13: =SUMIF('BALANCE N'!$A$2:$A$2000,"46*",'BALANCE N'!$G$2:$G$2000) | C13: =SUMIF('BALANCE N-1'!$A$2:$A$2000,"46*",'BALANCE N-1'!$G$2:$G$2000) | D13: =B13-C13 | E13: =IF(C13=0,"",(B13-C13)/C13)
A14: Débiteurs divers | B14: =SUMIF('BALANCE N'!$A$2:$A$2000,"471*",'BALANCE N'!$G$2:$G$2000)+SUMIF('BALANCE N'!$A$2:$A$2000,"472*",'BALANCE N'!$G$2:$G$2000)+SUMIF('BALANCE N'!$A$2:$A$2000,"473*",'BALANCE N'!$G$2:$G$2000)+SUMIF('BALANCE N'!$A$2:$A$2000,"475*",'BALANCE N'!$G$2:$G$2000) | C14: =SUMIF('BALANCE N-1'!$A$2:$A$2000,"471*",'BALANCE N-1'!$G$2:$G$2000)+SUMIF('BALANCE N-1'!$A$2:$A$2000,"472*",'BALANCE N-1'!$G$2:$G$2000)+SUMIF('BALANCE N-1'!$A$2:$A$2000,"473*",'BALANCE N-1'!$G$2:$G$2000)+SUMIF('BALANCE N-1'!$A$2:$A$2000,"475*",'BALANCE N-1'!$G$2:$G$2000) | D14: =B14-C14 | E14: =IF(C14=0,"",(B14-C14)/C14)
A15: Autres débiteurs divers | B15: =SUMIF('BALANCE N'!$A$2:$A$2000,"474*",'BALANCE N'!$G$2:$G$2000)+SUMIF('BALANCE N'!$A$2:$A$2000,"476*",'BALANCE N'!$G$2:$G$2000)+SUMIF('BALANCE N'!$A$2:$A$2000,"477*",'BALANCE N'!$G$2:$G$2000) | C15: =SUMIF('BALANCE N-1'!$A$2:$A$2000,"474*",'BALANCE N-1'!$G$2:$G$2000)+SUMIF('BALANCE N-1'!$A$2:$A$2000,"476*",'BALANCE N-1'!$G$2:$G$2000)+SUMIF('BALANCE N-1'!$A$2:$A$2000,"477*",'BALANCE N-1'!$G$2:$G$2000) | D15: =B15-C15 | E15: =IF(C15=0,"",(B15-C15)/C15)
A16: TOTAL BRUT | B16: =SUM(B9:B15) | C16: =SUM(C9:C15) | D16: =B16-C16 | E16: =IF(C16=0,"",(B16-C16)/C16)
A17: Dépréciations des autres créances | B17: =SUMIF('BALANCE N'!$A$2:$A$2000,"492*",'BALANCE N'!$H$2:$H$2000)-SUMIF('BALANCE N'!$A$2:$A$2000,"492*",'BALANCE N'!$G$2:$G$2000)+SUMIF('BALANCE N'!$A$2:$A$2000,"493*",'BALANCE N'!$H$2:$H$2000)-SUMIF('BALANCE N'!$A$2:$A$2000,"493*",'BALANCE N'!$G$2:$G$2000)+SUMIF('BALANCE N'!$A$2:$A$2000,"494*",'BALANCE N'!$H$2:$H$2000)-SUMIF('BALANCE N'!$A$2:$A$2000,"494*",'BALANCE N'!$G$2:$G$2000)+SUMIF('BALANCE N'!$A$2:$A$2000,"497*",'BALANCE N'!$H$2:$H$2000)-SUMIF('BALANCE N'!$A$2:$A$2000,"497*",'BALANCE N'!$G$2:$G$2000) | C17: =SUMIF('BALANCE N-1'!$A$2:$A$2000,"492*",'BALANCE N-1'!$H$2:$H$2000)-SUMIF('BALANCE N-1'!$A$2:$A$2000,"492*",'BALANCE N-1'!$G$2:$G$2000)+SUMIF('BALANCE N-1'!$A$2:$A$2000,"493*",'BALANCE N-1'!$H$2:$H$2000)-SUMIF('BALANCE N-1'!$A$2:$A$2000,"493*",'BALANCE N-1'!$G$2:$G$2000)+SUMIF('BALANCE N-1'!$A$2:$A$2000,"494*",'BALANCE N-1'!$H$2:$H$2000)-SUMIF('BALANCE N-1'!$A$2:$A$2000,"494*",'BALANCE N-1'!$G$2:$G$2000)+SUMIF('BALANCE N-1'!$A$2:$A$2000,"497*",'BALANCE N-1'!$H$2:$H$2000)-SUMIF('BALANCE N-1'!$A$2:$A$2000,"497*",'BALANCE N-1'!$G$2:$G$2000) | D17: =B17-C17 | E17: =IF(C17=0,"",(B17-C17)/C17)
B18: =SUM(B17:B17) | C18: =SUM(C17:C17) | D18: =B18-C18 | E18: =IF(C18=0,"",(B18-C18)/C18)
A19: TOTAL NET DE DÉPRÉCIATIONS | B19: =B16-B18 | C19: =C16-C18 | D19: =B19-C19 | E19: =IF(C19=0,"",(B19-C19)/C19)
A21: Commentaires :
A22: • Justifier toute variation significative ; détailler et justifier les créances significatives ou anciennes.
A24: =IF(SUM(B9:B19,C9:C19,D9:D19,F16:F19,G16:G19,H16:H19)=0,"NÉANT","")

Sheet NOTE 11
A1: - 26 -
D2: NOTE 11 SYSTEME NORMAL
A3: Dénomination sociale :
A4: Adresse : | D4: Sigle usuel :
A5: N° de compte contribuable (NCC) : | C5: Exercice clos le | D5: Durée (en mois) : 12
A6: N° de télédéclarant (NTD) :
A7: NOTE 11 : TITRES DE PLACEMENT
A8: Libellés | B8: Année N | C8: Année N-1 | D8: Variation en valeur | E8: Variation en %
A9: Titres de trésor et bons de caisse à court terme | B9: =SUMIF('BALANCE N'!$A$2:$A$2000,"501*",'BALANCE N'!$G$2:$G$2000)-SUMIF('BALANCE N'!$A$2:$A$2000,"501*",'BALANCE N'!$H$2:$H$2000) | C9: =SUMIF('BALANCE N-1'!$A$2:$A$2000,"501*",'BALANCE N-1'!$G$2:$G$2000)-SUMIF('BALANCE N-1'!$A$2:$A$2000,"501*",'BALANCE N-1'!$H$2:$H$2000) | D9: =B9-C9 | E9: =IF(C9=0,"",(B9-C9)/C9)
A10: Actions | B10: =SUMIF('BALANCE N'!$A$2:$A$2000,"502*",'BALANCE N'!$G$2:$G$2000)-SUMIF('BALANCE N'!$A$2:$A$2000,"502*",'BALANCE N'!$H$2:$H$2000) | C10: =SUMIF('BALANCE N-1'!$A$2:$A$2000,"502*",'BALANCE N-1'!$G$2:$G$2000)-SUMIF('BALANCE N-1'!$A$2:$A$2000,"502*",'BALANCE N-1'!$H$2:$H$2000) | D10: =B10-C10 | E10: =IF(C10=0,"",(B10-C10)/C10)
A11: Obligations | B11: =SUMIF('BALANCE N'!$A$2:$A$2000,"503*",'BALANCE N'!$G$2:$G$2000)-SUMIF('BALANCE N'!$A$2:$A$2000,"503*",'BALANCE N'!$H$2:$H$2000) | C11: =SUMIF('BALANCE N-1'!$A$2:$A$2000,"503*",'BALANCE N-1'!$G$2:$G$2000)-SUMIF('BALANCE N-1'!$A$2:$A$2000,"503*",'BALANCE N-1'!$H$2:$H$2000) | D11: =B11-C11 | E11: =IF(C11=0,"",(B11-C11)/C11)
A12: Bons de souscription | B12: =SUMIF('BALANCE N'!$A$2:$A$2000,"504*",'BALANCE N'!$G$2:$G$2000)-SUMIF('BALANCE N'!$A$2:$A$2000,"504*",'BALANCE N'!$H$2:$H$2000) | C12: =SUMIF('BALANCE N-1'!$A$2:$A$2000,"504*",'BALANCE N-1'!$G$2:$G$2000)-SUMIF('BALANCE N-1'!$A$2:$A$2000,"504*",'BALANCE N-1'!$H$2:$H$2000) | D12: =B12-C12 | E12: =IF(C12=0,"",(B12-C12)/C12)
A13: Titres négociables hors région | B13: =SUMIF('BALANCE N'!$A$2:$A$2000,"505*",'BALANCE N'!$G$2:$G$2000)-SUMIF('BALANCE N'!$A$2:$A$2000,"505*",'BALANCE N'!$H$2:$H$2000) | C13: =SUMIF('BALANCE N-1'!$A$2:$A$2000,"505*",'BALANCE N-1'!$G$2:$G$2000)-SUMIF('BALANCE N-1'!$A$2:$A$2000,"505*",'BALANCE N-1'!$H$2:$H$2000) | D13: =B13-C13 | E13: =IF(C13=0,"",(B13-C13)/C13)
A14: Intérêts courus | B14: =SUMIF('BALANCE N'!$A$2:$A$2000,"506*",'BALANCE N'!$G$2:$G$2000)-SUMIF('BALANCE N'!$A$2:$A$2000,"506*",'BALANCE N'!$H$2:$H$2000) | C14: =SUMIF('BALANCE N-1'!$A$2:$A$2000,"506*",'BALANCE N-1'!$G$2:$G$2000)-SUMIF('BALANCE N-1'!$A$2:$A$2000,"506*",'BALANCE N-1'!$H$2:$H$2000) | D14: =B14-C14 | E14: =IF(C14=0,"",(B14-C14)/C14)
A15: Autres valeurs assimilées | B15: =SUMIF('BALANCE N'!$A$2:$A$2000,"508*",'BALANCE N'!$G$2:$G$2000)-SUMIF('BALANCE N'!$A$2:$A$2000,"508*",'BALANCE N'!$H$2:$H$2000) | C15: =SUMIF('BALANCE N-1'!$A$2:$A$2000,"508*",'BALANCE N-1'!$G$2:$G$2000)-SUMIF('BALANCE N-1'!$A$2:$A$2000,"508*",'BALANCE N-1'!$H$2:$H$2000) | D15: =B15-C15 | E15: =IF(C15=0,"",(B15-C15)/C15)
A16: TOTAL BRUT | B16: =SUM(B9:B15) | C16: =SUM(C9:C15) | D16: =B16-C16 | E16: =IF(C16=0,"",(B16-C16)/C16)
A17: Dépréciations des titres de placement | B17: =SUMIF('BALANCE N'!$A$2:$A$2000,"590*",'BALANCE N'!$H$2:$H$2000)-SUMIF('BALANCE N'!$A$2:$A$2000,"590*",'BALANCE N'!$G$2:$G$2000) | C17: =SUMIF('BALANCE N-1'!$A$2:$A$2000,"590*",'BALANCE N-1'!$H$2:$H$2000)-SUMIF('BALANCE N-1'!$A$2:$A$2000,"590*",'BALANCE N-1'!$G$2:$G$2000) | D17: =B17-C17 | E17: =IF(C17=0,"",(B17-C17)/C17)
B18: =SUM(B17:B17) | C18: =SUM(C17:C17) | D18: =B18-C18 | E18: =IF(C18=0,"",(B18-C18)/C18)
A19: TOTAL NET DE DÉPRÉCIATIONS | B19: =B16-B18 | C19: =C16-C18 | D19: =B19-C19 | E19: =IF(C19=0,"",(B19-C19)/C19)
A21: =IF(SUM(B9:B19,C9:C19,D9:D19)=0,"NÉANT","")

Sheet NOTE 12
A1: - 27 -
D2: NOTE 12 SYSTEME NORMAL
A3: Dénomination sociale :
A4: Adresse : | D4: Sigle usuel :
A5: N° de compte contribuable (NCC) : | C5: Exercice clos le | D5: Durée (en mois) : 12
A6: N° de télédéclarant (NTD) :
A7: NOTE 12 : VALEURS À ENCAISSER
A8: Libellés | B8: Année N | C8: Année N-1 | D8: Variation en valeur | E8: Variation en %
A9: Chèques à encaisser | B9: =SUMIF('BALANCE N'!$A$2:$A$2000,"513*",'BALANCE N'!$G$2:$G$2000)-SUMIF('BALANCE N'!$A$2:$A$2000,"513*",'BALANCE N'!$H$2:$H$2000) | C9: =SUMIF('BALANCE N-1'!$A$2:$A$2000,"513*",'BALANCE N-1'!$G$2:$G$2000)-SUMIF('BALANCE N-1'!$A$2:$A$2000,"513*",'BALANCE N-1'!$H$2:$H$2000) | D9: =B9-C9 | E9: =IF(C9=0,"",(B9-C9)/C9)
A10: Chèques à l'encaissement | B10: =SUMIF('BALANCE N'!$A$2:$A$2000,"514*",'BALANCE N'!$G$2:$G$2000)-SUMIF('BALANCE N'!$A$2:$A$2000,"514*",'BALANCE N'!$H$2:$H$2000) | C10: =SUMIF('BALANCE N-1'!$A$2:$A$2000,"514*",'BALANCE N-1'!$G$2:$G$2000)-SUMIF('BALANCE N-1'!$A$2:$A$2000,"514*",'BALANCE N-1'!$H$2:$H$2000) | D10: =B10-C10 | E10: =IF(C10=0,"",(B10-C10)/C10)
A11: Cartes de crédit à encaisser | B11: =SUMIF('BALANCE N'!$A$2:$A$2000,"515*",'BALANCE N'!$G$2:$G$2000)-SUMIF('BALANCE N'!$A$2:$A$2000,"515*",'BALANCE N'!$H$2:$H$2000) | C11: =SUMIF('BALANCE N-1'!$A$2:$A$2000,"515*",'BALANCE N-1'!$G$2:$G$2000)-SUMIF('BALANCE N-1'!$A$2:$A$2000,"515*",'BALANCE N-1'!$H$2:$H$2000) | D11: =B11-C11 | E11: =IF(C11=0,"",(B11-C11)/C11)
A12: Autres valeurs à encaisser | B12: =SUMIF('BALANCE N'!$A$2:$A$2000,"518*",'BALANCE N'!$G$2:$G$2000)-SUMIF('BALANCE N'!$A$2:$A$2000,"518*",'BALANCE N'!$H$2:$H$2000) | C12: =SUMIF('BALANCE N-1'!$A$2:$A$2000,"518*",'BALANCE N-1'!$G$2:$G$2000)-SUMIF('BALANCE N-1'!$A$2:$A$2000,"518*",'BALANCE N-1'!$H$2:$H$2000) | D12: =B12-C12 | E12: =IF(C12=0,"",(B12-C12)/C12)
A13: TOTAL BRUT | B13: =SUM(B9:B12) | C13: =SUM(C9:C12) | D13: =B13-C13 | E13: =IF(C13=0,"",(B13-C13)/C13)
A14: Dépréciations des valeurs à encaisser | B14: =SUMIF('BALANCE N'!$A$2:$A$2000,"591*",'BALANCE N'!$H$2:$H$2000)-SUMIF('BALANCE N'!$A$2:$A$2000,"591*",'BALANCE N'!$G$2:$G$2000) | C14: =SUMIF('BALANCE N-1'!$A$2:$A$2000,"591*",'BALANCE N-1'!$H$2:$H$2000)-SUMIF('BALANCE N-1'!$A$2:$A$2000,"591*",'BALANCE N-1'!$G$2:$G$2000) | D14: =B14-C14 | E14: =IF(C14=0,"",(B14-C14)/C14)
B15: =SUM(B14:B14) | C15: =SUM(C14:C14) | D15: =B15-C15 | E15: =IF(C15=0,"",(B15-C15)/C15)
A16: TOTAL NET DE DÉPRÉCIATIONS | B16: =B13-B15 | C16: =C13-C15 | D16: =B16-C16 | E16: =IF(C16=0,"",(B16-C16)/C16)
A18: =IF(SUM(B9:B16,C9:C16,D9:D16)=0,"NÉANT","")

Sheet NOTE 13
A1: - 28 -
D2: NOTE 13 SYSTEME NORMAL
A3: Dénomination sociale :
A4: Adresse : | D4: Sigle usuel :
A5: N° de compte contribuable (NCC) : | C5: Exercice clos le | D5: Durée (en mois) : 12
A6: N° de télédéclarant (NTD) :
A7: NOTE 13 : DISPONIBILITÉS
A8: Libellés | B8: Année N | C8: Année N-1 | D8: Variation en valeur | E8: Variation en %
A9: Banques locales | B9: =SUMIF('BALANCE N'!$A$2:$A$2000,"521*",'BALANCE N'!$G$2:$G$2000) | C9: =SUMIF('BALANCE N-1'!$A$2:$A$2000,"521*",'BALANCE N-1'!$G$2:$G$2000) | D9: =B9-C9 | E9: =IF(C9=0,"",(B9-C9)/C9)
A10: Banques autres États région | B10: =SUMIF('BALANCE N'!$A$2:$A$2000,"522*",'BALANCE N'!$G$2:$G$2000) | C10: =SUMIF('BALANCE N-1'!$A$2:$A$2000,"522*",'BALANCE N-1'!$G$2:$G$2000) | D10: =B10-C10 | E10: =IF(C10=0,"",(B10-C10)/C10)
A11: Banques, dépôt à terme et assimilés | B11: =SUMIF('BALANCE N'!$A$2:$A$2000,"525*",'BALANCE N'!$G$2:$G$2000) | C11: =SUMIF('BALANCE N-1'!$A$2:$A$2000,"525*",'BALANCE N-1'!$G$2:$G$2000) | D11: =B11-C11 | E11: =IF(C11=0,"",(B11-C11)/C11)
A12: Autres banques | B12: =SUMIF('BALANCE N'!$A$2:$A$2000,"523*",'BALANCE N'!$G$2:$G$2000)+SUMIF('BALANCE N'!$A$2:$A$2000,"524*",'BALANCE N'!$G$2:$G$2000) | C12: =SUMIF('BALANCE N-1'!$A$2:$A$2000,"523*",'BALANCE N-1'!$G$2:$G$2000)+SUMIF('BALANCE N-1'!$A$2:$A$2000,"524*",'BALANCE N-1'!$G$2:$G$2000) | D12: =B12-C12 | E12: =IF(C12=0,"",(B12-C12)/C12)
A13: Banques intérêts courus | B13: =SUMIF('BALANCE N'!$A$2:$A$2000,"526*",'BALANCE N'!$G$2:$G$2000)-SUMIF('BALANCE N'!$A$2:$A$2000,"526*",'BALANCE N'!$H$2:$H$2000) | C13: =SUMIF('BALANCE N-1'!$A$2:$A$2000,"526*",'BALANCE N-1'!$G$2:$G$2000)-SUMIF('BALANCE N-1'!$A$2:$A$2000,"526*",'BALANCE N-1'!$H$2:$H$2000) | D13: =B13-C13 | E13: =IF(C13=0,"",(B13-C13)/C13)
A14: Banques postales | B14: =SUMIF('BALANCE N'!$A$2:$A$2000,"531*",'BALANCE N'!$G$2:$G$2000) | C14: =SUMIF('BALANCE N-1'!$A$2:$A$2000,"531*",'BALANCE N-1'!$G$2:$G$2000) | D14: =B14-C14 | E14: =IF(C14=0,"",(B14-C14)/C14)
A15: Autres établissements financiers | B15: =SUMIF('BALANCE N'!$A$2:$A$2000,"532*",'BALANCE N'!$G$2:$G$2000)+SUMIF('BALANCE N'!$A$2:$A$2000,"533*",'BALANCE N'!$G$2:$G$2000)+SUMIF('BALANCE N'!$A$2:$A$2000,"538*",'BALANCE N'!$G$2:$G$2000) | C15: =SUMIF('BALANCE N-1'!$A$2:$A$2000,"532*",'BALANCE N-1'!$G$2:$G$2000)+SUMIF('BALANCE N-1'!$A$2:$A$2000,"533*",'BALANCE N-1'!$G$2:$G$2000)+SUMIF('BALANCE N-1'!$A$2:$A$2000,"538*",'BALANCE N-1'!$G$2:$G$2000) | D15: =B15-C15 | E15: =IF(C15=0,"",(B15-C15)/C15)
A16: Établissements financiers intérêts courus | B16: =SUMIF('BALANCE N'!$A$2:$A$2000,"536*",'BALANCE N'!$G$2:$G$2000)-SUMIF('BALANCE N'!$A$2:$A$2000,"536*",'BALANCE N'!$H$2:$H$2000) | C16: =SUMIF('BALANCE N-1'!$A$2:$A$2000,"536*",'BALANCE N-1'!$G$2:$G$2000)-SUMIF('BALANCE N-1'!$A$2:$A$2000,"536*",'BALANCE N-1'!$H$2:$H$2000) | D16: =B16-C16 | E16: =IF(C16=0,"",(B16-C16)/C16)
A17: Instruments de monnaie électronique | B17: =SUMIF('BALANCE N'!$A$2:$A$2000,"55*",'BALANCE N'!$G$2:$G$2000)-SUMIF('BALANCE N'!$A$2:$A$2000,"55*",'BALANCE N'!$H$2:$H$2000) | C17: =SUMIF('BALANCE N-1'!$A$2:$A$2000,"55*",'BALANCE N-1'!$G$2:$G$2000)-SUMIF('BALANCE N-1'!$A$2:$A$2000,"55*",'BALANCE N-1'!$H$2:$H$2000) | D17: =B17-C17 | E17: =IF(C17=0,"",(B17-C17)/C17)
A18: Caisse | B18: =SUMIF('BALANCE N'!$A$2:$A$2000,"57*",'BALANCE N'!$G$2:$G$2000)-SUMIF('BALANCE N'!$A$2:$A$2000,"57*",'BALANCE N'!$H$2:$H$2000) | C18: =SUMIF('BALANCE N-1'!$A$2:$A$2000,"57*",'BALANCE N-1'!$G$2:$G$2000)-SUMIF('BALANCE N-1'!$A$2:$A$2000,"57*",'BALANCE N-1'!$H$2:$H$2000) | D18: =B18-C18 | E18: =IF(C18=0,"",(B18-C18)/C18)
A19: TOTAL BRUT | B19: =SUM(B9:B18) | C19: =SUM(C9:C18) | D19: =B19-C19 | E19: =IF(C19=0,"",(B19-C19)/C19)
